{
  "type": "Feature",
  "properties": {
    "gn:admin1_code":"18.0",
    "gn:admin2_code":"710.0",
    "gn:asciiname":"Hvallos",
    "gn:country_code":"DK",
    "gn:dem":47,
    "gn:feature_class":"P",
    "gn:feature_code":"PPL",
    "gn:name":"Hvall\u00f8s",
    "gn:population":0,
    "gn:timezone":"Europe/Copenhagen",
    "iso:country":"DK",
    "name:und_x_variant":[
        "Hvall\u00f6se",
        "Hvall\u00f8s"
    ],
    "wof:name":"Hvallos",
    "wof:placetype":"locality"
},
  "geometry": {"coordinates":[10.14537,56.37939],"type":"Point"}
}