{
  "type": "Feature",
  "properties": {
    "gn:admin1_code":"18.0",
    "gn:admin2_code":"707.0",
    "gn:asciiname":"Bode",
    "gn:country_code":"DK",
    "gn:dem":2,
    "gn:feature_class":"P",
    "gn:feature_code":"PPL",
    "gn:name":"Bode",
    "gn:population":0,
    "gn:timezone":"Europe/Copenhagen",
    "iso:country":"DK",
    "name:ceb_x_preferred":[
        "Bode"
    ],
    "name:ces_x_preferred":[
        "Bode"
    ],
    "name:deu_x_preferred":[
        "Bode"
    ],
    "name:epo_x_preferred":[
        "Bode"
    ],
    "name:fra_x_preferred":[
        "Bode"
    ],
    "name:ita_x_preferred":[
        "Bode"
    ],
    "name:nld_x_preferred":[
        "Bode"
    ],
    "name:pol_x_preferred":[
        "Bode"
    ],
    "name:rus_x_preferred":[
        "\u0411\u043e\u0434\u0435"
    ],
    "name:spa_x_preferred":[
        "Bode"
    ],
    "name:swe_x_preferred":[
        "Bode"
    ],
    "name:ukr_x_preferred":[
        "\u0411\u043e\u0434\u0435"
    ],
    "wof:name":"Bode",
    "wof:placetype":"locality"
},
  "geometry": {"coordinates":[10.30549,56.47751],"type":"Point"}
}