{
  "type": "Feature",
  "properties": {
    "gn:admin1_code":"18.0",
    "gn:admin2_code":"751.0",
    "gn:asciiname":"Battrup",
    "gn:country_code":"DK",
    "gn:dem":75,
    "gn:feature_class":"P",
    "gn:feature_code":"PPLL",
    "gn:name":"Battrup",
    "gn:population":0,
    "gn:timezone":"Europe/Copenhagen",
    "iso:country":"DK",
    "wof:name":"Battrup",
    "wof:placetype":"locality"
},
  "geometry": {"coordinates":[10.12527,56.05891],"type":"Point"}
}