{
  "type": "Feature",
  "properties": {
    "gn:admin1_code":"18.0",
    "gn:admin2_code":"746.0",
    "gn:asciiname":"Korsvej",
    "gn:country_code":"DK",
    "gn:dem":73,
    "gn:feature_class":"P",
    "gn:feature_code":"PPL",
    "gn:name":"Korsvej",
    "gn:population":0,
    "gn:timezone":"Europe/Copenhagen",
    "iso:country":"DK",
    "wof:name":"Korsvej",
    "wof:placetype":"locality"
},
  "geometry": {"coordinates":[9.80745,56.15002],"type":"Point"}
}