{
  "type": "Feature",
  "properties": {
    "gn:admin1_code":"18.0",
    "gn:admin2_code":"766.0",
    "gn:asciiname":"Neder Vrigsted",
    "gn:country_code":"DK",
    "gn:dem":75,
    "gn:feature_class":"P",
    "gn:feature_code":"PPL",
    "gn:name":"Neder Vrigsted",
    "gn:population":0,
    "gn:timezone":"Europe/Copenhagen",
    "iso:country":"DK",
    "wof:name":"Neder Vrigsted",
    "wof:placetype":"locality"
},
  "geometry": {"coordinates":[9.83727,55.72079],"type":"Point"}
}