{
  "type": "Feature",
  "properties": {
    "gn:admin1_code":"18.0",
    "gn:admin2_code":"751.0",
    "gn:asciiname":"Astrup",
    "gn:country_code":"DK",
    "gn:dem":8,
    "gn:feature_class":"P",
    "gn:feature_code":"PPL",
    "gn:name":"\u00c5strup",
    "gn:population":0,
    "gn:timezone":"Europe/Copenhagen",
    "iso:country":"DK",
    "name:dan_x_preferred":[
        "Astrup"
    ],
    "name:deu_x_preferred":[
        "Astrup"
    ],
    "name:fra_x_preferred":[
        "Astrup"
    ],
    "name:nld_x_preferred":[
        "Astrup"
    ],
    "name:nno_x_preferred":[
        "Astrup"
    ],
    "name:nor_x_preferred":[
        "Astrup"
    ],
    "name:rus_x_preferred":[
        "\u0410\u0441\u0442\u0440\u0443\u043f"
    ],
    "name:und_x_variant":[
        "Aastrup",
        "\u00c5strup"
    ],
    "wof:name":"Astrup",
    "wof:placetype":"locality"
},
  "geometry": {"coordinates":[10.31851,56.24949],"type":"Point"}
}