{
  "type": "Feature",
  "properties": {
    "gn:admin1_code":"19.0",
    "gn:admin2_code":"851.0",
    "gn:asciiname":"Sofiendal",
    "gn:country_code":"DK",
    "gn:dem":4,
    "gn:feature_class":"P",
    "gn:feature_code":"PPL",
    "gn:name":"Sofiendal",
    "gn:population":0,
    "gn:timezone":"Europe/Copenhagen",
    "iso:country":"DK",
    "name:und_x_variant":[
        "Ny-Hasseris",
        "Sofiedal",
        "Sofiendal"
    ],
    "wof:name":"Sofiendal",
    "wof:placetype":"locality"
},
  "geometry": {"coordinates":[9.87119,57.01708000000001],"type":"Point"}
}