{
  "type": "Feature",
  "properties": {
    "gn:admin1_code":"21.0",
    "gn:admin2_code":"510.0",
    "gn:asciiname":"Bjerning",
    "gn:country_code":"DK",
    "gn:dem":32,
    "gn:feature_class":"P",
    "gn:feature_code":"PPLR",
    "gn:name":"Bjerning",
    "gn:population":0,
    "gn:timezone":"Europe/Copenhagen",
    "iso:country":"DK",
    "wof:name":"Bjerning",
    "wof:placetype":"locality"
},
  "geometry": {"coordinates":[9.49294,55.3049],"type":"Point"}
}