{
  "type": "Feature",
  "properties": {
    "gn:admin1_code":"21.0",
    "gn:admin2_code":"420.0",
    "gn:asciiname":"Vedtofte",
    "gn:country_code":"DK",
    "gn:dem":64,
    "gn:feature_class":"P",
    "gn:feature_code":"PPL",
    "gn:name":"Vedtofte",
    "gn:population":0,
    "gn:timezone":"Europe/Copenhagen",
    "iso:country":"DK",
    "wof:name":"Vedtofte",
    "wof:placetype":"locality"
},
  "geometry": {"coordinates":[10.04958,55.30922],"type":"Point"}
}