{
  "type": "Feature",
  "properties": {
    "gn:admin1_code":"18.0",
    "gn:admin2_code":"657.0",
    "gn:asciiname":"Skjerk",
    "gn:country_code":"DK",
    "gn:dem":42,
    "gn:feature_class":"P",
    "gn:feature_code":"PPL",
    "gn:name":"Skjerk",
    "gn:population":0,
    "gn:timezone":"Europe/Copenhagen",
    "iso:country":"DK",
    "name:und_x_variant":[
        "Skerk",
        "Skjerk"
    ],
    "wof:name":"Skjerk",
    "wof:placetype":"locality"
},
  "geometry": {"coordinates":[8.82164,56.27069],"type":"Point"}
}