{
  "type": "Feature",
  "properties": {
    "gn:admin1_code":"20.0",
    "gn:admin2_code":"360.0",
    "gn:asciiname":"Alminde",
    "gn:country_code":"DK",
    "gn:dem":0,
    "gn:feature_class":"P",
    "gn:feature_code":"PPL",
    "gn:name":"Alminde",
    "gn:population":0,
    "gn:timezone":"Europe/Copenhagen",
    "iso:country":"DK",
    "wof:name":"Alminde",
    "wof:placetype":"locality"
},
  "geometry": {"coordinates":[11.25923,54.75673000000001],"type":"Point"}
}