{
  "type": "Feature",
  "properties": {
    "gn:admin1_code":"19.0",
    "gn:admin2_code":"846.0",
    "gn:asciiname":"Sondergarde",
    "gn:country_code":"DK",
    "gn:dem":6,
    "gn:feature_class":"P",
    "gn:feature_code":"PPL",
    "gn:name":"S\u00f8nderg\u00e5rde",
    "gn:population":0,
    "gn:timezone":"Europe/Copenhagen",
    "iso:country":"DK",
    "name:und_x_variant":[
        "S\u00f8ndergaarde",
        "S\u00f8nderg\u00e5rde"
    ],
    "wof:name":"Sondergarde",
    "wof:placetype":"locality"
},
  "geometry": {"coordinates":[10.12345,56.72436999999999],"type":"Point"}
}