{
  "type": "Feature",
  "properties": {
    "gn:admin1_code":"19.0",
    "gn:admin2_code":"849.0",
    "gn:asciiname":"Alsbjerg",
    "gn:country_code":"DK",
    "gn:dem":29,
    "gn:feature_class":"P",
    "gn:feature_code":"PPL",
    "gn:name":"Alsbjerg",
    "gn:population":0,
    "gn:timezone":"Europe/Copenhagen",
    "iso:country":"DK",
    "name:und_x_variant":[
        "Alsbj\u00e6rg",
        "Alsbjerg"
    ],
    "wof:name":"Alsbjerg",
    "wof:placetype":"locality"
},
  "geometry": {"coordinates":[9.44593,57.05138],"type":"Point"}
}