{
  "type": "Feature",
  "properties": {
    "gn:admin1_code":"21.0",
    "gn:admin2_code":"580.0",
    "gn:asciiname":"Hessel",
    "gn:country_code":"DK",
    "gn:dem":24,
    "gn:feature_class":"P",
    "gn:feature_code":"PPL",
    "gn:name":"Hessel",
    "gn:population":0,
    "gn:timezone":"Europe/Copenhagen",
    "iso:country":"DK",
    "name:chv_x_preferred":[
        "\u0425\u0435\u0441\u0441\u0435\u043b\u044c"
    ],
    "name:deu_x_preferred":[
        "Hessel"
    ],
    "name:fas_x_preferred":[
        "\u0647\u0633\u0644"
    ],
    "name:por_x_preferred":[
        "Hessel"
    ],
    "name:rus_x_preferred":[
        "\u0425\u0435\u0441\u0441\u0435\u043b\u044c"
    ],
    "wof:name":"Hessel",
    "wof:placetype":"locality"
},
  "geometry": {"coordinates":[9.11769,55.03653000000001],"type":"Point"}
}