{
  "type": "Feature",
  "properties": {
    "gn:admin1_code":"20.0",
    "gn:admin2_code":"330.0",
    "gn:asciiname":"Snekkerup",
    "gn:country_code":"DK",
    "gn:dem":39,
    "gn:feature_class":"P",
    "gn:feature_code":"PPL",
    "gn:name":"Snekkerup",
    "gn:population":0,
    "gn:timezone":"Europe/Copenhagen",
    "iso:country":"DK",
    "wof:name":"Snekkerup",
    "wof:placetype":"locality"
},
  "geometry": {"coordinates":[11.36153,55.31831],"type":"Point"}
}