{
  "type": "Feature",
  "properties": {
    "gn:admin1_code":"19.0",
    "gn:admin2_code":"840.0",
    "gn:asciiname":"Blenstrup",
    "gn:country_code":"DK",
    "gn:dem":41,
    "gn:feature_class":"P",
    "gn:feature_code":"PPL",
    "gn:name":"Blenstrup",
    "gn:population":0,
    "gn:timezone":"Europe/Copenhagen",
    "iso:country":"DK",
    "name:dan_x_preferred":[
        "Blenstrup"
    ],
    "name:deu_x_preferred":[
        "Blenstrup"
    ],
    "name:nld_x_preferred":[
        "Blenstrup"
    ],
    "name:spa_x_preferred":[
        "Blenstrup"
    ],
    "wof:name":"Blenstrup",
    "wof:placetype":"locality"
},
  "geometry": {"coordinates":[10.01241,56.88002],"type":"Point"}
}