{
  "type": "Feature",
  "properties": {
    "gn:admin1_code":"18.0",
    "gn:admin2_code":"779.0",
    "gn:asciiname":"Norre Andrup",
    "gn:country_code":"DK",
    "gn:dem":17,
    "gn:feature_class":"P",
    "gn:feature_code":"PPL",
    "gn:name":"N\u00f8rre Andrup",
    "gn:population":0,
    "gn:timezone":"Europe/Copenhagen",
    "iso:country":"DK",
    "wof:name":"Norre Andrup",
    "wof:placetype":"locality"
},
  "geometry": {"coordinates":[8.8783,56.67367],"type":"Point"}
}