{
  "type": "Feature",
  "properties": {
    "gn:admin1_code":"18.0",
    "gn:admin2_code":"746.0",
    "gn:asciiname":"Bjertrup",
    "gn:country_code":"DK",
    "gn:dem":77,
    "gn:feature_class":"P",
    "gn:feature_code":"PPL",
    "gn:name":"Bjertrup",
    "gn:population":0,
    "gn:timezone":"Europe/Copenhagen",
    "iso:country":"DK",
    "wof:name":"Bjertrup",
    "wof:placetype":"locality"
},
  "geometry": {"coordinates":[10.00041,56.08153000000001],"type":"Point"}
}