{
  "type": "Feature",
  "properties": {
    "gn:admin1_code":"18.0",
    "gn:admin2_code":"665.0",
    "gn:asciiname":"Lisby",
    "gn:country_code":"DK",
    "gn:dem":9,
    "gn:feature_class":"P",
    "gn:feature_code":"PPL",
    "gn:name":"Lisby",
    "gn:population":0,
    "gn:timezone":"Europe/Copenhagen",
    "iso:country":"DK",
    "wof:name":"Lisby",
    "wof:placetype":"locality"
},
  "geometry": {"coordinates":[8.13656,56.47109],"type":"Point"}
}