{
  "type": "Feature",
  "properties": {
    "gn:admin1_code":"18.0",
    "gn:admin2_code":"671.0",
    "gn:asciiname":"Osterby",
    "gn:country_code":"DK",
    "gn:dem":38,
    "gn:feature_class":"P",
    "gn:feature_code":"PPL",
    "gn:name":"\u00d8sterby",
    "gn:population":0,
    "gn:timezone":"Europe/Copenhagen",
    "iso:country":"DK",
    "name:ceb_x_preferred":[
        "Osterby"
    ],
    "name:deu_x_preferred":[
        "Osterby"
    ],
    "name:epo_x_preferred":[
        "Osterby"
    ],
    "name:eus_x_preferred":[
        "Osterby"
    ],
    "name:fra_x_preferred":[
        "Osterby"
    ],
    "name:ita_x_preferred":[
        "Osterby"
    ],
    "name:mkd_x_preferred":[
        "\u041e\u0441\u0442\u0435\u0440\u0431\u0438"
    ],
    "name:nds_x_preferred":[
        "Oosterby"
    ],
    "name:nld_x_preferred":[
        "Osterby"
    ],
    "name:pol_x_preferred":[
        "Osterby"
    ],
    "name:rus_x_preferred":[
        "\u041e\u0441\u0442\u0435\u0440\u0431\u0438"
    ],
    "name:srp_x_preferred":[
        "\u041e\u0441\u0442\u0435\u0440\u0431\u0438"
    ],
    "name:swe_x_preferred":[
        "Osterby"
    ],
    "wof:name":"Osterby",
    "wof:placetype":"locality"
},
  "geometry": {"coordinates":[8.51638,56.42996],"type":"Point"}
}