{
  "type": "Feature",
  "properties": {
    "gn:admin1_code":"21.0",
    "gn:admin2_code":"530.0",
    "gn:asciiname":"Krogager",
    "gn:country_code":"DK",
    "gn:dem":31,
    "gn:feature_class":"P",
    "gn:feature_code":"PPL",
    "gn:name":"Krogager",
    "gn:population":0,
    "gn:timezone":"Europe/Copenhagen",
    "iso:country":"DK",
    "wof:name":"Krogager",
    "wof:placetype":"locality"
},
  "geometry": {"coordinates":[8.84493,55.70138000000001],"type":"Point"}
}