{
  "type": "Feature",
  "properties": {
    "gn:admin1_code":"18.0",
    "gn:admin2_code":"615.0",
    "gn:asciiname":"Sonder Vissing",
    "gn:country_code":"DK",
    "gn:dem":108,
    "gn:feature_class":"P",
    "gn:feature_code":"PPL",
    "gn:name":"S\u00f8nder Vissing",
    "gn:population":0,
    "gn:timezone":"Europe/Copenhagen",
    "iso:country":"DK",
    "wof:name":"Sonder Vissing",
    "wof:placetype":"locality"
},
  "geometry": {"coordinates":[9.64341,56.02016999999999],"type":"Point"}
}