{
  "type": "Feature",
  "properties": {
    "iso:country":"DK",
    "name:dan_x_preferred":[
        "Rosen\u00f8rns All\u00e9"
    ],
    "name:eng_x_variant":[
        "St. Thomas All\u00e9"
    ],
    "qs:gn_adm0_cc":"DK",
    "qs:gn_local":2621942,
    "qs:gn_nam_loc":"Frederiksberg, Frederiksberg, Hovedstaden, DK",
    "qs:gn_namadm1":"17",
    "qs:local_max":4158,
    "qs:local_sum":18220,
    "qs:localhoods":20,
    "qs:name":"St. Thomas All\u00e9",
    "qs:name_adm0":"Danmark",
    "qs:name_adm1":"Hovedstaden",
    "qs:name_adm2":"Frederiksberg",
    "qs:name_en":"St. Thomas All\u00e9",
    "qs:name_local":"Frederiksberg",
    "qs:photo_max":47,
    "qs:photo_sum":153,
    "qs:placetype":"Suburb",
    "qs:quad_count":8,
    "qs:woe_adm0":23424796,
    "qs:woe_adm1":28362583,
    "qs:woe_adm2":12582714,
    "qs:woe_lau":0,
    "qs:woe_local":553307,
    "qs:woe_ver":"7.3.1",
    "wof:name":"St. Thomas All\u00e9",
    "wof:placetype":"neighbourhood"
},
  "geometry": {"coordinates":[12.548916,55.67409],"type":"Point"}
}