{
  "type": "Feature",
  "properties": {
    "gn:admin1_code":"21.0",
    "gn:admin2_code":"430.0",
    "gn:asciiname":"Norre Soby",
    "gn:country_code":"DK",
    "gn:dem":51,
    "gn:feature_class":"P",
    "gn:feature_code":"PPL",
    "gn:name":"N\u00f8rre S\u00f8by",
    "gn:population":0,
    "gn:timezone":"Europe/Copenhagen",
    "iso:country":"DK",
    "wof:name":"Norre Soby",
    "wof:placetype":"locality"
},
  "geometry": {"coordinates":[10.38241,55.28351],"type":"Point"}
}