{
  "type": "Feature",
  "properties": {
    "gn:admin1_code":"20.0",
    "gn:admin2_code":"329.0",
    "gn:asciiname":"Valsolille",
    "gn:country_code":"DK",
    "gn:dem":74,
    "gn:feature_class":"P",
    "gn:feature_code":"PPL",
    "gn:name":"Vals\u00f8lille",
    "gn:population":0,
    "gn:timezone":"Europe/Copenhagen",
    "iso:country":"DK",
    "name:und_x_variant":[
        "Vals\u00f6lille Gaard",
        "Vals\u00f8lille"
    ],
    "wof:name":"Valsolille",
    "wof:placetype":"locality"
},
  "geometry": {"coordinates":[11.83372,55.5223],"type":"Point"}
}