{
  "type": "Feature",
  "properties": {
    "gn:admin1_code":"19.0",
    "gn:admin2_code":"840.0",
    "gn:asciiname":"Gammel Norager",
    "gn:country_code":"DK",
    "gn:dem":38,
    "gn:feature_class":"P",
    "gn:feature_code":"PPL",
    "gn:name":"Gammel N\u00f8rager",
    "gn:population":0,
    "gn:timezone":"Europe/Copenhagen",
    "iso:country":"DK",
    "name:und_x_variant":[
        "N\u00f6rager",
        "Gammel N\u00f8rager"
    ],
    "wof:name":"Gammel Norager",
    "wof:placetype":"locality"
},
  "geometry": {"coordinates":[9.59711,56.72617],"type":"Point"}
}