{
  "type": "Feature",
  "properties": {
    "gn:admin1_code":"19.0",
    "gn:admin2_code":"851.0",
    "gn:asciiname":"Gammel Hasseris",
    "gn:country_code":"DK",
    "gn:dem":8,
    "gn:feature_class":"P",
    "gn:feature_code":"PPL",
    "gn:name":"Gammel Hasseris",
    "gn:population":0,
    "gn:timezone":"Europe/Copenhagen",
    "iso:country":"DK",
    "name:und_x_variant":[
        "Gamle Hasseris",
        "Gammel Hasseris"
    ],
    "wof:name":"Gammel Hasseris",
    "wof:placetype":"locality"
},
  "geometry": {"coordinates":[9.87076,57.02536],"type":"Point"}
}