{
  "type": "Feature",
  "properties": {
    "gn:admin1_code":"19.0",
    "gn:admin2_code":"787.0",
    "gn:asciiname":"Dollerup",
    "gn:country_code":"DK",
    "gn:dem":27,
    "gn:feature_class":"P",
    "gn:feature_code":"PPL",
    "gn:name":"Dollerup",
    "gn:population":0,
    "gn:timezone":"Europe/Copenhagen",
    "iso:country":"DK",
    "name:ceb_x_preferred":[
        "Dollerup"
    ],
    "name:dan_x_preferred":[
        "Dollerup"
    ],
    "name:deu_x_preferred":[
        "Dollerup"
    ],
    "name:epo_x_preferred":[
        "Dollerup"
    ],
    "name:eus_x_preferred":[
        "Dollerup"
    ],
    "name:fas_x_preferred":[
        "\u062f\u0648\u0644\u0631\u0648\u067e"
    ],
    "name:fra_x_preferred":[
        "Dollerup"
    ],
    "name:hun_x_preferred":[
        "Dollerup"
    ],
    "name:ita_x_preferred":[
        "Dollerup"
    ],
    "name:mkd_x_preferred":[
        "\u0414\u043e\u043b\u0435\u0440\u0443\u043f"
    ],
    "name:msa_x_preferred":[
        "Dollerup"
    ],
    "name:nld_x_preferred":[
        "Dollerup"
    ],
    "name:pol_x_preferred":[
        "Dollerup"
    ],
    "name:por_x_preferred":[
        "Dollerup"
    ],
    "name:ron_x_preferred":[
        "Dollerup"
    ],
    "name:rus_x_preferred":[
        "\u0414\u043e\u043b\u043b\u0435\u0440\u0443\u043f"
    ],
    "name:sco_x_preferred":[
        "Dollerup"
    ],
    "name:spa_x_preferred":[
        "Dollerup"
    ],
    "name:srp_x_preferred":[
        "\u0414\u043e\u043b\u0435\u0440\u0443\u043f"
    ],
    "name:tur_x_preferred":[
        "Dollerup"
    ],
    "name:ukr_x_preferred":[
        "\u0414\u043e\u043b\u043b\u0435\u0440\u0443\u043f"
    ],
    "name:uzb_x_preferred":[
        "Dollerup"
    ],
    "name:vie_x_preferred":[
        "Dollerup"
    ],
    "name:vol_x_preferred":[
        "Dollerup"
    ],
    "name:war_x_preferred":[
        "Dollerup"
    ],
    "name:zho_x_preferred":[
        "\u591a\u52d2\u9c81\u666e"
    ],
    "wof:name":"Dollerup",
    "wof:placetype":"locality"
},
  "geometry": {"coordinates":[8.5725,56.96258],"type":"Point"}
}