{
  "type": "Feature",
  "properties": {
    "gn:country":"DK",
    "gn:fcode":"PPLA2",
    "gn:population":0,
    "iso:country":"DK",
    "name:bul_x_preferred":[
        "\u0411\u0439\u0440\u0443\u043c"
    ],
    "name:cat_x_preferred":[
        "Byrum"
    ],
    "name:ceb_x_preferred":[
        "Byrum"
    ],
    "name:dan_x_preferred":[
        "Byrum"
    ],
    "name:eng_x_preferred":[
        "Byrum"
    ],
    "name:msa_x_preferred":[
        "Byrum"
    ],
    "name:nld_x_preferred":[
        "Byrum"
    ],
    "name:nob_x_preferred":[
        "Byrum"
    ],
    "name:spa_x_preferred":[
        "Byrum"
    ],
    "name:swe_x_preferred":[
        "Byrum"
    ],
    "qs_pg:aaroncc":"DK",
    "qs_pg:gn_country":"DK",
    "qs_pg:gn_fcode":"PPLA2",
    "qs_pg:gn_pop":0,
    "qs_pg:name":"Byrum",
    "qs_pg:name_adm0":"Danmark",
    "qs_pg:name_adm1":"Nordjylland",
    "qs_pg:photos":11,
    "qs_pg:photos_1k":2,
    "qs_pg:photos_9k":1,
    "qs_pg:photos_9r":0,
    "qs_pg:photos_all":11,
    "qs_pg:photos_sr":0,
    "qs_pg:pop_sr":0,
    "qs_pg:qs_pg_placetype":"locality",
    "qs_pg:qs_pg_placetype_gp":"Town",
    "qs_pg:woe_adm0":23424796,
    "wof:name":"Byrum",
    "wof:placetype":"locality"
},
  "geometry": {"coordinates":[10.99738,57.25679],"type":"Point"}
}