{
  "type": "Feature",
  "properties": {
    "gn:country":"DK",
    "gn:fcode":"PPL",
    "gn:population":0,
    "iso:country":"DK",
    "name:ast_x_preferred":[
        "Fjenneslev"
    ],
    "name:aze_x_preferred":[
        "Fenneslev"
    ],
    "name:bel_x_preferred":[
        "\u0424'\u0435\u043d\u0435\u0441\u043b\u0435\u045e"
    ],
    "name:cat_x_preferred":[
        "Fjenneslev"
    ],
    "name:ces_x_preferred":[
        "Fjenneslev"
    ],
    "name:dan_x_preferred":[
        "Fjenneslev"
    ],
    "name:deu_x_preferred":[
        "Fjenneslev"
    ],
    "name:eng_x_preferred":[
        "Fjenneslev"
    ],
    "name:nld_x_preferred":[
        "Fjenneslev"
    ],
    "name:pol_x_preferred":[
        "Fjenneslev"
    ],
    "name:rus_x_preferred":[
        "\u0424\u044c\u0435\u043d\u043d\u0435\u0441\u043b\u0435\u0432"
    ],
    "name:spa_x_preferred":[
        "Fjenneslev"
    ],
    "name:swe_x_preferred":[
        "Fjenneslev"
    ],
    "qs_pg:aaroncc":"DK",
    "qs_pg:gn_country":"DK",
    "qs_pg:gn_fcode":"PPL",
    "qs_pg:gn_pop":0,
    "qs_pg:name":"Kirke-Fjenneslev",
    "qs_pg:name_adm0":"Danmark",
    "qs_pg:name_adm1":"Sj\u00e6lland",
    "qs_pg:photos":81,
    "qs_pg:photos_1k":16,
    "qs_pg:photos_9k":1,
    "qs_pg:photos_9r":3,
    "qs_pg:photos_all":81,
    "qs_pg:photos_sr":3,
    "qs_pg:pop_sr":0,
    "qs_pg:qs_pg_placetype":"locality",
    "qs_pg:qs_pg_placetype_gp":"Town",
    "qs_pg:woe_adm0":23424796,
    "woe:adm0_id":23424796,
    "woe:name_adm0":"Danmark",
    "woe:name_adm1":"Sj\u00e6lland",
    "woe:placetype":"Town",
    "wof:name":"Kirke-Fjenneslev",
    "wof:placetype":"locality"
},
  "geometry": {"coordinates":[11.68802,55.43386],"type":"Point"}
}