{
  "type": "Feature",
  "properties": {
    "gn:admin1_code":"18.0",
    "gn:admin2_code":"706.0",
    "gn:asciiname":"Skiffard",
    "gn:country_code":"DK",
    "gn:dem":16,
    "gn:feature_class":"P",
    "gn:feature_code":"PPL",
    "gn:name":"Skiffard",
    "gn:population":0,
    "gn:timezone":"Europe/Copenhagen",
    "iso:country":"DK",
    "wof:name":"Skiffard",
    "wof:placetype":"locality"
},
  "geometry": {"coordinates":[10.67395,56.4004],"type":"Point"}
}