{
  "type": "Feature",
  "properties": {
    "gn:admin1_code":"21.0",
    "gn:admin2_code":"430.0",
    "gn:asciiname":"Radby",
    "gn:country_code":"DK",
    "gn:dem":37,
    "gn:feature_class":"P",
    "gn:feature_code":"PPL",
    "gn:name":"Radby",
    "gn:population":0,
    "gn:timezone":"Europe/Copenhagen",
    "iso:country":"DK",
    "wof:name":"Radby",
    "wof:placetype":"locality"
},
  "geometry": {"coordinates":[10.34232,55.28285],"type":"Point"}
}