{
  "type": "Feature",
  "properties": {
    "gn:admin1_code":"19.0",
    "gn:admin2_code":"813.0",
    "gn:asciiname":"Lodskovvad",
    "gn:country_code":"DK",
    "gn:dem":14,
    "gn:feature_class":"P",
    "gn:feature_code":"PPLL",
    "gn:name":"Lodskovvad",
    "gn:population":0,
    "gn:timezone":"Europe/Copenhagen",
    "iso:country":"DK",
    "wof:name":"Lodskovvad",
    "wof:placetype":"locality"
},
  "geometry": {"coordinates":[10.39095,57.62371],"type":"Point"}
}