{
  "type": "Feature",
  "properties": {
    "gn:admin1_code":"21.0",
    "gn:admin2_code":"430.0",
    "gn:asciiname":"Hastrup",
    "gn:country_code":"DK",
    "gn:dem":58,
    "gn:feature_class":"P",
    "gn:feature_code":"PPL",
    "gn:name":"H\u00e5strup",
    "gn:population":0,
    "gn:timezone":"Europe/Copenhagen",
    "iso:country":"DK",
    "name:dan_x_preferred":[
        "Hastrup"
    ],
    "name:und_x_variant":[
        "Hostrup",
        "Haastrup",
        "H\u00e5strup"
    ],
    "wof:name":"Hastrup",
    "wof:placetype":"locality"
},
  "geometry": {"coordinates":[10.19339,55.17265],"type":"Point"}
}