{
  "type": "Feature",
  "properties": {
    "gn:admin1_code":"20.0",
    "gn:admin2_code":"360.0",
    "gn:asciiname":"Vriet",
    "gn:country_code":"DK",
    "gn:dem":3,
    "gn:feature_class":"P",
    "gn:feature_code":"PPL",
    "gn:name":"Vriet",
    "gn:population":0,
    "gn:timezone":"Europe/Copenhagen",
    "iso:country":"DK",
    "wof:name":"Vriet",
    "wof:placetype":"locality"
},
  "geometry": {"coordinates":[11.45473,54.82791],"type":"Point"}
}