{
  "type": "Feature",
  "properties": {
    "gn:admin1_code":"20.0",
    "gn:admin2_code":"326.0",
    "gn:asciiname":"Raklev",
    "gn:country_code":"DK",
    "gn:dem":50,
    "gn:feature_class":"P",
    "gn:feature_code":"PPL",
    "gn:name":"Raklev",
    "gn:population":0,
    "gn:timezone":"Europe/Copenhagen",
    "iso:country":"DK",
    "wof:name":"Raklev",
    "wof:placetype":"locality"
},
  "geometry": {"coordinates":[11.06667,55.69723000000001],"type":"Point"}
}