{
  "type": "Feature",
  "properties": {
    "gn:admin1_code":"18.0",
    "gn:admin2_code":"756.0",
    "gn:asciiname":"Moselund",
    "gn:country_code":"DK",
    "gn:dem":81,
    "gn:feature_class":"P",
    "gn:feature_code":"PPL",
    "gn:name":"Moselund",
    "gn:population":0,
    "gn:timezone":"Europe/Copenhagen",
    "iso:country":"DK",
    "wof:name":"Moselund",
    "wof:placetype":"locality"
},
  "geometry": {"coordinates":[9.36815,56.16571999999999],"type":"Point"}
}