{
  "type": "Feature",
  "properties": {
    "gn:admin1_code":"19.0",
    "gn:admin2_code":"813.0",
    "gn:asciiname":"Mejling",
    "gn:country_code":"DK",
    "gn:dem":33,
    "gn:feature_class":"P",
    "gn:feature_code":"PPL",
    "gn:name":"Mejling",
    "gn:population":0,
    "gn:timezone":"Europe/Copenhagen",
    "iso:country":"DK",
    "wof:name":"Mejling",
    "wof:placetype":"locality"
},
  "geometry": {"coordinates":[10.39482,57.45794],"type":"Point"}
}