{
  "type": "Feature",
  "properties": {
    "gn:admin1_code":"21.0",
    "gn:admin2_code":"621.0",
    "gn:asciiname":"Vester Vamdrup",
    "gn:country_code":"DK",
    "gn:dem":38,
    "gn:feature_class":"P",
    "gn:feature_code":"PPL",
    "gn:name":"Vester Vamdrup",
    "gn:population":0,
    "gn:timezone":"Europe/Copenhagen",
    "iso:country":"DK",
    "wof:name":"Vester Vamdrup",
    "wof:placetype":"locality"
},
  "geometry": {"coordinates":[9.26307,55.43361],"type":"Point"}
}