{
  "type": "Feature",
  "properties": {
    "gn:admin1_code":"18.0",
    "gn:admin2_code":"760.0",
    "gn:asciiname":"Stadil",
    "gn:country_code":"DK",
    "gn:dem":4,
    "gn:feature_class":"P",
    "gn:feature_code":"PPL",
    "gn:name":"Stadil",
    "gn:population":0,
    "gn:timezone":"Europe/Copenhagen",
    "iso:country":"DK",
    "name:und_x_variant":[
        "Stadel",
        "Stadil"
    ],
    "wof:name":"Stadil",
    "wof:placetype":"locality"
},
  "geometry": {"coordinates":[8.21254,56.19732],"type":"Point"}
}