{
  "type": "Feature",
  "properties": {
    "gn:admin1_code":"17.0",
    "gn:admin2_code":"400.0",
    "gn:asciiname":"Tjorneby",
    "gn:country_code":"DK",
    "gn:dem":19,
    "gn:feature_class":"P",
    "gn:feature_code":"PPL",
    "gn:name":"Tj\u00f8rneby",
    "gn:population":0,
    "gn:timezone":"Europe/Copenhagen",
    "iso:country":"DK",
    "wof:name":"Tjorneby",
    "wof:placetype":"locality"
},
  "geometry": {"coordinates":[15.06448,55.01393],"type":"Point"}
}