{
  "type": "Feature",
  "properties": {
    "gn:admin1_code":"21.0",
    "gn:admin2_code":"420.0",
    "gn:asciiname":"Trunderup",
    "gn:country_code":"DK",
    "gn:dem":72,
    "gn:feature_class":"P",
    "gn:feature_code":"PPL",
    "gn:name":"Trunderup",
    "gn:population":0,
    "gn:timezone":"Europe/Copenhagen",
    "iso:country":"DK",
    "wof:name":"Trunderup",
    "wof:placetype":"locality"
},
  "geometry": {"coordinates":[10.1802,55.21836999999999],"type":"Point"}
}