{
  "type": "Feature",
  "properties": {
    "gn:admin1_code":"18.0",
    "gn:admin2_code":"791.0",
    "gn:asciiname":"Hobjerg",
    "gn:country_code":"DK",
    "gn:dem":54,
    "gn:feature_class":"P",
    "gn:feature_code":"PPL",
    "gn:name":"H\u00f8bjerg",
    "gn:population":0,
    "gn:timezone":"Europe/Copenhagen",
    "iso:country":"DK",
    "name:und_x_variant":[
        "H\u00f6bj\u00e6rg",
        "H\u00f8bjerg"
    ],
    "wof:name":"Hobjerg",
    "wof:placetype":"locality"
},
  "geometry": {"coordinates":[9.54232,56.33962],"type":"Point"}
}