{
  "type": "Feature",
  "properties": {
    "gn:admin1_code":"20.0",
    "gn:admin2_code":"376.0",
    "gn:asciiname":"Hullebaek",
    "gn:country_code":"DK",
    "gn:dem":11,
    "gn:feature_class":"P",
    "gn:feature_code":"PPL",
    "gn:name":"Hulleb\u00e6k",
    "gn:population":0,
    "gn:timezone":"Europe/Copenhagen",
    "iso:country":"DK",
    "wof:name":"Hullebaek",
    "wof:placetype":"locality"
},
  "geometry": {"coordinates":[11.92665,54.79956],"type":"Point"}
}