{
  "type": "Feature",
  "properties": {
    "gn:admin1_code":"18.0",
    "gn:admin2_code":"740.0",
    "gn:asciiname":"Ellerup",
    "gn:country_code":"DK",
    "gn:dem":61,
    "gn:feature_class":"P",
    "gn:feature_code":"PPL",
    "gn:name":"Ellerup",
    "gn:population":0,
    "gn:timezone":"Europe/Copenhagen",
    "iso:country":"DK",
    "wof:name":"Ellerup",
    "wof:placetype":"locality"
},
  "geometry": {"coordinates":[9.76579,56.23031999999999],"type":"Point"}
}