{
  "type": "Feature",
  "properties": {
    "gn:admin1_code":"21.0",
    "gn:admin2_code":"430.0",
    "gn:asciiname":"Ravnshojgyden",
    "gn:country_code":"DK",
    "gn:dem":82,
    "gn:feature_class":"P",
    "gn:feature_code":"PPL",
    "gn:name":"Ravnsh\u00f8jgyden",
    "gn:population":0,
    "gn:timezone":"Europe/Copenhagen",
    "iso:country":"DK",
    "name:und_x_variant":[
        "Ravnsh\u00f6j",
        "Ravnsh\u00f6jgyde",
        "Ravnsh\u00f8jgyden"
    ],
    "wof:name":"Ravnshojgyden",
    "wof:placetype":"locality"
},
  "geometry": {"coordinates":[10.4645,55.27359000000001],"type":"Point"}
}