{
  "type": "Feature",
  "properties": {
    "gn:admin1_code":"18.0",
    "gn:admin2_code":"665.0",
    "gn:asciiname":"Vandborg",
    "gn:country_code":"DK",
    "gn:dem":17,
    "gn:feature_class":"P",
    "gn:feature_code":"PPL",
    "gn:name":"Vandborg",
    "gn:population":0,
    "gn:timezone":"Europe/Copenhagen",
    "iso:country":"DK",
    "wof:name":"Vandborg",
    "wof:placetype":"locality"
},
  "geometry": {"coordinates":[8.17742,56.5467],"type":"Point"}
}