{
  "type": "Feature",
  "properties": {
    "gn:admin1_code":"20.0",
    "gn:admin2_code":"265.0",
    "gn:asciiname":"Truelstrup",
    "gn:country_code":"DK",
    "gn:dem":40,
    "gn:feature_class":"P",
    "gn:feature_code":"PPL",
    "gn:name":"Truelstrup",
    "gn:population":0,
    "gn:timezone":"Europe/Copenhagen",
    "iso:country":"DK",
    "wof:name":"Truelstrup",
    "wof:placetype":"locality"
},
  "geometry": {"coordinates":[12.02564,55.53117],"type":"Point"}
}