{
  "type": "Feature",
  "properties": {
    "gn:admin1_code":"21.0",
    "gn:admin2_code":"480.0",
    "gn:asciiname":"Guldbjerg",
    "gn:country_code":"DK",
    "gn:dem":24,
    "gn:feature_class":"P",
    "gn:feature_code":"PPL",
    "gn:name":"Guldbjerg",
    "gn:population":0,
    "gn:timezone":"Europe/Copenhagen",
    "iso:country":"DK",
    "name:und_x_variant":[
        "Guldbj\u00e6rg",
        "Guldbjerg Kirke",
        "Guldbjerg"
    ],
    "wof:name":"Guldbjerg",
    "wof:placetype":"locality"
},
  "geometry": {"coordinates":[10.14822,55.53816],"type":"Point"}
}