{
  "type": "Feature",
  "properties": {
    "gn:admin1_code":"19.0",
    "gn:admin2_code":"813.0",
    "gn:asciiname":"Horby",
    "gn:country_code":"DK",
    "gn:dem":37,
    "gn:feature_class":"P",
    "gn:feature_code":"PPL",
    "gn:name":"H\u00f8rby",
    "gn:population":0,
    "gn:timezone":"Europe/Copenhagen",
    "iso:country":"DK",
    "name:und_x_variant":[
        "H\u00f6rby Stationsby",
        "H\u00f8rby"
    ],
    "wof:name":"Horby",
    "wof:placetype":"locality"
},
  "geometry": {"coordinates":[10.38249,57.32304],"type":"Point"}
}