{
  "type": "Feature",
  "properties": {
    "gn:admin1_code":"18.0",
    "gn:admin2_code":"760.0",
    "gn:asciiname":"Norby",
    "gn:country_code":"DK",
    "gn:dem":5,
    "gn:feature_class":"P",
    "gn:feature_code":"PPLL",
    "gn:name":"N\u00f8rby",
    "gn:population":0,
    "gn:timezone":"Europe/Copenhagen",
    "iso:country":"DK",
    "name:fra_x_preferred":[
        "Norby"
    ],
    "wof:name":"Norby",
    "wof:placetype":"locality"
},
  "geometry": {"coordinates":[8.1624,56.12596],"type":"Point"}
}