{
  "type": "Feature",
  "properties": {
    "gn:admin1_code":"18.0",
    "gn:admin2_code":"615.0",
    "gn:asciiname":"Toftum",
    "gn:country_code":"DK",
    "gn:dem":25,
    "gn:feature_class":"P",
    "gn:feature_code":"PPL",
    "gn:name":"Toftum",
    "gn:population":0,
    "gn:timezone":"Europe/Copenhagen",
    "iso:country":"DK",
    "wof:name":"Toftum",
    "wof:placetype":"locality"
},
  "geometry": {"coordinates":[9.99002,55.89485],"type":"Point"}
}