{
  "type": "Feature",
  "properties": {
    "gn:admin1_code":"18.0",
    "gn:admin2_code":"706.0",
    "gn:asciiname":"Farup",
    "gn:country_code":"DK",
    "gn:dem":17,
    "gn:feature_class":"P",
    "gn:feature_code":"PPL",
    "gn:name":"F\u00e5rup",
    "gn:population":0,
    "gn:timezone":"Europe/Copenhagen",
    "iso:country":"DK",
    "name:und_x_variant":[
        "Faarup",
        "F\u00e5rup"
    ],
    "wof:name":"Farup",
    "wof:placetype":"locality"
},
  "geometry": {"coordinates":[10.24944,56.36666],"type":"Point"}
}