{
  "type": "Feature",
  "properties": {
    "gn:admin1_code":"17.0",
    "gn:admin2_code":"260.0",
    "gn:asciiname":"Sverkilstrup",
    "gn:country_code":"DK",
    "gn:dem":8,
    "gn:feature_class":"P",
    "gn:feature_code":"PPL",
    "gn:name":"Sverkilstrup",
    "gn:population":0,
    "gn:timezone":"Europe/Copenhagen",
    "iso:country":"DK",
    "wof:name":"Sverkilstrup",
    "wof:placetype":"locality"
},
  "geometry": {"coordinates":[11.94093,55.97301],"type":"Point"}
}