{
  "type": "Feature",
  "properties": {
    "gn:admin1_code":"20.0",
    "gn:admin2_code":"370.0",
    "gn:asciiname":"Ollerup",
    "gn:country_code":"DK",
    "gn:dem":19,
    "gn:feature_class":"P",
    "gn:feature_code":"PPL",
    "gn:name":"\u00d8llerup",
    "gn:population":0,
    "gn:timezone":"Europe/Copenhagen",
    "iso:country":"DK",
    "name:dan_x_preferred":[
        "Ollerup"
    ],
    "name:nld_x_preferred":[
        "Ollerup"
    ],
    "name:spa_x_preferred":[
        "Ollerup"
    ],
    "name:swe_x_preferred":[
        "Ollerup"
    ],
    "wof:name":"Ollerup",
    "wof:placetype":"locality"
},
  "geometry": {"coordinates":[11.66966,55.26638000000001],"type":"Point"}
}