{
  "type": "Feature",
  "properties": {
    "gn:admin1_code":"20.0",
    "gn:admin2_code":"330.0",
    "gn:asciiname":"Eggeslevlille",
    "gn:country_code":"DK",
    "gn:dem":22,
    "gn:feature_class":"P",
    "gn:feature_code":"PPL",
    "gn:name":"Eggeslevlille",
    "gn:population":0,
    "gn:timezone":"Europe/Copenhagen",
    "iso:country":"DK",
    "wof:name":"Eggeslevlille",
    "wof:placetype":"locality"
},
  "geometry": {"coordinates":[11.36224,55.26266999999999],"type":"Point"}
}