{
  "type": "Feature",
  "properties": {
    "gn:admin1_code":"17.0",
    "gn:admin2_code":"250.0",
    "gn:asciiname":"Sundbylille",
    "gn:country_code":"DK",
    "gn:dem":18,
    "gn:feature_class":"P",
    "gn:feature_code":"PPL",
    "gn:name":"Sundbylille",
    "gn:population":0,
    "gn:timezone":"Europe/Copenhagen",
    "iso:country":"DK",
    "wof:name":"Sundbylille",
    "wof:placetype":"locality"
},
  "geometry": {"coordinates":[12.11844,55.83616],"type":"Point"}
}