{
  "type": "Feature",
  "properties": {
    "gn:admin1_code":"18.0",
    "gn:admin2_code":"730.0",
    "gn:asciiname":"Over Fussing",
    "gn:country_code":"DK",
    "gn:dem":63,
    "gn:feature_class":"P",
    "gn:feature_code":"PPL",
    "gn:name":"Over Fussing",
    "gn:population":0,
    "gn:timezone":"Europe/Copenhagen",
    "iso:country":"DK",
    "wof:name":"Over Fussing",
    "wof:placetype":"locality"
},
  "geometry": {"coordinates":[9.89379,56.48123],"type":"Point"}
}