{
  "type": "Feature",
  "properties": {
    "gn:admin1_code":"18.0",
    "gn:admin2_code":"661.0",
    "gn:asciiname":"Alstrup",
    "gn:country_code":"DK",
    "gn:dem":26,
    "gn:feature_class":"P",
    "gn:feature_code":"PPL",
    "gn:name":"Alstrup",
    "gn:population":0,
    "gn:timezone":"Europe/Copenhagen",
    "iso:country":"DK",
    "wof:name":"Alstrup",
    "wof:placetype":"locality"
},
  "geometry": {"coordinates":[8.56282,56.38992],"type":"Point"}
}