{
  "type": "Feature",
  "properties": {
    "gn:admin1_code":"18.0",
    "gn:admin2_code":"791.0",
    "gn:asciiname":"Rogenstrup",
    "gn:country_code":"DK",
    "gn:dem":44,
    "gn:feature_class":"P",
    "gn:feature_code":"PPL",
    "gn:name":"Rogenstrup",
    "gn:population":0,
    "gn:timezone":"Europe/Copenhagen",
    "iso:country":"DK",
    "wof:name":"Rogenstrup",
    "wof:placetype":"locality"
},
  "geometry": {"coordinates":[9.34887,56.49839],"type":"Point"}
}