{
  "type": "Feature",
  "properties": {
    "gn:gn_country":"DK",
    "gn:gn_fcode":"PPL",
    "gn:gn_pop":0,
    "iso:country":"DK",
    "name:dan_x_preferred":[
        "\u00d8lby Lyng"
    ],
    "name:eng_x_preferred":[
        "\u00d8lby"
    ],
    "qs_pg:aaroncc":"DK",
    "qs_pg:gn_country":"DK",
    "qs_pg:gn_fcode":"PPL",
    "qs_pg:gn_pop":0,
    "qs_pg:name":"\u00d8lby",
    "qs_pg:name_adm0":"Danmark",
    "qs_pg:name_adm1":"Sj\u00e6lland",
    "qs_pg:photos":7,
    "qs_pg:photos_1k":1,
    "qs_pg:photos_9k":1,
    "qs_pg:photos_9r":1,
    "qs_pg:photos_all":7,
    "qs_pg:photos_sr":1,
    "qs_pg:pop_sr":0,
    "qs_pg:qs_pg_placetype":"locality",
    "qs_pg:qs_pg_placetype_gp":"Town",
    "qs_pg:woe_adm0":23424796,
    "woe:adm0_id":23424796,
    "woe:name_adm0":"Danmark",
    "woe:name_adm1":"Sj\u00e6lland",
    "woe:placetype":"Town",
    "wof:name":"\u00d8lby",
    "wof:placetype":"locality"
},
  "geometry": {"coordinates":[12.14643,55.48527],"type":"Point"}
}