{
  "type": "Feature",
  "properties": {
    "gn:admin1_code":"20.0",
    "gn:admin2_code":"330.0",
    "gn:asciiname":"Hemmeshoj",
    "gn:country_code":"DK",
    "gn:dem":8,
    "gn:feature_class":"P",
    "gn:feature_code":"PPL",
    "gn:name":"Hemmesh\u00f8j",
    "gn:population":0,
    "gn:timezone":"Europe/Copenhagen",
    "iso:country":"DK",
    "name:und_x_variant":[
        "Hemmershoi",
        "Hemmesh\u00f8j"
    ],
    "wof:name":"Hemmeshoj",
    "wof:placetype":"locality"
},
  "geometry": {"coordinates":[11.29146,55.34544],"type":"Point"}
}