{
  "type": "Feature",
  "properties": {
    "gn:admin1_code":"20.0",
    "gn:admin2_code":"330.0",
    "gn:asciiname":"Vemmelose",
    "gn:country_code":"DK",
    "gn:dem":37,
    "gn:feature_class":"P",
    "gn:feature_code":"PPL",
    "gn:name":"Vemmel\u00f8se",
    "gn:population":0,
    "gn:timezone":"Europe/Copenhagen",
    "iso:country":"DK",
    "wof:name":"Vemmelose",
    "wof:placetype":"locality"
},
  "geometry": {"coordinates":[11.42172,55.29912],"type":"Point"}
}