{
  "type": "Feature",
  "properties": {
    "gn:gn_country":"DK",
    "gn:gn_fcode":"PPL",
    "gn:gn_pop":0,
    "iso:country":"DK",
    "name:dan_x_preferred":[
        "Snogeb\u00e6k"
    ],
    "name:deu_x_preferred":[
        "Snogeb\u00e6k"
    ],
    "name:eng_x_preferred":[
        "Snogeb\u00e6k"
    ],
    "name:fra_x_preferred":[
        "Snogeb\u00e6k"
    ],
    "name:nld_x_preferred":[
        "Snogeb\u00e6k"
    ],
    "name:swe_x_preferred":[
        "Snogeb\u00e6k"
    ],
    "name:unk_x_variant":[
        "Snogeb\u00e4k"
    ],
    "qs_pg:aaroncc":"DK",
    "qs_pg:gn_country":"DK",
    "qs_pg:gn_fcode":"PPL",
    "qs_pg:gn_pop":0,
    "qs_pg:name":"Snogeb\u00e6k",
    "qs_pg:name_adm0":"Danmark",
    "qs_pg:name_adm1":"Hovedstaden",
    "qs_pg:photos":104,
    "qs_pg:photos_1k":21,
    "qs_pg:photos_9k":1,
    "qs_pg:photos_9r":3,
    "qs_pg:photos_all":104,
    "qs_pg:photos_sr":3,
    "qs_pg:pop_sr":0,
    "qs_pg:qs_pg_placetype":"locality",
    "qs_pg:qs_pg_placetype_gp":"Town",
    "qs_pg:woe_adm0":23424796,
    "woe:adm0_id":23424796,
    "woe:name_adm0":"Danmark",
    "woe:name_adm1":"Hovedstaden",
    "woe:placetype":"Town",
    "wof:name":"Snogeb\u00e6k",
    "wof:placetype":"locality"
},
  "geometry": {"coordinates":[15.11738,55.02551],"type":"Point"}
}