{
  "type": "Feature",
  "properties": {
    "gn:admin1_code":"18.0",
    "gn:admin2_code":"727.0",
    "gn:asciiname":"Kysing",
    "gn:country_code":"DK",
    "gn:dem":8,
    "gn:feature_class":"P",
    "gn:feature_code":"PPL",
    "gn:name":"Kysing",
    "gn:population":0,
    "gn:timezone":"Europe/Copenhagen",
    "iso:country":"DK",
    "wof:name":"Kysing",
    "wof:placetype":"locality"
},
  "geometry": {"coordinates":[10.25761,56.00692],"type":"Point"}
}