{
  "type": "Feature",
  "properties": {
    "gn:admin1_code":"18.0",
    "gn:admin2_code":"665.0",
    "gn:asciiname":"Langerhuse",
    "gn:cc2":"DK",
    "gn:country_code":"DK",
    "gn:dem":1,
    "gn:feature_class":"P",
    "gn:feature_code":"PPL",
    "gn:name":"Langerhuse",
    "gn:population":0,
    "gn:timezone":"Europe/Copenhagen",
    "iso:country":"DK",
    "name:und_x_variant":[
        "Langer"
    ],
    "wof:name":"Langerhuse",
    "wof:placetype":"locality"
},
  "geometry": {"coordinates":[8.16005,56.62869],"type":"Point"}
}