{
  "type": "Feature",
  "properties": {
    "gn:admin1_code":"20.0",
    "gn:admin2_code":"320.0",
    "gn:asciiname":"Store Toroje",
    "gn:country_code":"DK",
    "gn:dem":15,
    "gn:feature_class":"P",
    "gn:feature_code":"PPL",
    "gn:name":"Store Tor\u00f8je",
    "gn:population":0,
    "gn:timezone":"Europe/Copenhagen",
    "iso:country":"DK",
    "name:und_x_variant":[
        "T\u00e5r\u00f8je",
        "Store Tor\u00f8je"
    ],
    "wof:name":"Store Toroje",
    "wof:placetype":"locality"
},
  "geometry": {"coordinates":[12.26052,55.27334000000001],"type":"Point"}
}