{
  "type": "Feature",
  "properties": {
    "gn:admin1_code":"20.0",
    "gn:admin2_code":"320.0",
    "gn:asciiname":"Mosebolle",
    "gn:country_code":"DK",
    "gn:dem":9,
    "gn:feature_class":"P",
    "gn:feature_code":"PPL",
    "gn:name":"Moseb\u00f8lle",
    "gn:population":0,
    "gn:timezone":"Europe/Copenhagen",
    "iso:country":"DK",
    "wof:name":"Mosebolle",
    "wof:placetype":"locality"
},
  "geometry": {"coordinates":[12.05871,55.18528000000001],"type":"Point"}
}