{
  "type": "Feature",
  "properties": {
    "gn:admin1_code":"21.0",
    "gn:admin2_code":"630.0",
    "gn:asciiname":"Hastrup",
    "gn:country_code":"DK",
    "gn:dem":57,
    "gn:feature_class":"P",
    "gn:feature_code":"PPL",
    "gn:name":"H\u00e5strup",
    "gn:population":0,
    "gn:timezone":"Europe/Copenhagen",
    "iso:country":"DK",
    "name:und_x_variant":[
        "Haastrup",
        "H\u00e5strup"
    ],
    "wof:name":"Hastrup",
    "wof:placetype":"locality"
},
  "geometry": {"coordinates":[9.549,55.59235],"type":"Point"}
}