{
  "type": "Feature",
  "properties": {
    "gn:admin1_code":"19.0",
    "gn:admin2_code":"787.0",
    "gn:asciiname":"Kjaestrup",
    "gn:country_code":"DK",
    "gn:dem":20,
    "gn:feature_class":"P",
    "gn:feature_code":"PPL",
    "gn:name":"Kj\u00e6strup",
    "gn:population":0,
    "gn:timezone":"Europe/Copenhagen",
    "iso:country":"DK",
    "name:und_x_variant":[
        "K\u00e6strup",
        "Kj\u00e6strup"
    ],
    "wof:name":"Kjaestrup",
    "wof:placetype":"locality"
},
  "geometry": {"coordinates":[8.4621,56.77743],"type":"Point"}
}