{
  "type": "Feature",
  "properties": {
    "gn:admin1_code":"18.0",
    "gn:admin2_code":"706.0",
    "gn:asciiname":"Skorring",
    "gn:country_code":"DK",
    "gn:dem":19,
    "gn:feature_class":"P",
    "gn:feature_code":"PPL",
    "gn:name":"Sk\u00f8rring",
    "gn:population":0,
    "gn:timezone":"Europe/Copenhagen",
    "iso:country":"DK",
    "wof:name":"Skorring",
    "wof:placetype":"locality"
},
  "geometry": {"coordinates":[10.27584,56.36266],"type":"Point"}
}