{
  "type": "Feature",
  "properties": {
    "gn:admin1_code":"19.0",
    "gn:admin2_code":"810.0",
    "gn:asciiname":"Kalum",
    "gn:country_code":"DK",
    "gn:dem":26,
    "gn:feature_class":"P",
    "gn:feature_code":"PPL",
    "gn:name":"Kalum",
    "gn:population":0,
    "gn:timezone":"Europe/Copenhagen",
    "iso:country":"DK",
    "wof:name":"Kalum",
    "wof:placetype":"locality"
},
  "geometry": {"coordinates":[9.96095,57.32052],"type":"Point"}
}