{
  "type": "Feature",
  "properties": {
    "gn:admin1_code":"19.0",
    "gn:admin2_code":"787.0",
    "gn:asciiname":"Kjelstrup",
    "gn:country_code":"DK",
    "gn:dem":11,
    "gn:feature_class":"P",
    "gn:feature_code":"PPL",
    "gn:name":"Kjelstrup",
    "gn:population":0,
    "gn:timezone":"Europe/Copenhagen",
    "iso:country":"DK",
    "name:und_x_variant":[
        "Kjeldstrup",
        "Kelstrup",
        "Kjelstrup"
    ],
    "wof:name":"Kjelstrup",
    "wof:placetype":"locality"
},
  "geometry": {"coordinates":[8.75313,56.99389],"type":"Point"}
}