{
  "type": "Feature",
  "properties": {
    "gn:admin1_code":"19.0",
    "gn:admin2_code":"820.0",
    "gn:asciiname":"Vilsted",
    "gn:country_code":"DK",
    "gn:dem":12,
    "gn:feature_class":"P",
    "gn:feature_code":"PPL",
    "gn:name":"Vilsted",
    "gn:population":0,
    "gn:timezone":"Europe/Copenhagen",
    "iso:country":"DK",
    "wof:name":"Vilsted",
    "wof:placetype":"locality"
},
  "geometry": {"coordinates":[9.28576,56.90428000000001],"type":"Point"}
}