{
  "type": "Feature",
  "properties": {
    "gn:admin1_code":"18.0",
    "gn:admin2_code":"760.0",
    "gn:asciiname":"Grimstrup",
    "gn:country_code":"DK",
    "gn:dem":21,
    "gn:feature_class":"P",
    "gn:feature_code":"PPLL",
    "gn:name":"Grimstrup",
    "gn:population":0,
    "gn:timezone":"Europe/Copenhagen",
    "iso:country":"DK",
    "wof:name":"Grimstrup",
    "wof:placetype":"locality"
},
  "geometry": {"coordinates":[8.36258,56.12721],"type":"Point"}
}