{
  "type": "Feature",
  "properties": {
    "gn:population":2045,
    "iso:country":"DK",
    "name:bul_x_preferred":[
        "\u0412\u0438\u043d\u0434\u0438\u043d\u0433\u0435"
    ],
    "name:ceb_x_preferred":[
        "Vindinge"
    ],
    "name:dan_x_preferred":[
        "Vindinge"
    ],
    "name:eng_x_preferred":[
        "Vindinge"
    ],
    "name:fas_x_preferred":[
        "\u0648\u06cc\u0646\u062f\u06cc\u0646\u06af"
    ],
    "name:nld_x_preferred":[
        "Vindinge"
    ],
    "name:spa_x_preferred":[
        "Vindinge"
    ],
    "name:swe_x_preferred":[
        "Vindinge"
    ],
    "qs:a0":"Danmark",
    "qs:a1":"*Sj\u00e6lland",
    "qs:a1r":"0",
    "qs:adm0":"Danmark",
    "qs:la_lc":"*",
    "qs:level":"locality",
    "qs:loc":"Vindinge",
    "qs:loc_alt":"Vindinge",
    "qs:pop":0,
    "qs:type":"buffered point",
    "wof:name":"Vindinge",
    "wof:placetype":"locality",
    "wof:population":2045
},
  "geometry": {"coordinates":[12.12598,55.622521],"type":"Point"}
}