{
  "type": "Feature",
  "properties": {
    "gn:admin1_code":"18.0",
    "gn:admin2_code":"710.0",
    "gn:asciiname":"Hvorslev",
    "gn:country_code":"DK",
    "gn:dem":71,
    "gn:feature_class":"P",
    "gn:feature_code":"PPL",
    "gn:name":"Hvorslev",
    "gn:population":0,
    "gn:timezone":"Europe/Copenhagen",
    "iso:country":"DK",
    "name:dan_x_preferred":[
        "Hvorslev Kommune"
    ],
    "name:deu_x_preferred":[
        "Hvorslev Kommune"
    ],
    "name:fao_x_preferred":[
        "Hvorslev kommuna"
    ],
    "name:ita_x_preferred":[
        "Hvorslev"
    ],
    "name:nld_x_preferred":[
        "Hvorslev"
    ],
    "name:nor_x_preferred":[
        "Hvorslev kommune"
    ],
    "name:pol_x_preferred":[
        "Gmina Hvorslev"
    ],
    "name:por_x_preferred":[
        "Hvorslev"
    ],
    "name:ron_x_preferred":[
        "Comuna Hvorslev"
    ],
    "name:swe_x_preferred":[
        "Hvorslevs kommun"
    ],
    "name:und_x_variant":[
        "Horslev"
    ],
    "wof:name":"Hvorslev",
    "wof:placetype":"locality"
},
  "geometry": {"coordinates":[9.76722,56.36664],"type":"Point"}
}