{
  "type": "Feature",
  "properties": {
    "gn:admin1_code":"21.0",
    "gn:admin2_code":"440.0",
    "gn:asciiname":"Hersnap",
    "gn:country_code":"DK",
    "gn:dem":20,
    "gn:feature_class":"P",
    "gn:feature_code":"PPL",
    "gn:name":"Hersnap",
    "gn:population":0,
    "gn:timezone":"Europe/Copenhagen",
    "iso:country":"DK",
    "wof:name":"Hersnap",
    "wof:placetype":"locality"
},
  "geometry": {"coordinates":[10.6758,55.52169],"type":"Point"}
}