{
  "type": "Feature",
  "properties": {
    "iso:country":"DK",
    "qs_pg:aaroncc":"DK",
    "qs_pg:name":"T\u00f8rslev Hage",
    "qs_pg:name_adm0":"Danmark",
    "qs_pg:name_adm1":"Hovedstaden",
    "qs_pg:photos":26,
    "qs_pg:photos_1k":5,
    "qs_pg:photos_9k":1,
    "qs_pg:photos_9r":2,
    "qs_pg:photos_all":26,
    "qs_pg:photos_sr":2,
    "qs_pg:pop_sr":0,
    "qs_pg:qs_pg_placetype":"locality",
    "qs_pg:qs_pg_placetype_gp":"Town",
    "qs_pg:woe_adm0":23424796,
    "woe:adm0_id":23424796,
    "woe:name_adm0":"Danmark",
    "woe:name_adm1":"Hovedstaden",
    "woe:placetype":"Town",
    "wof:name":"T\u00f8rslev Hage",
    "wof:placetype":"locality"
},
  "geometry": {"coordinates":[12.065833,55.8179965],"type":"Point"}
}