{
  "type": "Feature",
  "properties": {
    "gn:admin1_code":"21.0",
    "gn:admin2_code":"440.0",
    "gn:asciiname":"Birkebjerg",
    "gn:country_code":"DK",
    "gn:dem":18,
    "gn:feature_class":"P",
    "gn:feature_code":"PPL",
    "gn:name":"Birkebjerg",
    "gn:population":0,
    "gn:timezone":"Europe/Copenhagen",
    "iso:country":"DK",
    "name:und_x_variant":[
        "Birkebj\u00e6rg",
        "Birkebjerg"
    ],
    "wof:name":"Birkebjerg",
    "wof:placetype":"locality"
},
  "geometry": {"coordinates":[10.68813,55.51371],"type":"Point"}
}