{
  "type": "Feature",
  "properties": {
    "gn:admin1_code":"18.0",
    "gn:admin2_code":"779.0",
    "gn:asciiname":"Hasum",
    "gn:country_code":"DK",
    "gn:dem":10,
    "gn:feature_class":"P",
    "gn:feature_code":"PPL",
    "gn:name":"H\u00e5sum",
    "gn:population":0,
    "gn:timezone":"Europe/Copenhagen",
    "iso:country":"DK",
    "name:und_x_variant":[
        "Haasum",
        "H\u00e5sum"
    ],
    "wof:name":"Hasum",
    "wof:placetype":"locality"
},
  "geometry": {"coordinates":[8.8506,56.57816],"type":"Point"}
}