{
  "type": "Feature",
  "properties": {
    "gn:admin1_code":"20.0",
    "gn:admin2_code":"376.0",
    "gn:asciiname":"Nagelsti",
    "gn:country_code":"DK",
    "gn:dem":4,
    "gn:feature_class":"P",
    "gn:feature_code":"PPL",
    "gn:name":"Nagelsti",
    "gn:population":0,
    "gn:timezone":"Europe/Copenhagen",
    "iso:country":"DK",
    "name:ceb_x_preferred":[
        "Nagelsti"
    ],
    "name:dan_x_preferred":[
        "Nagelsti"
    ],
    "name:nld_x_preferred":[
        "Nagelsti"
    ],
    "name:swe_x_preferred":[
        "Nagelsti"
    ],
    "wof:name":"Nagelsti",
    "wof:placetype":"locality"
},
  "geometry": {"coordinates":[11.84497,54.74757],"type":"Point"}
}