{
  "type": "Feature",
  "properties": {
    "gn:admin1_code":"18.0",
    "gn:admin2_code":"791.0",
    "gn:asciiname":"Orum Sondermark",
    "gn:country_code":"DK",
    "gn:dem":31,
    "gn:feature_class":"P",
    "gn:feature_code":"PPLL",
    "gn:name":"\u00d8rum S\u00f8ndermark",
    "gn:population":0,
    "gn:timezone":"Europe/Copenhagen",
    "iso:country":"DK",
    "name:und_x_variant":[
        "S\u00f6ndermark",
        "\u00d8rum S\u00f8ndermark"
    ],
    "wof:name":"Orum Sondermark",
    "wof:placetype":"locality"
},
  "geometry": {"coordinates":[9.64339,56.47061],"type":"Point"}
}