{
  "type": "Feature",
  "properties": {
    "gn:admin1_code":"17.0",
    "gn:admin2_code":"217.0",
    "gn:asciiname":"Horneby",
    "gn:country_code":"DK",
    "gn:dem":15,
    "gn:feature_class":"P",
    "gn:feature_code":"PPL",
    "gn:name":"Horneby",
    "gn:population":0,
    "gn:timezone":"Europe/Copenhagen",
    "iso:country":"DK",
    "wof:name":"Horneby",
    "wof:placetype":"locality"
},
  "geometry": {"coordinates":[12.45632,56.08115],"type":"Point"}
}