{
  "type": "Feature",
  "properties": {
    "gn:admin1_code":"21.0",
    "gn:admin2_code":"630.0",
    "gn:asciiname":"Lindet",
    "gn:country_code":"DK",
    "gn:dem":79,
    "gn:feature_class":"P",
    "gn:feature_code":"PPL",
    "gn:name":"Lindet",
    "gn:population":0,
    "gn:timezone":"Europe/Copenhagen",
    "iso:country":"DK",
    "wof:name":"Lindet",
    "wof:placetype":"locality"
},
  "geometry": {"coordinates":[9.31797,55.90108000000001],"type":"Point"}
}