{
  "type": "Feature",
  "properties": {
    "gn:admin1_code":"18.0",
    "gn:admin2_code":"760.0",
    "gn:asciiname":"Sundhuse",
    "gn:country_code":"DK",
    "gn:dem":0,
    "gn:feature_class":"P",
    "gn:feature_code":"PPL",
    "gn:name":"Sundhuse",
    "gn:population":0,
    "gn:timezone":"Europe/Copenhagen",
    "iso:country":"DK",
    "wof:name":"Sundhuse",
    "wof:placetype":"locality"
},
  "geometry": {"coordinates":[8.15,56.25],"type":"Point"}
}