{
  "type": "Feature",
  "properties": {
    "gn:admin1_code":"18.0",
    "gn:admin2_code":"779.0",
    "gn:asciiname":"Vester Lem",
    "gn:country_code":"DK",
    "gn:dem":30,
    "gn:feature_class":"P",
    "gn:feature_code":"PPL",
    "gn:name":"Vester Lem",
    "gn:population":0,
    "gn:timezone":"Europe/Copenhagen",
    "iso:country":"DK",
    "wof:name":"Vester Lem",
    "wof:placetype":"locality"
},
  "geometry": {"coordinates":[8.75612,56.58419],"type":"Point"}
}