{
  "type": "Feature",
  "properties": {
    "gn:admin1_code":"20.0",
    "gn:admin2_code":"326.0",
    "gn:asciiname":"Tindingebanke",
    "gn:country_code":"DK",
    "gn:dem":42,
    "gn:feature_class":"P",
    "gn:feature_code":"PPL",
    "gn:name":"Tindingebanke",
    "gn:population":0,
    "gn:timezone":"Europe/Copenhagen",
    "iso:country":"DK",
    "wof:name":"Tindingebanke",
    "wof:placetype":"locality"
},
  "geometry": {"coordinates":[11.36503,55.52192],"type":"Point"}
}