{
  "type": "Feature",
  "properties": {
    "gn:admin1_code":"21.0",
    "gn:admin2_code":"480.0",
    "gn:asciiname":"Rosendal",
    "gn:country_code":"DK",
    "gn:dem":12,
    "gn:feature_class":"P",
    "gn:feature_code":"PPL",
    "gn:name":"Rosendal",
    "gn:population":0,
    "gn:timezone":"Europe/Copenhagen",
    "iso:country":"DK",
    "wof:name":"Rosendal",
    "wof:placetype":"locality"
},
  "geometry": {"coordinates":[10.33333,55.46666999999999],"type":"Point"}
}