{
  "type": "Feature",
  "properties": {
    "gn:country":"DK",
    "gn:fcode":"PPLX",
    "gn:population":14845,
    "iso:country":"DK",
    "name:ceb_x_preferred":[
        "Solr\u00f8d Strand"
    ],
    "name:dan_x_preferred":[
        "Solr\u00f8d Strand"
    ],
    "name:msa_x_preferred":[
        "Solr\u00f8d Strand"
    ],
    "name:nld_x_preferred":[
        "Solr\u00f8d Strand"
    ],
    "name:nor_x_preferred":[
        "Solr\u00f8d Strand"
    ],
    "name:pol_x_preferred":[
        "Solr\u00f8d Strand"
    ],
    "name:spa_x_preferred":[
        "Solr\u00f8d Strand"
    ],
    "name:srp_x_preferred":[
        "\u0421\u043e\u043b\u0440\u0435\u0434 \u0421\u0442\u0440\u0430\u043d\u0434"
    ],
    "name:swe_x_preferred":[
        "Solr\u00f8d Strand"
    ],
    "qs_pg:aaroncc":"DK",
    "qs_pg:gn_country":"DK",
    "qs_pg:gn_fcode":"PPLX",
    "qs_pg:gn_pop":14845,
    "qs_pg:name":"Solr\u00f8d Strand",
    "qs_pg:photos_9r":0,
    "qs_pg:photos_sr":0,
    "qs_pg:pop_sr":6,
    "qs_pg:qs_pg_placetype":"neighbourhood",
    "wof:name":"Solr\u00f8d Strand",
    "wof:placetype":"neighbourhood",
    "wof:population":14845
},
  "geometry": {"coordinates":[12.22227,55.53285],"type":"Point"}
}