{
  "type": "Feature",
  "properties": {
    "gn:gn_country":"DK",
    "gn:gn_fcode":"PPLX",
    "gn:gn_pop":14845,
    "gn:population":14845,
    "iso:country":"DK",
    "qs_pg:aaroncc":"DK",
    "qs_pg:gn_country":"DK",
    "qs_pg:gn_fcode":"PPLX",
    "qs_pg:gn_pop":14845,
    "qs_pg:name":"Solr\u00f8d Strand",
    "qs_pg:photos_9r":0,
    "qs_pg:photos_sr":0,
    "qs_pg:pop_sr":6,
    "qs_pg:qs_pg_placetype":"neighbourhood",
    "wof:name":"Solr\u00f8d Strand",
    "wof:placetype":"neighbourhood",
    "wof:population":14845
},
  "geometry": {"coordinates":[12.22227,55.53285],"type":"Point"}
}