{
  "type": "Feature",
  "properties": {
    "gn:admin1_code":"21.0",
    "gn:admin2_code":"430.0",
    "gn:asciiname":"Munke",
    "gn:country_code":"DK",
    "gn:dem":7,
    "gn:feature_class":"P",
    "gn:feature_code":"PPL",
    "gn:name":"Munke",
    "gn:population":0,
    "gn:timezone":"Europe/Copenhagen",
    "iso:country":"DK",
    "name:und_x_variant":[
        "Munkeby",
        "Munk\u00f8",
        "Munke"
    ],
    "wof:name":"Munke",
    "wof:placetype":"locality"
},
  "geometry": {"coordinates":[10.27219,55.02343000000001],"type":"Point"}
}