{
  "type": "Feature",
  "properties": {
    "gn:admin1_code":"19.0",
    "gn:admin2_code":"840.0",
    "gn:asciiname":"Store Binderup",
    "gn:country_code":"DK",
    "gn:dem":27,
    "gn:feature_class":"P",
    "gn:feature_code":"PPL",
    "gn:name":"Store Binderup",
    "gn:population":0,
    "gn:timezone":"Europe/Copenhagen",
    "iso:country":"DK",
    "name:und_x_variant":[
        "Binderup",
        "Store Binderup"
    ],
    "wof:name":"Store Binderup",
    "wof:placetype":"locality"
},
  "geometry": {"coordinates":[9.55935,56.76378],"type":"Point"}
}