{
  "type": "Feature",
  "properties": {
    "gn:admin1_code":"21.0",
    "gn:admin2_code":"575.0",
    "gn:asciiname":"Vester Gjerndrup",
    "gn:country_code":"DK",
    "gn:dem":48,
    "gn:feature_class":"P",
    "gn:feature_code":"PPL",
    "gn:name":"Vester Gjerndrup",
    "gn:population":0,
    "gn:timezone":"Europe/Copenhagen",
    "iso:country":"DK",
    "wof:name":"Vester Gjerndrup",
    "wof:placetype":"locality"
},
  "geometry": {"coordinates":[9.00472,55.5167],"type":"Point"}
}