{
  "type": "Feature",
  "properties": {
    "gn:admin1_code":"19.0",
    "gn:admin2_code":"849.0",
    "gn:asciiname":"Oster Rendbaek",
    "gn:country_code":"DK",
    "gn:dem":4,
    "gn:feature_class":"P",
    "gn:feature_code":"PPL",
    "gn:name":"\u00d8ster Rendb\u00e6k",
    "gn:population":0,
    "gn:timezone":"Europe/Copenhagen",
    "iso:country":"DK",
    "wof:name":"Oster Rendbaek",
    "wof:placetype":"locality"
},
  "geometry": {"coordinates":[9.73317,57.23483],"type":"Point"}
}