{
  "type": "Feature",
  "properties": {
    "gn:admin1_code":"20.0",
    "gn:admin2_code":"360.0",
    "gn:asciiname":"Dannemare",
    "gn:country_code":"DK",
    "gn:dem":4,
    "gn:feature_class":"P",
    "gn:feature_code":"PPL",
    "gn:name":"Dannemare",
    "gn:population":0,
    "gn:timezone":"Europe/Copenhagen",
    "iso:country":"DK",
    "name:cat_x_preferred":[
        "Dannemare"
    ],
    "name:ceb_x_preferred":[
        "Dannemare"
    ],
    "name:dan_x_preferred":[
        "Dannemare"
    ],
    "name:nld_x_preferred":[
        "Dannemare"
    ],
    "name:swe_x_preferred":[
        "Dannemare"
    ],
    "wof:name":"Dannemare",
    "wof:placetype":"locality"
},
  "geometry": {"coordinates":[11.18727,54.76245],"type":"Point"}
}