{
  "type": "Feature",
  "properties": {
    "gn:admin1_code":"18.0",
    "gn:admin2_code":"706.0",
    "gn:asciiname":"Smouen",
    "gn:country_code":"DK",
    "gn:dem":45,
    "gn:feature_class":"P",
    "gn:feature_code":"PPLL",
    "gn:name":"Smouen",
    "gn:population":0,
    "gn:timezone":"Europe/Copenhagen",
    "iso:country":"DK",
    "name:und_x_variant":[
        "Smogen",
        "Smouen"
    ],
    "wof:name":"Smouen",
    "wof:placetype":"locality"
},
  "geometry": {"coordinates":[10.46708,56.32624000000001],"type":"Point"}
}