{
  "type": "Feature",
  "properties": {
    "gn:admin1_code":"21.0",
    "gn:admin2_code":"540.0",
    "gn:asciiname":"Katryde",
    "gn:cc2":"DK",
    "gn:country_code":"DK",
    "gn:dem":44,
    "gn:feature_class":"P",
    "gn:feature_code":"PPL",
    "gn:name":"Katryde",
    "gn:population":0,
    "gn:timezone":"Europe/Copenhagen",
    "iso:country":"DK",
    "name:und_x_variant":[
        "Katr\u00f6d",
        "Katryde"
    ],
    "wof:name":"Katryde",
    "wof:placetype":"locality"
},
  "geometry": {"coordinates":[9.96667,54.98333],"type":"Point"}
}