{
  "type": "Feature",
  "properties": {
    "gn:admin1_code":"20.0",
    "gn:admin2_code":"390.0",
    "gn:asciiname":"Kong Firgarde",
    "gn:country_code":"DK",
    "gn:dem":6,
    "gn:feature_class":"P",
    "gn:feature_code":"PPL",
    "gn:name":"K\u00f8ng Firg\u00e5rde",
    "gn:population":0,
    "gn:timezone":"Europe/Copenhagen",
    "iso:country":"DK",
    "name:und_x_variant":[
        "Firgaarde",
        "K\u00f8ng Fireg\u00e5rde",
        "K\u00f8ng Fireg\u00e5rd",
        "K\u00f6ng Firgaarde",
        "K\u00f8ng Firg\u00e5rde"
    ],
    "wof:name":"Kong Firgarde",
    "wof:placetype":"locality"
},
  "geometry": {"coordinates":[11.82719,55.09336999999999],"type":"Point"}
}