{
  "type": "Feature",
  "properties": {
    "gn:admin1_code":"21.0",
    "gn:admin2_code":"540.0",
    "gn:asciiname":"Iller",
    "gn:country_code":"DK",
    "gn:dem":28,
    "gn:feature_class":"P",
    "gn:feature_code":"PPL",
    "gn:name":"Iller",
    "gn:population":0,
    "gn:timezone":"Europe/Copenhagen",
    "iso:country":"DK",
    "name:aze_x_preferred":[
        "\u0130ller \u00e7ay\u0131"
    ],
    "name:bul_x_preferred":[
        "\u0418\u043b\u0435\u0440"
    ],
    "name:ceb_x_preferred":[
        "Iller"
    ],
    "name:ces_x_preferred":[
        "Iller"
    ],
    "name:chv_x_preferred":[
        "\u0418\u043b\u043b\u0435\u0440"
    ],
    "name:dan_x_preferred":[
        "Iller"
    ],
    "name:deu_x_preferred":[
        "Iller"
    ],
    "name:ell_x_preferred":[
        "\u038a\u03bb\u03bb\u03b5\u03c1"
    ],
    "name:epo_x_preferred":[
        "Iller"
    ],
    "name:eus_x_preferred":[
        "Iller ibaia"
    ],
    "name:fin_x_preferred":[
        "Iller"
    ],
    "name:fra_x_preferred":[
        "Iller"
    ],
    "name:hrv_x_preferred":[
        "Iller"
    ],
    "name:hun_x_preferred":[
        "Iller"
    ],
    "name:ind_x_preferred":[
        "Sungai Iller"
    ],
    "name:ita_x_preferred":[
        "Iller"
    ],
    "name:kat_x_preferred":[
        "\u10d8\u10da\u10d4\u10e0\u10d8"
    ],
    "name:kor_x_preferred":[
        "\uc77c\ub7ec\uac15"
    ],
    "name:lit_x_preferred":[
        "Ileris"
    ],
    "name:mkd_x_preferred":[
        "\u0418\u043b\u0435\u0440"
    ],
    "name:nld_x_preferred":[
        "Iller"
    ],
    "name:nno_x_preferred":[
        "Iller"
    ],
    "name:nor_x_preferred":[
        "Iller"
    ],
    "name:pnb_x_preferred":[
        "\u0627\u0644\u0631"
    ],
    "name:pol_x_preferred":[
        "Iller"
    ],
    "name:por_x_preferred":[
        "Rio Iller"
    ],
    "name:ron_x_preferred":[
        "Iller"
    ],
    "name:rus_x_preferred":[
        "\u0418\u043b\u043b\u0435\u0440"
    ],
    "name:slk_x_preferred":[
        "Iller"
    ],
    "name:spa_x_preferred":[
        "R\u00edo Iller"
    ],
    "name:swe_x_preferred":[
        "Iller"
    ],
    "name:tuk_x_preferred":[
        "Iller"
    ],
    "name:tur_x_preferred":[
        "\u0130ller Nehri"
    ],
    "name:ukr_x_preferred":[
        "\u0406\u043b\u043b\u0435\u0440"
    ],
    "name:wuu_x_preferred":[
        "\u4f0a\u52d2\u6cb3"
    ],
    "name:zho_x_preferred":[
        "\u4f0a\u52d2\u6cb3"
    ],
    "wof:name":"Iller",
    "wof:placetype":"locality"
},
  "geometry": {"coordinates":[9.6626,54.86991],"type":"Point"}
}