{
  "type": "Feature",
  "properties": {
    "gn:admin1_code":"21.0",
    "gn:admin2_code":"482.0",
    "gn:asciiname":"Tressebolle",
    "gn:country_code":"DK",
    "gn:dem":16,
    "gn:feature_class":"P",
    "gn:feature_code":"PPL",
    "gn:name":"Tresseb\u00f8lle",
    "gn:population":0,
    "gn:timezone":"Europe/Copenhagen",
    "iso:country":"DK",
    "wof:name":"Tressebolle",
    "wof:placetype":"locality"
},
  "geometry": {"coordinates":[10.89712,55.06462],"type":"Point"}
}