{
  "type": "Feature",
  "properties": {
    "gn:admin1_code":"18.0",
    "gn:admin2_code":"751.0",
    "gn:asciiname":"Bjostrup",
    "gn:country_code":"DK",
    "gn:dem":69,
    "gn:feature_class":"P",
    "gn:feature_code":"PPL",
    "gn:name":"Bj\u00f8strup",
    "gn:population":0,
    "gn:timezone":"Europe/Copenhagen",
    "iso:country":"DK",
    "name:und_x_variant":[
        "Bj\u00f6dstrup",
        "Bj\u00f8strup"
    ],
    "wof:name":"Bjostrup",
    "wof:placetype":"locality"
},
  "geometry": {"coordinates":[10.16436,56.1016],"type":"Point"}
}