{
  "type": "Feature",
  "properties": {
    "gn:admin1_code":"17.0",
    "gn:admin2_code":"400.0",
    "gn:asciiname":"Smorenge",
    "gn:country_code":"DK",
    "gn:dem":67,
    "gn:feature_class":"P",
    "gn:feature_code":"PPL",
    "gn:name":"Sm\u00f8renge",
    "gn:population":0,
    "gn:timezone":"Europe/Copenhagen",
    "iso:country":"DK",
    "name:und_x_variant":[
        "Sm\u00f6renge Gaarde",
        "Sm\u00f8renge"
    ],
    "wof:name":"Smorenge",
    "wof:placetype":"locality"
},
  "geometry": {"coordinates":[14.86438,55.08165],"type":"Point"}
}