{
  "type": "Feature",
  "properties": {
    "gn:admin1_code":"19.0",
    "gn:admin2_code":"849.0",
    "gn:asciiname":"Gottrup",
    "gn:country_code":"DK",
    "gn:dem":14,
    "gn:feature_class":"P",
    "gn:feature_code":"PPL",
    "gn:name":"G\u00f8ttrup",
    "gn:population":0,
    "gn:timezone":"Europe/Copenhagen",
    "iso:country":"DK",
    "name:und_x_variant":[
        "Gi\u00f6ttrup",
        "G\u00f8ttrup"
    ],
    "wof:name":"Gottrup",
    "wof:placetype":"locality"
},
  "geometry": {"coordinates":[9.21148,57.05853000000001],"type":"Point"}
}