{
  "type": "Feature",
  "properties": {
    "gn:admin1_code":"18.0",
    "gn:admin2_code":"615.0",
    "gn:asciiname":"Burgarde",
    "gn:country_code":"DK",
    "gn:dem":121,
    "gn:feature_class":"P",
    "gn:feature_code":"PPL",
    "gn:name":"Burg\u00e5rde",
    "gn:population":0,
    "gn:timezone":"Europe/Copenhagen",
    "iso:country":"DK",
    "name:und_x_variant":[
        "Burgaarde",
        "Burg\u00e5rde"
    ],
    "wof:name":"Burgarde",
    "wof:placetype":"locality"
},
  "geometry": {"coordinates":[9.59792,55.99672],"type":"Point"}
}