{
  "type": "Feature",
  "properties": {
    "gn:admin1_code":"21.0",
    "gn:admin2_code":"573.0",
    "gn:asciiname":"Tinghoj",
    "gn:country_code":"DK",
    "gn:dem":20,
    "gn:feature_class":"P",
    "gn:feature_code":"PPL",
    "gn:name":"Tingh\u00f8j",
    "gn:population":0,
    "gn:timezone":"Europe/Copenhagen",
    "iso:country":"DK",
    "wof:name":"Tinghoj",
    "wof:placetype":"locality"
},
  "geometry": {"coordinates":[8.46996,55.6603],"type":"Point"}
}