{
  "type": "Feature",
  "properties": {
    "gn:admin1_code":"20.0",
    "gn:admin2_code":"360.0",
    "gn:asciiname":"Magleskov Huse",
    "gn:country_code":"DK",
    "gn:dem":-2,
    "gn:feature_class":"P",
    "gn:feature_code":"PPL",
    "gn:name":"Magleskov Huse",
    "gn:population":0,
    "gn:timezone":"Europe/Copenhagen",
    "iso:country":"DK",
    "name:und_x_variant":[
        "Magleskov",
        "Magleskov Huse"
    ],
    "wof:name":"Magleskov Huse",
    "wof:placetype":"locality"
},
  "geometry": {"coordinates":[11.1868,54.72142],"type":"Point"}
}