{
  "type": "Feature",
  "properties": {
    "gn:admin1_code":"18.0",
    "gn:admin2_code":"766.0",
    "gn:asciiname":"Korshoj",
    "gn:country_code":"DK",
    "gn:dem":64,
    "gn:feature_class":"P",
    "gn:feature_code":"PPLL",
    "gn:name":"Korsh\u00f8j",
    "gn:population":0,
    "gn:timezone":"Europe/Copenhagen",
    "iso:country":"DK",
    "wof:name":"Korshoj",
    "wof:placetype":"locality"
},
  "geometry": {"coordinates":[9.69765,55.71948],"type":"Point"}
}