{
  "type": "Feature",
  "properties": {
    "gn:admin1_code":"19.0",
    "gn:admin2_code":"787.0",
    "gn:asciiname":"Gaerup",
    "gn:country_code":"DK",
    "gn:dem":22,
    "gn:feature_class":"P",
    "gn:feature_code":"PPL",
    "gn:name":"G\u00e6rup",
    "gn:population":0,
    "gn:timezone":"Europe/Copenhagen",
    "iso:country":"DK",
    "name:und_x_variant":[
        "Gjerup",
        "Gerup",
        "Gj\u00e6rup",
        "G\u00e6rup"
    ],
    "wof:name":"Gaerup",
    "wof:placetype":"locality"
},
  "geometry": {"coordinates":[8.61091,56.85459],"type":"Point"}
}