{
  "type": "Feature",
  "properties": {
    "gn:admin1_code":"18.0",
    "gn:admin2_code":"671.0",
    "gn:asciiname":"Lyngs",
    "gn:country_code":"DK",
    "gn:dem":10,
    "gn:feature_class":"P",
    "gn:feature_code":"PPL",
    "gn:name":"Lyngs",
    "gn:population":0,
    "gn:timezone":"Europe/Copenhagen",
    "iso:country":"DK",
    "wof:name":"Lyngs",
    "wof:placetype":"locality"
},
  "geometry": {"coordinates":[8.45206,56.66574],"type":"Point"}
}