{
  "type": "Feature",
  "properties": {
    "iso:country":"DK",
    "name:dan_x_preferred":[
        "Sletten"
    ],
    "qs:gn_adm0_cc":"DK",
    "qs:gn_fcode":"PPL",
    "qs:gn_local":2619669,
    "qs:gn_nam_loc":"humlebaek",
    "qs:gn_namadm1":"17",
    "qs:gn_name":"Sletten",
    "qs:local_max":2852,
    "qs:local_sum":3266,
    "qs:localhoods":2,
    "qs:name":"Sletten",
    "qs:name_adm0":"Danmark",
    "qs:name_adm1":"Hovedstaden",
    "qs:name_adm2":"Fredensborg",
    "qs:name_local":"Humleb\u00e6k",
    "qs:photo_max":165,
    "qs:photo_sum":414,
    "qs:placetype":"Suburb",
    "qs:quad_count":46,
    "qs:woe_adm0":23424796,
    "qs:woe_adm1":28362583,
    "qs:woe_adm2":28583798,
    "qs:woe_lau":0,
    "qs:woe_local":554380,
    "qs:woe_ver":"7.10.0",
    "wof:lang":[
        "dan"
    ],
    "wof:name":"Sletten",
    "wof:placetype":"neighbourhood"
},
  "geometry": {"coordinates":[12.529407,55.954421],"type":"Point"}
}