{
  "type": "Feature",
  "properties": {
    "gn:admin1_code":"17.0",
    "gn:admin2_code":"270.0",
    "gn:asciiname":"Esrum",
    "gn:country_code":"DK",
    "gn:dem":12,
    "gn:feature_class":"P",
    "gn:feature_code":"PPL",
    "gn:name":"Esrum",
    "gn:population":0,
    "gn:timezone":"Europe/Copenhagen",
    "iso:country":"DK",
    "wof:name":"Esrum",
    "wof:placetype":"locality"
},
  "geometry": {"coordinates":[12.37946,56.05093000000001],"type":"Point"}
}