{
  "type": "Feature",
  "properties": {
    "gn:gn_country":"DK",
    "gn:gn_fcode":"PPL",
    "gn:gn_pop":0,
    "iso:country":"DK",
    "qs_pg:aaroncc":"DK",
    "qs_pg:gn_country":"DK",
    "qs_pg:gn_fcode":"PPL",
    "qs_pg:gn_pop":0,
    "qs_pg:name":"Jerslev",
    "qs_pg:name_adm0":"Danmark",
    "qs_pg:name_adm1":"Nordjylland",
    "qs_pg:photos":79,
    "qs_pg:photos_1k":16,
    "qs_pg:photos_9k":1,
    "qs_pg:photos_9r":3,
    "qs_pg:photos_all":79,
    "qs_pg:photos_sr":3,
    "qs_pg:pop_sr":0,
    "qs_pg:qs_pg_placetype":"locality",
    "qs_pg:qs_pg_placetype_gp":"Town",
    "qs_pg:woe_adm0":23424796,
    "woe:adm0_id":23424796,
    "woe:name_adm0":"Danmark",
    "woe:name_adm1":"Nordjylland",
    "woe:placetype":"Town",
    "wof:name":"Jerslev",
    "wof:placetype":"locality"
},
  "geometry": {"coordinates":[10.09098,57.28516],"type":"Point"}
}