{
  "type": "Feature",
  "properties": {
    "gn:gn_country":"DK",
    "gn:gn_fcode":"PPL",
    "gn:gn_pop":0,
    "iso:country":"DK",
    "name:dan_x_preferred":[
        "Hasselager"
    ],
    "name:dut_x_preferred":[
        "Hasselager"
    ],
    "name:eng_x_preferred":[
        "Hasselager"
    ],
    "name:ger_x_preferred":[
        "Hasselager"
    ],
    "name:swe_x_preferred":[
        "Hasselager"
    ],
    "qs_pg:aaroncc":"DK",
    "qs_pg:gn_country":"DK",
    "qs_pg:gn_fcode":"PPL",
    "qs_pg:gn_pop":0,
    "qs_pg:name":"Hasselager",
    "qs_pg:name_adm0":"Danmark",
    "qs_pg:name_adm1":"Midtjylland",
    "qs_pg:photos":154,
    "qs_pg:photos_1k":31,
    "qs_pg:photos_9k":1,
    "qs_pg:photos_9r":4,
    "qs_pg:photos_all":154,
    "qs_pg:photos_sr":4,
    "qs_pg:pop_sr":0,
    "qs_pg:qs_pg_placetype":"locality",
    "qs_pg:qs_pg_placetype_gp":"Town",
    "qs_pg:woe_adm0":23424796,
    "woe:adm0_id":23424796,
    "woe:name_adm0":"Danmark",
    "woe:name_adm1":"Midtjylland",
    "woe:placetype":"Town",
    "wof:name":"Hasselager",
    "wof:placetype":"locality"
},
  "geometry": {"coordinates":[10.1065,56.10066],"type":"Point"}
}