{
  "type": "Feature",
  "properties": {
    "gn:admin1_code":"21.0",
    "gn:admin2_code":"510.0",
    "gn:asciiname":"Kestrup",
    "gn:country_code":"DK",
    "gn:dem":38,
    "gn:feature_class":"P",
    "gn:feature_code":"PPL",
    "gn:name":"Kestrup",
    "gn:population":0,
    "gn:timezone":"Europe/Copenhagen",
    "iso:country":"DK",
    "wof:name":"Kestrup",
    "wof:placetype":"locality"
},
  "geometry": {"coordinates":[9.2927,55.29431],"type":"Point"}
}