{
  "type": "Feature",
  "properties": {
    "gn:admin1_code":"21.0",
    "gn:admin2_code":"573.0",
    "gn:asciiname":"Frosig",
    "gn:country_code":"DK",
    "gn:dem":36,
    "gn:feature_class":"P",
    "gn:feature_code":"PPL",
    "gn:name":"Fr\u00f8sig",
    "gn:population":0,
    "gn:timezone":"Europe/Copenhagen",
    "iso:country":"DK",
    "wof:name":"Frosig",
    "wof:placetype":"locality"
},
  "geometry": {"coordinates":[8.63496,55.7723],"type":"Point"}
}