{
  "type": "Feature",
  "properties": {
    "gn:admin1_code":"21.0",
    "gn:admin2_code":"621.0",
    "gn:asciiname":"Hjarup",
    "gn:country_code":"DK",
    "gn:dem":47,
    "gn:feature_class":"P",
    "gn:feature_code":"PPL",
    "gn:name":"Hjarup",
    "gn:population":0,
    "gn:timezone":"Europe/Copenhagen",
    "iso:country":"DK",
    "wof:name":"Hjarup",
    "wof:placetype":"locality"
},
  "geometry": {"coordinates":[9.36114,55.44593],"type":"Point"}
}