{
  "type": "Feature",
  "properties": {
    "gn:admin1_code":"19.0",
    "gn:admin2_code":"787.0",
    "gn:asciiname":"Madsted",
    "gn:country_code":"DK",
    "gn:dem":10,
    "gn:feature_class":"P",
    "gn:feature_code":"PPLL",
    "gn:name":"Madsted",
    "gn:population":0,
    "gn:timezone":"Europe/Copenhagen",
    "iso:country":"DK",
    "wof:name":"Madsted",
    "wof:placetype":"locality"
},
  "geometry": {"coordinates":[8.39907,56.86208000000001],"type":"Point"}
}