{
  "type": "Feature",
  "properties": {
    "gn:admin1_code":"18.0",
    "gn:admin2_code":"740.0",
    "gn:asciiname":"Brokhuse",
    "gn:country_code":"DK",
    "gn:dem":74,
    "gn:feature_class":"P",
    "gn:feature_code":"PPLL",
    "gn:name":"Brokhuse",
    "gn:population":0,
    "gn:timezone":"Europe/Copenhagen",
    "iso:country":"DK",
    "wof:name":"Brokhuse",
    "wof:placetype":"locality"
},
  "geometry": {"coordinates":[9.38851,56.26158],"type":"Point"}
}