{
  "type": "Feature",
  "properties": {
    "gn:admin1_code":"21.0",
    "gn:admin2_code":"550.0",
    "gn:asciiname":"Oster Gammelby",
    "gn:country_code":"DK",
    "gn:dem":9,
    "gn:feature_class":"P",
    "gn:feature_code":"PPL",
    "gn:name":"\u00d8ster Gammelby",
    "gn:population":0,
    "gn:timezone":"Europe/Copenhagen",
    "iso:country":"DK",
    "wof:name":"Oster Gammelby",
    "wof:placetype":"locality"
},
  "geometry": {"coordinates":[8.76601,54.99548000000001],"type":"Point"}
}