{
  "type": "Feature",
  "properties": {
    "gn:admin1_code":"20.0",
    "gn:admin2_code":"350.0",
    "gn:asciiname":"Gershoj",
    "gn:country_code":"DK",
    "gn:dem":10,
    "gn:feature_class":"P",
    "gn:feature_code":"PPL",
    "gn:name":"Gersh\u00f8j",
    "gn:population":0,
    "gn:timezone":"Europe/Copenhagen",
    "iso:country":"DK",
    "name:und_x_variant":[
        "Gjersh\u00f6j",
        "Gersh\u00f8j"
    ],
    "wof:name":"Gershoj",
    "wof:placetype":"locality"
},
  "geometry": {"coordinates":[11.96953,55.71255],"type":"Point"}
}