{
  "type": "Feature",
  "properties": {
    "gn:admin1_code":"18.0",
    "gn:admin2_code":"751.0",
    "gn:asciiname":"Vorre",
    "gn:country_code":"DK",
    "gn:dem":110,
    "gn:feature_class":"P",
    "gn:feature_code":"PPL",
    "gn:name":"Vorre",
    "gn:population":0,
    "gn:timezone":"Europe/Copenhagen",
    "iso:country":"DK",
    "wof:name":"Vorre",
    "wof:placetype":"locality"
},
  "geometry": {"coordinates":[10.29454,56.27866],"type":"Point"}
}