{
  "type": "Feature",
  "properties": {
    "gn:admin1_code":"17.0",
    "gn:admin2_code":"210.0",
    "gn:asciiname":"Vejenbrod",
    "gn:country_code":"DK",
    "gn:dem":16,
    "gn:feature_class":"P",
    "gn:feature_code":"PPL",
    "gn:name":"Vejenbr\u00f8d",
    "gn:population":0,
    "gn:timezone":"Europe/Copenhagen",
    "iso:country":"DK",
    "wof:name":"Vejenbrod",
    "wof:placetype":"locality"
},
  "geometry": {"coordinates":[12.46955,55.93039],"type":"Point"}
}