{
  "type": "Feature",
  "properties": {
    "gn:admin1_code":"21.0",
    "gn:admin2_code":"420.0",
    "gn:asciiname":"Frobjerg",
    "gn:country_code":"DK",
    "gn:dem":64,
    "gn:feature_class":"P",
    "gn:feature_code":"PPL",
    "gn:name":"Fr\u00f8bjerg",
    "gn:population":0,
    "gn:timezone":"Europe/Copenhagen",
    "iso:country":"DK",
    "name:und_x_variant":[
        "Fr\u00f8bj\u00e6rg",
        "Fr\u00f8bjerg"
    ],
    "wof:name":"Frobjerg",
    "wof:placetype":"locality"
},
  "geometry": {"coordinates":[10.10082,55.33483],"type":"Point"}
}