{
  "type": "Feature",
  "properties": {
    "gn:admin1_code":"18.0",
    "gn:admin2_code":"760.0",
    "gn:asciiname":"Sonderdiger",
    "gn:country_code":"DK",
    "gn:dem":21,
    "gn:feature_class":"P",
    "gn:feature_code":"PPLL",
    "gn:name":"S\u00f8nderdiger",
    "gn:population":0,
    "gn:timezone":"Europe/Copenhagen",
    "iso:country":"DK",
    "wof:name":"Sonderdiger",
    "wof:placetype":"locality"
},
  "geometry": {"coordinates":[8.44369,55.80011],"type":"Point"}
}