{
  "type": "Feature",
  "properties": {
    "gn:admin1_code":"20.0",
    "gn:admin2_code":"316.0",
    "gn:asciiname":"Dramstrup",
    "gn:country_code":"DK",
    "gn:dem":41,
    "gn:feature_class":"P",
    "gn:feature_code":"PPL",
    "gn:name":"Dramstrup",
    "gn:population":0,
    "gn:timezone":"Europe/Copenhagen",
    "iso:country":"DK",
    "wof:name":"Dramstrup",
    "wof:placetype":"locality"
},
  "geometry": {"coordinates":[11.57975,55.65863],"type":"Point"}
}