{
  "type": "Feature",
  "properties": {
    "gn:admin1_code":"21.0",
    "gn:admin2_code":"482.0",
    "gn:asciiname":"Bostrup",
    "gn:country_code":"DK",
    "gn:dem":15,
    "gn:feature_class":"P",
    "gn:feature_code":"PPL",
    "gn:name":"B\u00f8strup",
    "gn:population":0,
    "gn:timezone":"Europe/Copenhagen",
    "iso:country":"DK",
    "wof:name":"Bostrup",
    "wof:placetype":"locality"
},
  "geometry": {"coordinates":[10.8813,55.04106],"type":"Point"}
}