{
  "type": "Feature",
  "properties": {
    "gn:admin1_code":"20.0",
    "gn:admin2_code":"326.0",
    "gn:asciiname":"Gierslev",
    "gn:cc2":"DK",
    "gn:country_code":"DK",
    "gn:dem":33,
    "gn:feature_class":"P",
    "gn:feature_code":"PPL",
    "gn:name":"Gierslev",
    "gn:population":0,
    "gn:timezone":"Europe/Copenhagen",
    "iso:country":"DK",
    "name:und_x_variant":[
        "Gjerslev",
        "Geeslev"
    ],
    "wof:name":"Gierslev",
    "wof:placetype":"locality"
},
  "geometry": {"coordinates":[11.32121,55.49056],"type":"Point"}
}