{
  "type": "Feature",
  "properties": {
    "gn:admin1_code":"21.0",
    "gn:admin2_code":"630.0",
    "gn:asciiname":"Mejsling",
    "gn:country_code":"DK",
    "gn:dem":76,
    "gn:feature_class":"P",
    "gn:feature_code":"PPL",
    "gn:name":"Mejsling",
    "gn:population":0,
    "gn:timezone":"Europe/Copenhagen",
    "iso:country":"DK",
    "wof:name":"Mejsling",
    "wof:placetype":"locality"
},
  "geometry": {"coordinates":[9.44119,55.6577],"type":"Point"}
}