{
  "type": "Feature",
  "properties": {
    "gn:admin1_code":"21.0",
    "gn:admin2_code":"630.0",
    "gn:asciiname":"Sonder Langelund",
    "gn:country_code":"DK",
    "gn:dem":66,
    "gn:feature_class":"P",
    "gn:feature_code":"PPL",
    "gn:name":"S\u00f8nder Langelund",
    "gn:population":0,
    "gn:timezone":"Europe/Copenhagen",
    "iso:country":"DK",
    "wof:name":"Sonder Langelund",
    "wof:placetype":"locality"
},
  "geometry": {"coordinates":[9.08305,55.78375],"type":"Point"}
}