{
  "type": "Feature",
  "properties": {
    "gn:admin1_code":"21.0",
    "gn:admin2_code":"621.0",
    "gn:asciiname":"Braenore",
    "gn:country_code":"DK",
    "gn:dem":57,
    "gn:feature_class":"P",
    "gn:feature_code":"PPL",
    "gn:name":"Br\u00e6nore",
    "gn:population":0,
    "gn:timezone":"Europe/Copenhagen",
    "iso:country":"DK",
    "wof:name":"Braenore",
    "wof:placetype":"locality"
},
  "geometry": {"coordinates":[9.42048,55.39119],"type":"Point"}
}