{
  "type": "Feature",
  "properties": {
    "gn:admin1_code":"20.0",
    "gn:admin2_code":"320.0",
    "gn:asciiname":"Bonderod",
    "gn:country_code":"DK",
    "gn:dem":23,
    "gn:feature_class":"P",
    "gn:feature_code":"PPL",
    "gn:name":"Bonder\u00f8d",
    "gn:population":0,
    "gn:timezone":"Europe/Copenhagen",
    "iso:country":"DK",
    "name:und_x_variant":[
        "Bunner\u00f8d",
        "Bonder\u00f8d"
    ],
    "wof:name":"Bonderod",
    "wof:placetype":"locality"
},
  "geometry": {"coordinates":[12.1759,55.27707],"type":"Point"}
}