{
  "type": "Feature",
  "properties": {
    "gn:admin1_code":"20.0",
    "gn:admin2_code":"376.0",
    "gn:asciiname":"Forneby",
    "gn:country_code":"DK",
    "gn:dem":12,
    "gn:feature_class":"P",
    "gn:feature_code":"PPL",
    "gn:name":"Forneby",
    "gn:population":0,
    "gn:timezone":"Europe/Copenhagen",
    "iso:country":"DK",
    "wof:name":"Forneby",
    "wof:placetype":"locality"
},
  "geometry": {"coordinates":[11.55924,54.78371],"type":"Point"}
}