{
  "type": "Feature",
  "properties": {
    "gn:admin1_code":"19.0",
    "gn:admin2_code":"813.0",
    "gn:asciiname":"Asted",
    "gn:country_code":"DK",
    "gn:dem":43,
    "gn:feature_class":"P",
    "gn:feature_code":"PPL",
    "gn:name":"\u00c5sted",
    "gn:population":0,
    "gn:timezone":"Europe/Copenhagen",
    "iso:country":"DK",
    "name:und_x_variant":[
        "Aasted",
        "\u00c5sted"
    ],
    "wof:name":"Asted",
    "wof:placetype":"locality"
},
  "geometry": {"coordinates":[10.40808,57.44204000000001],"type":"Point"}
}