{
  "type": "Feature",
  "properties": {
    "gn:admin1_code":"20.0",
    "gn:admin2_code":"370.0",
    "gn:asciiname":"Over Even",
    "gn:country_code":"DK",
    "gn:dem":53,
    "gn:feature_class":"P",
    "gn:feature_code":"PPL",
    "gn:name":"Over Even",
    "gn:population":0,
    "gn:timezone":"Europe/Copenhagen",
    "iso:country":"DK",
    "wof:name":"Over Even",
    "wof:placetype":"locality"
},
  "geometry": {"coordinates":[11.93488,55.19046],"type":"Point"}
}