{
  "type": "Feature",
  "properties": {
    "gn:admin1_code":"19.0",
    "gn:admin2_code":"846.0",
    "gn:asciiname":"Brodlos",
    "gn:country_code":"DK",
    "gn:dem":28,
    "gn:feature_class":"P",
    "gn:feature_code":"PPL",
    "gn:name":"Br\u00f8dl\u00f8s",
    "gn:population":0,
    "gn:timezone":"Europe/Copenhagen",
    "iso:country":"DK",
    "name:und_x_variant":[
        "Brol\u00f8s",
        "Br\u00f8dl\u00f8s"
    ],
    "wof:name":"Brodlos",
    "wof:placetype":"locality"
},
  "geometry": {"coordinates":[9.90319,56.60148],"type":"Point"}
}