{
  "type": "Feature",
  "properties": {
    "gn:admin1_code":"21.0",
    "gn:admin2_code":"561.0",
    "gn:asciiname":"Norre Farup",
    "gn:cc2":"DK",
    "gn:country_code":"DK",
    "gn:dem":4,
    "gn:feature_class":"P",
    "gn:feature_code":"PPL",
    "gn:name":"N\u00f8rre Farup",
    "gn:population":0,
    "gn:timezone":"Europe/Copenhagen",
    "iso:country":"DK",
    "name:und_x_variant":[
        "Farup"
    ],
    "wof:name":"Norre Farup",
    "wof:placetype":"locality"
},
  "geometry": {"coordinates":[8.73199,55.35443000000001],"type":"Point"}
}