{
  "type": "Feature",
  "properties": {
    "gn:admin1_code":"19.0",
    "gn:admin2_code":"787.0",
    "gn:asciiname":"Ginnerup",
    "gn:country_code":"DK",
    "gn:dem":20,
    "gn:feature_class":"P",
    "gn:feature_code":"PPL",
    "gn:name":"Ginnerup",
    "gn:population":0,
    "gn:timezone":"Europe/Copenhagen",
    "iso:country":"DK",
    "name:dan_x_preferred":[
        "Ginnerup Sogn"
    ],
    "name:ita_x_preferred":[
        "Ginnerup"
    ],
    "name:nds_x_preferred":[
        "Ginnerup"
    ],
    "name:nld_x_preferred":[
        "Ginnerup"
    ],
    "name:nor_x_preferred":[
        "Ginnerup"
    ],
    "name:pol_x_preferred":[
        "Ginnerup"
    ],
    "name:spa_x_preferred":[
        "Ginnerup"
    ],
    "name:swe_x_preferred":[
        "Ginnerup"
    ],
    "name:und_x_variant":[
        "Ginderup",
        "Ginnerup"
    ],
    "wof:name":"Ginnerup",
    "wof:placetype":"locality"
},
  "geometry": {"coordinates":[8.46002,56.73665],"type":"Point"}
}