{
  "type": "Feature",
  "properties": {
    "gn:admin1_code":"20.0",
    "gn:admin2_code":"340.0",
    "gn:asciiname":"Borod",
    "gn:country_code":"DK",
    "gn:dem":55,
    "gn:feature_class":"P",
    "gn:feature_code":"PPL",
    "gn:name":"Bor\u00f8d",
    "gn:population":0,
    "gn:timezone":"Europe/Copenhagen",
    "iso:country":"DK",
    "name:ara_x_preferred":[
        "\u0628\u0648\u0631\u0648\u062f"
    ],
    "name:ceb_x_preferred":[
        "Borod"
    ],
    "name:deu_x_preferred":[
        "Borod"
    ],
    "name:epo_x_preferred":[
        "Borod"
    ],
    "name:eus_x_preferred":[
        "Borod"
    ],
    "name:fas_x_preferred":[
        "\u0628\u0648\u0631\u0648\u062f"
    ],
    "name:fra_x_preferred":[
        "Borod"
    ],
    "name:hun_x_preferred":[
        "Borod"
    ],
    "name:ita_x_preferred":[
        "Borod"
    ],
    "name:kaz_x_preferred":[
        "\u0411\u043e\u0440\u043e\u0434"
    ],
    "name:kir_x_preferred":[
        "\u0411\u043e\u0440\u043e\u0434"
    ],
    "name:msa_x_preferred":[
        "Borod"
    ],
    "name:nld_x_preferred":[
        "Borod"
    ],
    "name:pol_x_preferred":[
        "Borod"
    ],
    "name:por_x_preferred":[
        "Borod"
    ],
    "name:ron_x_preferred":[
        "Borod"
    ],
    "name:rus_x_preferred":[
        "\u0411\u043e\u0440\u043e\u0434"
    ],
    "name:spa_x_preferred":[
        "Borod"
    ],
    "name:srp_x_preferred":[
        "\u0411\u043e\u0440\u043e\u0434"
    ],
    "name:ukr_x_preferred":[
        "\u0411\u043e\u0440\u043e\u0434"
    ],
    "name:uzb_x_preferred":[
        "Borod"
    ],
    "name:vie_x_preferred":[
        "Borod"
    ],
    "name:vol_x_preferred":[
        "Borod"
    ],
    "name:war_x_preferred":[
        "Borod"
    ],
    "name:zho_x_preferred":[
        "\u535a\u7f57\u5fb7"
    ],
    "wof:name":"Borod",
    "wof:placetype":"locality"
},
  "geometry": {"coordinates":[11.52062,55.42654],"type":"Point"}
}