{
  "type": "Feature",
  "properties": {
    "gn:admin1_code":"20.0",
    "gn:admin2_code":"340.0",
    "gn:asciiname":"Borod",
    "gn:country_code":"DK",
    "gn:dem":55,
    "gn:feature_class":"P",
    "gn:feature_code":"PPL",
    "gn:name":"Bor\u00f8d",
    "gn:population":0,
    "gn:timezone":"Europe/Copenhagen",
    "iso:country":"DK",
    "wof:name":"Borod",
    "wof:placetype":"locality"
},
  "geometry": {"coordinates":[11.52062,55.42654],"type":"Point"}
}