{
  "type": "Feature",
  "properties": {
    "gn:admin1_code":"20.0",
    "gn:admin2_code":"370.0",
    "gn:asciiname":"Bogeso",
    "gn:country_code":"DK",
    "gn:dem":49,
    "gn:feature_class":"P",
    "gn:feature_code":"PPL",
    "gn:name":"B\u00f8ges\u00f8",
    "gn:population":0,
    "gn:timezone":"Europe/Copenhagen",
    "iso:country":"DK",
    "wof:name":"Bogeso",
    "wof:placetype":"locality"
},
  "geometry": {"coordinates":[11.90353,55.1972],"type":"Point"}
}