{
  "type": "Feature",
  "properties": {
    "gn:admin1_code":"20.0",
    "gn:admin2_code":"376.0",
    "gn:asciiname":"Blaesebjerg",
    "gn:country_code":"DK",
    "gn:dem":10,
    "gn:feature_class":"P",
    "gn:feature_code":"PPL",
    "gn:name":"Bl\u00e6sebjerg",
    "gn:population":0,
    "gn:timezone":"Europe/Copenhagen",
    "iso:country":"DK",
    "name:und_x_variant":[
        "Bl\u00e6sebj\u00e6rg",
        "Bl\u00e6sebjerg"
    ],
    "wof:name":"Blaesebjerg",
    "wof:placetype":"locality"
},
  "geometry": {"coordinates":[11.98671,54.89352],"type":"Point"}
}