{
  "type": "Feature",
  "properties": {
    "gn:admin1_code":"17.0",
    "gn:admin2_code":"210.0",
    "gn:asciiname":"Gunderod",
    "gn:country_code":"DK",
    "gn:dem":34,
    "gn:feature_class":"P",
    "gn:feature_code":"PPL",
    "gn:name":"Gunder\u00f8d",
    "gn:population":0,
    "gn:timezone":"Europe/Copenhagen",
    "iso:country":"DK",
    "wof:name":"Gunderod",
    "wof:placetype":"locality"
},
  "geometry": {"coordinates":[12.42209,55.90169],"type":"Point"}
}