{
  "type": "Feature",
  "properties": {
    "gn:admin1_code":"20.0",
    "gn:admin2_code":"320.0",
    "gn:asciiname":"Haslev",
    "gn:country_code":"DK",
    "gn:dem":51,
    "gn:feature_class":"P",
    "gn:feature_code":"PPLA2",
    "gn:name":"Haslev",
    "gn:population":10588,
    "gn:timezone":"Europe/Copenhagen",
    "iso:country":"DK",
    "name:rus_x_preferred":[
        "\u0425\u0430\u0441\u043b\u0435\u0432"
    ],
    "wof:name":"Haslev",
    "wof:placetype":"locality",
    "wof:population":10588
},
  "geometry": {"coordinates":[11.96389,55.32346],"type":"Point"}
}