{
  "type": "Feature",
  "properties": {
    "gn:admin1_code":"20.0",
    "gn:admin2_code":"320.0",
    "gn:asciiname":"Haslev",
    "gn:country_code":"DK",
    "gn:dem":51,
    "gn:feature_class":"P",
    "gn:feature_code":"PPLA2",
    "gn:name":"Haslev",
    "gn:population":10588,
    "gn:timezone":"Europe/Copenhagen",
    "iso:country":"DK",
    "name:ceb_x_preferred":[
        "Haslev"
    ],
    "name:dan_x_preferred":[
        "Haslev"
    ],
    "name:deu_x_preferred":[
        "Haslev"
    ],
    "name:kor_x_preferred":[
        "\ud558\uc2ac\ub808\uc6b0"
    ],
    "name:msa_x_preferred":[
        "Haslev"
    ],
    "name:nld_x_preferred":[
        "Haslev"
    ],
    "name:pol_x_preferred":[
        "Haslev"
    ],
    "name:ron_x_preferred":[
        "Haslev"
    ],
    "name:rus_x_preferred":[
        "\u0425\u0430\u0441\u043b\u0435\u0432"
    ],
    "name:slv_x_preferred":[
        "Haslev"
    ],
    "name:spa_x_preferred":[
        "Haslev"
    ],
    "name:srp_x_preferred":[
        "\u0425\u0430\u0441\u043b\u0435\u0432"
    ],
    "name:swe_x_preferred":[
        "Haslev"
    ],
    "wof:name":"Haslev",
    "wof:placetype":"locality",
    "wof:population":10588
},
  "geometry": {"coordinates":[11.96389,55.32346],"type":"Point"}
}