{
  "type": "Feature",
  "properties": {
    "gn:admin1_code":"18.0",
    "gn:admin2_code":"791.0",
    "gn:asciiname":"Norre Vinge",
    "gn:country_code":"DK",
    "gn:dem":25,
    "gn:feature_class":"P",
    "gn:feature_code":"PPL",
    "gn:name":"N\u00f8rre Vinge",
    "gn:population":0,
    "gn:timezone":"Europe/Copenhagen",
    "iso:country":"DK",
    "name:und_x_variant":[
        "Vinge",
        "N\u00f8rre Vinge"
    ],
    "wof:name":"Norre Vinge",
    "wof:placetype":"locality"
},
  "geometry": {"coordinates":[9.65991,56.53249],"type":"Point"}
}