{
  "type": "Feature",
  "properties": {
    "gn:admin1_code":"21.0",
    "gn:admin2_code":"540.0",
    "gn:asciiname":"Fjelby",
    "gn:country_code":"DK",
    "gn:dem":20,
    "gn:feature_class":"P",
    "gn:feature_code":"PPL",
    "gn:name":"Fjelby",
    "gn:population":0,
    "gn:timezone":"Europe/Copenhagen",
    "iso:country":"DK",
    "wof:name":"Fjelby",
    "wof:placetype":"locality"
},
  "geometry": {"coordinates":[9.99026,54.89536999999999],"type":"Point"}
}