{
  "type": "Feature",
  "properties": {
    "gn:admin1_code":"19.0",
    "gn:admin2_code":"860.0",
    "gn:asciiname":"Altona",
    "gn:country_code":"DK",
    "gn:dem":18,
    "gn:feature_class":"P",
    "gn:feature_code":"PPLL",
    "gn:name":"Altona",
    "gn:population":0,
    "gn:timezone":"Europe/Copenhagen",
    "iso:country":"DK",
    "wof:name":"Altona",
    "wof:placetype":"locality"
},
  "geometry": {"coordinates":[10.25772,57.58618000000001],"type":"Point"}
}