{
  "type": "Feature",
  "properties": {
    "gn:admin1_code":"19.0",
    "gn:admin2_code":"860.0",
    "gn:asciiname":"Altona",
    "gn:country_code":"DK",
    "gn:dem":18,
    "gn:feature_class":"P",
    "gn:feature_code":"PPLL",
    "gn:name":"Altona",
    "gn:population":0,
    "gn:timezone":"Europe/Copenhagen",
    "iso:country":"DK",
    "name:cat_x_preferred":[
        "Altona"
    ],
    "name:ceb_x_preferred":[
        "Altona"
    ],
    "name:ces_x_preferred":[
        "Altona"
    ],
    "name:dan_x_preferred":[
        "Altona"
    ],
    "name:deu_x_preferred":[
        "Altona"
    ],
    "name:fra_x_preferred":[
        "Altona"
    ],
    "name:ita_x_preferred":[
        "Altona"
    ],
    "name:jpn_x_preferred":[
        "\u30a2\u30eb\u30c8\u30ca"
    ],
    "name:kor_x_preferred":[
        "\uc568\ud1a0\ub098"
    ],
    "name:nds_x_preferred":[
        "Altona"
    ],
    "name:nld_x_preferred":[
        "Altona"
    ],
    "name:pol_x_preferred":[
        "Altona"
    ],
    "name:por_x_preferred":[
        "Altona"
    ],
    "name:rus_x_preferred":[
        "\u0410\u043b\u044c\u0442\u043e\u043d\u0430"
    ],
    "name:slv_x_preferred":[
        "Altona"
    ],
    "name:spa_x_preferred":[
        "Altona"
    ],
    "name:srp_x_preferred":[
        "\u0410\u043b\u0442\u043e\u043d\u0430"
    ],
    "name:swe_x_preferred":[
        "Altona"
    ],
    "name:ukr_x_preferred":[
        "\u0410\u043b\u0442\u043e\u043d\u0430"
    ],
    "name:vol_x_preferred":[
        "Altona"
    ],
    "wof:name":"Altona",
    "wof:placetype":"locality"
},
  "geometry": {"coordinates":[10.25772,57.58618000000001],"type":"Point"}
}