{
  "type": "Feature",
  "properties": {
    "gn:admin1_code":"21.0",
    "gn:admin2_code":"430.0",
    "gn:asciiname":"Palleshave",
    "gn:country_code":"DK",
    "gn:dem":59,
    "gn:feature_class":"P",
    "gn:feature_code":"PPL",
    "gn:name":"Palleshave",
    "gn:population":0,
    "gn:timezone":"Europe/Copenhagen",
    "iso:country":"DK",
    "wof:name":"Palleshave",
    "wof:placetype":"locality"
},
  "geometry": {"coordinates":[10.41573,55.24764],"type":"Point"}
}