{
  "type": "Feature",
  "properties": {
    "gn:country":"DK",
    "gn:fcode":"PPL",
    "gn:population":0,
    "iso:country":"DK",
    "name:dan_x_preferred":[
        "J\u00e6gersborg"
    ],
    "name:swe_x_preferred":[
        "J\u00e6gersborg"
    ],
    "qs_pg:aaroncc":"DK",
    "qs_pg:gn_country":"DK",
    "qs_pg:gn_fcode":"PPL",
    "qs_pg:gn_pop":0,
    "qs_pg:name":"J\u00e6gersborg",
    "qs_pg:name_adm0":"Danmark",
    "qs_pg:name_adm1":"Hovedstaden",
    "qs_pg:photos":317,
    "qs_pg:photos_1k":64,
    "qs_pg:photos_9k":1,
    "qs_pg:photos_9r":5,
    "qs_pg:photos_all":317,
    "qs_pg:photos_sr":5,
    "qs_pg:pop_sr":0,
    "qs_pg:qs_pg_placetype":"locality",
    "qs_pg:qs_pg_placetype_gp":"Town",
    "qs_pg:woe_adm0":23424796,
    "woe:adm0_id":23424796,
    "woe:name_adm0":"Danmark",
    "woe:name_adm1":"Hovedstaden",
    "woe:placetype":"Town",
    "wof:name":"J\u00e6gersborg",
    "wof:placetype":"locality"
},
  "geometry": {"coordinates":[12.53504,55.75927],"type":"Point"}
}