{
  "type": "Feature",
  "properties": {
    "gn:admin1_code":"18.0",
    "gn:admin2_code":"657.0",
    "gn:asciiname":"Fejrskov Huse",
    "gn:country_code":"DK",
    "gn:dem":68,
    "gn:feature_class":"P",
    "gn:feature_code":"PPL",
    "gn:name":"Fejrskov Huse",
    "gn:population":0,
    "gn:timezone":"Europe/Copenhagen",
    "iso:country":"DK",
    "wof:name":"Fejrskov Huse",
    "wof:placetype":"locality"
},
  "geometry": {"coordinates":[9.00271,56.10629],"type":"Point"}
}