{
  "type": "Feature",
  "properties": {
    "gn:country":"DK",
    "gn:fcode":"PPLA2",
    "gn:population":49380,
    "iso:country":"DK",
    "name:ceb_x_preferred":[
        "Hvidovre"
    ],
    "name:dan_x_preferred":[
        "Hvidovre"
    ],
    "name:deu_x_preferred":[
        "Hvidovre"
    ],
    "name:eng_x_preferred":[
        "Hvidovre"
    ],
    "name:eus_x_preferred":[
        "Hvidovre"
    ],
    "name:fao_x_preferred":[
        "Hvidovre"
    ],
    "name:fin_x_preferred":[
        "Hvidovre"
    ],
    "name:fra_x_preferred":[
        "Hvidovre"
    ],
    "name:frr_x_preferred":[
        "Hvidovre"
    ],
    "name:ita_x_preferred":[
        "Hvidovre"
    ],
    "name:msa_x_preferred":[
        "Hvidovre"
    ],
    "name:nld_x_preferred":[
        "Hvidovre"
    ],
    "name:nor_x_preferred":[
        "Hvidovre"
    ],
    "name:pol_x_preferred":[
        "Hvidovre"
    ],
    "name:por_x_preferred":[
        "Hvidovre"
    ],
    "name:ron_x_preferred":[
        "Hvidovre"
    ],
    "name:rus_x_preferred":[
        "\u0425\u0432\u0438\u0434\u043e\u0432\u0440\u0435"
    ],
    "name:swe_x_preferred":[
        "Hvidovre"
    ],
    "qs_pg:aaroncc":"DK",
    "qs_pg:gn_country":"DK",
    "qs_pg:gn_fcode":"PPLA2",
    "qs_pg:gn_pop":49380,
    "qs_pg:name":"Hvidovre",
    "qs_pg:name_adm0":"Danmark",
    "qs_pg:name_adm1":"Hovedstaden",
    "qs_pg:photos":1479,
    "qs_pg:photos_1k":300,
    "qs_pg:photos_9k":7,
    "qs_pg:photos_9r":7,
    "qs_pg:photos_all":1479,
    "qs_pg:photos_sr":12,
    "qs_pg:pop_sr":7,
    "qs_pg:qs_pg_placetype":"locality",
    "qs_pg:qs_pg_placetype_gp":"Town",
    "qs_pg:woe_adm0":23424796,
    "woe:adm0_id":23424796,
    "woe:name_adm0":"Danmark",
    "woe:name_adm1":"Hovedstaden",
    "woe:placetype":"Town",
    "wof:name":"Hvidovre",
    "wof:placetype":"locality",
    "wof:population":49380
},
  "geometry": {"coordinates":[12.47364,55.65719],"type":"Point"}
}