{
  "type": "Feature",
  "properties": {
    "gn:admin1_code":"21.0",
    "gn:admin2_code":"479.0",
    "gn:asciiname":"Ny Hesselager",
    "gn:country_code":"DK",
    "gn:dem":43,
    "gn:feature_class":"P",
    "gn:feature_code":"PPL",
    "gn:name":"Ny Hesselager",
    "gn:population":0,
    "gn:timezone":"Europe/Copenhagen",
    "iso:country":"DK",
    "wof:name":"Ny Hesselager",
    "wof:placetype":"locality"
},
  "geometry": {"coordinates":[10.73514,55.17007],"type":"Point"}
}