{
  "type": "Feature",
  "properties": {
    "gn:admin1_code":"21.0",
    "gn:admin2_code":"440.0",
    "gn:asciiname":"Dalby",
    "gn:country_code":"DK",
    "gn:dem":10,
    "gn:feature_class":"P",
    "gn:feature_code":"PPL",
    "gn:name":"Dalby",
    "gn:population":0,
    "gn:timezone":"Europe/Copenhagen",
    "iso:country":"DK",
    "wof:name":"Dalby",
    "wof:placetype":"locality"
},
  "geometry": {"coordinates":[10.65922,55.51698],"type":"Point"}
}