{
  "type": "Feature",
  "properties": {
    "gn:admin1_code":"21.0",
    "gn:admin2_code":"440.0",
    "gn:asciiname":"Dalby",
    "gn:country_code":"DK",
    "gn:dem":10,
    "gn:feature_class":"P",
    "gn:feature_code":"PPL",
    "gn:name":"Dalby",
    "gn:population":0,
    "gn:timezone":"Europe/Copenhagen",
    "iso:country":"DK",
    "name:ceb_x_preferred":[
        "Dalby"
    ],
    "name:dan_x_preferred":[
        "Dalby"
    ],
    "name:deu_x_preferred":[
        "Dalby"
    ],
    "name:fin_x_preferred":[
        "Dalby"
    ],
    "name:fra_x_preferred":[
        "Dalby"
    ],
    "name:ita_x_preferred":[
        "Dalby"
    ],
    "name:jpn_x_preferred":[
        "\u30c0\u30eb\u30d3\u30fc"
    ],
    "name:mlg_x_preferred":[
        "Dalby"
    ],
    "name:nld_x_preferred":[
        "Dalby"
    ],
    "name:pol_x_preferred":[
        "Dalby"
    ],
    "name:rus_x_preferred":[
        "\u0414\u044d\u043b\u0431\u0438"
    ],
    "name:swe_x_preferred":[
        "Dalby"
    ],
    "wof:name":"Dalby",
    "wof:placetype":"locality"
},
  "geometry": {"coordinates":[10.65922,55.51698],"type":"Point"}
}