{
  "type": "Feature",
  "properties": {
    "gn:admin1_code":"19.0",
    "gn:admin2_code":"846.0",
    "gn:asciiname":"Gunderup",
    "gn:country_code":"DK",
    "gn:dem":57,
    "gn:feature_class":"P",
    "gn:feature_code":"PPL",
    "gn:name":"Gunderup",
    "gn:population":0,
    "gn:timezone":"Europe/Copenhagen",
    "iso:country":"DK",
    "wof:name":"Gunderup",
    "wof:placetype":"locality"
},
  "geometry": {"coordinates":[9.97077,56.60618],"type":"Point"}
}