{
  "type": "Feature",
  "properties": {
    "gn:admin1_code":"18.0",
    "gn:admin2_code":"730.0",
    "gn:asciiname":"Skalmstrup",
    "gn:country_code":"DK",
    "gn:dem":16,
    "gn:feature_class":"P",
    "gn:feature_code":"PPL",
    "gn:name":"Skalmstrup",
    "gn:population":0,
    "gn:timezone":"Europe/Copenhagen",
    "iso:country":"DK",
    "wof:name":"Skalmstrup",
    "wof:placetype":"locality"
},
  "geometry": {"coordinates":[10.20452,56.53757],"type":"Point"}
}