{
  "type": "Feature",
  "properties": {
    "gn:admin1_code":"17.0",
    "gn:admin2_code":"185.0",
    "gn:asciiname":"Maglebylille",
    "gn:country_code":"DK",
    "gn:dem":2,
    "gn:feature_class":"P",
    "gn:feature_code":"PPL",
    "gn:name":"Maglebylille",
    "gn:population":0,
    "gn:timezone":"Europe/Copenhagen",
    "iso:country":"DK",
    "wof:name":"Maglebylille",
    "wof:placetype":"locality"
},
  "geometry": {"coordinates":[12.65,55.63333000000001],"type":"Point"}
}