{
  "type": "Feature",
  "properties": {
    "gn:admin1_code":"21.0",
    "gn:admin2_code":"482.0",
    "gn:asciiname":"Skattebolle",
    "gn:country_code":"DK",
    "gn:dem":8,
    "gn:feature_class":"P",
    "gn:feature_code":"PPL",
    "gn:name":"Skatteb\u00f8lle",
    "gn:population":0,
    "gn:timezone":"Europe/Copenhagen",
    "iso:country":"DK",
    "wof:name":"Skattebolle",
    "wof:placetype":"locality"
},
  "geometry": {"coordinates":[10.88293,55.09088000000001],"type":"Point"}
}