{
  "type": "Feature",
  "properties": {
    "gn:admin1_code":"18.0",
    "gn:admin2_code":"779.0",
    "gn:asciiname":"Kastrup",
    "gn:country_code":"DK",
    "gn:dem":32,
    "gn:feature_class":"P",
    "gn:feature_code":"PPL",
    "gn:name":"K\u00e5strup",
    "gn:population":0,
    "gn:timezone":"Europe/Copenhagen",
    "iso:country":"DK",
    "name:ces_x_preferred":[
        "Kastrup"
    ],
    "name:dan_x_preferred":[
        "Kastrup"
    ],
    "name:deu_x_preferred":[
        "Kastrup"
    ],
    "name:fra_x_preferred":[
        "Kastrup"
    ],
    "name:isl_x_preferred":[
        "Kastrup"
    ],
    "name:nor_x_preferred":[
        "Kastrup"
    ],
    "name:pol_x_preferred":[
        "Kastrup"
    ],
    "name:ron_x_preferred":[
        "Kastrup"
    ],
    "name:sco_x_preferred":[
        "Kastrup"
    ],
    "name:und_x_variant":[
        "Kaastrup",
        "K\u00e5strup"
    ],
    "wof:name":"Kastrup",
    "wof:placetype":"locality"
},
  "geometry": {"coordinates":[8.97064,56.64207],"type":"Point"}
}