{
  "type": "Feature",
  "properties": {
    "gn:admin1_code":"18.0",
    "gn:admin2_code":"727.0",
    "gn:asciiname":"Neder Randlev",
    "gn:country_code":"DK",
    "gn:dem":13,
    "gn:feature_class":"P",
    "gn:feature_code":"PPL",
    "gn:name":"Neder Randlev",
    "gn:population":0,
    "gn:timezone":"Europe/Copenhagen",
    "iso:country":"DK",
    "wof:name":"Neder Randlev",
    "wof:placetype":"locality"
},
  "geometry": {"coordinates":[10.18703,55.95771],"type":"Point"}
}