{
  "type": "Feature",
  "properties": {
    "gn:admin1_code":"17.0",
    "gn:admin2_code":"159.0",
    "gn:asciiname":"Morkhoj",
    "gn:country_code":"DK",
    "gn:dem":26,
    "gn:feature_class":"P",
    "gn:feature_code":"PPL",
    "gn:name":"M\u00f8rkh\u00f8j",
    "gn:population":0,
    "gn:timezone":"Europe/Copenhagen",
    "iso:country":"DK",
    "name:und_x_variant":[
        "M\u00f8rkh\u00f8j"
    ],
    "wof:name":"Morkhoj",
    "wof:placetype":"locality"
},
  "geometry": {"coordinates":[12.47021,55.72592],"type":"Point"}
}