{
  "type": "Feature",
  "properties": {
    "gn:admin1_code":"18.0",
    "gn:admin2_code":"727.0",
    "gn:asciiname":"Sander",
    "gn:country_code":"DK",
    "gn:dem":14,
    "gn:feature_class":"P",
    "gn:feature_code":"PPL",
    "gn:name":"Sander",
    "gn:population":0,
    "gn:timezone":"Europe/Copenhagen",
    "iso:country":"DK",
    "name:cat_x_preferred":[
        "Fregadora"
    ],
    "name:deu_x_preferred":[
        "Schwingschleifer"
    ],
    "name:fra_x_preferred":[
        "Ponceuse"
    ],
    "name:heb_x_preferred":[
        "\u05de\u05dc\u05d8\u05e9\u05ea"
    ],
    "name:ita_x_preferred":[
        "Levigatrice"
    ],
    "name:jpn_x_preferred":[
        "\u96fb\u52d5\u30b5\u30f3\u30c0\u30fc"
    ],
    "name:nld_x_preferred":[
        "Schuurmachine"
    ],
    "name:por_x_preferred":[
        "Lixadeira"
    ],
    "name:rus_x_preferred":[
        "\u0428\u043b\u0438\u0444\u043e\u0432\u0430\u043b\u044c\u043d\u044b\u0435 \u043c\u0430\u0448\u0438\u043d\u044b"
    ],
    "name:spa_x_preferred":[
        "Lijadora"
    ],
    "name:zho_x_preferred":[
        "\u7802\u78e8\u6a5f"
    ],
    "wof:name":"Sander",
    "wof:placetype":"locality"
},
  "geometry": {"coordinates":[10.1532,55.98899],"type":"Point"}
}