{
  "type": "Feature",
  "properties": {
    "gn:admin1_code":"21.0",
    "gn:admin2_code":"573.0",
    "gn:asciiname":"Lonne",
    "gn:country_code":"DK",
    "gn:dem":3,
    "gn:feature_class":"P",
    "gn:feature_code":"PPLL",
    "gn:name":"L\u00f8nne",
    "gn:population":0,
    "gn:timezone":"Europe/Copenhagen",
    "iso:country":"DK",
    "wof:name":"Lonne",
    "wof:placetype":"locality"
},
  "geometry": {"coordinates":[8.23709,55.8006],"type":"Point"}
}