{
  "type": "Feature",
  "properties": {
    "gn:admin1_code":"21.0",
    "gn:admin2_code":"550.0",
    "gn:asciiname":"Rejsby",
    "gn:country_code":"DK",
    "gn:dem":5,
    "gn:feature_class":"P",
    "gn:feature_code":"PPL",
    "gn:name":"Rejsby",
    "gn:population":0,
    "gn:timezone":"Europe/Copenhagen",
    "iso:country":"DK",
    "name:und_x_variant":[
        "Reisby",
        "Rejsby"
    ],
    "wof:name":"Rejsby",
    "wof:placetype":"locality"
},
  "geometry": {"coordinates":[8.72349,55.23242],"type":"Point"}
}