{
  "type": "Feature",
  "properties": {
    "gn:admin1_code":"18.0",
    "gn:admin2_code":"760.0",
    "gn:asciiname":"Hanning",
    "gn:country_code":"DK",
    "gn:dem":35,
    "gn:feature_class":"P",
    "gn:feature_code":"PPL",
    "gn:name":"Hanning",
    "gn:population":0,
    "gn:timezone":"Europe/Copenhagen",
    "iso:country":"DK",
    "name:rus_x_preferred":[
        "\u0425\u0430\u043d\u043d\u0438\u043d\u0433"
    ],
    "wof:name":"Hanning",
    "wof:placetype":"locality"
},
  "geometry": {"coordinates":[8.51359,56.01819],"type":"Point"}
}