{
  "type": "Feature",
  "properties": {
    "gn:admin1_code":"20.0",
    "gn:admin2_code":"370.0",
    "gn:asciiname":"Sandby",
    "gn:country_code":"DK",
    "gn:dem":41,
    "gn:feature_class":"P",
    "gn:feature_code":"PPL",
    "gn:name":"Sandby",
    "gn:population":0,
    "gn:timezone":"Europe/Copenhagen",
    "iso:country":"DK",
    "name:ceb_x_preferred":[
        "Sandby"
    ],
    "name:dan_x_preferred":[
        "Sandby"
    ],
    "name:nld_x_preferred":[
        "Sandby"
    ],
    "name:swe_x_preferred":[
        "Sandby"
    ],
    "wof:name":"Sandby",
    "wof:placetype":"locality"
},
  "geometry": {"coordinates":[11.7437,55.37901],"type":"Point"}
}