{
  "type": "Feature",
  "properties": {
    "iso:country":"DK",
    "name:ast_x_preferred":[
        "Guldborg"
    ],
    "name:bul_x_preferred":[
        "\u0413\u0443\u043b\u0434\u0431\u043e\u0440\u0433"
    ],
    "name:cat_x_preferred":[
        "Guldborg"
    ],
    "name:ceb_x_preferred":[
        "Guldborg"
    ],
    "name:dan_x_preferred":[
        "Guldborg"
    ],
    "name:deu_x_preferred":[
        "Guldborg"
    ],
    "name:eng_x_preferred":[
        "Guldborg"
    ],
    "name:fra_x_preferred":[
        "Guldborg"
    ],
    "name:nld_x_preferred":[
        "Guldborg"
    ],
    "name:nno_x_preferred":[
        "Guldborg"
    ],
    "name:nob_x_preferred":[
        "Guldborg"
    ],
    "name:pol_x_preferred":[
        "Guldborg"
    ],
    "name:swe_x_preferred":[
        "Guldborg"
    ],
    "qs_pg:aaroncc":"DK",
    "qs_pg:name":"Guldborg",
    "qs_pg:name_adm0":"Danmark",
    "qs_pg:name_adm1":"Sj\u00e6lland",
    "qs_pg:photos":41,
    "qs_pg:photos_1k":8,
    "qs_pg:photos_9k":1,
    "qs_pg:photos_9r":2,
    "qs_pg:photos_all":41,
    "qs_pg:photos_sr":2,
    "qs_pg:pop_sr":0,
    "qs_pg:qs_pg_placetype":"locality",
    "qs_pg:qs_pg_placetype_gp":"Town",
    "qs_pg:woe_adm0":23424796,
    "woe:adm0_id":23424796,
    "woe:name_adm0":"Danmark",
    "woe:name_adm1":"Sj\u00e6lland",
    "woe:placetype":"Town",
    "wof:name":"Guldborg",
    "wof:placetype":"locality"
},
  "geometry": {"coordinates":[11.755371,54.878384],"type":"Point"}
}