{
  "type": "Feature",
  "properties": {
    "gn:admin1_code":"20.0",
    "gn:admin2_code":"330.0",
    "gn:asciiname":"Stude",
    "gn:country_code":"DK",
    "gn:dem":12,
    "gn:feature_class":"P",
    "gn:feature_code":"PPL",
    "gn:name":"Stude",
    "gn:population":0,
    "gn:timezone":"Europe/Copenhagen",
    "iso:country":"DK",
    "wof:name":"Stude",
    "wof:placetype":"locality"
},
  "geometry": {"coordinates":[11.27446,55.33149],"type":"Point"}
}