{
  "type": "Feature",
  "properties": {
    "gn:admin1_code":"18.0",
    "gn:admin2_code":"657.0",
    "gn:asciiname":"Asbaekhede",
    "gn:country_code":"DK",
    "gn:dem":49,
    "gn:feature_class":"P",
    "gn:feature_code":"PPLL",
    "gn:name":"Asb\u00e6khede",
    "gn:population":0,
    "gn:timezone":"Europe/Copenhagen",
    "iso:country":"DK",
    "wof:name":"Asbaekhede",
    "wof:placetype":"locality"
},
  "geometry": {"coordinates":[8.79859,56.22755],"type":"Point"}
}