{
  "type": "Feature",
  "properties": {
    "gn:admin1_code":"18.0",
    "gn:admin2_code":"791.0",
    "gn:asciiname":"Daugbjerg",
    "gn:country_code":"DK",
    "gn:dem":25,
    "gn:feature_class":"P",
    "gn:feature_code":"PPL",
    "gn:name":"Daugbjerg",
    "gn:population":0,
    "gn:timezone":"Europe/Copenhagen",
    "iso:country":"DK",
    "name:und_x_variant":[
        "Davbjerg",
        "Dagbj\u00e6rg",
        "Daugbjerg"
    ],
    "wof:name":"Daugbjerg",
    "wof:placetype":"locality"
},
  "geometry": {"coordinates":[9.13141,56.43592],"type":"Point"}
}