{
  "type": "Feature",
  "properties": {
    "gn:admin1_code":"20.0",
    "gn:admin2_code":"360.0",
    "gn:asciiname":"Norre Tvede",
    "gn:country_code":"DK",
    "gn:dem":9,
    "gn:feature_class":"P",
    "gn:feature_code":"PPL",
    "gn:name":"N\u00f8rre Tvede",
    "gn:population":0,
    "gn:timezone":"Europe/Copenhagen",
    "iso:country":"DK",
    "wof:name":"Norre Tvede",
    "wof:placetype":"locality"
},
  "geometry": {"coordinates":[11.24749,54.93485],"type":"Point"}
}