{
  "type": "Feature",
  "properties": {
    "gn:admin1_code":"20.0",
    "gn:admin2_code":"370.0",
    "gn:asciiname":"Snesere",
    "gn:country_code":"DK",
    "gn:dem":45,
    "gn:feature_class":"P",
    "gn:feature_code":"PPL",
    "gn:name":"Snesere",
    "gn:population":0,
    "gn:timezone":"Europe/Copenhagen",
    "iso:country":"DK",
    "wof:name":"Snesere",
    "wof:placetype":"locality"
},
  "geometry": {"coordinates":[11.93267,55.16513000000001],"type":"Point"}
}