{
  "type": "Feature",
  "properties": {
    "gn:admin1_code":"21.0",
    "gn:admin2_code":"450.0",
    "gn:asciiname":"Alokke",
    "gn:country_code":"DK",
    "gn:dem":8,
    "gn:feature_class":"P",
    "gn:feature_code":"PPL",
    "gn:name":"\u00c5l\u00f8kke",
    "gn:population":0,
    "gn:timezone":"Europe/Copenhagen",
    "iso:country":"DK",
    "name:und_x_variant":[
        "Aal\u00f6kke",
        "Aalykke",
        "\u00c5l\u00f8kke"
    ],
    "wof:name":"Alokke",
    "wof:placetype":"locality"
},
  "geometry": {"coordinates":[10.71452,55.33619],"type":"Point"}
}