{
  "type": "Feature",
  "properties": {
    "gn:admin1_code":"18.0",
    "gn:admin2_code":"710.0",
    "gn:asciiname":"Tinning",
    "gn:country_code":"DK",
    "gn:dem":78,
    "gn:feature_class":"P",
    "gn:feature_code":"PPL",
    "gn:name":"Tinning",
    "gn:population":0,
    "gn:timezone":"Europe/Copenhagen",
    "iso:country":"DK",
    "name:ara_x_preferred":[
        "\u0642\u0635\u062f\u0631\u0629"
    ],
    "name:aze_x_preferred":[
        "Qalay\u00e7\u0131l\u0131q"
    ],
    "name:bul_x_preferred":[
        "\u041a\u0430\u043b\u0430\u0439\u0434\u0438\u0441\u0432\u0430\u043d\u0435"
    ],
    "name:cat_x_preferred":[
        "Llauna"
    ],
    "name:deu_x_preferred":[
        "Verzinnen"
    ],
    "name:fas_x_preferred":[
        "\u0642\u0644\u0639\u200c\u0627\u0646\u062f\u0648\u062f \u06a9\u0631\u062f\u0646"
    ],
    "name:fra_x_preferred":[
        "\u00c9tamage"
    ],
    "name:gle_x_preferred":[
        "St\u00e1nphl\u00e1ta"
    ],
    "name:hrv_x_preferred":[
        "Kositrenje"
    ],
    "name:hun_x_preferred":[
        "B\u00e1dog"
    ],
    "name:hye_x_preferred":[
        "\u0531\u0576\u0561\u0563\u0561\u057a\u0561\u057f\u0578\u0582\u0574"
    ],
    "name:kan_x_preferred":[
        "\u0ca4\u0cb5\u0cb0 \u0cb2\u0cc7\u0caa\u0ca8"
    ],
    "name:nld_x_preferred":[
        "Vertinnen"
    ],
    "name:pol_x_preferred":[
        "Cynowanie"
    ],
    "name:rus_x_preferred":[
        "\u041b\u0443\u0436\u0435\u043d\u0438\u0435"
    ],
    "name:swe_x_preferred":[
        "F\u00f6rtenning"
    ],
    "name:ukr_x_preferred":[
        "\u041b\u0443\u0434\u0456\u043d\u043d\u044f"
    ],
    "wof:name":"Tinning",
    "wof:placetype":"locality"
},
  "geometry": {"coordinates":[9.99634,56.26438],"type":"Point"}
}