{
  "type": "Feature",
  "properties": {
    "gn:admin1_code":"18.0",
    "gn:admin2_code":"756.0",
    "gn:asciiname":"Dorslund",
    "gn:country_code":"DK",
    "gn:dem":52,
    "gn:feature_class":"P",
    "gn:feature_code":"PPL",
    "gn:name":"D\u00f8rslund",
    "gn:population":0,
    "gn:timezone":"Europe/Copenhagen",
    "iso:country":"DK",
    "wof:name":"Dorslund",
    "wof:placetype":"locality"
},
  "geometry": {"coordinates":[9.12383,55.96591],"type":"Point"}
}