{
  "type": "Feature",
  "properties": {
    "gn:admin1_code":"20.0",
    "gn:admin2_code":"360.0",
    "gn:asciiname":"Ryde",
    "gn:country_code":"DK",
    "gn:dem":2,
    "gn:feature_class":"P",
    "gn:feature_code":"PPL",
    "gn:name":"Ryde",
    "gn:population":0,
    "gn:timezone":"Europe/Copenhagen",
    "iso:country":"DK",
    "name:azb_x_preferred":[
        "\u0631\u0627\u06cc\u062f"
    ],
    "name:ceb_x_preferred":[
        "Ryde"
    ],
    "name:cym_x_preferred":[
        "Ryde"
    ],
    "name:dan_x_preferred":[
        "Ryde"
    ],
    "name:deu_x_preferred":[
        "Ryde"
    ],
    "name:fas_x_preferred":[
        "\u0631\u0627\u06cc\u062f"
    ],
    "name:fra_x_preferred":[
        "Ryde"
    ],
    "name:gle_x_preferred":[
        "Ryde"
    ],
    "name:ita_x_preferred":[
        "Ryde"
    ],
    "name:lat_x_preferred":[
        "Ryde"
    ],
    "name:nld_x_preferred":[
        "Ryde"
    ],
    "name:nno_x_preferred":[
        "Ryde"
    ],
    "name:pol_x_preferred":[
        "Ryde"
    ],
    "name:ron_x_preferred":[
        "Ryde"
    ],
    "name:rus_x_preferred":[
        "\u0420\u0430\u0439\u0434"
    ],
    "name:spa_x_preferred":[
        "Ryde"
    ],
    "name:swe_x_preferred":[
        "Ryde"
    ],
    "name:vol_x_preferred":[
        "Ryde"
    ],
    "name:zho_x_preferred":[
        "\u8cf4\u5fb7"
    ],
    "wof:name":"Ryde",
    "wof:placetype":"locality"
},
  "geometry": {"coordinates":[11.30538,54.79646],"type":"Point"}
}