{
  "type": "Feature",
  "properties": {
    "gn:admin1_code":"19.0",
    "gn:admin2_code":"846.0",
    "gn:asciiname":"Onsild Stationsby",
    "gn:country_code":"DK",
    "gn:dem":13,
    "gn:feature_class":"P",
    "gn:feature_code":"PPL",
    "gn:name":"Onsild Stationsby",
    "gn:population":0,
    "gn:timezone":"Europe/Copenhagen",
    "iso:country":"DK",
    "name:und_x_variant":[
        "Onsilo",
        "Onsild Stationsby"
    ],
    "wof:name":"Onsild Stationsby",
    "wof:placetype":"locality"
},
  "geometry": {"coordinates":[9.74751,56.57685],"type":"Point"}
}