{
  "type": "Feature",
  "properties": {
    "gn:admin1_code":"18.0",
    "gn:admin2_code":"766.0",
    "gn:asciiname":"Bogballe",
    "gn:country_code":"DK",
    "gn:dem":63,
    "gn:feature_class":"P",
    "gn:feature_code":"PPL",
    "gn:name":"B\u00f8gballe",
    "gn:population":0,
    "gn:timezone":"Europe/Copenhagen",
    "iso:country":"DK",
    "wof:name":"Bogballe",
    "wof:placetype":"locality"
},
  "geometry": {"coordinates":[9.61767,55.82526],"type":"Point"}
}