{
  "type": "Feature",
  "properties": {
    "gn:admin1_code":"18.0",
    "gn:admin2_code":"791.0",
    "gn:asciiname":"Bredholt",
    "gn:country_code":"DK",
    "gn:dem":50,
    "gn:feature_class":"P",
    "gn:feature_code":"PPL",
    "gn:name":"Bredholt",
    "gn:population":0,
    "gn:timezone":"Europe/Copenhagen",
    "iso:country":"DK",
    "wof:name":"Bredholt",
    "wof:placetype":"locality"
},
  "geometry": {"coordinates":[9.66488,56.33049000000001],"type":"Point"}
}