{
  "type": "Feature",
  "properties": {
    "iso:country":"DK",
    "name:cat_x_preferred":[
        "Elling"
    ],
    "name:dan_x_preferred":[
        "Elling"
    ],
    "name:deu_x_preferred":[
        "Elling"
    ],
    "name:eng_x_preferred":[
        "Elling"
    ],
    "name:fra_x_preferred":[
        "Elling"
    ],
    "name:glg_x_preferred":[
        "Elling"
    ],
    "name:ita_x_preferred":[
        "Elling"
    ],
    "name:nld_x_preferred":[
        "Elling"
    ],
    "name:nob_x_preferred":[
        "Elling"
    ],
    "name:spa_x_preferred":[
        "Elling"
    ],
    "qs:a0":"Danmark",
    "qs:a1":"*Nordjylland",
    "qs:a1r":"0",
    "qs:adm0":"Danmark",
    "qs:la_lc":"*",
    "qs:level":"locality",
    "qs:loc":"Elling",
    "qs:loc_alt":"Elling",
    "qs:pop":0,
    "qs:type":"buffered point",
    "wd:wordcount":182,
    "wof:name":"Elling",
    "wof:placetype":"locality"
},
  "geometry": {"coordinates":[10.487197,57.482427],"type":"Point"}
}