{
  "type": "Feature",
  "properties": {
    "gn:admin1_code":"20.0",
    "gn:admin2_code":"340.0",
    "gn:asciiname":"Verup",
    "gn:country_code":"DK",
    "gn:dem":31,
    "gn:feature_class":"P",
    "gn:feature_code":"PPL",
    "gn:name":"Verup",
    "gn:population":0,
    "gn:timezone":"Europe/Copenhagen",
    "iso:country":"DK",
    "wof:name":"Verup",
    "wof:placetype":"locality"
},
  "geometry": {"coordinates":[11.50982,55.56138000000001],"type":"Point"}
}