{
  "type": "Feature",
  "properties": {
    "gn:admin1_code":"18.0",
    "gn:admin2_code":"791.0",
    "gn:asciiname":"Kjeldbjerg",
    "gn:country_code":"DK",
    "gn:dem":55,
    "gn:feature_class":"P",
    "gn:feature_code":"PPL",
    "gn:name":"Kjeldbjerg",
    "gn:population":0,
    "gn:timezone":"Europe/Copenhagen",
    "iso:country":"DK",
    "name:und_x_variant":[
        "Keldbj\u00e6rg",
        "Kjeldbjerg"
    ],
    "wof:name":"Kjeldbjerg",
    "wof:placetype":"locality"
},
  "geometry": {"coordinates":[9.05226,56.47363000000001],"type":"Point"}
}