{
  "type": "Feature",
  "properties": {
    "gn:admin1_code":"18.0",
    "gn:admin2_code":"730.0",
    "gn:asciiname":"Tebbestrup",
    "gn:country_code":"DK",
    "gn:dem":56,
    "gn:feature_class":"P",
    "gn:feature_code":"PPL",
    "gn:name":"Tebbestrup",
    "gn:population":0,
    "gn:timezone":"Europe/Copenhagen",
    "iso:country":"DK",
    "wof:name":"Tebbestrup",
    "wof:placetype":"locality"
},
  "geometry": {"coordinates":[10.00753,56.43526],"type":"Point"}
}