{
  "type": "Feature",
  "properties": {
    "gn:admin1_code":"17.0",
    "gn:admin2_code":"400.0",
    "gn:asciiname":"Svinemose",
    "gn:country_code":"DK",
    "gn:dem":106,
    "gn:feature_class":"P",
    "gn:feature_code":"PPL",
    "gn:name":"Svinemose",
    "gn:population":0,
    "gn:timezone":"Europe/Copenhagen",
    "iso:country":"DK",
    "wof:name":"Svinemose",
    "wof:placetype":"locality"
},
  "geometry": {"coordinates":[14.94827,55.10796],"type":"Point"}
}