{
  "type": "Feature",
  "properties": {
    "gn:admin1_code":"19.0",
    "gn:admin2_code":"849.0",
    "gn:asciiname":"Bleggrav",
    "gn:country_code":"DK",
    "gn:dem":11,
    "gn:feature_class":"P",
    "gn:feature_code":"PPL",
    "gn:name":"Bleggrav",
    "gn:population":0,
    "gn:timezone":"Europe/Copenhagen",
    "iso:country":"DK",
    "wof:name":"Bleggrav",
    "wof:placetype":"locality"
},
  "geometry": {"coordinates":[9.64129,57.19485],"type":"Point"}
}