{
  "type": "Feature",
  "properties": {
    "gn:admin1_code":"20.0",
    "gn:admin2_code":"390.0",
    "gn:asciiname":"Keldbylille",
    "gn:country_code":"DK",
    "gn:dem":13,
    "gn:feature_class":"P",
    "gn:feature_code":"PPL",
    "gn:name":"Keldbylille",
    "gn:population":0,
    "gn:timezone":"Europe/Copenhagen",
    "iso:country":"DK",
    "wof:name":"Keldbylille",
    "wof:placetype":"locality"
},
  "geometry": {"coordinates":[12.35384,54.97881],"type":"Point"}
}