{
  "type": "Feature",
  "properties": {
    "gn:country":"DK",
    "gn:fcode":"PPL",
    "gn:population":0,
    "iso:country":"DK",
    "name:ceb_x_preferred":[
        "Nyord"
    ],
    "name:dan_x_preferred":[
        "Nyord"
    ],
    "name:deu_x_preferred":[
        "Nyord"
    ],
    "name:fra_x_preferred":[
        "Nyord"
    ],
    "name:kat_x_preferred":[
        "\u10dc\u10d8\u10dd\u10e0\u10d3\u10d8"
    ],
    "name:lit_x_preferred":[
        "Niordas"
    ],
    "name:nno_x_preferred":[
        "\u00d8ya Nyord"
    ],
    "name:nor_x_preferred":[
        "Nyord"
    ],
    "name:spa_x_preferred":[
        "Nyord"
    ],
    "name:swe_x_preferred":[
        "Nyord"
    ],
    "name:und_x_variant":[
        "Nyord By"
    ],
    "name:vie_x_preferred":[
        "Nyord"
    ],
    "name:zho_x_preferred":[
        "\u5c3c\u5967\u5cf6"
    ],
    "qs_pg:aaroncc":"DK",
    "qs_pg:gn_country":"DK",
    "qs_pg:gn_fcode":"PPL",
    "qs_pg:gn_pop":0,
    "qs_pg:name":"Nyord",
    "qs_pg:name_adm0":"Danmark",
    "qs_pg:name_adm1":"Sj\u00e6lland",
    "qs_pg:photos":114,
    "qs_pg:photos_1k":23,
    "qs_pg:photos_9k":1,
    "qs_pg:photos_9r":3,
    "qs_pg:photos_all":114,
    "qs_pg:photos_sr":3,
    "qs_pg:pop_sr":0,
    "qs_pg:qs_pg_placetype":"locality",
    "qs_pg:qs_pg_placetype_gp":"Town",
    "qs_pg:woe_adm0":23424796,
    "woe:adm0_id":23424796,
    "woe:name_adm0":"Danmark",
    "woe:name_adm1":"Sj\u00e6lland",
    "woe:placetype":"Town",
    "wof:name":"Nyord",
    "wof:placetype":"locality"
},
  "geometry": {"coordinates":[12.19458,55.04093],"type":"Point"}
}