{
  "type": "Feature",
  "properties": {
    "gn:admin1_code":"18.0",
    "gn:admin2_code":"756.0",
    "gn:asciiname":"Store Norlund",
    "gn:country_code":"DK",
    "gn:dem":73,
    "gn:feature_class":"P",
    "gn:feature_code":"PPLL",
    "gn:name":"Store N\u00f8rlund",
    "gn:population":0,
    "gn:timezone":"Europe/Copenhagen",
    "iso:country":"DK",
    "wof:name":"Store Norlund",
    "wof:placetype":"locality"
},
  "geometry": {"coordinates":[9.26134,56.04577],"type":"Point"}
}