{
  "type": "Feature",
  "properties": {
    "gn:admin1_code":"21.0",
    "gn:admin2_code":"479.0",
    "gn:asciiname":"Holmdrup",
    "gn:country_code":"DK",
    "gn:dem":61,
    "gn:feature_class":"P",
    "gn:feature_code":"PPL",
    "gn:name":"Holmdrup",
    "gn:population":0,
    "gn:timezone":"Europe/Copenhagen",
    "iso:country":"DK",
    "wof:name":"Holmdrup",
    "wof:placetype":"locality"
},
  "geometry": {"coordinates":[10.65835,55.09589],"type":"Point"}
}