{
  "type": "Feature",
  "properties": {
    "gn:admin1_code":"19.0",
    "gn:admin2_code":"851.0",
    "gn:asciiname":"Sonderholm",
    "gn:country_code":"DK",
    "gn:dem":15,
    "gn:feature_class":"P",
    "gn:feature_code":"PPL",
    "gn:name":"S\u00f8nderholm",
    "gn:population":0,
    "gn:timezone":"Europe/Copenhagen",
    "iso:country":"DK",
    "wof:name":"Sonderholm",
    "wof:placetype":"locality"
},
  "geometry": {"coordinates":[9.73543,57.00308],"type":"Point"}
}