{
  "type": "Feature",
  "properties": {
    "gn:admin1_code":"17.0",
    "gn:admin2_code":"250.0",
    "gn:asciiname":"Store Rorbaek",
    "gn:country_code":"DK",
    "gn:dem":22,
    "gn:feature_class":"P",
    "gn:feature_code":"PPL",
    "gn:name":"Store R\u00f8rb\u00e6k",
    "gn:population":0,
    "gn:timezone":"Europe/Copenhagen",
    "iso:country":"DK",
    "wof:name":"Store Rorbaek",
    "wof:placetype":"locality"
},
  "geometry": {"coordinates":[12.11661,55.79913000000001],"type":"Point"}
}