{
  "type": "Feature",
  "properties": {
    "gn:country":"DK",
    "gn:fcode":"PPL",
    "gn:population":0,
    "iso:country":"DK",
    "name:ast_x_preferred":[
        "Lejre"
    ],
    "name:ceb_x_preferred":[
        "Lejre"
    ],
    "name:dan_x_preferred":[
        "Lejre"
    ],
    "name:deu_x_preferred":[
        "Lejre"
    ],
    "name:eng_x_preferred":[
        "Lejre"
    ],
    "name:epo_x_preferred":[
        "Lejre"
    ],
    "name:fra_x_preferred":[
        "Lejre"
    ],
    "name:heb_x_preferred":[
        "\u05dc\u05d9\u05d9\u05e8\u05d4"
    ],
    "name:hun_x_preferred":[
        "Lejre"
    ],
    "name:ita_x_preferred":[
        "Lejre"
    ],
    "name:jpn_x_preferred":[
        "\u30ec\u30a4\u30ec"
    ],
    "name:lav_x_preferred":[
        "Lejre"
    ],
    "name:lit_x_preferred":[
        "Lair\u0117"
    ],
    "name:nld_x_preferred":[
        "Lejre"
    ],
    "name:nob_x_preferred":[
        "Lejre"
    ],
    "name:pol_x_preferred":[
        "Lejre"
    ],
    "name:por_x_preferred":[
        "Lejre"
    ],
    "name:spa_x_preferred":[
        "Lejre"
    ],
    "name:swe_x_preferred":[
        "Lejre"
    ],
    "name:zho_x_preferred":[
        "\u83b1\u5c14"
    ],
    "qs_pg:aaroncc":"DK",
    "qs_pg:gn_country":"DK",
    "qs_pg:gn_fcode":"PPL",
    "qs_pg:gn_pop":0,
    "qs_pg:name":"Gammel Lejre",
    "qs_pg:name_adm0":"Danmark",
    "qs_pg:name_adm1":"Sj\u00e6lland",
    "qs_pg:photos":266,
    "qs_pg:photos_1k":54,
    "qs_pg:photos_9k":1,
    "qs_pg:photos_9r":4,
    "qs_pg:photos_all":266,
    "qs_pg:photos_sr":5,
    "qs_pg:pop_sr":0,
    "qs_pg:qs_pg_placetype":"locality",
    "qs_pg:qs_pg_placetype_gp":"Town",
    "qs_pg:woe_adm0":23424796,
    "woe:adm0_id":23424796,
    "woe:name_adm0":"Danmark",
    "woe:name_adm1":"Sj\u00e6lland",
    "woe:placetype":"Town",
    "wof:name":"Gammel Lejre",
    "wof:placetype":"locality"
},
  "geometry": {"coordinates":[11.96904,55.61784],"type":"Point"}
}