{
  "type": "Feature",
  "properties": {
    "gn:admin1_code":"20.0",
    "gn:admin2_code":"370.0",
    "gn:asciiname":"Aversi",
    "gn:country_code":"DK",
    "gn:dem":40,
    "gn:feature_class":"P",
    "gn:feature_code":"PPL",
    "gn:name":"Aversi",
    "gn:population":0,
    "gn:timezone":"Europe/Copenhagen",
    "iso:country":"DK",
    "wof:name":"Aversi",
    "wof:placetype":"locality"
},
  "geometry": {"coordinates":[11.85411,55.34452],"type":"Point"}
}