{
  "type": "Feature",
  "properties": {
    "gn:admin1_code":"20.0",
    "gn:admin2_code":"370.0",
    "gn:asciiname":"Aversi",
    "gn:country_code":"DK",
    "gn:dem":40,
    "gn:feature_class":"P",
    "gn:feature_code":"PPL",
    "gn:name":"Aversi",
    "gn:population":0,
    "gn:timezone":"Europe/Copenhagen",
    "iso:country":"DK",
    "name:ara_x_preferred":[
        "\u0623\u0648\u0631\u0633\u064a"
    ],
    "name:azb_x_preferred":[
        "\u0627\u0648\u0631\u0633\u06cc"
    ],
    "name:aze_x_preferred":[
        "Aversi"
    ],
    "name:ceb_x_preferred":[
        "Avers\u012b"
    ],
    "name:ckb_x_preferred":[
        "\u0626\u06d5\u0648\u0631\u0633\u06cc"
    ],
    "name:fas_x_preferred":[
        "\u0627\u0648\u0631\u0633\u06cc"
    ],
    "name:kur_x_preferred":[
        "Ewrisi"
    ],
    "name:msa_x_preferred":[
        "Aversi"
    ],
    "name:swe_x_preferred":[
        "Avers\u012b"
    ],
    "wof:name":"Aversi",
    "wof:placetype":"locality"
},
  "geometry": {"coordinates":[11.85411,55.34452],"type":"Point"}
}