{
  "type": "Feature",
  "properties": {
    "gn:admin1_code":"21.0",
    "gn:admin2_code":"420.0",
    "gn:asciiname":"Skarup",
    "gn:country_code":"DK",
    "gn:dem":27,
    "gn:feature_class":"P",
    "gn:feature_code":"PPL",
    "gn:name":"Sk\u00e5rup",
    "gn:population":0,
    "gn:timezone":"Europe/Copenhagen",
    "iso:country":"DK",
    "name:und_x_variant":[
        "Skaarup",
        "Sk\u00e5rup"
    ],
    "wof:name":"Skarup",
    "wof:placetype":"locality"
},
  "geometry": {"coordinates":[10.05488,55.21751999999999],"type":"Point"}
}