{
  "type": "Feature",
  "properties": {
    "gn:admin1_code":"21.0",
    "gn:admin2_code":"550.0",
    "gn:asciiname":"Jejsing",
    "gn:country_code":"DK",
    "gn:dem":7,
    "gn:feature_class":"P",
    "gn:feature_code":"PPL",
    "gn:name":"Jejsing",
    "gn:population":0,
    "gn:timezone":"Europe/Copenhagen",
    "iso:country":"DK",
    "wof:name":"Jejsing",
    "wof:placetype":"locality"
},
  "geometry": {"coordinates":[8.96224,54.93861999999999],"type":"Point"}
}