{
  "type": "Feature",
  "properties": {
    "gn:gn_country":"DK",
    "gn:gn_fcode":"PPL",
    "gn:gn_pop":0,
    "iso:country":"DK",
    "name:dan_x_preferred":[
        "Gladsaxe"
    ],
    "name:deu_x_preferred":[
        "Gladsaxe"
    ],
    "name:eng_x_preferred":[
        "Gladsaxe"
    ],
    "name:fao_x_preferred":[
        "Gladsaxe"
    ],
    "name:fra_x_preferred":[
        "Gladsaxe"
    ],
    "name:ita_x_preferred":[
        "Gladsaxe"
    ],
    "name:nld_x_preferred":[
        "Gladsaxe"
    ],
    "name:nor_x_preferred":[
        "Gladsaxe"
    ],
    "name:pol_x_preferred":[
        "Gmina Gladsaxe"
    ],
    "name:por_x_preferred":[
        "Gladsaxe"
    ],
    "name:swe_x_preferred":[
        "Gladsaxe"
    ],
    "qs_pg:aaroncc":"DK",
    "qs_pg:gn_country":"DK",
    "qs_pg:gn_fcode":"PPL",
    "qs_pg:gn_pop":0,
    "qs_pg:name":"Gladsaxe",
    "qs_pg:name_adm0":"Danmark",
    "qs_pg:name_adm1":"Hovedstaden",
    "qs_pg:photos":243,
    "qs_pg:photos_1k":49,
    "qs_pg:photos_9k":39,
    "qs_pg:photos_9r":15,
    "qs_pg:photos_all":8708,
    "qs_pg:photos_sr":4,
    "qs_pg:pop_sr":0,
    "qs_pg:qs_pg_placetype":"locality",
    "qs_pg:qs_pg_placetype_gp":"Town",
    "qs_pg:woe_adm0":23424796,
    "woe:adm0_id":23424796,
    "woe:name_adm0":"Danmark",
    "woe:name_adm1":"Hovedstaden",
    "woe:placetype":"Town",
    "wof:name":"Gladsaxe",
    "wof:placetype":"locality"
},
  "geometry": {"coordinates":[12.48159,55.73797],"type":"Point"}
}