{
  "type": "Feature",
  "properties": {
    "gn:admin1_code":"20.0",
    "gn:admin2_code":"316.0",
    "gn:asciiname":"Krojerup",
    "gn:country_code":"DK",
    "gn:dem":43,
    "gn:feature_class":"P",
    "gn:feature_code":"PPL",
    "gn:name":"Kr\u00f8jerup",
    "gn:population":0,
    "gn:timezone":"Europe/Copenhagen",
    "iso:country":"DK",
    "wof:name":"Krojerup",
    "wof:placetype":"locality"
},
  "geometry": {"coordinates":[11.59676,55.6486],"type":"Point"}
}