{
  "type": "Feature",
  "properties": {
    "gn:admin1_code":"20.0",
    "gn:admin2_code":"320.0",
    "gn:asciiname":"Rode",
    "gn:country_code":"DK",
    "gn:dem":31,
    "gn:feature_class":"P",
    "gn:feature_code":"PPL",
    "gn:name":"Rode",
    "gn:population":0,
    "gn:timezone":"Europe/Copenhagen",
    "iso:country":"DK",
    "name:cat_x_preferred":[
        "Rode"
    ],
    "name:ceb_x_preferred":[
        "Rode"
    ],
    "name:dan_x_preferred":[
        "Rode"
    ],
    "name:deu_x_preferred":[
        "Rode"
    ],
    "name:fra_x_preferred":[
        "Rode"
    ],
    "name:ita_x_preferred":[
        "Rode"
    ],
    "name:lav_x_preferred":[
        "Rode"
    ],
    "name:nld_x_preferred":[
        "Rode"
    ],
    "name:pol_x_preferred":[
        "Rode"
    ],
    "name:por_x_preferred":[
        "Rode"
    ],
    "name:rus_x_preferred":[
        "\u0420\u043e\u0434\u0435"
    ],
    "name:swe_x_preferred":[
        "Rode"
    ],
    "name:ukr_x_preferred":[
        "\u0420\u043e\u0434\u0435"
    ],
    "wof:name":"Rode",
    "wof:placetype":"locality"
},
  "geometry": {"coordinates":[12.05253,55.29945],"type":"Point"}
}