{
  "type": "Feature",
  "properties": {
    "gn:admin1_code":"20.0",
    "gn:admin2_code":"340.0",
    "gn:asciiname":"Alsted-Flinterup",
    "gn:country_code":"DK",
    "gn:dem":34,
    "gn:feature_class":"P",
    "gn:feature_code":"PPL",
    "gn:name":"Alsted-Flinterup",
    "gn:population":0,
    "gn:timezone":"Europe/Copenhagen",
    "iso:country":"DK",
    "wof:name":"Alsted-Flinterup",
    "wof:placetype":"locality"
},
  "geometry": {"coordinates":[11.68116,55.42283000000001],"type":"Point"}
}