{
  "type": "Feature",
  "properties": {
    "gn:admin1_code":"20.0",
    "gn:admin2_code":"360.0",
    "gn:asciiname":"Lilleskovland",
    "gn:country_code":"DK",
    "gn:dem":-3,
    "gn:feature_class":"P",
    "gn:feature_code":"PPL",
    "gn:name":"Lilleskovland",
    "gn:population":0,
    "gn:timezone":"Europe/Copenhagen",
    "iso:country":"DK",
    "wof:name":"Lilleskovland",
    "wof:placetype":"locality"
},
  "geometry": {"coordinates":[11.20916,54.72554],"type":"Point"}
}