{
  "type": "Feature",
  "properties": {
    "gn:admin1_code":"21.0",
    "gn:admin2_code":"410.0",
    "gn:asciiname":"Rydskov",
    "gn:country_code":"DK",
    "gn:dem":52,
    "gn:feature_class":"P",
    "gn:feature_code":"PPL",
    "gn:name":"Rydskov",
    "gn:population":0,
    "gn:timezone":"Europe/Copenhagen",
    "iso:country":"DK",
    "wof:name":"Rydskov",
    "wof:placetype":"locality"
},
  "geometry": {"coordinates":[10.06005,55.43346],"type":"Point"}
}