{
  "type": "Feature",
  "properties": {
    "gn:admin1_code":"20.0",
    "gn:admin2_code":"376.0",
    "gn:asciiname":"Byskov",
    "gn:country_code":"DK",
    "gn:dem":4,
    "gn:feature_class":"P",
    "gn:feature_code":"PPL",
    "gn:name":"Byskov",
    "gn:population":0,
    "gn:timezone":"Europe/Copenhagen",
    "iso:country":"DK",
    "wof:name":"Byskov",
    "wof:placetype":"locality"
},
  "geometry": {"coordinates":[11.84121,54.83771],"type":"Point"}
}