{
  "type": "Feature",
  "properties": {
    "gn:admin1_code":"18.0",
    "gn:admin2_code":"706.0",
    "gn:asciiname":"Bjodstrup",
    "gn:country_code":"DK",
    "gn:dem":28,
    "gn:feature_class":"P",
    "gn:feature_code":"PPL",
    "gn:name":"Bj\u00f8dstrup",
    "gn:population":0,
    "gn:timezone":"Europe/Copenhagen",
    "iso:country":"DK",
    "wof:name":"Bjodstrup",
    "wof:placetype":"locality"
},
  "geometry": {"coordinates":[10.39599,56.17538],"type":"Point"}
}