{
  "type": "Feature",
  "properties": {
    "gn:country":"DK",
    "gn:fcode":"PPL",
    "gn:population":0,
    "iso:country":"DK",
    "name:dan_x_preferred":[
        "Brundby"
    ],
    "name:deu_x_preferred":[
        "Brundby"
    ],
    "name:eng_x_preferred":[
        "Brundby"
    ],
    "name:fao_x_preferred":[
        "Brundby"
    ],
    "name:fra_x_preferred":[
        "Brundby"
    ],
    "name:isl_x_preferred":[
        "Brundby"
    ],
    "name:kal_x_preferred":[
        "Brundby"
    ],
    "name:nld_x_preferred":[
        "Brundby"
    ],
    "name:nno_x_preferred":[
        "Brundby"
    ],
    "name:nob_x_preferred":[
        "Brundby"
    ],
    "name:swe_x_preferred":[
        "Brundby"
    ],
    "name:und_x_variant":[
        "Brunby"
    ],
    "qs_pg:aaroncc":"DK",
    "qs_pg:gn_country":"DK",
    "qs_pg:gn_fcode":"PPL",
    "qs_pg:gn_pop":0,
    "qs_pg:name":"Brundby",
    "qs_pg:name_adm0":"Danmark",
    "qs_pg:name_adm1":"Midtjylland",
    "qs_pg:photos_9r":0,
    "qs_pg:photos_sr":0,
    "qs_pg:pop_sr":0,
    "qs_pg:qs_pg_placetype":"locality",
    "qs_pg:qs_pg_placetype_gp":"Town",
    "qs_pg:woe_adm0":23424796,
    "woe:adm0_id":23424796,
    "woe:name_adm0":"Danmark",
    "woe:name_adm1":"Midtjylland",
    "woe:placetype":"Town",
    "wof:name":"Brundby",
    "wof:placetype":"locality"
},
  "geometry": {"coordinates":[10.60402,55.81335],"type":"Point"}
}