{
  "type": "Feature",
  "properties": {
    "gn:admin1_code":"20.0",
    "gn:admin2_code":"320.0",
    "gn:asciiname":"Vivede",
    "gn:country_code":"DK",
    "gn:dem":19,
    "gn:feature_class":"P",
    "gn:feature_code":"PPL",
    "gn:name":"Vivede",
    "gn:population":0,
    "gn:timezone":"Europe/Copenhagen",
    "iso:country":"DK",
    "name:und_x_variant":[
        "Vibede",
        "Vivede"
    ],
    "wof:name":"Vivede",
    "wof:placetype":"locality"
},
  "geometry": {"coordinates":[12.17721,55.25538],"type":"Point"}
}