{
  "type": "Feature",
  "properties": {
    "gn:gn_country":"DK",
    "gn:gn_fcode":"PPL",
    "gn:gn_pop":0,
    "iso:country":"DK",
    "name:dan_x_preferred":[
        "Pedersker"
    ],
    "name:dut_x_preferred":[
        "Pedersker"
    ],
    "name:eng_x_preferred":[
        "Pedersker"
    ],
    "name:fre_x_preferred":[
        "Pedersker"
    ],
    "name:ger_x_preferred":[
        "Pedersker"
    ],
    "name:unk_x_variant":[
        "Sankt Peter"
    ],
    "qs_pg:aaroncc":"DK",
    "qs_pg:gn_country":"DK",
    "qs_pg:gn_fcode":"PPL",
    "qs_pg:gn_pop":0,
    "qs_pg:name":"Pedersker",
    "qs_pg:name_adm0":"Danmark",
    "qs_pg:name_adm1":"Hovedstaden",
    "qs_pg:photos":59,
    "qs_pg:photos_1k":12,
    "qs_pg:photos_9k":1,
    "qs_pg:photos_9r":2,
    "qs_pg:photos_all":59,
    "qs_pg:photos_sr":2,
    "qs_pg:pop_sr":0,
    "qs_pg:qs_pg_placetype":"locality",
    "qs_pg:qs_pg_placetype_gp":"Town",
    "qs_pg:woe_adm0":23424796,
    "woe:adm0_id":23424796,
    "woe:name_adm0":"Danmark",
    "woe:name_adm1":"Hovedstaden",
    "woe:placetype":"Town",
    "wof:name":"Pedersker",
    "wof:placetype":"locality"
},
  "geometry": {"coordinates":[14.99313,55.03091],"type":"Point"}
}