{
  "type": "Feature",
  "properties": {
    "gn:admin1_code":"21.0",
    "gn:admin2_code":"461.0",
    "gn:asciiname":"Stegsted",
    "gn:country_code":"DK",
    "gn:dem":26,
    "gn:feature_class":"P",
    "gn:feature_code":"PPL",
    "gn:name":"Stegsted",
    "gn:population":0,
    "gn:timezone":"Europe/Copenhagen",
    "iso:country":"DK",
    "wof:name":"Stegsted",
    "wof:placetype":"locality"
},
  "geometry": {"coordinates":[10.3067,55.39552],"type":"Point"}
}