{
  "type": "Feature",
  "properties": {
    "gn:admin1_code":"17.0",
    "gn:admin2_code":"400.0",
    "gn:asciiname":"Smalyngen",
    "gn:cc2":"DK",
    "gn:country_code":"DK",
    "gn:dem":40,
    "gn:feature_class":"P",
    "gn:feature_code":"PPLL",
    "gn:name":"Sm\u00e5lyngen",
    "gn:population":0,
    "gn:timezone":"Europe/Copenhagen",
    "iso:country":"DK",
    "name:und_x_variant":[
        "Smaalyngen"
    ],
    "wof:name":"Smalyngen",
    "wof:placetype":"locality"
},
  "geometry": {"coordinates":[14.97342,55.04342],"type":"Point"}
}