{
  "type": "Feature",
  "properties": {
    "gn:admin1_code":"19.0",
    "gn:admin2_code":"849.0",
    "gn:asciiname":"Holmso",
    "gn:country_code":"DK",
    "gn:dem":4,
    "gn:feature_class":"P",
    "gn:feature_code":"PPL",
    "gn:name":"Holms\u00f8",
    "gn:population":0,
    "gn:timezone":"Europe/Copenhagen",
    "iso:country":"DK",
    "wof:name":"Holmso",
    "wof:placetype":"locality"
},
  "geometry": {"coordinates":[9.40812,57.04206],"type":"Point"}
}