{
  "type": "Feature",
  "properties": {
    "gn:admin1_code":"21.0",
    "gn:admin2_code":"420.0",
    "gn:asciiname":"So Soby",
    "gn:country_code":"DK",
    "gn:dem":56,
    "gn:feature_class":"P",
    "gn:feature_code":"PPL",
    "gn:name":"S\u00f8 S\u00f8by",
    "gn:population":0,
    "gn:timezone":"Europe/Copenhagen",
    "iso:country":"DK",
    "wof:name":"So Soby",
    "wof:placetype":"locality"
},
  "geometry": {"coordinates":[10.01938,55.27499],"type":"Point"}
}