{
  "type": "Feature",
  "properties": {
    "gn:admin1_code":"17.0",
    "gn:admin2_code":"400.0",
    "gn:asciiname":"Gongeherred",
    "gn:country_code":"DK",
    "gn:dem":41,
    "gn:feature_class":"P",
    "gn:feature_code":"PPL",
    "gn:name":"G\u00f8ngeherred",
    "gn:population":0,
    "gn:timezone":"Europe/Copenhagen",
    "iso:country":"DK",
    "wof:name":"Gongeherred",
    "wof:placetype":"locality"
},
  "geometry": {"coordinates":[14.75558,55.13451],"type":"Point"}
}