{
  "type": "Feature",
  "properties": {
    "gn:gn_country":"DK",
    "iso:country":"DK",
    "qs_pg:aaroncc":"DK",
    "qs_pg:gn_country":"DK",
    "qs_pg:name":"Hegnet",
    "qs_pg:name_adm0":"Danmark",
    "qs_pg:name_adm1":"Midtjylland",
    "qs_pg:photos":76,
    "qs_pg:photos_1k":15,
    "qs_pg:photos_9k":1,
    "qs_pg:photos_9r":3,
    "qs_pg:photos_all":76,
    "qs_pg:photos_sr":3,
    "qs_pg:pop_sr":0,
    "qs_pg:qs_pg_placetype":"locality",
    "qs_pg:qs_pg_placetype_gp":"Town",
    "qs_pg:woe_adm0":23424796,
    "woe:adm0_id":23424796,
    "woe:name_adm0":"Danmark",
    "woe:name_adm1":"Midtjylland",
    "woe:placetype":"Town",
    "wof:name":"Hegnet",
    "wof:placetype":"locality"
},
  "geometry": {"coordinates":[8.163135,55.851194],"type":"Point"}
}