{
  "type": "Feature",
  "properties": {
    "gn:admin1_code":"18.0",
    "gn:admin2_code":"657.0",
    "gn:asciiname":"Lustrup",
    "gn:country_code":"DK",
    "gn:dem":35,
    "gn:feature_class":"P",
    "gn:feature_code":"PPL",
    "gn:name":"Lustrup",
    "gn:population":0,
    "gn:timezone":"Europe/Copenhagen",
    "iso:country":"DK",
    "wof:name":"Lustrup",
    "wof:placetype":"locality"
},
  "geometry": {"coordinates":[8.8931,55.9953],"type":"Point"}
}