{
  "type": "Feature",
  "properties": {
    "gn:admin1_code":"19.0",
    "gn:admin2_code":"810.0",
    "gn:asciiname":"Serritslev",
    "gn:country_code":"DK",
    "gn:dem":32,
    "gn:feature_class":"P",
    "gn:feature_code":"PPL",
    "gn:name":"Serritslev",
    "gn:population":0,
    "gn:timezone":"Europe/Copenhagen",
    "iso:country":"DK",
    "name:und_x_variant":[
        "Serreslev",
        "Serridslev",
        "Serritslev"
    ],
    "wof:name":"Serritslev",
    "wof:placetype":"locality"
},
  "geometry": {"coordinates":[9.97398,57.31381],"type":"Point"}
}