{
  "type": "Feature",
  "properties": {
    "gn:admin1_code":"21.0",
    "gn:admin2_code":"540.0",
    "gn:asciiname":"Ludvigsro",
    "gn:country_code":"DK",
    "gn:dem":51,
    "gn:feature_class":"P",
    "gn:feature_code":"PPL",
    "gn:name":"Ludvigsro",
    "gn:population":0,
    "gn:timezone":"Europe/Copenhagen",
    "iso:country":"DK",
    "wof:name":"Ludvigsro",
    "wof:placetype":"locality"
},
  "geometry": {"coordinates":[9.53194,54.9429],"type":"Point"}
}