{
  "type": "Feature",
  "properties": {
    "gn:admin1_code":"18.0",
    "gn:admin2_code":"740.0",
    "gn:asciiname":"Impgarde",
    "gn:country_code":"DK",
    "gn:dem":69,
    "gn:feature_class":"P",
    "gn:feature_code":"PPL",
    "gn:name":"Impg\u00e5rde",
    "gn:population":0,
    "gn:timezone":"Europe/Copenhagen",
    "iso:country":"DK",
    "name:und_x_variant":[
        "Impgaarde",
        "Impg\u00e5rde"
    ],
    "wof:name":"Impgarde",
    "wof:placetype":"locality"
},
  "geometry": {"coordinates":[9.33994,56.30308],"type":"Point"}
}