{
  "type": "Feature",
  "properties": {
    "gn:gn_country":"DK",
    "gn:gn_fcode":"PPLF",
    "gn:gn_pop":92,
    "gn:population":92,
    "iso:country":"DK",
    "qs_pg:aaroncc":"DK",
    "qs_pg:gn_country":"DK",
    "qs_pg:gn_fcode":"PPLF",
    "qs_pg:gn_pop":92,
    "qs_pg:name":"Rejnstrup",
    "qs_pg:photos_9r":0,
    "qs_pg:photos_sr":0,
    "qs_pg:pop_sr":1,
    "qs_pg:qs_pg_placetype":"locality",
    "wof:name":"Rejnstrup",
    "wof:placetype":"locality",
    "wof:population":92
},
  "geometry": {"coordinates":[11.62804,55.32236],"type":"Point"}
}