{
  "type": "Feature",
  "properties": {
    "gn:admin1_code":"20.0",
    "gn:admin2_code":"360.0",
    "gn:asciiname":"Raa",
    "gn:country_code":"DK",
    "gn:dem":12,
    "gn:feature_class":"P",
    "gn:feature_code":"PPL",
    "gn:name":"Raa",
    "gn:population":0,
    "gn:timezone":"Europe/Copenhagen",
    "iso:country":"DK",
    "name:fas_x_preferred":[
        "\u0631\u0627"
    ],
    "name:und_x_variant":[
        "R\u00e5"
    ],
    "wof:name":"Raa",
    "wof:placetype":"locality"
},
  "geometry": {"coordinates":[11.43554,54.76193],"type":"Point"}
}