{
  "type": "Feature",
  "properties": {
    "gn:admin1_code":"18.0",
    "gn:admin2_code":"740.0",
    "gn:asciiname":"Midstrup",
    "gn:country_code":"DK",
    "gn:dem":66,
    "gn:feature_class":"P",
    "gn:feature_code":"PPL",
    "gn:name":"Midstrup",
    "gn:population":0,
    "gn:timezone":"Europe/Copenhagen",
    "iso:country":"DK",
    "wof:name":"Midstrup",
    "wof:placetype":"locality"
},
  "geometry": {"coordinates":[9.4921,56.29853000000001],"type":"Point"}
}