{
  "type": "Feature",
  "properties": {
    "iso:country":"DK",
    "qs_pg:aaroncc":"DK",
    "qs_pg:name":"Resen \u00d8sterhede",
    "qs_pg:name_adm0":"Danmark",
    "qs_pg:name_adm1":"Midtjylland",
    "qs_pg:photos":8,
    "qs_pg:photos_1k":2,
    "qs_pg:photos_9k":1,
    "qs_pg:photos_9r":1,
    "qs_pg:photos_all":8,
    "qs_pg:photos_sr":1,
    "qs_pg:pop_sr":0,
    "qs_pg:qs_pg_placetype":"locality",
    "qs_pg:qs_pg_placetype_gp":"Town",
    "qs_pg:woe_adm0":23424796,
    "woe:adm0_id":23424796,
    "woe:name_adm0":"Danmark",
    "woe:name_adm1":"Midtjylland",
    "woe:placetype":"Town",
    "wof:name":"Resen \u00d8sterhede",
    "wof:placetype":"locality"
},
  "geometry": {"coordinates":[9.1451305,56.380175],"type":"Point"}
}