{
  "type": "Feature",
  "properties": {
    "gn:admin1_code":"17.0",
    "gn:admin2_code":"230.0",
    "gn:asciiname":"Overod",
    "gn:country_code":"DK",
    "gn:dem":50,
    "gn:feature_class":"P",
    "gn:feature_code":"PPL",
    "gn:name":"\u00d8ver\u00f8d",
    "gn:population":0,
    "gn:timezone":"Europe/Copenhagen",
    "iso:country":"DK",
    "name:dan_x_preferred":[
        "\u00d8ver\u00f8d"
    ],
    "name:ita_x_preferred":[
        "\u00d8ver\u00f8d"
    ],
    "name:und_x_variant":[
        "\u00d8ver\u00f8d"
    ],
    "wof:name":"Overod",
    "wof:placetype":"locality"
},
  "geometry": {"coordinates":[12.48412,55.82209],"type":"Point"}
}