{
  "type": "Feature",
  "properties": {
    "gn:admin1_code":"17.0",
    "gn:admin2_code":"400.0",
    "gn:asciiname":"Klinteby",
    "gn:country_code":"DK",
    "gn:dem":57,
    "gn:feature_class":"P",
    "gn:feature_code":"PPL",
    "gn:name":"Klinteby",
    "gn:population":0,
    "gn:timezone":"Europe/Copenhagen",
    "iso:country":"DK",
    "name:und_x_variant":[
        "Klintebyg\u00e5rd",
        "Klinteby"
    ],
    "wof:name":"Klinteby",
    "wof:placetype":"locality"
},
  "geometry": {"coordinates":[15.10017,55.07849],"type":"Point"}
}