{
  "type": "Feature",
  "properties": {
    "gn:admin1_code":"19.0",
    "gn:admin2_code":"773.0",
    "gn:asciiname":"Torup",
    "gn:country_code":"DK",
    "gn:dem":10,
    "gn:feature_class":"P",
    "gn:feature_code":"PPL",
    "gn:name":"Torup",
    "gn:population":0,
    "gn:timezone":"Europe/Copenhagen",
    "iso:country":"DK",
    "wof:name":"Torup",
    "wof:placetype":"locality"
},
  "geometry": {"coordinates":[8.65926,56.8485],"type":"Point"}
}