{
  "type": "Feature",
  "properties": {
    "gn:admin1_code":"21.0",
    "gn:admin2_code":"482.0",
    "gn:asciiname":"Stoense",
    "gn:country_code":"DK",
    "gn:dem":20,
    "gn:feature_class":"P",
    "gn:feature_code":"PPL",
    "gn:name":"Stoense",
    "gn:population":0,
    "gn:timezone":"Europe/Copenhagen",
    "iso:country":"DK",
    "wof:name":"Stoense",
    "wof:placetype":"locality"
},
  "geometry": {"coordinates":[10.90014,55.0926],"type":"Point"}
}