{
  "type": "Feature",
  "properties": {
    "iso:country":"DK",
    "name:eng_x_variant":[
        "Acaciavej"
    ],
    "name:unk_x_variant":[
        "Acaciavej"
    ],
    "qs:gn_adm0_cc":"DK",
    "qs:gn_local":2621942,
    "qs:gn_nam_loc":"Frederiksberg, Frederiksberg, Hovedstaden, DK",
    "qs:gn_namadm1":"17",
    "qs:local_max":4158,
    "qs:local_sum":18220,
    "qs:localhoods":20,
    "qs:name":"Acaciavej",
    "qs:name_adm0":"Danmark",
    "qs:name_adm1":"Hovedstaden",
    "qs:name_adm2":"Frederiksberg",
    "qs:name_en":"Acaciavej",
    "qs:name_local":"Frederiksberg",
    "qs:photo_max":120,
    "qs:photo_sum":246,
    "qs:placetype":"Suburb",
    "qs:quad_count":6,
    "qs:woe_adm0":23424796,
    "qs:woe_adm1":28362583,
    "qs:woe_adm2":12582714,
    "qs:woe_lau":0,
    "qs:woe_local":553307,
    "qs:woe_ver":"7.3.1",
    "wof:name":"Acaciavej",
    "wof:placetype":"neighbourhood"
},
  "geometry": {"coordinates":[12.542956,55.681723],"type":"Point"}
}