{
  "type": "Feature",
  "properties": {
    "gn:country":"DK",
    "gn:fcode":"PPL",
    "gn:population":0,
    "iso:country":"DK",
    "name:und_x_variant":[
        "Helsinge"
    ],
    "qs_pg:aaroncc":"DK",
    "qs_pg:gn_country":"DK",
    "qs_pg:gn_fcode":"PPL",
    "qs_pg:gn_pop":0,
    "qs_pg:name":"Kirke Helsinge Strand",
    "qs_pg:name_adm0":"Danmark",
    "qs_pg:name_adm1":"Sj\u00e6lland",
    "qs_pg:photos_9r":0,
    "qs_pg:photos_sr":0,
    "qs_pg:pop_sr":0,
    "qs_pg:qs_pg_placetype":"locality",
    "qs_pg:qs_pg_placetype_gp":"Town",
    "qs_pg:woe_adm0":23424796,
    "woe:adm0_id":23424796,
    "woe:name_adm0":"Danmark",
    "woe:name_adm1":"Sj\u00e6lland",
    "woe:placetype":"Town",
    "wof:name":"Kirke Helsinge Strand",
    "wof:placetype":"locality"
},
  "geometry": {"coordinates":[11.20605,55.51614],"type":"Point"}
}