{
  "type": "Feature",
  "properties": {
    "gn:admin1_code":"19.0",
    "gn:admin2_code":"810.0",
    "gn:asciiname":"Lem",
    "gn:country_code":"DK",
    "gn:dem":30,
    "gn:feature_class":"P",
    "gn:feature_code":"PPLL",
    "gn:name":"Lem",
    "gn:population":0,
    "gn:timezone":"Europe/Copenhagen",
    "iso:country":"DK",
    "name:ceb_x_preferred":[
        "Lem"
    ],
    "name:dan_x_preferred":[
        "Lem"
    ],
    "name:deu_x_preferred":[
        "Lem"
    ],
    "name:fin_x_preferred":[
        "Lem"
    ],
    "name:hun_x_preferred":[
        "Lem"
    ],
    "name:lav_x_preferred":[
        "Lem"
    ],
    "name:nld_x_preferred":[
        "Lem"
    ],
    "name:nno_x_preferred":[
        "Lem"
    ],
    "name:nor_x_preferred":[
        "Lem"
    ],
    "name:pol_x_preferred":[
        "Lem"
    ],
    "name:rus_x_preferred":[
        "\u041b\u0435\u043c"
    ],
    "name:slv_x_preferred":[
        "Lem"
    ],
    "name:swe_x_preferred":[
        "Lem"
    ],
    "name:ukr_x_preferred":[
        "\u041b\u0435\u043c"
    ],
    "name:und_x_variant":[
        "Lemb"
    ],
    "wof:name":"Lem",
    "wof:placetype":"locality"
},
  "geometry": {"coordinates":[10.13851,57.2002],"type":"Point"}
}