{
  "type": "Feature",
  "properties": {
    "gn:admin1_code":"19.0",
    "gn:admin2_code":"820.0",
    "gn:asciiname":"Vegger",
    "gn:country_code":"DK",
    "gn:dem":9,
    "gn:feature_class":"P",
    "gn:feature_code":"PPL",
    "gn:name":"Vegger",
    "gn:population":0,
    "gn:timezone":"Europe/Copenhagen",
    "iso:country":"DK",
    "name:und_x_variant":[
        "V\u00e6gger",
        "Vegger"
    ],
    "wof:name":"Vegger",
    "wof:placetype":"locality"
},
  "geometry": {"coordinates":[9.5711,56.88497],"type":"Point"}
}