{
  "type": "Feature",
  "properties": {
    "gn:gn_country":"DK",
    "gn:gn_fcode":"PPL",
    "gn:gn_pop":0,
    "iso:country":"DK",
    "name:ara_x_preferred":[
        "\u0647\u0644\u064a\u0631\u0628"
    ],
    "name:cat_x_preferred":[
        "Hellerup"
    ],
    "name:dan_x_preferred":[
        "Hellerup"
    ],
    "name:deu_x_preferred":[
        "Hellerup"
    ],
    "name:eng_x_preferred":[
        "Hellerup"
    ],
    "name:fao_x_preferred":[
        "Hellerup"
    ],
    "name:fin_x_preferred":[
        "Hellerup"
    ],
    "name:fra_x_preferred":[
        "Hellerup"
    ],
    "name:heb_x_preferred":[
        "\u05d4\u05dc\u05e8\u05d5\u05e4"
    ],
    "name:hun_x_preferred":[
        "Hellerup"
    ],
    "name:hye_x_preferred":[
        "\u0540\u0565\u056c\u0565\u0580\u0578\u0582\u057a"
    ],
    "name:isl_x_preferred":[
        "Hellerup"
    ],
    "name:ita_x_preferred":[
        "Hellerup"
    ],
    "name:jpn_x_preferred":[
        "\u30d8\u30e9\u30ed\u30c3\u30d7"
    ],
    "name:kal_x_preferred":[
        "Hellerup"
    ],
    "name:nld_x_preferred":[
        "Hellerup"
    ],
    "name:nno_x_preferred":[
        "Hellerup"
    ],
    "name:nob_x_preferred":[
        "Hellerup"
    ],
    "name:rus_x_preferred":[
        "\u0425\u0435\u043b\u043b\u0435\u0440\u0443\u043f"
    ],
    "name:spa_x_preferred":[
        "Hellerup"
    ],
    "name:swe_x_preferred":[
        "Hellerup"
    ],
    "name:zho_x_preferred":[
        "\u6d77\u52d2\u9b6f\u666e"
    ],
    "qs_pg:aaroncc":"DK",
    "qs_pg:gn_country":"DK",
    "qs_pg:gn_fcode":"PPL",
    "qs_pg:gn_pop":0,
    "qs_pg:name":"Hellerup",
    "qs_pg:name_adm0":"Danmark",
    "qs_pg:name_adm1":"Hovedstaden",
    "qs_pg:photos":1099,
    "qs_pg:photos_1k":223,
    "qs_pg:photos_9k":5,
    "qs_pg:photos_9r":7,
    "qs_pg:photos_all":1099,
    "qs_pg:photos_sr":11,
    "qs_pg:pop_sr":0,
    "qs_pg:qs_pg_placetype":"locality",
    "qs_pg:qs_pg_placetype_gp":"Town",
    "qs_pg:woe_adm0":23424796,
    "woe:adm0_id":23424796,
    "woe:name_adm0":"Danmark",
    "woe:name_adm1":"Hovedstaden",
    "woe:placetype":"Town",
    "wof:name":"Hellerup",
    "wof:placetype":"locality"
},
  "geometry": {"coordinates":[12.57093,55.73204],"type":"Point"}
}