{
  "type": "Feature",
  "properties": {
    "gn:gn_country":"DK",
    "gn:gn_fcode":"PPL",
    "gn:gn_pop":0,
    "iso:country":"DK",
    "name:ceb_x_preferred":[
        "\u00c5rsdale"
    ],
    "name:dan_x_preferred":[
        "Aarsdale"
    ],
    "name:deu_x_preferred":[
        "Aarsdale"
    ],
    "name:eng_x_preferred":[
        "Aarsdale"
    ],
    "name:fas_x_preferred":[
        "\u0622\u0631\u0633\u062f\u0627\u0644"
    ],
    "name:fra_x_preferred":[
        "Aarsdale"
    ],
    "name:nld_x_preferred":[
        "Aarsdale"
    ],
    "name:pol_x_preferred":[
        "Aarsdale"
    ],
    "name:swe_x_preferred":[
        "\u00c5rsdale"
    ],
    "name:unk_x_variant":[
        "Aarsdale"
    ],
    "name:urd_x_preferred":[
        "\u0622\u0631\u0633\u0688\u0627\u0644\u06d2"
    ],
    "qs_pg:aaroncc":"DK",
    "qs_pg:gn_country":"DK",
    "qs_pg:gn_fcode":"PPL",
    "qs_pg:gn_pop":0,
    "qs_pg:name":"\u00c5rsdale",
    "qs_pg:name_adm0":"Danmark",
    "qs_pg:name_adm1":"Hovedstaden",
    "qs_pg:photos":92,
    "qs_pg:photos_1k":19,
    "qs_pg:photos_9k":1,
    "qs_pg:photos_9r":3,
    "qs_pg:photos_all":92,
    "qs_pg:photos_sr":3,
    "qs_pg:pop_sr":0,
    "qs_pg:qs_pg_placetype":"locality",
    "qs_pg:qs_pg_placetype_gp":"Town",
    "qs_pg:woe_adm0":23424796,
    "woe:adm0_id":23424796,
    "woe:name_adm0":"Danmark",
    "woe:name_adm1":"Hovedstaden",
    "woe:placetype":"Town",
    "wof:name":"\u00c5rsdale",
    "wof:placetype":"locality"
},
  "geometry": {"coordinates":[15.14525,55.10662],"type":"Point"}
}