{
  "type": "Feature",
  "properties": {
    "gn:admin1_code":"20.0",
    "gn:admin2_code":"326.0",
    "gn:asciiname":"Rye",
    "gn:country_code":"DK",
    "gn:dem":7,
    "gn:feature_class":"P",
    "gn:feature_code":"PPL",
    "gn:name":"Rye",
    "gn:population":0,
    "gn:timezone":"Europe/Copenhagen",
    "iso:country":"DK",
    "wof:name":"Rye",
    "wof:placetype":"locality"
},
  "geometry": {"coordinates":[11.2384,55.52151],"type":"Point"}
}