{
  "type": "Feature",
  "properties": {
    "gn:admin1_code":"21.0",
    "gn:admin2_code":"561.0",
    "gn:asciiname":"Rahede",
    "gn:country_code":"DK",
    "gn:dem":8,
    "gn:feature_class":"P",
    "gn:feature_code":"PPL",
    "gn:name":"R\u00e5hede",
    "gn:population":0,
    "gn:timezone":"Europe/Copenhagen",
    "iso:country":"DK",
    "name:und_x_variant":[
        "Raahede",
        "R\u00e5hede"
    ],
    "wof:name":"Rahede",
    "wof:placetype":"locality"
},
  "geometry": {"coordinates":[8.69501,55.26707],"type":"Point"}
}