{
  "type": "Feature",
  "properties": {
    "gn:admin1_code":"18.0",
    "gn:admin2_code":"760.0",
    "gn:asciiname":"Bjerregarde",
    "gn:country_code":"DK",
    "gn:dem":70,
    "gn:feature_class":"P",
    "gn:feature_code":"PPL",
    "gn:name":"Bjerreg\u00e5rde",
    "gn:population":0,
    "gn:timezone":"Europe/Copenhagen",
    "iso:country":"DK",
    "wof:name":"Bjerregarde",
    "wof:placetype":"locality"
},
  "geometry": {"coordinates":[8.85,56.06667],"type":"Point"}
}