{
  "type": "Feature",
  "properties": {
    "iso:country":"DK",
    "qs_pg:aaroncc":"DK",
    "qs_pg:name":"Harrerenden",
    "qs_pg:name_adm0":"Danmark",
    "qs_pg:name_adm1":"Nordjylland",
    "qs_pg:photos":82,
    "qs_pg:photos_1k":17,
    "qs_pg:photos_9k":1,
    "qs_pg:photos_9r":3,
    "qs_pg:photos_all":82,
    "qs_pg:photos_sr":3,
    "qs_pg:pop_sr":0,
    "qs_pg:qs_pg_placetype":"locality",
    "qs_pg:qs_pg_placetype_gp":"Town",
    "qs_pg:woe_adm0":23424796,
    "woe:adm0_id":23424796,
    "woe:name_adm0":"Danmark",
    "woe:name_adm1":"Nordjylland",
    "woe:placetype":"Town",
    "wof:name":"Harrerenden",
    "wof:placetype":"locality"
},
  "geometry": {"coordinates":[9.841432,57.496157],"type":"Point"}
}