{
  "type": "Feature",
  "properties": {
    "gn:admin1_code":"18.0",
    "gn:admin2_code":"615.0",
    "gn:asciiname":"Kattrup",
    "gn:country_code":"DK",
    "gn:dem":87,
    "gn:feature_class":"P",
    "gn:feature_code":"PPL",
    "gn:name":"Kattrup",
    "gn:population":0,
    "gn:timezone":"Europe/Copenhagen",
    "iso:country":"DK",
    "name:dan_x_preferred":[
        "Kattrup Gods"
    ],
    "wof:name":"Kattrup",
    "wof:placetype":"locality"
},
  "geometry": {"coordinates":[9.91686,55.95296],"type":"Point"}
}