{
  "type": "Feature",
  "properties": {
    "gn:admin1_code":"20.0",
    "gn:admin2_code":"320.0",
    "gn:asciiname":"Kvaerrede",
    "gn:country_code":"DK",
    "gn:dem":34,
    "gn:feature_class":"P",
    "gn:feature_code":"PPL",
    "gn:name":"Kv\u00e6rrede",
    "gn:population":0,
    "gn:timezone":"Europe/Copenhagen",
    "iso:country":"DK",
    "name:und_x_variant":[
        "Kv\u00e6rede",
        "Kv\u00e6rrede"
    ],
    "wof:name":"Kvaerrede",
    "wof:placetype":"locality"
},
  "geometry": {"coordinates":[12.02044,55.36496],"type":"Point"}
}