{
  "type": "Feature",
  "properties": {
    "gn:admin1_code":"21.0",
    "gn:admin2_code":"550.0",
    "gn:asciiname":"Arndrup",
    "gn:country_code":"DK",
    "gn:dem":24,
    "gn:feature_class":"P",
    "gn:feature_code":"PPL",
    "gn:name":"Arndrup",
    "gn:population":0,
    "gn:timezone":"Europe/Copenhagen",
    "iso:country":"DK",
    "wof:name":"Arndrup",
    "wof:placetype":"locality"
},
  "geometry": {"coordinates":[9.09307,55.04253000000001],"type":"Point"}
}