{
  "type": "Feature",
  "properties": {
    "gn:admin1_code":"21.0",
    "gn:admin2_code":"450.0",
    "gn:asciiname":"Kongshoj",
    "gn:country_code":"DK",
    "gn:dem":14,
    "gn:feature_class":"P",
    "gn:feature_code":"PPLL",
    "gn:name":"Kongsh\u00f8j",
    "gn:population":0,
    "gn:timezone":"Europe/Copenhagen",
    "iso:country":"DK",
    "wof:name":"Kongshoj",
    "wof:placetype":"locality"
},
  "geometry": {"coordinates":[10.80087,55.22582],"type":"Point"}
}