{
  "type": "Feature",
  "properties": {
    "gn:admin1_code":"19.0",
    "gn:admin2_code":"851.0",
    "gn:asciiname":"Ostergarde",
    "gn:country_code":"DK",
    "gn:dem":23,
    "gn:feature_class":"P",
    "gn:feature_code":"PPL",
    "gn:name":"\u00d8sterg\u00e5rde",
    "gn:population":0,
    "gn:timezone":"Europe/Copenhagen",
    "iso:country":"DK",
    "name:und_x_variant":[
        "\u00d6stergaarde",
        "\u00d8sterg\u00e5rde"
    ],
    "wof:name":"Ostergarde",
    "wof:placetype":"locality"
},
  "geometry": {"coordinates":[10.14727,56.90065],"type":"Point"}
}