{
  "type": "Feature",
  "properties": {
    "gn:admin1_code":"18.0",
    "gn:admin2_code":"760.0",
    "gn:asciiname":"Troldhede",
    "gn:country_code":"DK",
    "gn:dem":28,
    "gn:feature_class":"P",
    "gn:feature_code":"PPL",
    "gn:name":"Troldhede",
    "gn:population":0,
    "gn:timezone":"Europe/Copenhagen",
    "iso:country":"DK",
    "name:und_x_variant":[
        "Trolhede",
        "Troldhede"
    ],
    "wof:name":"Troldhede",
    "wof:placetype":"locality"
},
  "geometry": {"coordinates":[8.74471,55.99154],"type":"Point"}
}