{
  "type": "Feature",
  "properties": {
    "gn:admin1_code":"19.0",
    "gn:admin2_code":"851.0",
    "gn:asciiname":"Sejlflod",
    "gn:country_code":"DK",
    "gn:dem":13,
    "gn:feature_class":"P",
    "gn:feature_code":"PPL",
    "gn:name":"Sejlflod",
    "gn:population":0,
    "gn:timezone":"Europe/Copenhagen",
    "iso:country":"DK",
    "name:dan_x_preferred":[
        "Sejlflod"
    ],
    "name:dan_x_variant":[
        "Sejlflod Kommune"
    ],
    "name:deu_x_preferred":[
        "Sejlflod Kommune"
    ],
    "name:eng_x_preferred":[
        "Sejlflod"
    ],
    "name:fao_x_preferred":[
        "Sejlflod"
    ],
    "name:fao_x_variant":[
        "Sejlflod kommuna"
    ],
    "name:ita_x_preferred":[
        "Sejlflod"
    ],
    "name:nld_x_preferred":[
        "Sejlflod"
    ],
    "name:nor_x_preferred":[
        "Sejlflod"
    ],
    "name:nor_x_variant":[
        "Sejlflod kommune"
    ],
    "name:pol_x_preferred":[
        "Gmina Sejlflod"
    ],
    "name:por_x_preferred":[
        "Sejlflod"
    ],
    "name:ron_x_preferred":[
        "Comuna Sejlflod"
    ],
    "name:swe_x_preferred":[
        "Sejlflod"
    ],
    "name:swe_x_variant":[
        "Sejlflods kommun"
    ],
    "name:und_x_variant":[
        "Seglflod",
        "Sejlflo"
    ],
    "wof:name":"Sejlflod",
    "wof:placetype":"locality"
},
  "geometry": {"coordinates":[10.10053,56.98694],"type":"Point"}
}