{
  "type": "Feature",
  "properties": {
    "gn:admin1_code":"21.0",
    "gn:admin2_code":"573.0",
    "gn:asciiname":"Rodebaek",
    "gn:country_code":"DK",
    "gn:dem":29,
    "gn:feature_class":"P",
    "gn:feature_code":"PPL",
    "gn:name":"Rodeb\u00e6k",
    "gn:population":0,
    "gn:timezone":"Europe/Copenhagen",
    "iso:country":"DK",
    "wof:name":"Rodebaek",
    "wof:placetype":"locality"
},
  "geometry": {"coordinates":[8.76101,55.59228],"type":"Point"}
}