{
  "type": "Feature",
  "properties": {
    "gn:admin1_code":"21.0",
    "gn:admin2_code":"575.0",
    "gn:asciiname":"Tirslund",
    "gn:country_code":"DK",
    "gn:dem":50,
    "gn:feature_class":"P",
    "gn:feature_code":"PPL",
    "gn:name":"Tirslund",
    "gn:population":0,
    "gn:timezone":"Europe/Copenhagen",
    "iso:country":"DK",
    "name:und_x_variant":[
        "Tislund",
        "Tirslund"
    ],
    "wof:name":"Tirslund",
    "wof:placetype":"locality"
},
  "geometry": {"coordinates":[8.94099,55.47255],"type":"Point"}
}