{
  "type": "Feature",
  "properties": {
    "gn:admin1_code":"18.0",
    "gn:admin2_code":"710.0",
    "gn:asciiname":"Mogelby",
    "gn:country_code":"DK",
    "gn:dem":66,
    "gn:feature_class":"P",
    "gn:feature_code":"PPL",
    "gn:name":"M\u00f8gelby",
    "gn:population":0,
    "gn:timezone":"Europe/Copenhagen",
    "iso:country":"DK",
    "wof:name":"Mogelby",
    "wof:placetype":"locality"
},
  "geometry": {"coordinates":[9.79473,56.23731],"type":"Point"}
}