{
  "type": "Feature",
  "properties": {
    "gn:admin1_code":"20.0",
    "gn:admin2_code":"360.0",
    "gn:asciiname":"Saedinge",
    "gn:country_code":"DK",
    "gn:dem":5,
    "gn:feature_class":"P",
    "gn:feature_code":"PPL",
    "gn:name":"S\u00e6dinge",
    "gn:population":0,
    "gn:timezone":"Europe/Copenhagen",
    "iso:country":"DK",
    "name:und_x_variant":[
        "S\u00e5dinge",
        "S\u00e6dinge"
    ],
    "wof:name":"Saedinge",
    "wof:placetype":"locality"
},
  "geometry": {"coordinates":[11.41655,54.70926],"type":"Point"}
}