{
  "type": "Feature",
  "properties": {
    "gn:admin1_code":"17.0",
    "gn:admin2_code":"270.0",
    "gn:asciiname":"Holt",
    "gn:country_code":"DK",
    "gn:dem":15,
    "gn:feature_class":"P",
    "gn:feature_code":"PPL",
    "gn:name":"Holt",
    "gn:population":0,
    "gn:timezone":"Europe/Copenhagen",
    "iso:country":"DK",
    "name:bul_x_preferred":[
        "\u0425\u043e\u043b\u0442"
    ],
    "name:cat_x_preferred":[
        "Holt"
    ],
    "name:ceb_x_preferred":[
        "Holt"
    ],
    "name:ces_x_preferred":[
        "Holt"
    ],
    "name:cor_x_preferred":[
        "Holt"
    ],
    "name:dan_x_preferred":[
        "Holt"
    ],
    "name:deu_x_preferred":[
        "Holt"
    ],
    "name:fra_x_preferred":[
        "Holt"
    ],
    "name:heb_x_preferred":[
        "\u05d4\u05d5\u05dc\u05d8"
    ],
    "name:ita_x_preferred":[
        "Holt"
    ],
    "name:jpn_x_preferred":[
        "\u30db\u30eb\u30c8"
    ],
    "name:nds_x_preferred":[
        "Holt"
    ],
    "name:nld_x_preferred":[
        "Holt"
    ],
    "name:nor_x_preferred":[
        "Holt"
    ],
    "name:pol_x_preferred":[
        "Holt"
    ],
    "name:por_x_preferred":[
        "Holt"
    ],
    "name:rus_x_preferred":[
        "\u0425\u043e\u043b\u044c\u0442"
    ],
    "name:spa_x_preferred":[
        "Holt"
    ],
    "name:srp_x_preferred":[
        "\u0425\u043e\u043b\u0442"
    ],
    "name:swe_x_preferred":[
        "Holt"
    ],
    "name:ukr_x_preferred":[
        "\u0413\u043e\u043b\u0442"
    ],
    "name:vol_x_preferred":[
        "Holt"
    ],
    "wof:name":"Holt",
    "wof:placetype":"locality"
},
  "geometry": {"coordinates":[12.29061,56.08026],"type":"Point"}
}