{
  "type": "Feature",
  "properties": {
    "gn:admin1_code":"18.0",
    "gn:admin2_code":"657.0",
    "gn:asciiname":"Tranholm",
    "gn:country_code":"DK",
    "gn:dem":46,
    "gn:feature_class":"P",
    "gn:feature_code":"PPLL",
    "gn:name":"Tranholm",
    "gn:population":0,
    "gn:timezone":"Europe/Copenhagen",
    "iso:country":"DK",
    "name:und_x_variant":[
        "Traneholm",
        "Tranholm"
    ],
    "wof:name":"Tranholm",
    "wof:placetype":"locality"
},
  "geometry": {"coordinates":[8.78613,56.19144],"type":"Point"}
}