{
  "type": "Feature",
  "properties": {
    "gn:country":"DK",
    "gn:fcode":"PPL",
    "gn:population":0,
    "iso:country":"DK",
    "name:cat_x_preferred":[
        "Store Havelse"
    ],
    "name:dan_x_preferred":[
        "Store Havelse"
    ],
    "name:deu_x_preferred":[
        "Store Havelse"
    ],
    "name:eng_x_preferred":[
        "Store Havelse"
    ],
    "name:glg_x_preferred":[
        "Store Havelse"
    ],
    "name:nld_x_preferred":[
        "Store Havelse"
    ],
    "name:spa_x_preferred":[
        "Store Havelse"
    ],
    "name:und_x_variant":[
        "Store Hagelse"
    ],
    "qs_pg:aaroncc":"DK",
    "qs_pg:gn_country":"DK",
    "qs_pg:gn_fcode":"PPL",
    "qs_pg:gn_pop":0,
    "qs_pg:name":"Store Havelse",
    "qs_pg:name_adm0":"Danmark",
    "qs_pg:name_adm1":"Hovedstaden",
    "qs_pg:photos":15,
    "qs_pg:photos_1k":3,
    "qs_pg:photos_9k":1,
    "qs_pg:photos_9r":1,
    "qs_pg:photos_all":15,
    "qs_pg:photos_sr":1,
    "qs_pg:pop_sr":0,
    "qs_pg:qs_pg_placetype":"locality",
    "qs_pg:qs_pg_placetype_gp":"Town",
    "qs_pg:woe_adm0":23424796,
    "woe:adm0_id":23424796,
    "woe:name_adm0":"Danmark",
    "woe:name_adm1":"Hovedstaden",
    "woe:placetype":"Town",
    "wof:name":"Store Havelse",
    "wof:placetype":"locality"
},
  "geometry": {"coordinates":[12.07033,55.90452],"type":"Point"}
}