{
  "type": "Feature",
  "properties": {
    "gn:admin1_code":"20.0",
    "gn:admin2_code":"370.0",
    "gn:asciiname":"Kagstrup",
    "gn:country_code":"DK",
    "gn:dem":26,
    "gn:feature_class":"P",
    "gn:feature_code":"PPL",
    "gn:name":"Kagstrup",
    "gn:population":0,
    "gn:timezone":"Europe/Copenhagen",
    "iso:country":"DK",
    "wof:name":"Kagstrup",
    "wof:placetype":"locality"
},
  "geometry": {"coordinates":[11.70373,55.30314],"type":"Point"}
}