{
  "type": "Feature",
  "properties": {
    "gn:admin1_code":"19.0",
    "gn:admin2_code":"840.0",
    "gn:asciiname":"Hjedsbaek",
    "gn:country_code":"DK",
    "gn:dem":35,
    "gn:feature_class":"P",
    "gn:feature_code":"PPL",
    "gn:name":"Hjedsb\u00e6k",
    "gn:population":0,
    "gn:timezone":"Europe/Copenhagen",
    "iso:country":"DK",
    "wof:name":"Hjedsbaek",
    "wof:placetype":"locality"
},
  "geometry": {"coordinates":[9.70728,56.86201],"type":"Point"}
}