{
  "type": "Feature",
  "properties": {
    "gn:admin1_code":"21.0",
    "gn:admin2_code":"420.0",
    "gn:asciiname":"Bago By",
    "gn:country_code":"DK",
    "gn:dem":6,
    "gn:feature_class":"P",
    "gn:feature_code":"PPL",
    "gn:name":"B\u00e5g\u00f8 By",
    "gn:population":0,
    "gn:timezone":"Europe/Copenhagen",
    "iso:country":"DK",
    "name:und_x_variant":[
        "Baag\u00f6 By",
        "B\u00e5g\u00f8",
        "B\u00e5g\u00f8 By"
    ],
    "wof:name":"Bago By",
    "wof:placetype":"locality"
},
  "geometry": {"coordinates":[9.80841,55.31393000000001],"type":"Point"}
}