{
  "type": "Feature",
  "properties": {
    "gn:admin1_code":"21.0",
    "gn:admin2_code":"561.0",
    "gn:asciiname":"Norre Vong",
    "gn:country_code":"DK",
    "gn:dem":12,
    "gn:feature_class":"P",
    "gn:feature_code":"PPL",
    "gn:name":"N\u00f8rre Vong",
    "gn:population":0,
    "gn:timezone":"Europe/Copenhagen",
    "iso:country":"DK",
    "name:und_x_variant":[
        "Vong",
        "N\u00f8rre Vong"
    ],
    "wof:name":"Norre Vong",
    "wof:placetype":"locality"
},
  "geometry": {"coordinates":[8.66055,55.49879],"type":"Point"}
}