{
  "type": "Feature",
  "properties": {
    "gn:admin1_code":"18.0",
    "gn:admin2_code":"740.0",
    "gn:asciiname":"Holmstol",
    "gn:country_code":"DK",
    "gn:dem":57,
    "gn:feature_class":"P",
    "gn:feature_code":"PPL",
    "gn:name":"Holmstol",
    "gn:population":0,
    "gn:timezone":"Europe/Copenhagen",
    "iso:country":"DK",
    "wof:name":"Holmstol",
    "wof:placetype":"locality"
},
  "geometry": {"coordinates":[9.75018,56.21559],"type":"Point"}
}