{
  "type": "Feature",
  "properties": {
    "gn:admin1_code":"20.0",
    "gn:admin2_code":"376.0",
    "gn:asciiname":"Maderne",
    "gn:country_code":"DK",
    "gn:dem":10,
    "gn:feature_class":"P",
    "gn:feature_code":"PPL",
    "gn:name":"Maderne",
    "gn:population":0,
    "gn:timezone":"Europe/Copenhagen",
    "iso:country":"DK",
    "name:und_x_variant":[
        "Marnehuse",
        "Maderne"
    ],
    "wof:name":"Maderne",
    "wof:placetype":"locality"
},
  "geometry": {"coordinates":[11.97304,54.79482],"type":"Point"}
}