{
  "type": "Feature",
  "properties": {
    "gn:admin1_code":"18.0",
    "gn:admin2_code":"707.0",
    "gn:asciiname":"Alsrode",
    "gn:country_code":"DK",
    "gn:dem":24,
    "gn:feature_class":"P",
    "gn:feature_code":"PPL",
    "gn:name":"\u00c5lsrode",
    "gn:population":0,
    "gn:timezone":"Europe/Copenhagen",
    "iso:country":"DK",
    "name:und_x_variant":[
        "Aalsrode",
        "\u00c5lsrode"
    ],
    "wof:name":"Alsrode",
    "wof:placetype":"locality"
},
  "geometry": {"coordinates":[10.86336,56.34741999999999],"type":"Point"}
}