{
  "type": "Feature",
  "properties": {
    "gn:admin1_code":"21.0",
    "gn:admin2_code":"580.0",
    "gn:asciiname":"Barsmark",
    "gn:country_code":"DK",
    "gn:dem":38,
    "gn:feature_class":"P",
    "gn:feature_code":"PPL",
    "gn:name":"Barsmark",
    "gn:population":0,
    "gn:timezone":"Europe/Copenhagen",
    "iso:country":"DK",
    "wof:name":"Barsmark",
    "wof:placetype":"locality"
},
  "geometry": {"coordinates":[9.53106,55.08194],"type":"Point"}
}