{
  "type": "Feature",
  "properties": {
    "gn:admin1_code":"18.0",
    "gn:admin2_code":"727.0",
    "gn:asciiname":"Amstrup",
    "gn:country_code":"DK",
    "gn:dem":10,
    "gn:feature_class":"P",
    "gn:feature_code":"PPL",
    "gn:name":"Amstrup",
    "gn:population":0,
    "gn:timezone":"Europe/Copenhagen",
    "iso:country":"DK",
    "wof:name":"Amstrup",
    "wof:placetype":"locality"
},
  "geometry": {"coordinates":[10.12182,55.88873],"type":"Point"}
}