{
  "type": "Feature",
  "properties": {
    "gn:admin1_code":"18.0",
    "gn:admin2_code":"707.0",
    "gn:asciiname":"Vester Alling",
    "gn:country_code":"DK",
    "gn:dem":11,
    "gn:feature_class":"P",
    "gn:feature_code":"PPL",
    "gn:name":"Vester Alling",
    "gn:population":0,
    "gn:timezone":"Europe/Copenhagen",
    "iso:country":"DK",
    "wof:name":"Vester Alling",
    "wof:placetype":"locality"
},
  "geometry": {"coordinates":[10.27621,56.4115],"type":"Point"}
}