{
  "type": "Feature",
  "properties": {
    "gn:admin1_code":"19.0",
    "gn:admin2_code":"810.0",
    "gn:asciiname":"Hvilshoj",
    "gn:country_code":"DK",
    "gn:dem":25,
    "gn:feature_class":"P",
    "gn:feature_code":"PPL",
    "gn:name":"Hvilsh\u00f8j",
    "gn:population":0,
    "gn:timezone":"Europe/Copenhagen",
    "iso:country":"DK",
    "wof:name":"Hvilshoj",
    "wof:placetype":"locality"
},
  "geometry": {"coordinates":[10.03925,57.22358000000001],"type":"Point"}
}