{
  "type": "Feature",
  "properties": {
    "gn:admin1_code":"21.0",
    "gn:admin2_code":"480.0",
    "gn:asciiname":"Kelleby",
    "gn:country_code":"DK",
    "gn:dem":28,
    "gn:feature_class":"P",
    "gn:feature_code":"PPL",
    "gn:name":"Kelleby",
    "gn:population":0,
    "gn:timezone":"Europe/Copenhagen",
    "iso:country":"DK",
    "name:und_x_variant":[
        "Keldeby",
        "Kelleby"
    ],
    "wof:name":"Kelleby",
    "wof:placetype":"locality"
},
  "geometry": {"coordinates":[10.22063,55.484],"type":"Point"}
}