{
  "type": "Feature",
  "properties": {
    "gn:admin1_code":"18.0",
    "gn:admin2_code":"791.0",
    "gn:asciiname":"Hvidding",
    "gn:country_code":"DK",
    "gn:dem":50,
    "gn:feature_class":"P",
    "gn:feature_code":"PPL",
    "gn:name":"Hvidding",
    "gn:population":0,
    "gn:timezone":"Europe/Copenhagen",
    "iso:country":"DK",
    "name:und_x_variant":[
        "Hviding",
        "Hvidding"
    ],
    "wof:name":"Hvidding",
    "wof:placetype":"locality"
},
  "geometry": {"coordinates":[9.77174,56.53461],"type":"Point"}
}