{
  "type": "Feature",
  "properties": {
    "gn:admin1_code":"21.0",
    "gn:admin2_code":"430.0",
    "gn:asciiname":"Faaborg",
    "gn:country_code":"DK",
    "gn:dem":7,
    "gn:feature_class":"P",
    "gn:feature_code":"PPL",
    "gn:name":"Faaborg",
    "gn:population":7239,
    "gn:timezone":"Europe/Copenhagen",
    "iso:country":"DK",
    "name:ceb_x_preferred":[
        "Faaborg"
    ],
    "name:ces_x_preferred":[
        "Faaborg"
    ],
    "name:dan_x_preferred":[
        "Faaborg"
    ],
    "name:deu_x_preferred":[
        "Faaborg"
    ],
    "name:epo_x_preferred":[
        "Faaborg"
    ],
    "name:fas_x_preferred":[
        "\u0641\u0627\u0628\u0648\u0631\u06af"
    ],
    "name:fra_x_preferred":[
        "F\u00e5borg"
    ],
    "name:fry_x_preferred":[
        "Faaborg"
    ],
    "name:hun_x_preferred":[
        "Faaborg"
    ],
    "name:ind_x_preferred":[
        "F\u00e5borg"
    ],
    "name:kor_x_preferred":[
        "\ud3ec\ubcf4\ub974"
    ],
    "name:nld_x_preferred":[
        "Faaborg"
    ],
    "name:nor_x_preferred":[
        "Faaborg"
    ],
    "name:pol_x_preferred":[
        "Faaborg"
    ],
    "name:ron_x_preferred":[
        "Faaborg"
    ],
    "name:rus_x_preferred":[
        "\u0424\u043e\u0431\u043e\u0440\u0433"
    ],
    "name:spa_x_preferred":[
        "Faaborg"
    ],
    "name:swe_x_preferred":[
        "F\u00e5borg"
    ],
    "name:und_x_variant":[
        "Fabberg",
        "F\u00e5borg"
    ],
    "wof:name":"Faaborg",
    "wof:placetype":"locality",
    "wof:population":7239
},
  "geometry": {"coordinates":[10.24226,55.0951],"type":"Point"}
}