{
  "type": "Feature",
  "properties": {
    "gn:admin1_code":"21.0",
    "gn:admin2_code":"430.0",
    "gn:asciiname":"Faaborg",
    "gn:country_code":"DK",
    "gn:dem":7,
    "gn:feature_class":"P",
    "gn:feature_code":"PPL",
    "gn:name":"Faaborg",
    "gn:population":7239,
    "gn:timezone":"Europe/Copenhagen",
    "iso:country":"DK",
    "name:und_x_variant":[
        "Fabberg",
        "F\u00e5borg"
    ],
    "wof:name":"Faaborg",
    "wof:placetype":"locality",
    "wof:population":7239
},
  "geometry": {"coordinates":[10.24226,55.0951],"type":"Point"}
}