{
  "type": "Feature",
  "properties": {
    "gn:admin1_code":"18.0",
    "gn:admin2_code":"671.0",
    "gn:asciiname":"Osterby",
    "gn:country_code":"DK",
    "gn:dem":10,
    "gn:feature_class":"P",
    "gn:feature_code":"PPL",
    "gn:name":"\u00d8sterby",
    "gn:population":0,
    "gn:timezone":"Europe/Copenhagen",
    "iso:country":"DK",
    "wof:name":"Osterby",
    "wof:placetype":"locality"
},
  "geometry": {"coordinates":[8.61207,56.47742],"type":"Point"}
}