{
  "type": "Feature",
  "properties": {
    "gn:admin1_code":"21.0",
    "gn:admin2_code":"530.0",
    "gn:asciiname":"Bolding",
    "gn:country_code":"DK",
    "gn:dem":61,
    "gn:feature_class":"P",
    "gn:feature_code":"PPL",
    "gn:name":"Bolding",
    "gn:population":0,
    "gn:timezone":"Europe/Copenhagen",
    "iso:country":"DK",
    "wof:name":"Bolding",
    "wof:placetype":"locality"
},
  "geometry": {"coordinates":[8.99761,55.70925],"type":"Point"}
}