{
  "type": "Feature",
  "properties": {
    "gn:admin1_code":"19.0",
    "gn:admin2_code":"846.0",
    "gn:asciiname":"Weiss A/S",
    "gn:country_code":"DK",
    "gn:dem":3,
    "gn:elevation":"0.0",
    "gn:feature_class":"P",
    "gn:feature_code":"PPLL",
    "gn:name":"Weiss A/S",
    "gn:population":0,
    "gn:timezone":"Europe/Copenhagen",
    "iso:country":"DK",
    "wof:name":"Weiss A/S",
    "wof:placetype":"locality"
},
  "geometry": {"coordinates":[10.12658,56.71998000000001],"type":"Point"}
}