{
  "type": "Feature",
  "properties": {
    "gn:admin1_code":"18.0",
    "gn:admin2_code":"710.0",
    "gn:asciiname":"Klintrup",
    "gn:country_code":"DK",
    "gn:dem":64,
    "gn:feature_class":"P",
    "gn:feature_code":"PPL",
    "gn:name":"Klintrup",
    "gn:population":0,
    "gn:timezone":"Europe/Copenhagen",
    "iso:country":"DK",
    "wof:name":"Klintrup",
    "wof:placetype":"locality"
},
  "geometry": {"coordinates":[9.78872,56.20884],"type":"Point"}
}