{
  "type": "Feature",
  "properties": {
    "gn:admin1_code":"18.0",
    "gn:admin2_code":"706.0",
    "gn:asciiname":"Skarreso",
    "gn:country_code":"DK",
    "gn:dem":6,
    "gn:feature_class":"P",
    "gn:feature_code":"PPL",
    "gn:name":"Skarres\u00f8",
    "gn:population":0,
    "gn:timezone":"Europe/Copenhagen",
    "iso:country":"DK",
    "wof:name":"Skarreso",
    "wof:placetype":"locality"
},
  "geometry": {"coordinates":[10.52555,56.35876999999999],"type":"Point"}
}