{
  "type": "Feature",
  "properties": {
    "gn:admin1_code":"19.0",
    "gn:admin2_code":"820.0",
    "gn:asciiname":"Naesborg",
    "gn:country_code":"DK",
    "gn:dem":49,
    "gn:feature_class":"P",
    "gn:feature_code":"PPL",
    "gn:name":"N\u00e6sborg",
    "gn:population":0,
    "gn:timezone":"Europe/Copenhagen",
    "iso:country":"DK",
    "wof:name":"Naesborg",
    "wof:placetype":"locality"
},
  "geometry": {"coordinates":[9.34113,56.97713],"type":"Point"}
}