{
  "type": "Feature",
  "properties": {
    "gn:admin1_code":"19.0",
    "gn:admin2_code":"787.0",
    "gn:asciiname":"Sjorring",
    "gn:country_code":"DK",
    "gn:dem":22,
    "gn:feature_class":"P",
    "gn:feature_code":"PPL",
    "gn:name":"Sj\u00f8rring",
    "gn:population":0,
    "gn:timezone":"Europe/Copenhagen",
    "iso:country":"DK",
    "name:und_x_variant":[
        "Sj\u00f6rrind",
        "Si\u00f6rring",
        "Sj\u00f8rring"
    ],
    "wof:name":"Sjorring",
    "wof:placetype":"locality"
},
  "geometry": {"coordinates":[8.5893,56.9529],"type":"Point"}
}