{
  "type": "Feature",
  "properties": {
    "gn:admin1_code":"21.0",
    "gn:admin2_code":"450.0",
    "gn:asciiname":"Blaesenborg",
    "gn:country_code":"DK",
    "gn:dem":45,
    "gn:feature_class":"P",
    "gn:feature_code":"PPL",
    "gn:name":"Bl\u00e6senborg",
    "gn:population":0,
    "gn:timezone":"Europe/Copenhagen",
    "iso:country":"DK",
    "wof:name":"Blaesenborg",
    "wof:placetype":"locality"
},
  "geometry": {"coordinates":[10.75156,55.23637],"type":"Point"}
}