{
  "type": "Feature",
  "properties": {
    "iso:country":"DK",
    "name:bul_x_preferred":[
        "\u0425\u0432\u0438\u0434\u043e\u0432\u0440\u0435"
    ],
    "name:ceb_x_preferred":[
        "Hvidovre"
    ],
    "name:dan_x_preferred":[
        "Hvidovre"
    ],
    "name:deu_x_preferred":[
        "Hvidovre"
    ],
    "name:eng_x_preferred":[
        "Hvidovre"
    ],
    "name:eus_x_preferred":[
        "Hvidovre"
    ],
    "name:fao_x_preferred":[
        "Hvidovre"
    ],
    "name:fin_x_preferred":[
        "Hvidovre"
    ],
    "name:fra_x_preferred":[
        "Hvidovre"
    ],
    "name:frr_x_preferred":[
        "Hvidovre"
    ],
    "name:jpn_x_preferred":[
        "\u30d3\u30ba\u30aa\u30a6\u30a2"
    ],
    "name:kal_x_preferred":[
        "Hvidovre"
    ],
    "name:lit_x_preferred":[
        "Vidovr\u0117"
    ],
    "name:msa_x_preferred":[
        "Hvidovre"
    ],
    "name:nld_x_preferred":[
        "Hvidovre"
    ],
    "name:nno_x_preferred":[
        "Hvidovre"
    ],
    "name:nob_x_preferred":[
        "Hvidovre"
    ],
    "name:pol_x_preferred":[
        "Hvidovre"
    ],
    "name:ron_x_preferred":[
        "Hvidovre"
    ],
    "name:rus_x_preferred":[
        "\u0412\u0438\u0434\u043e\u0432\u0440\u0435"
    ],
    "name:swe_x_preferred":[
        "Hvidovre"
    ],
    "name:zho_x_preferred":[
        "\u54c8\u7dad\u5fb7\u592b"
    ],
    "wd:wordcount":440,
    "wof:name":"Hvidovre",
    "wof:placetype":"neighbourhood"
},
  "geometry": {"coordinates":[12.47672366976381,55.6444477978385],"type":"Point"}
}