{
  "type": "Feature",
  "properties": {
    "iso:country":"DK",
    "name:ceb_x_preferred":[
        "Hvidovre"
    ],
    "name:dan_x_preferred":[
        "Hvidovre"
    ],
    "name:eus_x_preferred":[
        "Hvidovre"
    ],
    "name:fin_x_preferred":[
        "Hvidovre"
    ],
    "name:frr_x_preferred":[
        "Hvidovre"
    ],
    "name:msa_x_preferred":[
        "Hvidovre"
    ],
    "name:pol_x_preferred":[
        "Hvidovre"
    ],
    "name:ron_x_preferred":[
        "Hvidovre"
    ],
    "wd:wordcount":440,
    "wof:name":"Hvidovre",
    "wof:placetype":"neighbourhood"
},
  "geometry": {"coordinates":[12.47672366976381,55.6444477978385],"type":"Point"}
}