{
  "type": "Feature",
  "properties": {
    "gn:admin1_code":"20.0",
    "gn:admin2_code":"329.0",
    "gn:asciiname":"Torpet",
    "gn:country_code":"DK",
    "gn:dem":49,
    "gn:feature_class":"P",
    "gn:feature_code":"PPL",
    "gn:name":"Torpet",
    "gn:population":0,
    "gn:timezone":"Europe/Copenhagen",
    "iso:country":"DK",
    "wof:name":"Torpet",
    "wof:placetype":"locality"
},
  "geometry": {"coordinates":[11.75935,55.44305],"type":"Point"}
}