{
  "type": "Feature",
  "properties": {
    "gn:admin1_code":"18.0",
    "gn:admin2_code":"791.0",
    "gn:asciiname":"Sonder Raevind",
    "gn:country_code":"DK",
    "gn:dem":18,
    "gn:feature_class":"P",
    "gn:feature_code":"PPLL",
    "gn:name":"S\u00f8nder R\u00e6vind",
    "gn:population":0,
    "gn:timezone":"Europe/Copenhagen",
    "iso:country":"DK",
    "name:und_x_variant":[
        "Revn",
        "R\u00e6vind",
        "S\u00f8nder R\u00e6vind"
    ],
    "wof:name":"Sonder Raevind",
    "wof:placetype":"locality"
},
  "geometry": {"coordinates":[9.22607,56.50408],"type":"Point"}
}