{
  "type": "Feature",
  "properties": {
    "gn:admin1_code":"20.0",
    "gn:admin2_code":"350.0",
    "gn:asciiname":"Store Karleby",
    "gn:country_code":"DK",
    "gn:dem":17,
    "gn:feature_class":"P",
    "gn:feature_code":"PPL",
    "gn:name":"Store Karleby",
    "gn:population":0,
    "gn:timezone":"Europe/Copenhagen",
    "iso:country":"DK",
    "wof:name":"Store Karleby",
    "wof:placetype":"locality"
},
  "geometry": {"coordinates":[11.91098,55.69239],"type":"Point"}
}