{
  "type": "Feature",
  "properties": {
    "gn:admin1_code":"18.0",
    "gn:admin2_code":"657.0",
    "gn:asciiname":"Green",
    "gn:country_code":"DK",
    "gn:dem":34,
    "gn:feature_class":"P",
    "gn:feature_code":"PPLL",
    "gn:name":"Green",
    "gn:population":0,
    "gn:timezone":"Europe/Copenhagen",
    "iso:country":"DK",
    "name:rus_x_preferred":[
        "\u0413\u0440\u0435\u043d\u043e"
    ],
    "name:und_x_variant":[
        "Gren",
        "Green"
    ],
    "wof:name":"Green",
    "wof:placetype":"locality"
},
  "geometry": {"coordinates":[8.99691,55.99752],"type":"Point"}
}