{
  "type": "Feature",
  "properties": {
    "gn:admin1_code":"21.0",
    "gn:admin2_code":"561.0",
    "gn:asciiname":"Opsneum",
    "gn:country_code":"DK",
    "gn:dem":6,
    "gn:feature_class":"P",
    "gn:feature_code":"PPL",
    "gn:name":"Opsneum",
    "gn:population":0,
    "gn:timezone":"Europe/Copenhagen",
    "iso:country":"DK",
    "wof:name":"Opsneum",
    "wof:placetype":"locality"
},
  "geometry": {"coordinates":[8.62536,55.48184000000001],"type":"Point"}
}