{
  "type": "Feature",
  "properties": {
    "iso:country":"DK",
    "name:dan_x_preferred":[
        "Odense SO"
    ],
    "name:eng_x_preferred":[
        "Odense South East"
    ],
    "name:eng_x_variant":[
        "Odense South East"
    ],
    "name:unk_x_variant":[
        "Odense SO"
    ],
    "qs:gn_adm0_cc":"DK",
    "qs:gn_local":2615876,
    "qs:gn_nam_loc":"Odense, Odense, Syddanmark, DK",
    "qs:gn_namadm1":"21",
    "qs:local_max":7922,
    "qs:local_sum":17175,
    "qs:localhoods":8,
    "qs:name":"Odense SO",
    "qs:name_adm0":"Danmark",
    "qs:name_adm1":"Syddanmark",
    "qs:name_adm2":"Odense",
    "qs:name_en":"Odense South East",
    "qs:name_local":"Odense",
    "qs:photo_max":1893,
    "qs:photo_sum":2221,
    "qs:placetype":"Suburb",
    "qs:quad_count":29,
    "qs:woe_adm0":23424796,
    "qs:woe_adm1":28362581,
    "qs:woe_adm2":12582683,
    "qs:woe_lau":0,
    "qs:woe_local":556053,
    "qs:woe_ver":"7.10.0",
    "wof:lang":[
        "dan"
    ],
    "wof:name":"Odense SO",
    "wof:placetype":"neighbourhood"
},
  "geometry": {"coordinates":[10.495404,55.342108],"type":"Point"}
}