{
  "type": "Feature",
  "properties": {
    "gn:admin1_code":"19.0",
    "gn:admin2_code":"773.0",
    "gn:asciiname":"Sundby",
    "gn:country_code":"DK",
    "gn:dem":47,
    "gn:feature_class":"P",
    "gn:feature_code":"PPL",
    "gn:name":"Sundby",
    "gn:population":0,
    "gn:timezone":"Europe/Copenhagen",
    "iso:country":"DK",
    "name:ceb_x_preferred":[
        "Sundby"
    ],
    "name:dan_x_preferred":[
        "Sundby"
    ],
    "name:deu_x_preferred":[
        "Sundby"
    ],
    "name:fra_x_preferred":[
        "Sundby"
    ],
    "name:ita_x_preferred":[
        "Sundby"
    ],
    "name:nld_x_preferred":[
        "Sundby"
    ],
    "name:nor_x_preferred":[
        "Sundby"
    ],
    "name:rus_x_preferred":[
        "\u0421\u0443\u043d\u0434\u0431\u044e"
    ],
    "name:swe_x_preferred":[
        "Sundby"
    ],
    "wof:name":"Sundby",
    "wof:placetype":"locality"
},
  "geometry": {"coordinates":[8.67406,56.87379],"type":"Point"}
}