{
  "type": "Feature",
  "properties": {
    "gn:admin1_code":"21.0",
    "gn:admin2_code":"550.0",
    "gn:asciiname":"Norrevaerre",
    "gn:country_code":"DK",
    "gn:dem":3,
    "gn:feature_class":"P",
    "gn:feature_code":"PPL",
    "gn:name":"N\u00f8rrev\u00e6rre",
    "gn:population":0,
    "gn:timezone":"Europe/Copenhagen",
    "iso:country":"DK",
    "wof:name":"Norrevaerre",
    "wof:placetype":"locality"
},
  "geometry": {"coordinates":[8.72575,54.92574000000001],"type":"Point"}
}