{
  "type": "Feature",
  "properties": {
    "gn:admin1_code":"21.0",
    "gn:admin2_code":"450.0",
    "gn:asciiname":"Frederikshoj",
    "gn:country_code":"DK",
    "gn:dem":57,
    "gn:feature_class":"P",
    "gn:feature_code":"PPLL",
    "gn:name":"Frederiksh\u00f8j",
    "gn:population":0,
    "gn:timezone":"Europe/Copenhagen",
    "iso:country":"DK",
    "wof:name":"Frederikshoj",
    "wof:placetype":"locality"
},
  "geometry": {"coordinates":[10.72817,55.26376],"type":"Point"}
}