{
  "type": "Feature",
  "properties": {
    "gn:admin1_code":"18.0",
    "gn:admin2_code":"760.0",
    "gn:asciiname":"Tim",
    "gn:country_code":"DK",
    "gn:dem":10,
    "gn:feature_class":"P",
    "gn:feature_code":"PPL",
    "gn:name":"Tim",
    "gn:population":0,
    "gn:timezone":"Europe/Copenhagen",
    "iso:country":"DK",
    "name:und_x_variant":[
        "\u00d8ster Tim",
        "Tiim Stationsby",
        "Tim"
    ],
    "wof:name":"Tim",
    "wof:placetype":"locality"
},
  "geometry": {"coordinates":[8.30785,56.19563],"type":"Point"}
}