{
  "type": "Feature",
  "properties": {
    "gn:admin1_code":"18.0",
    "gn:admin2_code":"779.0",
    "gn:asciiname":"Ilbjerg",
    "gn:country_code":"DK",
    "gn:dem":36,
    "gn:feature_class":"P",
    "gn:feature_code":"PPL",
    "gn:name":"Ilbjerg",
    "gn:population":0,
    "gn:timezone":"Europe/Copenhagen",
    "iso:country":"DK",
    "name:und_x_variant":[
        "Ilbj\u00e6rg",
        "Ilbjerg"
    ],
    "wof:name":"Ilbjerg",
    "wof:placetype":"locality"
},
  "geometry": {"coordinates":[9.01408,56.70438000000001],"type":"Point"}
}