{
  "type": "Feature",
  "properties": {
    "gn:admin1_code":"19.0",
    "gn:admin2_code":"851.0",
    "gn:asciiname":"Alebaek",
    "gn:country_code":"DK",
    "gn:dem":6,
    "gn:feature_class":"P",
    "gn:feature_code":"PPL",
    "gn:name":"\u00c5leb\u00e6k",
    "gn:population":0,
    "gn:timezone":"Europe/Copenhagen",
    "iso:country":"DK",
    "name:und_x_variant":[
        "Aaleb\u00e6k",
        "Aaleb\u00e6k Huse",
        "\u00c5leb\u00e6k"
    ],
    "wof:name":"Alebaek",
    "wof:placetype":"locality"
},
  "geometry": {"coordinates":[10.26062,57.01217],"type":"Point"}
}