{
  "type": "Feature",
  "properties": {
    "gn:admin1_code":"20.0",
    "gn:admin2_code":"360.0",
    "gn:asciiname":"Keldernaesskov",
    "gn:country_code":"DK",
    "gn:dem":7,
    "gn:feature_class":"P",
    "gn:feature_code":"PPL",
    "gn:name":"Keldern\u00e6sskov",
    "gn:population":0,
    "gn:timezone":"Europe/Copenhagen",
    "iso:country":"DK",
    "wof:name":"Keldernaesskov",
    "wof:placetype":"locality"
},
  "geometry": {"coordinates":[11.39334,54.84311999999999],"type":"Point"}
}