{
  "type": "Feature",
  "properties": {
    "gn:admin1_code":"21.0",
    "gn:admin2_code":"461.0",
    "gn:asciiname":"Anderup",
    "gn:country_code":"DK",
    "gn:dem":4,
    "gn:feature_class":"P",
    "gn:feature_code":"PPL",
    "gn:name":"Anderup",
    "gn:population":0,
    "gn:timezone":"Europe/Copenhagen",
    "iso:country":"DK",
    "name:dan_x_preferred":[
        "Anderup"
    ],
    "wof:name":"Anderup",
    "wof:placetype":"locality"
},
  "geometry": {"coordinates":[10.39111,55.43376],"type":"Point"}
}