{
  "type": "Feature",
  "properties": {
    "gn:admin1_code":"21.0",
    "gn:admin2_code":"561.0",
    "gn:asciiname":"Vester Nebel",
    "gn:country_code":"DK",
    "gn:dem":25,
    "gn:feature_class":"P",
    "gn:feature_code":"PPL",
    "gn:name":"Vester Nebel",
    "gn:population":0,
    "gn:timezone":"Europe/Copenhagen",
    "iso:country":"DK",
    "wof:name":"Vester Nebel",
    "wof:placetype":"locality"
},
  "geometry": {"coordinates":[8.54355,55.5404],"type":"Point"}
}