{
  "type": "Feature",
  "properties": {
    "gn:admin1_code":"17.0",
    "gn:admin2_code":"400.0",
    "gn:asciiname":"Robbedale",
    "gn:country_code":"DK",
    "gn:dem":35,
    "gn:feature_class":"P",
    "gn:feature_code":"PPLL",
    "gn:name":"Robbedale",
    "gn:population":0,
    "gn:timezone":"Europe/Copenhagen",
    "iso:country":"DK",
    "wof:name":"Robbedale",
    "wof:placetype":"locality"
},
  "geometry": {"coordinates":[14.75199,55.08389],"type":"Point"}
}