{
  "type": "Feature",
  "properties": {
    "gn:admin1_code":"20.0",
    "gn:admin2_code":"265.0",
    "gn:asciiname":"Ramsomagle",
    "gn:country_code":"DK",
    "gn:dem":44,
    "gn:feature_class":"P",
    "gn:feature_code":"PPL",
    "gn:name":"Rams\u00f8magle",
    "gn:population":0,
    "gn:timezone":"Europe/Copenhagen",
    "iso:country":"DK",
    "wof:name":"Ramsomagle",
    "wof:placetype":"locality"
},
  "geometry": {"coordinates":[12.06857,55.5701],"type":"Point"}
}