{
  "type": "Feature",
  "properties": {
    "gn:admin1_code":"18.0",
    "gn:admin2_code":"706.0",
    "gn:asciiname":"Balle",
    "gn:country_code":"DK",
    "gn:dem":11,
    "gn:feature_class":"P",
    "gn:feature_code":"PPL",
    "gn:name":"Balle",
    "gn:population":0,
    "gn:timezone":"Europe/Copenhagen",
    "iso:country":"DK",
    "name:und_x_variant":[
        "Vester Balle",
        "Balle"
    ],
    "wof:name":"Balle",
    "wof:placetype":"locality"
},
  "geometry": {"coordinates":[10.80979,56.3173],"type":"Point"}
}