{
  "type": "Feature",
  "properties": {
    "gn:admin1_code":"21.0",
    "gn:admin2_code":"430.0",
    "gn:asciiname":"Sandholts-Lyndelse",
    "gn:country_code":"DK",
    "gn:dem":30,
    "gn:feature_class":"P",
    "gn:feature_code":"PPL",
    "gn:name":"Sandholts-Lyndelse",
    "gn:population":0,
    "gn:timezone":"Europe/Copenhagen",
    "iso:country":"DK",
    "name:und_x_variant":[
        "Lyndelse",
        "Sandholts-Lyndelse"
    ],
    "wof:name":"Sandholts-Lyndelse",
    "wof:placetype":"locality"
},
  "geometry": {"coordinates":[10.30098,55.20675],"type":"Point"}
}