{
  "type": "Feature",
  "properties": {
    "gn:admin1_code":"20.0",
    "gn:admin2_code":"390.0",
    "gn:asciiname":"Busemarke",
    "gn:country_code":"DK",
    "gn:dem":29,
    "gn:feature_class":"P",
    "gn:feature_code":"PPL",
    "gn:name":"Busemarke",
    "gn:population":0,
    "gn:timezone":"Europe/Copenhagen",
    "iso:country":"DK",
    "name:und_x_variant":[
        "Budsemarke",
        "Busemarke"
    ],
    "wof:name":"Busemarke",
    "wof:placetype":"locality"
},
  "geometry": {"coordinates":[12.47828,54.96954],"type":"Point"}
}