{
  "type": "Feature",
  "properties": {
    "gn:admin1_code":"20.0",
    "gn:admin2_code":"390.0",
    "gn:asciiname":"Lundby Torp",
    "gn:country_code":"DK",
    "gn:dem":17,
    "gn:feature_class":"P",
    "gn:feature_code":"PPL",
    "gn:name":"Lundby Torp",
    "gn:population":0,
    "gn:timezone":"Europe/Copenhagen",
    "iso:country":"DK",
    "name:und_x_variant":[
        "Lille Torp",
        "Lundby Torp"
    ],
    "wof:name":"Lundby Torp",
    "wof:placetype":"locality"
},
  "geometry": {"coordinates":[11.86591,55.1205],"type":"Point"}
}