{
  "type": "Feature",
  "properties": {
    "gn:admin1_code":"20.0",
    "gn:admin2_code":"376.0",
    "gn:asciiname":"Bregninge",
    "gn:country_code":"DK",
    "gn:dem":12,
    "gn:feature_class":"P",
    "gn:feature_code":"PPL",
    "gn:name":"Bregninge",
    "gn:population":0,
    "gn:timezone":"Europe/Copenhagen",
    "iso:country":"DK",
    "name:dan_x_preferred":[
        "Bregninge"
    ],
    "name:deu_x_preferred":[
        "Bregninge"
    ],
    "name:nds_x_preferred":[
        "Bregninge"
    ],
    "name:nld_x_preferred":[
        "Bregninge"
    ],
    "name:swe_x_preferred":[
        "Bregninge"
    ],
    "wof:name":"Bregninge",
    "wof:placetype":"locality"
},
  "geometry": {"coordinates":[11.69981,54.7157],"type":"Point"}
}