{
  "type": "Feature",
  "properties": {
    "gn:admin1_code":"21.0",
    "gn:admin2_code":"573.0",
    "gn:asciiname":"Lonne Hede",
    "gn:country_code":"DK",
    "gn:dem":4,
    "gn:feature_class":"P",
    "gn:feature_code":"PPL",
    "gn:name":"L\u00f8nne Hede",
    "gn:population":0,
    "gn:timezone":"Europe/Copenhagen",
    "iso:country":"DK",
    "wof:name":"Lonne Hede",
    "wof:placetype":"locality"
},
  "geometry": {"coordinates":[8.2576,55.77538000000001],"type":"Point"}
}