{
  "type": "Feature",
  "properties": {
    "gn:admin1_code":"19.0",
    "gn:admin2_code":"773.0",
    "gn:asciiname":"Blabjerg Garde",
    "gn:country_code":"DK",
    "gn:dem":7,
    "gn:feature_class":"P",
    "gn:feature_code":"PPLL",
    "gn:name":"Bl\u00e5bjerg G\u00e5rde",
    "gn:population":0,
    "gn:timezone":"Europe/Copenhagen",
    "iso:country":"DK",
    "name:und_x_variant":[
        "Bl\u00e5bjerg",
        "Blaabjerg Gaarde",
        "Blaabj\u00e6rg Gaarde",
        "Bl\u00e5bjerg G\u00e5rde"
    ],
    "wof:name":"Blabjerg Garde",
    "wof:placetype":"locality"
},
  "geometry": {"coordinates":[8.59564,56.77451],"type":"Point"}
}