{
  "type": "Feature",
  "properties": {
    "gn:admin1_code":"21.0",
    "gn:admin2_code":"580.0",
    "gn:asciiname":"Gaskaer",
    "gn:country_code":"DK",
    "gn:dem":25,
    "gn:feature_class":"P",
    "gn:feature_code":"PPL",
    "gn:name":"G\u00e5sk\u00e6r",
    "gn:population":0,
    "gn:timezone":"Europe/Copenhagen",
    "iso:country":"DK",
    "name:und_x_variant":[
        "Gaask\u00e6r",
        "G\u00e5sk\u00e6r"
    ],
    "wof:name":"Gaskaer",
    "wof:placetype":"locality"
},
  "geometry": {"coordinates":[9.22378,54.97006],"type":"Point"}
}