{
  "type": "Feature",
  "properties": {
    "gn:admin1_code":"21.0",
    "gn:admin2_code":"550.0",
    "gn:asciiname":"Solsted",
    "gn:country_code":"DK",
    "gn:dem":17,
    "gn:feature_class":"P",
    "gn:feature_code":"PPL",
    "gn:name":"S\u00f8lsted",
    "gn:population":0,
    "gn:timezone":"Europe/Copenhagen",
    "iso:country":"DK",
    "wof:name":"Solsted",
    "wof:placetype":"locality"
},
  "geometry": {"coordinates":[8.8466,55.01503],"type":"Point"}
}