{
  "type": "Feature",
  "properties": {
    "gn:admin1_code":"18.0",
    "gn:admin2_code":"751.0",
    "gn:asciiname":"Elsted",
    "gn:country_code":"DK",
    "gn:dem":62,
    "gn:feature_class":"P",
    "gn:feature_code":"PPL",
    "gn:name":"Elsted",
    "gn:population":0,
    "gn:timezone":"Europe/Copenhagen",
    "iso:country":"DK",
    "wof:name":"Elsted",
    "wof:placetype":"locality"
},
  "geometry": {"coordinates":[10.23832,56.24612],"type":"Point"}
}