{
  "type": "Feature",
  "properties": {
    "gn:admin1_code":"21.0",
    "gn:admin2_code":"573.0",
    "gn:asciiname":"Jyllerup",
    "gn:country_code":"DK",
    "gn:dem":22,
    "gn:feature_class":"P",
    "gn:feature_code":"PPLL",
    "gn:name":"Jyllerup",
    "gn:population":0,
    "gn:timezone":"Europe/Copenhagen",
    "iso:country":"DK",
    "wof:name":"Jyllerup",
    "wof:placetype":"locality"
},
  "geometry": {"coordinates":[8.69342,55.55588],"type":"Point"}
}