{
  "type": "Feature",
  "properties": {
    "gn:admin1_code":"20.0",
    "gn:admin2_code":"370.0",
    "gn:asciiname":"Arlose",
    "gn:country_code":"DK",
    "gn:dem":36,
    "gn:feature_class":"P",
    "gn:feature_code":"PPL",
    "gn:name":"Arl\u00f8se",
    "gn:population":0,
    "gn:timezone":"Europe/Copenhagen",
    "iso:country":"DK",
    "wof:name":"Arlose",
    "wof:placetype":"locality"
},
  "geometry": {"coordinates":[11.55429,55.27522],"type":"Point"}
}