{
  "type": "Feature",
  "properties": {
    "gn:gn_country":"DK",
    "gn:gn_fcode":"PPL",
    "gn:gn_pop":0,
    "iso:country":"DK",
    "name:dan_x_preferred":[
        "Blokhus"
    ],
    "name:deu_x_preferred":[
        "Blokhus"
    ],
    "name:eng_x_preferred":[
        "Blokhus"
    ],
    "name:fra_x_preferred":[
        "Blokhus"
    ],
    "name:isl_x_preferred":[
        "Blokhus"
    ],
    "name:nld_x_preferred":[
        "Blokhus"
    ],
    "name:nob_x_preferred":[
        "Blokhus"
    ],
    "qs_pg:aaroncc":"DK",
    "qs_pg:gn_country":"DK",
    "qs_pg:gn_fcode":"PPL",
    "qs_pg:gn_pop":0,
    "qs_pg:name":"Blokhus",
    "qs_pg:name_adm0":"Danmark",
    "qs_pg:name_adm1":"Nordjylland",
    "qs_pg:photos":552,
    "qs_pg:photos_1k":112,
    "qs_pg:photos_9k":2,
    "qs_pg:photos_9r":5,
    "qs_pg:photos_all":552,
    "qs_pg:photos_sr":8,
    "qs_pg:pop_sr":0,
    "qs_pg:qs_pg_placetype":"locality",
    "qs_pg:qs_pg_placetype_gp":"Town",
    "qs_pg:woe_adm0":23424796,
    "woe:adm0_id":23424796,
    "woe:name_adm0":"Danmark",
    "woe:name_adm1":"Nordjylland",
    "woe:placetype":"Town",
    "wof:name":"Blokhus",
    "wof:placetype":"locality"
},
  "geometry": {"coordinates":[9.5897,57.24797],"type":"Point"}
}