{
  "type": "Feature",
  "properties": {
    "gn:admin1_code":"19.0",
    "gn:admin2_code":"810.0",
    "gn:asciiname":"Oster Bronderslev",
    "gn:country_code":"DK",
    "gn:dem":24,
    "gn:feature_class":"P",
    "gn:feature_code":"PPL",
    "gn:name":"\u00d8ster Br\u00f8nderslev",
    "gn:population":0,
    "gn:timezone":"Europe/Copenhagen",
    "iso:country":"DK",
    "wof:name":"Oster Bronderslev",
    "wof:placetype":"locality"
},
  "geometry": {"coordinates":[9.99593,57.24841],"type":"Point"}
}