{
  "type": "Feature",
  "properties": {
    "gn:admin1_code":"19.0",
    "gn:admin2_code":"851.0",
    "gn:asciiname":"Kolby",
    "gn:country_code":"DK",
    "gn:dem":11,
    "gn:feature_class":"P",
    "gn:feature_code":"PPL",
    "gn:name":"K\u00f8lby",
    "gn:population":0,
    "gn:timezone":"Europe/Copenhagen",
    "iso:country":"DK",
    "name:dan_x_preferred":[
        "Kolby Sogn"
    ],
    "name:deu_x_preferred":[
        "Kolby Sogn"
    ],
    "name:nld_x_preferred":[
        "Kolby"
    ],
    "name:und_x_variant":[
        "Kj\u00f6lby",
        "K\u00f8lby"
    ],
    "wof:name":"Kolby",
    "wof:placetype":"locality"
},
  "geometry": {"coordinates":[9.42563,56.98022],"type":"Point"}
}