{
  "type": "Feature",
  "properties": {
    "gn:admin1_code":"19.0",
    "gn:admin2_code":"810.0",
    "gn:asciiname":"Gammelkirke",
    "gn:country_code":"DK",
    "gn:dem":34,
    "gn:feature_class":"P",
    "gn:feature_code":"PPLL",
    "gn:name":"Gammelkirke",
    "gn:population":0,
    "gn:timezone":"Europe/Copenhagen",
    "iso:country":"DK",
    "name:und_x_variant":[
        "Gammelkirk",
        "Gammelkirke"
    ],
    "wof:name":"Gammelkirke",
    "wof:placetype":"locality"
},
  "geometry": {"coordinates":[10.21449,57.17534000000001],"type":"Point"}
}