{
  "type": "Feature",
  "properties": {
    "gn:admin1_code":"20.0",
    "gn:admin2_code":"330.0",
    "gn:asciiname":"Skovse",
    "gn:country_code":"DK",
    "gn:dem":39,
    "gn:feature_class":"P",
    "gn:feature_code":"PPL",
    "gn:name":"Skovse",
    "gn:population":0,
    "gn:timezone":"Europe/Copenhagen",
    "iso:country":"DK",
    "name:und_x_variant":[
        "Skovs\u00f6",
        "Skovse"
    ],
    "wof:name":"Skovse",
    "wof:placetype":"locality"
},
  "geometry": {"coordinates":[11.40711,55.4163],"type":"Point"}
}