{
  "type": "Feature",
  "properties": {
    "gn:admin1_code":"21.0",
    "gn:admin2_code":"561.0",
    "gn:asciiname":"Oksvang",
    "gn:country_code":"DK",
    "gn:dem":24,
    "gn:feature_class":"P",
    "gn:feature_code":"PPL",
    "gn:name":"Oksvang",
    "gn:population":0,
    "gn:timezone":"Europe/Copenhagen",
    "iso:country":"DK",
    "name:und_x_variant":[
        "Oxvang",
        "Oksvang"
    ],
    "wof:name":"Oksvang",
    "wof:placetype":"locality"
},
  "geometry": {"coordinates":[8.52808,55.51303000000001],"type":"Point"}
}