{
  "type": "Feature",
  "properties": {
    "gn:admin1_code":"18.0",
    "gn:admin2_code":"710.0",
    "gn:asciiname":"Fajstrup",
    "gn:country_code":"DK",
    "gn:dem":70,
    "gn:feature_class":"P",
    "gn:feature_code":"PPL",
    "gn:name":"Fajstrup",
    "gn:population":0,
    "gn:timezone":"Europe/Copenhagen",
    "iso:country":"DK",
    "wof:name":"Fajstrup",
    "wof:placetype":"locality"
},
  "geometry": {"coordinates":[9.95922,56.22598000000001],"type":"Point"}
}