{
  "type": "Feature",
  "properties": {
    "gn:admin1_code":"21.0",
    "gn:admin2_code":"630.0",
    "gn:asciiname":"Bjerlev",
    "gn:country_code":"DK",
    "gn:dem":101,
    "gn:feature_class":"P",
    "gn:feature_code":"PPL",
    "gn:name":"Bjerlev",
    "gn:population":0,
    "gn:timezone":"Europe/Copenhagen",
    "iso:country":"DK",
    "wof:name":"Bjerlev",
    "wof:placetype":"locality"
},
  "geometry": {"coordinates":[9.43332,55.82066],"type":"Point"}
}