{
  "type": "Feature",
  "properties": {
    "gn:admin1_code":"21.0",
    "gn:admin2_code":"550.0",
    "gn:asciiname":"Gejlbjerg",
    "gn:country_code":"DK",
    "gn:dem":59,
    "gn:feature_class":"P",
    "gn:feature_code":"PPL",
    "gn:name":"Gejlbjerg",
    "gn:population":0,
    "gn:timezone":"Europe/Copenhagen",
    "iso:country":"DK",
    "name:und_x_variant":[
        "Gejlbj\u00e6rg",
        "Gejlbjerg"
    ],
    "wof:name":"Gejlbjerg",
    "wof:placetype":"locality"
},
  "geometry": {"coordinates":[9.14934,55.11729],"type":"Point"}
}