{
  "type": "Feature",
  "properties": {
    "gn:admin1_code":"21.0",
    "gn:admin2_code":"540.0",
    "gn:asciiname":"Helleved",
    "gn:country_code":"DK",
    "gn:dem":37,
    "gn:feature_class":"P",
    "gn:feature_code":"PPL",
    "gn:name":"Helleved",
    "gn:population":0,
    "gn:timezone":"Europe/Copenhagen",
    "iso:country":"DK",
    "name:und_x_variant":[
        "Helved",
        "Helleved"
    ],
    "wof:name":"Helleved",
    "wof:placetype":"locality"
},
  "geometry": {"coordinates":[9.95402,54.99976],"type":"Point"}
}