{
  "type": "Feature",
  "properties": {
    "gn:admin1_code":"21.0",
    "gn:admin2_code":"540.0",
    "gn:asciiname":"Lagmade",
    "gn:country_code":"DK",
    "gn:dem":3,
    "gn:feature_class":"P",
    "gn:feature_code":"PPL",
    "gn:name":"L\u00e5gmade",
    "gn:population":0,
    "gn:timezone":"Europe/Copenhagen",
    "iso:country":"DK",
    "name:und_x_variant":[
        "L\u00e5gemade",
        "L\u00e5gmade"
    ],
    "wof:name":"Lagmade",
    "wof:placetype":"locality"
},
  "geometry": {"coordinates":[9.61621,54.90102],"type":"Point"}
}