{
  "type": "Feature",
  "properties": {
    "gn:admin1_code":"20.0",
    "gn:admin2_code":"320.0",
    "gn:asciiname":"Hovby",
    "gn:country_code":"DK",
    "gn:dem":27,
    "gn:feature_class":"P",
    "gn:feature_code":"PPL",
    "gn:name":"Hovby",
    "gn:population":0,
    "gn:timezone":"Europe/Copenhagen",
    "iso:country":"DK",
    "wof:name":"Hovby",
    "wof:placetype":"locality"
},
  "geometry": {"coordinates":[12.10187,55.24544],"type":"Point"}
}