{
  "type": "Feature",
  "properties": {
    "gn:admin1_code":"21.0",
    "gn:admin2_code":"461.0",
    "gn:asciiname":"Skovs-Hjrup",
    "gn:country_code":"DK",
    "gn:dem":21,
    "gn:feature_class":"P",
    "gn:feature_code":"PPL",
    "gn:name":"Skovs-Hjrup",
    "gn:population":0,
    "gn:timezone":"Europe/Copenhagen",
    "iso:country":"DK",
    "wof:name":"Skovs-Hjrup",
    "wof:placetype":"locality"
},
  "geometry": {"coordinates":[10.27377,55.44959],"type":"Point"}
}