{
  "type": "Feature",
  "properties": {
    "gn:admin1_code":"18.0",
    "gn:admin2_code":"791.0",
    "gn:asciiname":"Vester Tostrup",
    "gn:country_code":"DK",
    "gn:dem":32,
    "gn:feature_class":"P",
    "gn:feature_code":"PPL",
    "gn:name":"Vester Tostrup",
    "gn:population":0,
    "gn:timezone":"Europe/Copenhagen",
    "iso:country":"DK",
    "name:und_x_variant":[
        "Tostrup",
        "Vester Tostrup"
    ],
    "wof:name":"Vester Tostrup",
    "wof:placetype":"locality"
},
  "geometry": {"coordinates":[9.4664,56.62007],"type":"Point"}
}