{
  "type": "Feature",
  "properties": {
    "gn:admin1_code":"21.0",
    "gn:admin2_code":"482.0",
    "gn:asciiname":"Uglebjerg",
    "gn:country_code":"DK",
    "gn:dem":2,
    "gn:feature_class":"P",
    "gn:feature_code":"PPL",
    "gn:name":"Uglebjerg",
    "gn:population":0,
    "gn:timezone":"Europe/Copenhagen",
    "iso:country":"DK",
    "name:und_x_variant":[
        "Uglebj\u00e6rg",
        "Ullebj\u00e6rg",
        "Uglebjerg"
    ],
    "wof:name":"Uglebjerg",
    "wof:placetype":"locality"
},
  "geometry": {"coordinates":[10.94724,55.13774],"type":"Point"}
}