{
  "type": "Feature",
  "properties": {
    "gn:admin1_code":"19.0",
    "gn:admin2_code":"813.0",
    "gn:asciiname":"Rydal",
    "gn:country_code":"DK",
    "gn:dem":50,
    "gn:feature_class":"P",
    "gn:feature_code":"PPL",
    "gn:name":"Rydal",
    "gn:population":0,
    "gn:timezone":"Europe/Copenhagen",
    "iso:country":"DK",
    "name:ceb_x_preferred":[
        "Rydal"
    ],
    "name:deu_x_preferred":[
        "Rydal"
    ],
    "name:fra_x_preferred":[
        "Rydal"
    ],
    "name:sco_x_preferred":[
        "Rydal"
    ],
    "wof:name":"Rydal",
    "wof:placetype":"locality"
},
  "geometry": {"coordinates":[10.3869,57.42731],"type":"Point"}
}