{
  "type": "Feature",
  "properties": {
    "gn:admin1_code":"20.0",
    "gn:admin2_code":"320.0",
    "gn:asciiname":"Vallebo",
    "gn:country_code":"DK",
    "gn:dem":11,
    "gn:feature_class":"P",
    "gn:feature_code":"PPL",
    "gn:name":"Vallebo",
    "gn:population":0,
    "gn:timezone":"Europe/Copenhagen",
    "iso:country":"DK",
    "wof:name":"Vallebo",
    "wof:placetype":"locality"
},
  "geometry": {"coordinates":[12.12894,55.22456999999999],"type":"Point"}
}