{
  "type": "Feature",
  "properties": {
    "gn:admin1_code":"21.0",
    "gn:admin2_code":"450.0",
    "gn:asciiname":"Slude",
    "gn:country_code":"DK",
    "gn:dem":44,
    "gn:feature_class":"P",
    "gn:feature_code":"PPLL",
    "gn:name":"Slude",
    "gn:population":0,
    "gn:timezone":"Europe/Copenhagen",
    "iso:country":"DK",
    "wof:name":"Slude",
    "wof:placetype":"locality"
},
  "geometry": {"coordinates":[10.74744,55.25686999999999],"type":"Point"}
}