{
  "type": "Feature",
  "properties": {
    "gn:admin1_code":"19.0",
    "gn:admin2_code":"773.0",
    "gn:asciiname":"Emb",
    "gn:country_code":"DK",
    "gn:dem":7,
    "gn:feature_class":"P",
    "gn:feature_code":"PPL",
    "gn:name":"Emb",
    "gn:population":0,
    "gn:timezone":"Europe/Copenhagen",
    "iso:country":"DK",
    "name:und_x_variant":[
        "Em",
        "Emb"
    ],
    "wof:name":"Emb",
    "wof:placetype":"locality"
},
  "geometry": {"coordinates":[8.68439,56.71673000000001],"type":"Point"}
}