{
  "type": "Feature",
  "properties": {
    "gn:admin1_code":"20.0",
    "gn:admin2_code":"360.0",
    "gn:asciiname":"Tillitse",
    "gn:country_code":"DK",
    "gn:dem":1,
    "gn:feature_class":"P",
    "gn:feature_code":"PPL",
    "gn:name":"Tillitse",
    "gn:population":0,
    "gn:timezone":"Europe/Copenhagen",
    "iso:country":"DK",
    "name:und_x_variant":[
        "Tillidse",
        "Tillitse"
    ],
    "wof:name":"Tillitse",
    "wof:placetype":"locality"
},
  "geometry": {"coordinates":[11.15187,54.76691999999999],"type":"Point"}
}