{
  "type": "Feature",
  "properties": {
    "gn:admin1_code":"21.0",
    "gn:admin2_code":"575.0",
    "gn:asciiname":"Atte",
    "gn:country_code":"DK",
    "gn:dem":31,
    "gn:feature_class":"P",
    "gn:feature_code":"PPL",
    "gn:name":"\u00c5tte",
    "gn:population":0,
    "gn:timezone":"Europe/Copenhagen",
    "iso:country":"DK",
    "wof:name":"Atte",
    "wof:placetype":"locality"
},
  "geometry": {"coordinates":[8.96662,55.44658],"type":"Point"}
}