{
  "type": "Feature",
  "properties": {
    "iso:country":"DK",
    "name:afr_x_preferred":[
        "Gandrup"
    ],
    "name:dan_x_preferred":[
        "Gandrup"
    ],
    "name:deu_x_preferred":[
        "Gandrup"
    ],
    "name:eng_x_preferred":[
        "Gandrup"
    ],
    "name:fra_x_preferred":[
        "Gandrup"
    ],
    "name:nld_x_preferred":[
        "Gandrup"
    ],
    "name:nob_x_preferred":[
        "Gandrup"
    ],
    "name:nor_x_preferred":[
        "Gandrup"
    ],
    "name:sco_x_preferred":[
        "Gandrup"
    ],
    "name:unk_x_variant":[
        "Ganderup"
    ],
    "qs:a0":"Danmark",
    "qs:a1":"*Nordjylland",
    "qs:a1r":"0",
    "qs:adm0":"Danmark",
    "qs:la_lc":"*",
    "qs:level":"locality",
    "qs:loc":"Gandrup",
    "qs:loc_alt":"Gandrup",
    "qs:pop":0,
    "qs:type":"buffered point",
    "wd:wordcount":79,
    "wof:name":"Gandrup",
    "wof:placetype":"locality"
},
  "geometry": {"coordinates":[10.190649,57.057373],"type":"Point"}
}