{
  "type": "Feature",
  "properties": {
    "gn:admin1_code":"18.0",
    "gn:admin2_code":"746.0",
    "gn:asciiname":"Horndrup",
    "gn:country_code":"DK",
    "gn:dem":38,
    "gn:feature_class":"P",
    "gn:feature_code":"PPL",
    "gn:name":"Horndrup",
    "gn:population":0,
    "gn:timezone":"Europe/Copenhagen",
    "iso:country":"DK",
    "wof:name":"Horndrup",
    "wof:placetype":"locality"
},
  "geometry": {"coordinates":[9.86677,56.00668],"type":"Point"}
}