{
  "type": "Feature",
  "properties": {
    "gn:admin1_code":"17.0",
    "gn:admin2_code":"260.0",
    "gn:asciiname":"Asebro Huse",
    "gn:cc2":"DK",
    "gn:country_code":"DK",
    "gn:dem":3,
    "gn:feature_class":"P",
    "gn:feature_code":"PPL",
    "gn:name":"\u00c5sebro Huse",
    "gn:population":0,
    "gn:timezone":"Europe/Copenhagen",
    "iso:country":"DK",
    "name:und_x_variant":[
        "\u00c5sebro",
        "Aasebro",
        "Aasebro Huse",
        "\u00c5sebro Huse"
    ],
    "wof:name":"Asebro Huse",
    "wof:placetype":"locality"
},
  "geometry": {"coordinates":[12.01667,55.98333],"type":"Point"}
}