{
  "type": "Feature",
  "properties": {
    "gn:admin1_code":"20.0",
    "gn:admin2_code":"259.0",
    "gn:asciiname":"Hastrup",
    "gn:country_code":"DK",
    "gn:dem":11,
    "gn:feature_class":"P",
    "gn:feature_code":"PPL",
    "gn:name":"Hastrup",
    "gn:population":0,
    "gn:timezone":"Europe/Copenhagen",
    "iso:country":"DK",
    "wof:name":"Hastrup",
    "wof:placetype":"locality"
},
  "geometry": {"coordinates":[12.16437,55.44218000000001],"type":"Point"}
}