{
  "type": "Feature",
  "properties": {
    "gn:admin1_code":"21.0",
    "gn:admin2_code":"430.0",
    "gn:asciiname":"Avernak By",
    "gn:country_code":"DK",
    "gn:dem":6,
    "gn:feature_class":"P",
    "gn:feature_code":"PPL",
    "gn:name":"Avernak By",
    "gn:population":0,
    "gn:timezone":"Europe/Copenhagen",
    "iso:country":"DK",
    "name:und_x_variant":[
        "Avernak\u00f8",
        "Avernak\u00f6 By",
        "Avernak By"
    ],
    "wof:name":"Avernak By",
    "wof:placetype":"locality"
},
  "geometry": {"coordinates":[10.25698,55.03236999999999],"type":"Point"}
}