{
  "type": "Feature",
  "properties": {
    "gn:admin1_code":"21.0",
    "gn:admin2_code":"630.0",
    "gn:asciiname":"Jennum",
    "gn:country_code":"DK",
    "gn:dem":85,
    "gn:feature_class":"P",
    "gn:feature_code":"PPL",
    "gn:name":"Jennum",
    "gn:population":0,
    "gn:timezone":"Europe/Copenhagen",
    "iso:country":"DK",
    "wof:name":"Jennum",
    "wof:placetype":"locality"
},
  "geometry": {"coordinates":[9.43302,55.72026],"type":"Point"}
}