{
  "type": "Feature",
  "properties": {
    "gn:admin1_code":"18.0",
    "gn:admin2_code":"746.0",
    "gn:asciiname":"Emborg",
    "gn:country_code":"DK",
    "gn:dem":26,
    "gn:feature_class":"P",
    "gn:feature_code":"PPL",
    "gn:name":"Emborg",
    "gn:population":0,
    "gn:timezone":"Europe/Copenhagen",
    "iso:country":"DK",
    "wof:name":"Emborg",
    "wof:placetype":"locality"
},
  "geometry": {"coordinates":[9.74951,56.0519],"type":"Point"}
}