{
  "type": "Feature",
  "properties": {
    "gn:admin1_code":"20.0",
    "gn:admin2_code":"306.0",
    "gn:asciiname":"Stenstrup",
    "gn:country_code":"DK",
    "gn:dem":15,
    "gn:feature_class":"P",
    "gn:feature_code":"PPL",
    "gn:name":"Stenstrup",
    "gn:population":0,
    "gn:timezone":"Europe/Copenhagen",
    "iso:country":"DK",
    "name:dan_x_preferred":[
        "Stenstrup"
    ],
    "name:nld_x_preferred":[
        "Stenstrup"
    ],
    "name:pol_x_preferred":[
        "Stenstrup"
    ],
    "name:spa_x_preferred":[
        "Stenstrup"
    ],
    "name:swe_x_preferred":[
        "Stenstrup"
    ],
    "wof:name":"Stenstrup",
    "wof:placetype":"locality"
},
  "geometry": {"coordinates":[11.55293,55.92694],"type":"Point"}
}