{
  "type": "Feature",
  "properties": {
    "gn:admin1_code":"21.0",
    "gn:admin2_code":"621.0",
    "gn:asciiname":"Rorkaer Huse",
    "gn:country_code":"DK",
    "gn:dem":41,
    "gn:feature_class":"P",
    "gn:feature_code":"PPLL",
    "gn:name":"R\u00f8rk\u00e6r Huse",
    "gn:population":0,
    "gn:timezone":"Europe/Copenhagen",
    "iso:country":"DK",
    "name:und_x_variant":[
        "R\u00f8rk\u00e6r",
        "R\u00f8rk\u00e6r Huse"
    ],
    "wof:name":"Rorkaer Huse",
    "wof:placetype":"locality"
},
  "geometry": {"coordinates":[9.23581,55.41476],"type":"Point"}
}