{
  "type": "Feature",
  "properties": {
    "gn:admin1_code":"21.0",
    "gn:admin2_code":"450.0",
    "gn:asciiname":"Lindeskov",
    "gn:country_code":"DK",
    "gn:dem":67,
    "gn:feature_class":"P",
    "gn:feature_code":"PPL",
    "gn:name":"Lindeskov",
    "gn:population":0,
    "gn:timezone":"Europe/Copenhagen",
    "iso:country":"DK",
    "wof:name":"Lindeskov",
    "wof:placetype":"locality"
},
  "geometry": {"coordinates":[10.64106,55.25084],"type":"Point"}
}