{
  "type": "Feature",
  "properties": {
    "gn:admin1_code":"19.0",
    "gn:admin2_code":"840.0",
    "gn:asciiname":"Hellum",
    "gn:country_code":"DK",
    "gn:dem":53,
    "gn:feature_class":"P",
    "gn:feature_code":"PPL",
    "gn:name":"Hellum",
    "gn:population":0,
    "gn:timezone":"Europe/Copenhagen",
    "iso:country":"DK",
    "name:ceb_x_preferred":[
        "Hellum"
    ],
    "name:epo_x_preferred":[
        "Hellum"
    ],
    "name:fra_x_preferred":[
        "Hellum"
    ],
    "name:nld_x_preferred":[
        "Hellum"
    ],
    "name:pol_x_preferred":[
        "Hellum"
    ],
    "wof:name":"Hellum",
    "wof:placetype":"locality"
},
  "geometry": {"coordinates":[9.95648,56.81961999999999],"type":"Point"}
}