{
  "type": "Feature",
  "properties": {
    "gn:admin1_code":"20.0",
    "gn:admin2_code":"350.0",
    "gn:asciiname":"Ordrup",
    "gn:country_code":"DK",
    "gn:dem":40,
    "gn:feature_class":"P",
    "gn:feature_code":"PPL",
    "gn:name":"Ordrup",
    "gn:population":0,
    "gn:timezone":"Europe/Copenhagen",
    "iso:country":"DK",
    "name:dan_x_preferred":[
        "Ordrup"
    ],
    "name:fra_x_preferred":[
        "Ordrup"
    ],
    "name:nor_x_preferred":[
        "Ordrup"
    ],
    "name:swe_x_preferred":[
        "Ordrup"
    ],
    "wof:name":"Ordrup",
    "wof:placetype":"locality"
},
  "geometry": {"coordinates":[11.80512,55.64693000000001],"type":"Point"}
}