{
  "type": "Feature",
  "properties": {
    "gn:country":"DK",
    "gn:fcode":"PPL",
    "gn:population":0,
    "iso:country":"DK",
    "name:dan_x_preferred":[
        "Astrup"
    ],
    "name:deu_x_preferred":[
        "Astrup"
    ],
    "name:fra_x_preferred":[
        "Astrup"
    ],
    "name:nld_x_preferred":[
        "Astrup"
    ],
    "name:nno_x_preferred":[
        "Astrup"
    ],
    "name:nor_x_preferred":[
        "Astrup"
    ],
    "name:rus_x_preferred":[
        "\u0410\u0441\u0442\u0440\u0443\u043f"
    ],
    "qs_pg:aaroncc":"DK",
    "qs_pg:gn_country":"DK",
    "qs_pg:gn_fcode":"PPL",
    "qs_pg:gn_pop":0,
    "qs_pg:name":"Astrup",
    "qs_pg:name_adm0":"Danmark",
    "qs_pg:name_adm1":"Syddanmark",
    "qs_pg:photos":25,
    "qs_pg:photos_1k":5,
    "qs_pg:photos_9k":1,
    "qs_pg:photos_9r":1,
    "qs_pg:photos_all":25,
    "qs_pg:photos_sr":1,
    "qs_pg:pop_sr":0,
    "qs_pg:qs_pg_placetype":"locality",
    "qs_pg:qs_pg_placetype_gp":"Town",
    "qs_pg:woe_adm0":23424796,
    "woe:adm0_id":23424796,
    "woe:name_adm0":"Danmark",
    "woe:name_adm1":"Syddanmark",
    "woe:placetype":"Town",
    "wof:name":"Astrup",
    "wof:placetype":"locality"
},
  "geometry": {"coordinates":[8.71674,55.17452],"type":"Point"}
}