{
  "type": "Feature",
  "properties": {
    "gn:admin1_code":"21.0",
    "gn:admin2_code":"430.0",
    "gn:asciiname":"Fleninge",
    "gn:country_code":"DK",
    "gn:dem":43,
    "gn:feature_class":"P",
    "gn:feature_code":"PPL",
    "gn:name":"Fleninge",
    "gn:population":0,
    "gn:timezone":"Europe/Copenhagen",
    "iso:country":"DK",
    "wof:name":"Fleninge",
    "wof:placetype":"locality"
},
  "geometry": {"coordinates":[10.329,55.14827],"type":"Point"}
}