{
  "type": "Feature",
  "properties": {
    "gn:admin1_code":"20.0",
    "gn:admin2_code":"259.0",
    "gn:asciiname":"Ashoje",
    "gn:country_code":"DK",
    "gn:dem":21,
    "gn:feature_class":"P",
    "gn:feature_code":"PPL",
    "gn:name":"\u00c5sh\u00f8je",
    "gn:population":0,
    "gn:timezone":"Europe/Copenhagen",
    "iso:country":"DK",
    "name:und_x_variant":[
        "Aash\u00f6j",
        "Aash\u00f6je",
        "\u00c5sh\u00f8je"
    ],
    "wof:name":"Ashoje",
    "wof:placetype":"locality"
},
  "geometry": {"coordinates":[12.13152,55.4434],"type":"Point"}
}