{
  "type": "Feature",
  "properties": {
    "gn:admin1_code":"18.0",
    "gn:admin2_code":"730.0",
    "gn:asciiname":"Stovby",
    "gn:country_code":"DK",
    "gn:dem":30,
    "gn:feature_class":"P",
    "gn:feature_code":"PPL",
    "gn:name":"Stovby",
    "gn:population":0,
    "gn:timezone":"Europe/Copenhagen",
    "iso:country":"DK",
    "wof:name":"Stovby",
    "wof:placetype":"locality"
},
  "geometry": {"coordinates":[10.1298,56.57074],"type":"Point"}
}