{
  "type": "Feature",
  "properties": {
    "gn:admin1_code":"19.0",
    "gn:admin2_code":"820.0",
    "gn:asciiname":"Borregard",
    "gn:country_code":"DK",
    "gn:dem":11,
    "gn:feature_class":"P",
    "gn:feature_code":"PPL",
    "gn:name":"Borreg\u00e5rd",
    "gn:population":0,
    "gn:timezone":"Europe/Copenhagen",
    "iso:country":"DK",
    "name:und_x_variant":[
        "Borregaard",
        "Borreg\u00e5rd"
    ],
    "wof:name":"Borregard",
    "wof:placetype":"locality"
},
  "geometry": {"coordinates":[9.23886,56.84902],"type":"Point"}
}