{
  "type": "Feature",
  "properties": {
    "gn:admin1_code":"18.0",
    "gn:admin2_code":"661.0",
    "gn:asciiname":"Hvam",
    "gn:country_code":"DK",
    "gn:dem":39,
    "gn:feature_class":"P",
    "gn:feature_code":"PPLL",
    "gn:name":"Hvam",
    "gn:population":0,
    "gn:timezone":"Europe/Copenhagen",
    "iso:country":"DK",
    "name:deu_x_preferred":[
        "Hvam"
    ],
    "name:nor_x_preferred":[
        "Hvam"
    ],
    "wof:name":"Hvam",
    "wof:placetype":"locality"
},
  "geometry": {"coordinates":[8.69839,56.41702],"type":"Point"}
}