{
  "type": "Feature",
  "properties": {
    "gn:gn_country":"DK",
    "gn:gn_fcode":"PPL",
    "gn:gn_pop":0,
    "iso:country":"DK",
    "name:dan_x_preferred":[
        "Ballebro"
    ],
    "name:deu_x_preferred":[
        "Ballebro"
    ],
    "name:eng_x_preferred":[
        "Ballebro"
    ],
    "name:fra_x_preferred":[
        "Ballebro"
    ],
    "name:nld_x_preferred":[
        "Ballebro"
    ],
    "qs_pg:aaroncc":"DK",
    "qs_pg:gn_country":"DK",
    "qs_pg:gn_fcode":"PPL",
    "qs_pg:gn_pop":0,
    "qs_pg:name":"Ballebro",
    "qs_pg:name_adm0":"Danmark",
    "qs_pg:name_adm1":"Syddanmark",
    "qs_pg:photos":74,
    "qs_pg:photos_1k":15,
    "qs_pg:photos_9k":1,
    "qs_pg:photos_9r":2,
    "qs_pg:photos_all":74,
    "qs_pg:photos_sr":2,
    "qs_pg:pop_sr":0,
    "qs_pg:qs_pg_placetype":"locality",
    "qs_pg:qs_pg_placetype_gp":"Town",
    "qs_pg:woe_adm0":23424796,
    "woe:adm0_id":23424796,
    "woe:name_adm0":"Danmark",
    "woe:name_adm1":"Syddanmark",
    "woe:placetype":"Town",
    "wof:name":"Ballebro",
    "wof:placetype":"locality"
},
  "geometry": {"coordinates":[9.66844,54.99868],"type":"Point"}
}