{
  "type": "Feature",
  "properties": {
    "gn:admin1_code":"21.0",
    "gn:admin2_code":"630.0",
    "gn:asciiname":"Slelde",
    "gn:country_code":"DK",
    "gn:dem":26,
    "gn:feature_class":"P",
    "gn:feature_code":"PPL",
    "gn:name":"Slelde",
    "gn:population":0,
    "gn:timezone":"Europe/Copenhagen",
    "iso:country":"DK",
    "wof:name":"Slelde",
    "wof:placetype":"locality"
},
  "geometry": {"coordinates":[9.45081,55.71336],"type":"Point"}
}