{
  "type": "Feature",
  "properties": {
    "gn:admin1_code":"19.0",
    "gn:admin2_code":"860.0",
    "gn:asciiname":"Borrisholt",
    "gn:country_code":"DK",
    "gn:dem":63,
    "gn:feature_class":"P",
    "gn:feature_code":"PPLL",
    "gn:name":"Borrisholt",
    "gn:population":0,
    "gn:timezone":"Europe/Copenhagen",
    "iso:country":"DK",
    "name:und_x_variant":[
        "Borresholt",
        "Borrisholt"
    ],
    "wof:name":"Borrisholt",
    "wof:placetype":"locality"
},
  "geometry": {"coordinates":[10.123,57.49545],"type":"Point"}
}