{
  "type": "Feature",
  "properties": {
    "gn:gn_country":"DK",
    "iso:country":"DK",
    "qs_pg:aaroncc":"DK",
    "qs_pg:gn_country":"DK",
    "qs_pg:name":"Vesterby",
    "qs_pg:name_adm0":"Danmark",
    "qs_pg:name_adm1":"Nordjylland",
    "qs_pg:photos":35,
    "qs_pg:photos_1k":7,
    "qs_pg:photos_9k":1,
    "qs_pg:photos_9r":2,
    "qs_pg:photos_all":35,
    "qs_pg:photos_sr":2,
    "qs_pg:pop_sr":0,
    "qs_pg:qs_pg_placetype":"locality",
    "qs_pg:qs_pg_placetype_gp":"Town",
    "qs_pg:woe_adm0":23424796,
    "woe:adm0_id":23424796,
    "woe:name_adm0":"Danmark",
    "woe:name_adm1":"Nordjylland",
    "woe:placetype":"Town",
    "wof:name":"Vesterby",
    "wof:placetype":"locality"
},
  "geometry": {"coordinates":[10.58361,57.716234],"type":"Point"}
}