{
  "type": "Feature",
  "properties": {
    "gn:admin1_code":"21.0",
    "gn:admin2_code":"480.0",
    "gn:asciiname":"Emmelev",
    "gn:country_code":"DK",
    "gn:dem":20,
    "gn:feature_class":"P",
    "gn:feature_code":"PPL",
    "gn:name":"Emmelev",
    "gn:population":0,
    "gn:timezone":"Europe/Copenhagen",
    "iso:country":"DK",
    "wof:name":"Emmelev",
    "wof:placetype":"locality"
},
  "geometry": {"coordinates":[10.36533,55.53447],"type":"Point"}
}