{
  "type": "Feature",
  "properties": {
    "gn:admin1_code":"18.0",
    "gn:admin2_code":"615.0",
    "gn:asciiname":"Slagballe",
    "gn:country_code":"DK",
    "gn:dem":125,
    "gn:feature_class":"P",
    "gn:feature_code":"PPL",
    "gn:name":"Slagballe",
    "gn:population":0,
    "gn:timezone":"Europe/Copenhagen",
    "iso:country":"DK",
    "wof:name":"Slagballe",
    "wof:placetype":"locality"
},
  "geometry": {"coordinates":[9.57126,56.00201],"type":"Point"}
}