{
  "type": "Feature",
  "properties": {
    "gn:admin1_code":"20.0",
    "gn:admin2_code":"316.0",
    "gn:asciiname":"Brokob",
    "gn:country_code":"DK",
    "gn:dem":42,
    "gn:feature_class":"P",
    "gn:feature_code":"PPL",
    "gn:name":"Brok\u00f8b",
    "gn:population":0,
    "gn:timezone":"Europe/Copenhagen",
    "iso:country":"DK",
    "wof:name":"Brokob",
    "wof:placetype":"locality"
},
  "geometry": {"coordinates":[11.43229,55.60014],"type":"Point"}
}