{
  "type": "Feature",
  "properties": {
    "gn:admin1_code":"18.0",
    "gn:admin2_code":"766.0",
    "gn:asciiname":"Hedensted",
    "gn:country_code":"DK",
    "gn:dem":65,
    "gn:feature_class":"P",
    "gn:feature_code":"PPLA2",
    "gn:name":"Hedensted",
    "gn:population":10048,
    "gn:timezone":"Europe/Copenhagen",
    "iso:country":"DK",
    "wof:name":"Hedensted",
    "wof:placetype":"locality",
    "wof:population":10048
},
  "geometry": {"coordinates":[9.7011,55.77043000000001],"type":"Point"}
}