{
  "type": "Feature",
  "properties": {
    "gn:admin1_code":"18.0",
    "gn:admin2_code":"766.0",
    "gn:asciiname":"Hedensted",
    "gn:country_code":"DK",
    "gn:dem":65,
    "gn:feature_class":"P",
    "gn:feature_code":"PPLA2",
    "gn:name":"Hedensted",
    "gn:population":10048,
    "gn:timezone":"Europe/Copenhagen",
    "iso:country":"DK",
    "name:ast_x_preferred":[
        "Hedensted"
    ],
    "name:cat_x_preferred":[
        "Hedensted"
    ],
    "name:ceb_x_preferred":[
        "Hedensted"
    ],
    "name:dan_x_preferred":[
        "Hedensted"
    ],
    "name:hun_x_preferred":[
        "Hedensted"
    ],
    "name:nld_x_preferred":[
        "Hedensted"
    ],
    "name:nor_x_preferred":[
        "Hedensted"
    ],
    "name:pol_x_preferred":[
        "Hedensted"
    ],
    "name:ron_x_preferred":[
        "Hedensted"
    ],
    "name:spa_x_preferred":[
        "Hedensted"
    ],
    "name:srp_x_preferred":[
        "\u0425\u0435\u0434\u0435\u043d\u0441\u0442\u0435\u0434"
    ],
    "name:swe_x_preferred":[
        "Hedensted"
    ],
    "wof:name":"Hedensted",
    "wof:placetype":"locality",
    "wof:population":10048
},
  "geometry": {"coordinates":[9.7011,55.77043000000001],"type":"Point"}
}