{
  "type": "Feature",
  "properties": {
    "gn:admin1_code":"20.0",
    "gn:admin2_code":"340.0",
    "gn:asciiname":"Pedersborg",
    "gn:country_code":"DK",
    "gn:dem":37,
    "gn:feature_class":"P",
    "gn:feature_code":"PPL",
    "gn:name":"Pedersborg",
    "gn:population":0,
    "gn:timezone":"Europe/Copenhagen",
    "iso:country":"DK",
    "wof:name":"Pedersborg",
    "wof:placetype":"locality"
},
  "geometry": {"coordinates":[11.56249,55.45341],"type":"Point"}
}