{
  "type": "Feature",
  "properties": {
    "gn:admin1_code":"21.0",
    "gn:admin2_code":"480.0",
    "gn:asciiname":"Kolshave",
    "gn:country_code":"DK",
    "gn:dem":27,
    "gn:feature_class":"P",
    "gn:feature_code":"PPL",
    "gn:name":"Kolshave",
    "gn:population":0,
    "gn:timezone":"Europe/Copenhagen",
    "iso:country":"DK",
    "name:und_x_variant":[
        "Kaalshave",
        "Kolshave"
    ],
    "wof:name":"Kolshave",
    "wof:placetype":"locality"
},
  "geometry": {"coordinates":[10.14238,55.52883000000001],"type":"Point"}
}