{
  "type": "Feature",
  "properties": {
    "gn:admin1_code":"19.0",
    "gn:admin2_code":"820.0",
    "gn:asciiname":"Flejsborg",
    "gn:country_code":"DK",
    "gn:dem":38,
    "gn:feature_class":"P",
    "gn:feature_code":"PPL",
    "gn:name":"Flejsborg",
    "gn:population":0,
    "gn:timezone":"Europe/Copenhagen",
    "iso:country":"DK",
    "wof:name":"Flejsborg",
    "wof:placetype":"locality"
},
  "geometry": {"coordinates":[9.33918,56.8618],"type":"Point"}
}