{
  "type": "Feature",
  "properties": {
    "gn:admin1_code":"18.0",
    "gn:admin2_code":"760.0",
    "gn:asciiname":"Kyvling",
    "gn:country_code":"DK",
    "gn:dem":10,
    "gn:feature_class":"P",
    "gn:feature_code":"PPL",
    "gn:name":"Kyvling",
    "gn:population":0,
    "gn:timezone":"Europe/Copenhagen",
    "iso:country":"DK",
    "name:und_x_variant":[
        "Kjufling",
        "Kyvlinge",
        "Kyvling"
    ],
    "wof:name":"Kyvling",
    "wof:placetype":"locality"
},
  "geometry": {"coordinates":[8.48992,55.89469],"type":"Point"}
}