{
  "type": "Feature",
  "properties": {
    "gn:admin1_code":"20.0",
    "gn:admin2_code":"390.0",
    "gn:asciiname":"Hjelm Kobbel",
    "gn:country_code":"DK",
    "gn:dem":8,
    "gn:feature_class":"P",
    "gn:feature_code":"PPLL",
    "gn:name":"Hjelm Kobbel",
    "gn:population":0,
    "gn:timezone":"Europe/Copenhagen",
    "iso:country":"DK",
    "name:und_x_variant":[
        "Hj\u00e6lmkobbel",
        "Hjelm Kobbel"
    ],
    "wof:name":"Hjelm Kobbel",
    "wof:placetype":"locality"
},
  "geometry": {"coordinates":[12.24294,54.91328000000001],"type":"Point"}
}