{
  "type": "Feature",
  "properties": {
    "gn:admin1_code":"21.0",
    "gn:admin2_code":"580.0",
    "gn:asciiname":"Rise Hjarup",
    "gn:country_code":"DK",
    "gn:dem":47,
    "gn:feature_class":"P",
    "gn:feature_code":"PPL",
    "gn:name":"Rise Hjarup",
    "gn:population":0,
    "gn:timezone":"Europe/Copenhagen",
    "iso:country":"DK",
    "wof:name":"Rise Hjarup",
    "wof:placetype":"locality"
},
  "geometry": {"coordinates":[9.38624,55.08066],"type":"Point"}
}