{
  "type": "Feature",
  "properties": {
    "gn:admin1_code":"18.0",
    "gn:admin2_code":"615.0",
    "gn:asciiname":"Molger",
    "gn:country_code":"DK",
    "gn:dem":71,
    "gn:feature_class":"P",
    "gn:feature_code":"PPL",
    "gn:name":"Molger",
    "gn:population":0,
    "gn:timezone":"Europe/Copenhagen",
    "iso:country":"DK",
    "name:und_x_variant":[
        "Molg\u00e6r",
        "Molger"
    ],
    "wof:name":"Molger",
    "wof:placetype":"locality"
},
  "geometry": {"coordinates":[9.69775,55.89166],"type":"Point"}
}