{
  "type": "Feature",
  "properties": {
    "gn:admin1_code":"19.0",
    "gn:admin2_code":"820.0",
    "gn:asciiname":"Sonderlade",
    "gn:country_code":"DK",
    "gn:dem":5,
    "gn:feature_class":"P",
    "gn:feature_code":"PPLL",
    "gn:name":"S\u00f8nderlade",
    "gn:population":0,
    "gn:timezone":"Europe/Copenhagen",
    "iso:country":"DK",
    "wof:name":"Sonderlade",
    "wof:placetype":"locality"
},
  "geometry": {"coordinates":[9.25001,56.8378],"type":"Point"}
}