{
  "type": "Feature",
  "properties": {
    "gn:country":"DK",
    "gn:fcode":"PPLA2",
    "gn:population":9326,
    "iso:country":"DK",
    "name:afr_x_preferred":[
        "Nyk\u00f8bing Mors"
    ],
    "name:ast_x_preferred":[
        "Nyk\u00f8bing Mors"
    ],
    "name:aze_x_preferred":[
        "Nyukyobinq-Mors"
    ],
    "name:cat_x_preferred":[
        "Nyk\u00f8bing Mors"
    ],
    "name:ceb_x_preferred":[
        "Nyk\u00f8bing Mors"
    ],
    "name:ces_x_preferred":[
        "Nyk\u00f8bing Mors"
    ],
    "name:dan_x_preferred":[
        "Nyk\u00f8bing Mors"
    ],
    "name:deu_x_preferred":[
        "Nyk\u00f8bing Mors"
    ],
    "name:eng_x_preferred":[
        "Nyk\u00f8bing Mors"
    ],
    "name:fao_x_preferred":[
        "Nyk\u00f8bing Mors"
    ],
    "name:fra_x_preferred":[
        "Nyk\u00f8bing Mors"
    ],
    "name:gle_x_preferred":[
        "Nyk\u00f8bing Mors"
    ],
    "name:isl_x_preferred":[
        "Nyk\u00f8bing Mors"
    ],
    "name:ita_x_preferred":[
        "Nyk\u00f8bing Mors"
    ],
    "name:jpn_x_preferred":[
        "\u30cb\u30e5\u30fc\u30af\u30d3\u30f3\u30fb\u30e2\u30fc\u30b9"
    ],
    "name:jpn_x_variant":[
        "\u30cb\u30e5\u30af\u30fc\u30d3\u30f3\u30fb\u30e2\u30fc\u30b9"
    ],
    "name:msa_x_preferred":[
        "Nyk\u00f8bing Mors"
    ],
    "name:nld_x_preferred":[
        "Nyk\u00f8bing Mors"
    ],
    "name:nno_x_preferred":[
        "Nyk\u00f8bing Mors"
    ],
    "name:nob_x_preferred":[
        "Nyk\u00f8bing Mors"
    ],
    "name:oss_x_preferred":[
        "\u041d\u044e\u043a\u0451\u0431\u0438\u043d\u0433-\u041c\u043e\u0440\u0441"
    ],
    "name:ron_x_preferred":[
        "Nyk\u00f8bing Mors"
    ],
    "name:rus_x_preferred":[
        "\u041d\u044e\u043a\u0451\u0431\u0438\u043d\u0433-\u041c\u043e\u0440\u0441"
    ],
    "name:spa_x_preferred":[
        "Nyk\u00f8bing Mors"
    ],
    "name:swe_x_preferred":[
        "Nyk\u00f8bing Mors"
    ],
    "name:szl_x_preferred":[
        "Nyk\u00f8bing Mors"
    ],
    "name:und_x_variant":[
        "Nykj\u00f6bing"
    ],
    "name:urd_x_preferred":[
        "\u0646\u0627\u0626\u06a9\u0648\u0628\u0646\u06af \u0645\u0648\u0631\u0633"
    ],
    "name:zho_x_preferred":[
        "\u5c3c\u514b\u8cd3\u6469\u65af"
    ],
    "qs_pg:aaroncc":"DK",
    "qs_pg:gn_country":"DK",
    "qs_pg:gn_fcode":"PPLA2",
    "qs_pg:gn_pop":9326,
    "qs_pg:name":"Nyk\u00f8bing Mors",
    "qs_pg:photos_9r":0,
    "qs_pg:photos_sr":0,
    "qs_pg:pop_sr":5,
    "qs_pg:qs_pg_placetype":"locality",
    "wof:name":"Nyk\u00f8bing Mors",
    "wof:placetype":"locality",
    "wof:population":9326
},
  "geometry": {"coordinates":[8.85282,56.79334],"type":"Point"}
}