{
  "type": "Feature",
  "properties": {
    "gn:gn_country":"DK",
    "gn:gn_fcode":"PPLA2",
    "gn:gn_pop":9326,
    "gn:population":9326,
    "iso:country":"DK",
    "name:afr_x_preferred":[
        "Nyk\u00f8bing Mors"
    ],
    "name:cat_x_preferred":[
        "Nyk\u00f8bing Mors"
    ],
    "name:chi_x_preferred":[
        "\u5c3c\u514b\u8cd3\u6469\u65af"
    ],
    "name:cze_x_preferred":[
        "Nyk\u00f8bing Mors"
    ],
    "name:dan_x_preferred":[
        "Nyk\u00f8bing Mors"
    ],
    "name:dut_x_preferred":[
        "Nyk\u00f8bing Mors"
    ],
    "name:eng_x_preferred":[
        "Nyk\u00f8bing Mors"
    ],
    "name:fao_x_preferred":[
        "Nyk\u00f8bing Mors"
    ],
    "name:fre_x_preferred":[
        "Nyk\u00f8bing Mors"
    ],
    "name:ger_x_preferred":[
        "Nyk\u00f8bing Mors"
    ],
    "name:ice_x_preferred":[
        "Nyk\u00f8bing Mors"
    ],
    "name:jpn_x_preferred":[
        "\u30cb\u30e5\u30fc\u30af\u30d3\u30f3\u30fb\u30e2\u30fc\u30b9"
    ],
    "name:may_x_preferred":[
        "Nyk\u00f8bing Mors"
    ],
    "name:nno_x_preferred":[
        "Nyk\u00f8bing Mors"
    ],
    "name:nob_x_preferred":[
        "Nyk\u00f8bing Mors"
    ],
    "name:rum_x_preferred":[
        "Nyk\u00f8bing Mors"
    ],
    "name:spa_x_preferred":[
        "Nyk\u00f8bing Mors"
    ],
    "name:swe_x_preferred":[
        "Nyk\u00f8bing Mors"
    ],
    "name:szl_x_preferred":[
        "Nyk\u00f8bing Mors"
    ],
    "name:unk_x_variant":[
        "Nykj\u00f6bing"
    ],
    "qs_pg:aaroncc":"DK",
    "qs_pg:gn_country":"DK",
    "qs_pg:gn_fcode":"PPLA2",
    "qs_pg:gn_pop":9326,
    "qs_pg:name":"Nyk\u00f8bing Mors",
    "qs_pg:photos_9r":0,
    "qs_pg:photos_sr":0,
    "qs_pg:pop_sr":5,
    "qs_pg:qs_pg_placetype":"locality",
    "wof:name":"Nyk\u00f8bing Mors",
    "wof:placetype":"locality",
    "wof:population":9326
},
  "geometry": {"coordinates":[8.85282,56.79334],"type":"Point"}
}