{
  "type": "Feature",
  "properties": {
    "gn:admin1_code":"19.0",
    "gn:admin2_code":"849.0",
    "gn:asciiname":"Skovsgard",
    "gn:country_code":"DK",
    "gn:dem":8,
    "gn:feature_class":"P",
    "gn:feature_code":"PPL",
    "gn:name":"Skovsg\u00e5rd",
    "gn:population":0,
    "gn:timezone":"Europe/Copenhagen",
    "iso:country":"DK",
    "name:und_x_variant":[
        "Skovsgaard",
        "Skovsg\u00e5rd"
    ],
    "wof:name":"Skovsgard",
    "wof:placetype":"locality"
},
  "geometry": {"coordinates":[9.48528,57.0874],"type":"Point"}
}