{
  "type": "Feature",
  "properties": {
    "gn:admin1_code":"20.0",
    "gn:admin2_code":"269.0",
    "gn:asciiname":"Kirke-Skensved",
    "gn:country_code":"DK",
    "gn:dem":20,
    "gn:feature_class":"P",
    "gn:feature_code":"PPL",
    "gn:name":"Kirke-Skensved",
    "gn:population":0,
    "gn:timezone":"Europe/Copenhagen",
    "iso:country":"DK",
    "wof:name":"Kirke-Skensved",
    "wof:placetype":"locality"
},
  "geometry": {"coordinates":[12.11828,55.52456],"type":"Point"}
}