{
  "type": "Feature",
  "properties": {
    "gn:admin1_code":"19.0",
    "gn:admin2_code":"851.0",
    "gn:asciiname":"Klattrup",
    "gn:country_code":"DK",
    "gn:dem":8,
    "gn:feature_class":"P",
    "gn:feature_code":"PPLL",
    "gn:name":"Klattrup",
    "gn:population":0,
    "gn:timezone":"Europe/Copenhagen",
    "iso:country":"DK",
    "name:und_x_variant":[
        "Klattrup Huse",
        "Klattrup"
    ],
    "wof:name":"Klattrup",
    "wof:placetype":"locality"
},
  "geometry": {"coordinates":[10.26321,56.93793],"type":"Point"}
}