{
  "type": "Feature",
  "properties": {
    "gn:admin1_code":"20.0",
    "gn:admin2_code":"316.0",
    "gn:asciiname":"Sasserup",
    "gn:country_code":"DK",
    "gn:dem":18,
    "gn:feature_class":"P",
    "gn:feature_code":"PPL",
    "gn:name":"Sasserup",
    "gn:population":0,
    "gn:timezone":"Europe/Copenhagen",
    "iso:country":"DK",
    "wof:name":"Sasserup",
    "wof:placetype":"locality"
},
  "geometry": {"coordinates":[11.66523,55.68089000000001],"type":"Point"}
}