{
  "type": "Feature",
  "properties": {
    "gn:admin1_code":"18.0",
    "gn:admin2_code":"615.0",
    "gn:asciiname":"Vestbirk",
    "gn:country_code":"DK",
    "gn:dem":59,
    "gn:feature_class":"P",
    "gn:feature_code":"PPL",
    "gn:name":"Vestbirk",
    "gn:population":0,
    "gn:timezone":"Europe/Copenhagen",
    "iso:country":"DK",
    "wof:name":"Vestbirk",
    "wof:placetype":"locality"
},
  "geometry": {"coordinates":[9.71843,55.96556999999999],"type":"Point"}
}