{
  "type": "Feature",
  "properties": {
    "gn:admin1_code":"20.0",
    "gn:admin2_code":"350.0",
    "gn:asciiname":"Vintre Moller",
    "gn:country_code":"DK",
    "gn:dem":24,
    "gn:feature_class":"P",
    "gn:feature_code":"PPL",
    "gn:name":"Vintre M\u00f8ller",
    "gn:population":0,
    "gn:timezone":"Europe/Copenhagen",
    "iso:country":"DK",
    "wof:name":"Vintre Moller",
    "wof:placetype":"locality"
},
  "geometry": {"coordinates":[11.80999,55.65039],"type":"Point"}
}