{
  "type": "Feature",
  "properties": {
    "gn:admin1_code":"20.0",
    "gn:admin2_code":"370.0",
    "gn:asciiname":"Guderup",
    "gn:country_code":"DK",
    "gn:dem":29,
    "gn:feature_class":"P",
    "gn:feature_code":"PPL",
    "gn:name":"Guderup",
    "gn:population":0,
    "gn:timezone":"Europe/Copenhagen",
    "iso:country":"DK",
    "name:ceb_x_preferred":[
        "Guderup"
    ],
    "name:dan_x_preferred":[
        "Guderup"
    ],
    "name:deu_x_preferred":[
        "Guderup"
    ],
    "name:nld_x_preferred":[
        "Guderup"
    ],
    "name:nor_x_preferred":[
        "Guderup"
    ],
    "name:spa_x_preferred":[
        "Guderup"
    ],
    "name:swe_x_preferred":[
        "Guderup"
    ],
    "wof:name":"Guderup",
    "wof:placetype":"locality"
},
  "geometry": {"coordinates":[11.68826,55.26496],"type":"Point"}
}