{
  "type": "Feature",
  "properties": {
    "gn:admin1_code":"21.0",
    "gn:admin2_code":"573.0",
    "gn:asciiname":"Kvong",
    "gn:country_code":"DK",
    "gn:dem":31,
    "gn:feature_class":"P",
    "gn:feature_code":"PPL",
    "gn:name":"Kvong",
    "gn:population":0,
    "gn:timezone":"Europe/Copenhagen",
    "iso:country":"DK",
    "name:dan_x_preferred":[
        "Kvong"
    ],
    "name:nld_x_preferred":[
        "Kvong"
    ],
    "wof:name":"Kvong",
    "wof:placetype":"locality"
},
  "geometry": {"coordinates":[8.44055,55.75751],"type":"Point"}
}