{
  "type": "Feature",
  "properties": {
    "gn:admin1_code":"20.0",
    "gn:admin2_code":"326.0",
    "gn:asciiname":"Brokkebjerg",
    "gn:country_code":"DK",
    "gn:dem":12,
    "gn:feature_class":"P",
    "gn:feature_code":"PPL",
    "gn:name":"Brokkebjerg",
    "gn:population":0,
    "gn:timezone":"Europe/Copenhagen",
    "iso:country":"DK",
    "wof:name":"Brokkebjerg",
    "wof:placetype":"locality"
},
  "geometry": {"coordinates":[11.10697,55.7162],"type":"Point"}
}