{
  "type": "Feature",
  "properties": {
    "gn:gn_country":"DK",
    "gn:gn_fcode":"PPL",
    "gn:gn_pop":0,
    "iso:country":"DK",
    "name:bre_x_preferred":[
        "Trans"
    ],
    "name:ces_x_preferred":[
        "Trans"
    ],
    "name:dan_x_preferred":[
        "Trans"
    ],
    "name:deu_x_preferred":[
        "Trans"
    ],
    "name:fra_x_preferred":[
        "Trans"
    ],
    "name:isl_x_preferred":[
        "Trans"
    ],
    "name:ita_x_preferred":[
        "Trans"
    ],
    "name:jpn_x_preferred":[
        "\u30c8\u30e9\u30f3\u30b9"
    ],
    "name:kor_x_preferred":[
        "\ud2b8\ub79c\uc2a4"
    ],
    "name:lit_x_preferred":[
        "Trans"
    ],
    "name:nld_x_preferred":[
        "Trans"
    ],
    "name:nor_x_preferred":[
        "Trans"
    ],
    "name:oci_x_preferred":[
        "Trans"
    ],
    "name:pms_x_preferred":[
        "Trans"
    ],
    "name:pol_x_preferred":[
        "Trans"
    ],
    "name:por_x_preferred":[
        "Trans"
    ],
    "name:ron_x_preferred":[
        "Trans"
    ],
    "name:spa_x_preferred":[
        "Trans"
    ],
    "name:swe_x_preferred":[
        "Trans"
    ],
    "name:tur_x_preferred":[
        "Trans"
    ],
    "name:unk_x_variant":[
        "Kirkeby"
    ],
    "name:vie_x_preferred":[
        "Trans"
    ],
    "name:zho_x_preferred":[
        "Trans"
    ],
    "qs_pg:aaroncc":"DK",
    "qs_pg:gn_country":"DK",
    "qs_pg:gn_fcode":"PPL",
    "qs_pg:gn_pop":0,
    "qs_pg:name":"Trans",
    "qs_pg:name_adm0":"Danmark",
    "qs_pg:name_adm1":"Midtjylland",
    "qs_pg:photos":111,
    "qs_pg:photos_1k":22,
    "qs_pg:photos_9k":1,
    "qs_pg:photos_9r":3,
    "qs_pg:photos_all":111,
    "qs_pg:photos_sr":3,
    "qs_pg:pop_sr":0,
    "qs_pg:qs_pg_placetype":"locality",
    "qs_pg:qs_pg_placetype_gp":"Town",
    "qs_pg:woe_adm0":23424796,
    "woe:adm0_id":23424796,
    "woe:name_adm0":"Danmark",
    "woe:name_adm1":"Midtjylland",
    "woe:placetype":"Town",
    "wof:name":"Trans",
    "wof:placetype":"locality"
},
  "geometry": {"coordinates":[8.12204,56.49988],"type":"Point"}
}