{
  "type": "Feature",
  "properties": {
    "gn:admin1_code":"18.0",
    "gn:admin2_code":"740.0",
    "gn:asciiname":"Vandet",
    "gn:country_code":"DK",
    "gn:dem":50,
    "gn:feature_class":"P",
    "gn:feature_code":"PPL",
    "gn:name":"Vandet",
    "gn:population":0,
    "gn:timezone":"Europe/Copenhagen",
    "iso:country":"DK",
    "wof:name":"Vandet",
    "wof:placetype":"locality"
},
  "geometry": {"coordinates":[9.44235,56.35058000000001],"type":"Point"}
}