{
  "type": "Feature",
  "properties": {
    "gn:admin1_code":"21.0",
    "gn:admin2_code":"420.0",
    "gn:asciiname":"Mellemballe",
    "gn:country_code":"DK",
    "gn:dem":59,
    "gn:feature_class":"P",
    "gn:feature_code":"PPL",
    "gn:name":"Mellemballe",
    "gn:population":0,
    "gn:timezone":"Europe/Copenhagen",
    "iso:country":"DK",
    "wof:name":"Mellemballe",
    "wof:placetype":"locality"
},
  "geometry": {"coordinates":[10.0387,55.30883000000001],"type":"Point"}
}