{
  "type": "Feature",
  "properties": {
    "gn:admin1_code":"21.0",
    "gn:admin2_code":"461.0",
    "gn:asciiname":"Lumby",
    "gn:country_code":"DK",
    "gn:dem":17,
    "gn:feature_class":"P",
    "gn:feature_code":"PPL",
    "gn:name":"Lumby",
    "gn:population":0,
    "gn:timezone":"Europe/Copenhagen",
    "iso:country":"DK",
    "name:dan_x_preferred":[
        "Lumby"
    ],
    "name:nld_x_preferred":[
        "Lumby"
    ],
    "name:spa_x_preferred":[
        "Lumby"
    ],
    "name:swe_x_preferred":[
        "Lumby"
    ],
    "wof:name":"Lumby",
    "wof:placetype":"locality"
},
  "geometry": {"coordinates":[10.3781,55.45878],"type":"Point"}
}