{
  "type": "Feature",
  "properties": {
    "gn:admin1_code":"19.0",
    "gn:admin2_code":"851.0",
    "gn:asciiname":"Erkilstrup",
    "gn:country_code":"DK",
    "gn:dem":17,
    "gn:feature_class":"P",
    "gn:feature_code":"PPL",
    "gn:name":"Erkilstrup",
    "gn:population":0,
    "gn:timezone":"Europe/Copenhagen",
    "iso:country":"DK",
    "name:und_x_variant":[
        "Erkildstrup",
        "Erkilstrup"
    ],
    "wof:name":"Erkilstrup",
    "wof:placetype":"locality"
},
  "geometry": {"coordinates":[9.43494,56.95686],"type":"Point"}
}