{
  "type": "Feature",
  "properties": {
    "gn:admin1_code":"18.0",
    "gn:admin2_code":"657.0",
    "gn:asciiname":"Orre",
    "gn:country_code":"DK",
    "gn:dem":33,
    "gn:feature_class":"P",
    "gn:feature_code":"PPL",
    "gn:name":"\u00d8rre",
    "gn:population":0,
    "gn:timezone":"Europe/Copenhagen",
    "iso:country":"DK",
    "name:ita_x_preferred":[
        "Orre"
    ],
    "wof:name":"Orre",
    "wof:placetype":"locality"
},
  "geometry": {"coordinates":[8.87204,56.23444],"type":"Point"}
}