{
  "type": "Feature",
  "properties": {
    "gn:admin1_code":"18.0",
    "gn:admin2_code":"766.0",
    "gn:asciiname":"Breth",
    "gn:country_code":"DK",
    "gn:dem":65,
    "gn:feature_class":"P",
    "gn:feature_code":"PPL",
    "gn:name":"Breth",
    "gn:population":0,
    "gn:timezone":"Europe/Copenhagen",
    "iso:country":"DK",
    "name:und_x_variant":[
        "Bret",
        "Breth"
    ],
    "wof:name":"Breth",
    "wof:placetype":"locality"
},
  "geometry": {"coordinates":[9.87475,55.72892],"type":"Point"}
}