{
  "type": "Feature",
  "properties": {
    "gn:admin1_code":"21.0",
    "gn:admin2_code":"480.0",
    "gn:asciiname":"Bladstrup",
    "gn:country_code":"DK",
    "gn:dem":21,
    "gn:feature_class":"P",
    "gn:feature_code":"PPL",
    "gn:name":"Bladstrup",
    "gn:population":0,
    "gn:timezone":"Europe/Copenhagen",
    "iso:country":"DK",
    "wof:name":"Bladstrup",
    "wof:placetype":"locality"
},
  "geometry": {"coordinates":[10.33813,55.5115],"type":"Point"}
}