{
  "type": "Feature",
  "properties": {
    "gn:admin1_code":"20.0",
    "gn:admin2_code":"376.0",
    "gn:asciiname":"Killerup",
    "gn:country_code":"DK",
    "gn:dem":5,
    "gn:feature_class":"P",
    "gn:feature_code":"PPL",
    "gn:name":"Killerup",
    "gn:population":0,
    "gn:timezone":"Europe/Copenhagen",
    "iso:country":"DK",
    "wof:name":"Killerup",
    "wof:placetype":"locality"
},
  "geometry": {"coordinates":[11.64032,54.82785],"type":"Point"}
}