{
  "type": "Feature",
  "properties": {
    "gn:admin1_code":"17.0",
    "gn:admin2_code":"217.0",
    "gn:asciiname":"Tibberup",
    "gn:country_code":"DK",
    "gn:dem":14,
    "gn:feature_class":"P",
    "gn:feature_code":"PPL",
    "gn:name":"Tibberup",
    "gn:population":0,
    "gn:timezone":"Europe/Copenhagen",
    "iso:country":"DK",
    "wof:name":"Tibberup",
    "wof:placetype":"locality"
},
  "geometry": {"coordinates":[12.55144,55.98426],"type":"Point"}
}