{
  "type": "Feature",
  "properties": {
    "gn:admin1_code":"20.0",
    "gn:admin2_code":"390.0",
    "gn:asciiname":"Tageby",
    "gn:country_code":"DK",
    "gn:dem":37,
    "gn:feature_class":"P",
    "gn:feature_code":"PPL",
    "gn:name":"T\u00e5geby",
    "gn:population":0,
    "gn:timezone":"Europe/Copenhagen",
    "iso:country":"DK",
    "name:und_x_variant":[
        "Togeby",
        "Taageby",
        "T\u00e5geby"
    ],
    "wof:name":"Tageby",
    "wof:placetype":"locality"
},
  "geometry": {"coordinates":[12.09577,55.05607],"type":"Point"}
}