{
  "type": "Feature",
  "properties": {
    "gn:admin1_code":"18.0",
    "gn:admin2_code":"657.0",
    "gn:asciiname":"Lundby",
    "gn:country_code":"DK",
    "gn:dem":47,
    "gn:feature_class":"P",
    "gn:feature_code":"PPL",
    "gn:name":"Lundby",
    "gn:population":0,
    "gn:timezone":"Europe/Copenhagen",
    "iso:country":"DK",
    "name:ceb_x_preferred":[
        "Lundby"
    ],
    "name:dan_x_preferred":[
        "Lundby"
    ],
    "name:deu_x_preferred":[
        "Lundby"
    ],
    "name:nld_x_preferred":[
        "Lundby"
    ],
    "name:swe_x_preferred":[
        "Lundby"
    ],
    "wof:name":"Lundby",
    "wof:placetype":"locality"
},
  "geometry": {"coordinates":[8.76667,56.28333000000001],"type":"Point"}
}