{
  "type": "Feature",
  "properties": {
    "gn:admin1_code":"20.0",
    "gn:admin2_code":"329.0",
    "gn:asciiname":"Orslevvester",
    "gn:country_code":"DK",
    "gn:dem":39,
    "gn:feature_class":"P",
    "gn:feature_code":"PPL",
    "gn:name":"\u00d8rslevvester",
    "gn:population":0,
    "gn:timezone":"Europe/Copenhagen",
    "iso:country":"DK",
    "wof:name":"Orslevvester",
    "wof:placetype":"locality"
},
  "geometry": {"coordinates":[11.7012,55.46824],"type":"Point"}
}