{
  "type": "Feature",
  "properties": {
    "gn:admin1_code":"21.0",
    "gn:admin2_code":"607.0",
    "gn:asciiname":"Sanddal",
    "gn:country_code":"DK",
    "gn:dem":16,
    "gn:feature_class":"P",
    "gn:feature_code":"PPL",
    "gn:name":"Sanddal",
    "gn:population":0,
    "gn:timezone":"Europe/Copenhagen",
    "iso:country":"DK",
    "name:und_x_variant":[
        "Sandal",
        "Sanddal"
    ],
    "wof:name":"Sanddal",
    "wof:placetype":"locality"
},
  "geometry": {"coordinates":[9.72579,55.54756],"type":"Point"}
}