{
  "type": "Feature",
  "properties": {
    "gn:admin1_code":"18.0",
    "gn:admin2_code":"791.0",
    "gn:asciiname":"Vinkel",
    "gn:country_code":"DK",
    "gn:dem":46,
    "gn:feature_class":"P",
    "gn:feature_code":"PPL",
    "gn:name":"Vinkel",
    "gn:population":0,
    "gn:timezone":"Europe/Copenhagen",
    "iso:country":"DK",
    "wof:name":"Vinkel",
    "wof:placetype":"locality"
},
  "geometry": {"coordinates":[9.50081,56.41656999999999],"type":"Point"}
}