{
  "type": "Feature",
  "properties": {
    "iso:country":"DK",
    "name:dan_x_preferred":[
        "Pr\u00f8vestenen"
    ],
    "name:eng_x_preferred":[
        "Pr\u00f8vestenen"
    ],
    "name:nob_x_preferred":[
        "Pr\u00f8vestenen"
    ],
    "name:nor_x_preferred":[
        "Pr\u00f8vestenen"
    ],
    "name:swe_x_preferred":[
        "Pr\u00f8vestenen"
    ],
    "wd:wordcount":50,
    "wof:name":"Pr\u00f8vestenen",
    "wof:placetype":"neighbourhood"
},
  "geometry": {"coordinates":[12.63316448334037,55.67633836471527],"type":"Point"}
}