{
  "type": "Feature",
  "properties": {
    "gn:admin1_code":"21.0",
    "gn:admin2_code":"510.0",
    "gn:asciiname":"Hoptrup",
    "gn:country_code":"DK",
    "gn:dem":5,
    "gn:feature_class":"P",
    "gn:feature_code":"PPL",
    "gn:name":"Hoptrup",
    "gn:population":0,
    "gn:timezone":"Europe/Copenhagen",
    "iso:country":"DK",
    "name:und_x_variant":[
        "Hoptrup Kirkeby",
        "Hoptrup"
    ],
    "wof:name":"Hoptrup",
    "wof:placetype":"locality"
},
  "geometry": {"coordinates":[9.45654,55.18081],"type":"Point"}
}