{
  "type": "Feature",
  "properties": {
    "gn:admin1_code":"18.0",
    "gn:admin2_code":"760.0",
    "gn:asciiname":"Adum",
    "gn:cc2":"DK",
    "gn:country_code":"DK",
    "gn:dem":30,
    "gn:feature_class":"P",
    "gn:feature_code":"PPL",
    "gn:name":"\u00c5dum",
    "gn:population":0,
    "gn:timezone":"Europe/Copenhagen",
    "iso:country":"DK",
    "name:und_x_variant":[
        "Oddum",
        "Kirkeby",
        "\u00c5dum Kirkeby",
        "\u00c5dum"
    ],
    "wof:name":"Adum",
    "wof:placetype":"locality"
},
  "geometry": {"coordinates":[8.59373,55.87453000000001],"type":"Point"}
}