{
  "type": "Feature",
  "properties": {
    "gn:admin1_code":"20.0",
    "gn:admin2_code":"350.0",
    "gn:asciiname":"Saerlose",
    "gn:country_code":"DK",
    "gn:dem":57,
    "gn:feature_class":"P",
    "gn:feature_code":"PPL",
    "gn:name":"S\u00e6rl\u00f8se",
    "gn:population":0,
    "gn:timezone":"Europe/Copenhagen",
    "iso:country":"DK",
    "wof:name":"Saerlose",
    "wof:placetype":"locality"
},
  "geometry": {"coordinates":[11.91784,55.57754],"type":"Point"}
}