{
  "type": "Feature",
  "properties": {
    "gn:admin1_code":"20.0",
    "gn:admin2_code":"265.0",
    "gn:asciiname":"Brordrup",
    "gn:country_code":"DK",
    "gn:dem":29,
    "gn:feature_class":"P",
    "gn:feature_code":"PPL",
    "gn:name":"Brordrup",
    "gn:population":0,
    "gn:timezone":"Europe/Copenhagen",
    "iso:country":"DK",
    "wof:name":"Brordrup",
    "wof:placetype":"locality"
},
  "geometry": {"coordinates":[12.08466,55.57692],"type":"Point"}
}