{
  "type": "Feature",
  "properties": {
    "gn:admin1_code":"20.0",
    "gn:admin2_code":"316.0",
    "gn:asciiname":"Tornved",
    "gn:country_code":"DK",
    "gn:dem":24,
    "gn:feature_class":"P",
    "gn:feature_code":"PPL",
    "gn:name":"Tornved",
    "gn:population":0,
    "gn:timezone":"Europe/Copenhagen",
    "iso:country":"DK",
    "wof:name":"Tornved",
    "wof:placetype":"locality"
},
  "geometry": {"coordinates":[11.43844,55.65182],"type":"Point"}
}