{
  "type": "Feature",
  "properties": {
    "gn:admin1_code":"20.0",
    "gn:admin2_code":"316.0",
    "gn:asciiname":"Tornved",
    "gn:country_code":"DK",
    "gn:dem":24,
    "gn:feature_class":"P",
    "gn:feature_code":"PPL",
    "gn:name":"Tornved",
    "gn:population":0,
    "gn:timezone":"Europe/Copenhagen",
    "iso:country":"DK",
    "name:dan_x_preferred":[
        "Tornved Kommune"
    ],
    "name:deu_x_preferred":[
        "Tornved Kommune"
    ],
    "name:fao_x_preferred":[
        "Tornved kommuna"
    ],
    "name:ita_x_preferred":[
        "Tornved"
    ],
    "name:nld_x_preferred":[
        "Tornved"
    ],
    "name:nor_x_preferred":[
        "Tornved kommune"
    ],
    "name:pol_x_preferred":[
        "Gmina Tornved"
    ],
    "name:por_x_preferred":[
        "Tornved"
    ],
    "name:ron_x_preferred":[
        "Comuna Tornved"
    ],
    "name:swe_x_preferred":[
        "Tornveds kommun"
    ],
    "wof:name":"Tornved",
    "wof:placetype":"locality"
},
  "geometry": {"coordinates":[11.43844,55.65182],"type":"Point"}
}