{
  "type": "Feature",
  "properties": {
    "gn:admin1_code":"18.0",
    "gn:admin2_code":"766.0",
    "gn:asciiname":"Kalhave",
    "gn:country_code":"DK",
    "gn:dem":74,
    "gn:feature_class":"P",
    "gn:feature_code":"PPL",
    "gn:name":"Kalhave",
    "gn:population":0,
    "gn:timezone":"Europe/Copenhagen",
    "iso:country":"DK",
    "wof:name":"Kalhave",
    "wof:placetype":"locality"
},
  "geometry": {"coordinates":[9.62371,55.85248000000001],"type":"Point"}
}