{
  "type": "Feature",
  "properties": {
    "gn:admin1_code":"20.0",
    "gn:admin2_code":"336.0",
    "gn:asciiname":"Lille Linde",
    "gn:country_code":"DK",
    "gn:dem":9,
    "gn:feature_class":"P",
    "gn:feature_code":"PPL",
    "gn:name":"Lille Linde",
    "gn:population":0,
    "gn:timezone":"Europe/Copenhagen",
    "iso:country":"DK",
    "wof:name":"Lille Linde",
    "wof:placetype":"locality"
},
  "geometry": {"coordinates":[12.20911,55.33448000000001],"type":"Point"}
}