{
  "type": "Feature",
  "properties": {
    "gn:admin1_code":"17.0",
    "gn:admin2_code":"270.0",
    "gn:asciiname":"Donnevaelde",
    "gn:country_code":"DK",
    "gn:dem":38,
    "gn:feature_class":"P",
    "gn:feature_code":"PPL",
    "gn:name":"D\u00f8nnev\u00e6lde",
    "gn:population":0,
    "gn:timezone":"Europe/Copenhagen",
    "iso:country":"DK",
    "wof:name":"Donnevaelde",
    "wof:placetype":"locality"
},
  "geometry": {"coordinates":[12.26088,56.04888],"type":"Point"}
}