{
  "type": "Feature",
  "properties": {
    "gn:admin1_code":"20.0",
    "gn:admin2_code":"306.0",
    "gn:asciiname":"Brade",
    "gn:country_code":"DK",
    "gn:dem":30,
    "gn:feature_class":"P",
    "gn:feature_code":"PPL",
    "gn:name":"Br\u00e5de",
    "gn:population":0,
    "gn:timezone":"Europe/Copenhagen",
    "iso:country":"DK",
    "name:und_x_variant":[
        "Braade",
        "Br\u00e5de"
    ],
    "wof:name":"Brade",
    "wof:placetype":"locality"
},
  "geometry": {"coordinates":[11.69284,55.83206],"type":"Point"}
}