{
  "type": "Feature",
  "properties": {
    "gn:admin1_code":"21.0",
    "gn:admin2_code":"479.0",
    "gn:asciiname":"Bolsmose",
    "gn:country_code":"DK",
    "gn:dem":38,
    "gn:feature_class":"P",
    "gn:feature_code":"PPL",
    "gn:name":"Bolsmose",
    "gn:population":0,
    "gn:timezone":"Europe/Copenhagen",
    "iso:country":"DK",
    "wof:name":"Bolsmose",
    "wof:placetype":"locality"
},
  "geometry": {"coordinates":[10.75062,55.13088000000001],"type":"Point"}
}