{
  "type": "Feature",
  "properties": {
    "gn:admin1_code":"20.0",
    "gn:admin2_code":"329.0",
    "gn:asciiname":"Orslev under Skoven",
    "gn:country_code":"DK",
    "gn:dem":51,
    "gn:feature_class":"P",
    "gn:feature_code":"PPL",
    "gn:name":"\u00d8rslev under Skoven",
    "gn:population":0,
    "gn:timezone":"Europe/Copenhagen",
    "iso:country":"DK",
    "name:und_x_variant":[
        "\u00d6rslevunderskov",
        "\u00d8rslev under Skoven"
    ],
    "wof:name":"Orslev under Skoven",
    "wof:placetype":"locality"
},
  "geometry": {"coordinates":[11.73037,55.45826],"type":"Point"}
}