{
  "type": "Feature",
  "properties": {
    "gn:gn_country":"DK",
    "gn:gn_fcode":"PPL",
    "gn:gn_pop":0,
    "iso:country":"DK",
    "name:bul_x_preferred":[
        "\u041a\u043b\u0435\u043c\u0435\u043d\u0441\u043a\u0435\u0440"
    ],
    "name:ceb_x_preferred":[
        "Klemensker"
    ],
    "name:dan_x_preferred":[
        "Klemensker"
    ],
    "name:deu_x_preferred":[
        "Klemensker"
    ],
    "name:eng_x_preferred":[
        "Klemensker"
    ],
    "name:fra_x_preferred":[
        "Klemensker"
    ],
    "name:nld_x_preferred":[
        "Klemensker"
    ],
    "name:swe_x_preferred":[
        "Klemensker"
    ],
    "name:unk_x_variant":[
        "Sankt Clemens"
    ],
    "qs_pg:aaroncc":"DK",
    "qs_pg:gn_country":"DK",
    "qs_pg:gn_fcode":"PPL",
    "qs_pg:gn_pop":0,
    "qs_pg:name":"Klemensker",
    "qs_pg:name_adm0":"Danmark",
    "qs_pg:name_adm1":"Hovedstaden",
    "qs_pg:photos":115,
    "qs_pg:photos_1k":23,
    "qs_pg:photos_9k":1,
    "qs_pg:photos_9r":3,
    "qs_pg:photos_all":115,
    "qs_pg:photos_sr":3,
    "qs_pg:pop_sr":0,
    "qs_pg:qs_pg_placetype":"locality",
    "qs_pg:qs_pg_placetype_gp":"Town",
    "qs_pg:woe_adm0":23424796,
    "woe:adm0_id":23424796,
    "woe:name_adm0":"Danmark",
    "woe:name_adm1":"Hovedstaden",
    "woe:placetype":"Town",
    "wof:name":"Klemensker",
    "wof:placetype":"locality"
},
  "geometry": {"coordinates":[14.8099,55.17267],"type":"Point"}
}