{
  "type": "Feature",
  "properties": {
    "gn:admin1_code":"19.0",
    "gn:admin2_code":"773.0",
    "gn:asciiname":"Torp",
    "gn:country_code":"DK",
    "gn:dem":2,
    "gn:feature_class":"P",
    "gn:feature_code":"PPL",
    "gn:name":"Torp",
    "gn:population":0,
    "gn:timezone":"Europe/Copenhagen",
    "iso:country":"DK",
    "wof:name":"Torp",
    "wof:placetype":"locality"
},
  "geometry": {"coordinates":[8.56916,56.76132],"type":"Point"}
}