{
  "type": "Feature",
  "properties": {
    "gn:admin1_code":"18.0",
    "gn:admin2_code":"760.0",
    "gn:asciiname":"Kolby",
    "gn:country_code":"DK",
    "gn:dem":-2,
    "gn:feature_class":"P",
    "gn:feature_code":"PPL",
    "gn:name":"Kolby",
    "gn:population":0,
    "gn:timezone":"Europe/Copenhagen",
    "iso:country":"DK",
    "wof:name":"Kolby",
    "wof:placetype":"locality"
},
  "geometry": {"coordinates":[8.21667,56.18333000000001],"type":"Point"}
}