{
  "type": "Feature",
  "properties": {
    "gn:admin1_code":"18.0",
    "gn:admin2_code":"760.0",
    "gn:asciiname":"Hee",
    "gn:country_code":"DK",
    "gn:dem":6,
    "gn:feature_class":"P",
    "gn:feature_code":"PPL",
    "gn:name":"Hee",
    "gn:population":0,
    "gn:timezone":"Europe/Copenhagen",
    "iso:country":"DK",
    "name:deu_x_preferred":[
        "Hee"
    ],
    "name:nld_x_preferred":[
        "Hee"
    ],
    "name:und_x_variant":[
        "He",
        "Hee"
    ],
    "wof:name":"Hee",
    "wof:placetype":"locality"
},
  "geometry": {"coordinates":[8.28439,56.14437],"type":"Point"}
}