{
  "type": "Feature",
  "properties": {
    "gn:admin1_code":"21.0",
    "gn:admin2_code":"479.0",
    "gn:asciiname":"Brohave",
    "gn:country_code":"DK",
    "gn:dem":5,
    "gn:feature_class":"P",
    "gn:feature_code":"PPL",
    "gn:name":"Brohave",
    "gn:population":0,
    "gn:timezone":"Europe/Copenhagen",
    "iso:country":"DK",
    "wof:name":"Brohave",
    "wof:placetype":"locality"
},
  "geometry": {"coordinates":[10.75195,55.08205],"type":"Point"}
}