{
  "type": "Feature",
  "properties": {
    "gn:admin1_code":"18.0",
    "gn:admin2_code":"760.0",
    "gn:asciiname":"Hover",
    "gn:country_code":"DK",
    "gn:dem":33,
    "gn:feature_class":"P",
    "gn:feature_code":"PPL",
    "gn:name":"Hover",
    "gn:population":0,
    "gn:timezone":"Europe/Copenhagen",
    "iso:country":"DK",
    "name:deu_x_preferred":[
        "Hover"
    ],
    "name:nld_x_preferred":[
        "Hover"
    ],
    "name:pol_x_preferred":[
        "Zawis"
    ],
    "name:rus_x_preferred":[
        "\u0417\u0430\u0432\u0438\u0441\u0430\u043d\u0438\u0435"
    ],
    "wof:name":"Hover",
    "wof:placetype":"locality"
},
  "geometry": {"coordinates":[8.43101,56.14317],"type":"Point"}
}