{
  "type": "Feature",
  "properties": {
    "gn:admin1_code":"18.0",
    "gn:admin2_code":"730.0",
    "gn:asciiname":"Kondrup",
    "gn:country_code":"DK",
    "gn:dem":31,
    "gn:feature_class":"P",
    "gn:feature_code":"PPL",
    "gn:name":"Kondrup",
    "gn:population":0,
    "gn:timezone":"Europe/Copenhagen",
    "iso:country":"DK",
    "wof:name":"Kondrup",
    "wof:placetype":"locality"
},
  "geometry": {"coordinates":[9.96884,56.51812],"type":"Point"}
}