{
  "type": "Feature",
  "properties": {
    "gn:admin1_code":"21.0",
    "gn:admin2_code":"420.0",
    "gn:asciiname":"Nordby",
    "gn:country_code":"DK",
    "gn:dem":25,
    "gn:feature_class":"P",
    "gn:feature_code":"PPL",
    "gn:name":"Nordby",
    "gn:population":0,
    "gn:timezone":"Europe/Copenhagen",
    "iso:country":"DK",
    "name:dan_x_preferred":[
        "Nordby"
    ],
    "name:ita_x_preferred":[
        "Nordby"
    ],
    "name:msa_x_preferred":[
        "Nordby"
    ],
    "name:nld_x_preferred":[
        "Nordby"
    ],
    "name:nor_x_preferred":[
        "Nordby"
    ],
    "name:ron_x_preferred":[
        "Nordby"
    ],
    "name:rus_x_preferred":[
        "\u041d\u043e\u0440\u0431\u044e"
    ],
    "name:spa_x_preferred":[
        "Nordby"
    ],
    "name:swe_x_preferred":[
        "Nordby"
    ],
    "wof:name":"Nordby",
    "wof:placetype":"locality"
},
  "geometry": {"coordinates":[9.96631,55.25763000000001],"type":"Point"}
}