{
  "type": "Feature",
  "properties": {
    "gn:admin1_code":"21.0",
    "gn:admin2_code":"550.0",
    "gn:asciiname":"Bovlund Bjerg",
    "gn:country_code":"DK",
    "gn:dem":44,
    "gn:feature_class":"P",
    "gn:feature_code":"PPL",
    "gn:name":"Bovlund Bjerg",
    "gn:population":0,
    "gn:timezone":"Europe/Copenhagen",
    "iso:country":"DK",
    "name:und_x_variant":[
        "Bovlundbj\u00e6rg",
        "Bovlund Bjerg"
    ],
    "wof:name":"Bovlund Bjerg",
    "wof:placetype":"locality"
},
  "geometry": {"coordinates":[9.10283,55.10178000000001],"type":"Point"}
}