{
  "type": "Feature",
  "properties": {
    "gn:admin1_code":"20.0",
    "gn:admin2_code":"390.0",
    "gn:asciiname":"Sallerup",
    "gn:country_code":"DK",
    "gn:dem":2,
    "gn:feature_class":"P",
    "gn:feature_code":"PPL",
    "gn:name":"Sallerup",
    "gn:population":0,
    "gn:timezone":"Europe/Copenhagen",
    "iso:country":"DK",
    "wof:name":"Sallerup",
    "wof:placetype":"locality"
},
  "geometry": {"coordinates":[11.82109,55.08391],"type":"Point"}
}