{
  "type": "Feature",
  "properties": {
    "gn:admin1_code":"18.0",
    "gn:admin2_code":"779.0",
    "gn:asciiname":"Oksenvad",
    "gn:country_code":"DK",
    "gn:dem":16,
    "gn:feature_class":"P",
    "gn:feature_code":"PPL",
    "gn:name":"\u00d8ksenvad",
    "gn:population":0,
    "gn:timezone":"Europe/Copenhagen",
    "iso:country":"DK",
    "name:und_x_variant":[
        "\u00d6xenvad",
        "\u00d8ksenvad"
    ],
    "wof:name":"Oksenvad",
    "wof:placetype":"locality"
},
  "geometry": {"coordinates":[9.00806,56.6131],"type":"Point"}
}