{
  "type": "Feature",
  "properties": {
    "gn:admin1_code":"20.0",
    "gn:admin2_code":"390.0",
    "gn:asciiname":"Graesbjerg",
    "gn:country_code":"DK",
    "gn:dem":41,
    "gn:feature_class":"P",
    "gn:feature_code":"PPL",
    "gn:name":"Gr\u00e6sbjerg",
    "gn:population":0,
    "gn:timezone":"Europe/Copenhagen",
    "iso:country":"DK",
    "name:und_x_variant":[
        "Gr\u00e6sbj\u00e6rg",
        "Gr\u00e6sbjerg"
    ],
    "wof:name":"Graesbjerg",
    "wof:placetype":"locality"
},
  "geometry": {"coordinates":[11.95738,55.01159000000001],"type":"Point"}
}