{
  "type": "Feature",
  "properties": {
    "gn:admin1_code":"18.0",
    "gn:admin2_code":"766.0",
    "gn:asciiname":"Glattrup",
    "gn:country_code":"DK",
    "gn:dem":47,
    "gn:feature_class":"P",
    "gn:feature_code":"PPL",
    "gn:name":"Glattrup",
    "gn:population":0,
    "gn:timezone":"Europe/Copenhagen",
    "iso:country":"DK",
    "wof:name":"Glattrup",
    "wof:placetype":"locality"
},
  "geometry": {"coordinates":[9.93282,55.78003],"type":"Point"}
}