{
  "type": "Feature",
  "properties": {
    "gn:admin1_code":"18.0",
    "gn:admin2_code":"661.0",
    "gn:asciiname":"Rast",
    "gn:country_code":"DK",
    "gn:dem":10,
    "gn:feature_class":"P",
    "gn:feature_code":"PPL",
    "gn:name":"R\u00e5st",
    "gn:population":0,
    "gn:timezone":"Europe/Copenhagen",
    "iso:country":"DK",
    "name:aze_x_preferred":[
        "Rast"
    ],
    "name:bos_x_preferred":[
        "Rast"
    ],
    "name:ceb_x_preferred":[
        "Rast"
    ],
    "name:deu_x_preferred":[
        "Rast"
    ],
    "name:fra_x_preferred":[
        "Rast"
    ],
    "name:hrv_x_preferred":[
        "Rast"
    ],
    "name:hun_x_preferred":[
        "Rast"
    ],
    "name:nld_x_preferred":[
        "Rast"
    ],
    "name:rus_x_preferred":[
        "\u0420\u0430\u0441\u0442"
    ],
    "name:slk_x_preferred":[
        "Rast"
    ],
    "name:slv_x_preferred":[
        "Rast"
    ],
    "name:srp_x_preferred":[
        "\u0420\u0430\u0441\u0442"
    ],
    "name:swe_x_preferred":[
        "Rast"
    ],
    "name:tur_x_preferred":[
        "Rast"
    ],
    "name:und_x_variant":[
        "Raast",
        "R\u00e5st"
    ],
    "wof:name":"Rast",
    "wof:placetype":"locality"
},
  "geometry": {"coordinates":[8.75824,56.50831],"type":"Point"}
}