{
  "type": "Feature",
  "properties": {
    "gn:admin1_code":"18.0",
    "gn:admin2_code":"661.0",
    "gn:asciiname":"Rast",
    "gn:country_code":"DK",
    "gn:dem":10,
    "gn:feature_class":"P",
    "gn:feature_code":"PPL",
    "gn:name":"R\u00e5st",
    "gn:population":0,
    "gn:timezone":"Europe/Copenhagen",
    "iso:country":"DK",
    "name:und_x_variant":[
        "Raast",
        "R\u00e5st"
    ],
    "wof:name":"Rast",
    "wof:placetype":"locality"
},
  "geometry": {"coordinates":[8.75824,56.50831],"type":"Point"}
}