{
  "type": "Feature",
  "properties": {
    "gn:admin1_code":"20.0",
    "gn:admin2_code":"370.0",
    "gn:asciiname":"Havnskov",
    "gn:country_code":"DK",
    "gn:dem":25,
    "gn:feature_class":"P",
    "gn:feature_code":"PPL",
    "gn:name":"Havnskov",
    "gn:population":0,
    "gn:timezone":"Europe/Copenhagen",
    "iso:country":"DK",
    "name:und_x_variant":[
        "Hagenskov",
        "Havnskov"
    ],
    "wof:name":"Havnskov",
    "wof:placetype":"locality"
},
  "geometry": {"coordinates":[11.59935,55.27459],"type":"Point"}
}