{
  "type": "Feature",
  "properties": {
    "gn:admin1_code":"19.0",
    "gn:admin2_code":"860.0",
    "gn:asciiname":"Sindallund",
    "gn:country_code":"DK",
    "gn:dem":34,
    "gn:feature_class":"P",
    "gn:feature_code":"PPL",
    "gn:name":"Sindallund",
    "gn:population":0,
    "gn:timezone":"Europe/Copenhagen",
    "iso:country":"DK",
    "wof:name":"Sindallund",
    "wof:placetype":"locality"
},
  "geometry": {"coordinates":[10.18864,57.47728000000001],"type":"Point"}
}