{
  "type": "Feature",
  "properties": {
    "gn:admin1_code":"18.0",
    "gn:admin2_code":"707.0",
    "gn:asciiname":"Norager",
    "gn:country_code":"DK",
    "gn:dem":21,
    "gn:feature_class":"P",
    "gn:feature_code":"PPL",
    "gn:name":"N\u00f8rager",
    "gn:population":0,
    "gn:timezone":"Europe/Copenhagen",
    "iso:country":"DK",
    "wof:name":"Norager",
    "wof:placetype":"locality"
},
  "geometry": {"coordinates":[10.50421,56.47671999999999],"type":"Point"}
}