{
  "type": "Feature",
  "properties": {
    "gn:admin1_code":"20.0",
    "gn:admin2_code":"390.0",
    "gn:asciiname":"Oster Egesborg",
    "gn:country_code":"DK",
    "gn:dem":39,
    "gn:feature_class":"P",
    "gn:feature_code":"PPL",
    "gn:name":"\u00d8ster Egesborg",
    "gn:population":0,
    "gn:timezone":"Europe/Copenhagen",
    "iso:country":"DK",
    "wof:name":"Oster Egesborg",
    "wof:placetype":"locality"
},
  "geometry": {"coordinates":[12.01879,55.04006999999999],"type":"Point"}
}