{
  "type": "Feature",
  "properties": {
    "gn:admin1_code":"21.0",
    "gn:admin2_code":"480.0",
    "gn:asciiname":"Bastrup",
    "gn:country_code":"DK",
    "gn:dem":29,
    "gn:feature_class":"P",
    "gn:feature_code":"PPL",
    "gn:name":"Bastrup",
    "gn:population":0,
    "gn:timezone":"Europe/Copenhagen",
    "iso:country":"DK",
    "wof:name":"Bastrup",
    "wof:placetype":"locality"
},
  "geometry": {"coordinates":[10.30106,55.52135],"type":"Point"}
}