{
  "type": "Feature",
  "properties": {
    "gn:admin1_code":"20.0",
    "gn:admin2_code":"329.0",
    "gn:asciiname":"Fredsgarde",
    "gn:country_code":"DK",
    "gn:dem":20,
    "gn:feature_class":"P",
    "gn:feature_code":"PPL",
    "gn:name":"Fredsg\u00e5rde",
    "gn:population":0,
    "gn:timezone":"Europe/Copenhagen",
    "iso:country":"DK",
    "wof:name":"Fredsgarde",
    "wof:placetype":"locality"
},
  "geometry": {"coordinates":[11.85996,55.37982],"type":"Point"}
}