{
  "type": "Feature",
  "properties": {
    "gn:admin1_code":"18.0",
    "gn:admin2_code":"779.0",
    "gn:asciiname":"Vester Lyby",
    "gn:country_code":"DK",
    "gn:dem":17,
    "gn:feature_class":"P",
    "gn:feature_code":"PPL",
    "gn:name":"Vester Lyby",
    "gn:population":0,
    "gn:timezone":"Europe/Copenhagen",
    "iso:country":"DK",
    "wof:name":"Vester Lyby",
    "wof:placetype":"locality"
},
  "geometry": {"coordinates":[8.99424,56.64291],"type":"Point"}
}