{
  "type": "Feature",
  "properties": {
    "gn:admin1_code":"17.0",
    "gn:admin2_code":"217.0",
    "gn:asciiname":"Apperup",
    "gn:country_code":"DK",
    "gn:dem":24,
    "gn:feature_class":"P",
    "gn:feature_code":"PPL",
    "gn:name":"Apperup",
    "gn:population":0,
    "gn:timezone":"Europe/Copenhagen",
    "iso:country":"DK",
    "wof:name":"Apperup",
    "wof:placetype":"locality"
},
  "geometry": {"coordinates":[12.52862,56.07711],"type":"Point"}
}