{
  "type": "Feature",
  "properties": {
    "gn:admin1_code":"21.0",
    "gn:admin2_code":"492.0",
    "gn:asciiname":"Dunkaer",
    "gn:country_code":"DK",
    "gn:dem":34,
    "gn:feature_class":"P",
    "gn:feature_code":"PPL",
    "gn:name":"Dunk\u00e6r",
    "gn:population":0,
    "gn:timezone":"Europe/Copenhagen",
    "iso:country":"DK",
    "name:und_x_variant":[
        "Dungki\u00e6r",
        "Dunkj\u00e6r",
        "Dunk\u00e6r"
    ],
    "wof:name":"Dunkaer",
    "wof:placetype":"locality"
},
  "geometry": {"coordinates":[10.41773,54.84797],"type":"Point"}
}