{
  "type": "Feature",
  "properties": {
    "gn:admin1_code":"19.0",
    "gn:admin2_code":"860.0",
    "gn:asciiname":"Vestermark",
    "gn:country_code":"DK",
    "gn:dem":42,
    "gn:feature_class":"P",
    "gn:feature_code":"PPL",
    "gn:name":"Vestermark",
    "gn:population":0,
    "gn:timezone":"Europe/Copenhagen",
    "iso:country":"DK",
    "wof:name":"Vestermark",
    "wof:placetype":"locality"
},
  "geometry": {"coordinates":[10.02249,57.51368000000001],"type":"Point"}
}