{
  "type": "Feature",
  "properties": {
    "gn:admin1_code":"17.0",
    "gn:admin2_code":"151.0",
    "gn:asciiname":"Agerup",
    "gn:country_code":"DK",
    "gn:dem":31,
    "gn:feature_class":"P",
    "gn:feature_code":"PPL",
    "gn:name":"\u00c5gerup",
    "gn:population":0,
    "gn:timezone":"Europe/Copenhagen",
    "iso:country":"DK",
    "name:und_x_variant":[
        "Aagerup",
        "\u00c5gerup"
    ],
    "wof:name":"Agerup",
    "wof:placetype":"locality"
},
  "geometry": {"coordinates":[12.33095,55.72122],"type":"Point"}
}