{
  "type": "Feature",
  "properties": {
    "gn:admin1_code":"20.0",
    "gn:admin2_code":"306.0",
    "gn:asciiname":"Glostrup",
    "gn:country_code":"DK",
    "gn:dem":29,
    "gn:feature_class":"P",
    "gn:feature_code":"PPL",
    "gn:name":"Glostrup",
    "gn:population":0,
    "gn:timezone":"Europe/Copenhagen",
    "iso:country":"DK",
    "name:ara_x_preferred":[
        "\u063a\u0644\u0648\u0633\u062a\u0631\u0648\u0628"
    ],
    "name:ast_x_preferred":[
        "Glostrup"
    ],
    "name:bul_x_preferred":[
        "\u0413\u043b\u043e\u0441\u0442\u0440\u0443\u043f"
    ],
    "name:ceb_x_preferred":[
        "Glostrup"
    ],
    "name:dan_x_preferred":[
        "Glostrup"
    ],
    "name:frr_x_preferred":[
        "Glostrup"
    ],
    "name:kat_x_preferred":[
        "\u10d2\u10da\u10dd\u10e1\u10e2\u10e0\u10e3\u10de\u10d8"
    ],
    "name:lav_x_preferred":[
        "Glostrupa"
    ],
    "name:msa_x_preferred":[
        "Glostrup"
    ],
    "name:pol_x_preferred":[
        "Glostrup"
    ],
    "name:rus_x_preferred":[
        "\u0413\u043b\u043e\u0441\u0442\u0440\u0443\u043f"
    ],
    "name:spa_x_preferred":[
        "Glostrup"
    ],
    "name:swe_x_preferred":[
        "Glostrup"
    ],
    "name:zho_x_preferred":[
        "\u683c\u6d1b\u65af\u695a\u666e"
    ],
    "wof:name":"Glostrup",
    "wof:placetype":"locality"
},
  "geometry": {"coordinates":[11.66675,55.84354],"type":"Point"}
}