{
  "type": "Feature",
  "properties": {
    "gn:admin1_code":"20.0",
    "gn:admin2_code":"306.0",
    "gn:asciiname":"Glostrup",
    "gn:country_code":"DK",
    "gn:dem":29,
    "gn:feature_class":"P",
    "gn:feature_code":"PPL",
    "gn:name":"Glostrup",
    "gn:population":0,
    "gn:timezone":"Europe/Copenhagen",
    "iso:country":"DK",
    "wof:name":"Glostrup",
    "wof:placetype":"locality"
},
  "geometry": {"coordinates":[11.66675,55.84354],"type":"Point"}
}