{
  "type": "Feature",
  "properties": {
    "gn:admin1_code":"19.0",
    "gn:admin2_code":"851.0",
    "gn:asciiname":"Klitgards Fiskerleje",
    "gn:country_code":"DK",
    "gn:dem":7,
    "gn:feature_class":"P",
    "gn:feature_code":"PPL",
    "gn:name":"Klitg\u00e5rds Fiskerleje",
    "gn:population":0,
    "gn:timezone":"Europe/Copenhagen",
    "iso:country":"DK",
    "name:und_x_variant":[
        "Klithuse",
        "Klitgaarde",
        "Klitg\u00e5rds Fiskerleje"
    ],
    "wof:name":"Klitgards Fiskerleje",
    "wof:placetype":"locality"
},
  "geometry": {"coordinates":[9.67995,57.02944],"type":"Point"}
}