{
  "type": "Feature",
  "properties": {
    "gn:admin1_code":"19.0",
    "gn:admin2_code":"860.0",
    "gn:asciiname":"Vogn",
    "gn:country_code":"DK",
    "gn:dem":33,
    "gn:feature_class":"P",
    "gn:feature_code":"PPL",
    "gn:name":"Vogn",
    "gn:population":0,
    "gn:timezone":"Europe/Copenhagen",
    "iso:country":"DK",
    "wof:name":"Vogn",
    "wof:placetype":"locality"
},
  "geometry": {"coordinates":[10.32036,57.50264],"type":"Point"}
}