{
  "type": "Feature",
  "properties": {
    "gn:admin1_code":"18.0",
    "gn:admin2_code":"657.0",
    "gn:asciiname":"Moltrup Hede",
    "gn:country_code":"DK",
    "gn:dem":48,
    "gn:feature_class":"P",
    "gn:feature_code":"PPLL",
    "gn:name":"M\u00f8ltrup Hede",
    "gn:population":0,
    "gn:timezone":"Europe/Copenhagen",
    "iso:country":"DK",
    "wof:name":"Moltrup Hede",
    "wof:placetype":"locality"
},
  "geometry": {"coordinates":[8.66194,56.14949],"type":"Point"}
}