{
  "type": "Feature",
  "properties": {
    "gn:admin1_code":"21.0",
    "gn:admin2_code":"621.0",
    "gn:asciiname":"Frydenborg",
    "gn:country_code":"DK",
    "gn:dem":2,
    "gn:feature_class":"P",
    "gn:feature_code":"PPL",
    "gn:name":"Frydenborg",
    "gn:population":0,
    "gn:timezone":"Europe/Copenhagen",
    "iso:country":"DK",
    "wof:name":"Frydenborg",
    "wof:placetype":"locality"
},
  "geometry": {"coordinates":[9.6874,55.45444000000001],"type":"Point"}
}