{
  "type": "Feature",
  "properties": {
    "gn:admin1_code":"19.0",
    "gn:admin2_code":"846.0",
    "gn:asciiname":"Vra",
    "gn:country_code":"DK",
    "gn:dem":13,
    "gn:feature_class":"P",
    "gn:feature_code":"PPL",
    "gn:name":"Vr\u00e5",
    "gn:population":0,
    "gn:timezone":"Europe/Copenhagen",
    "iso:country":"DK",
    "name:und_x_variant":[
        "Vraa",
        "Vr\u00e5"
    ],
    "wof:name":"Vra",
    "wof:placetype":"locality"
},
  "geometry": {"coordinates":[9.97936,56.72755],"type":"Point"}
}