{
  "type": "Feature",
  "properties": {
    "gn:admin1_code":"21.0",
    "gn:admin2_code":"510.0",
    "gn:asciiname":"Over Astrup",
    "gn:country_code":"DK",
    "gn:dem":46,
    "gn:feature_class":"P",
    "gn:feature_code":"PPL",
    "gn:name":"Over \u00c5strup",
    "gn:population":0,
    "gn:timezone":"Europe/Copenhagen",
    "iso:country":"DK",
    "name:und_x_variant":[
        "Aastrup",
        "Over \u00c5strup"
    ],
    "wof:name":"Over Astrup",
    "wof:placetype":"locality"
},
  "geometry": {"coordinates":[9.55723,55.26745],"type":"Point"}
}