{
  "type": "Feature",
  "properties": {
    "gn:admin1_code":"18.0",
    "gn:admin2_code":"746.0",
    "gn:asciiname":"Jeksen",
    "gn:country_code":"DK",
    "gn:dem":95,
    "gn:feature_class":"P",
    "gn:feature_code":"PPL",
    "gn:name":"Jeksen",
    "gn:population":0,
    "gn:timezone":"Europe/Copenhagen",
    "iso:country":"DK",
    "wof:name":"Jeksen",
    "wof:placetype":"locality"
},
  "geometry": {"coordinates":[9.97061,56.09441],"type":"Point"}
}