{
  "type": "Feature",
  "properties": {
    "gn:country":"DK",
    "gn:fcode":"PPL",
    "gn:population":0,
    "iso:country":"DK",
    "name:dan_x_preferred":[
        "M\u00f8nsted"
    ],
    "name:deu_x_preferred":[
        "M\u00f8nsted"
    ],
    "name:eng_x_preferred":[
        "M\u00f8nsted"
    ],
    "name:nld_x_preferred":[
        "M\u00f8nsted"
    ],
    "qs_pg:aaroncc":"DK",
    "qs_pg:gn_country":"DK",
    "qs_pg:gn_fcode":"PPL",
    "qs_pg:gn_pop":0,
    "qs_pg:name":"M\u00f8nsted",
    "qs_pg:name_adm0":"Danmark",
    "qs_pg:name_adm1":"Midtjylland",
    "qs_pg:photos":25,
    "qs_pg:photos_1k":5,
    "qs_pg:photos_9k":1,
    "qs_pg:photos_9r":1,
    "qs_pg:photos_all":25,
    "qs_pg:photos_sr":1,
    "qs_pg:pop_sr":0,
    "qs_pg:qs_pg_placetype":"locality",
    "qs_pg:qs_pg_placetype_gp":"Town",
    "qs_pg:woe_adm0":23424796,
    "woe:adm0_id":23424796,
    "woe:name_adm0":"Danmark",
    "woe:name_adm1":"Midtjylland",
    "woe:placetype":"Town",
    "wof:name":"M\u00f8nsted",
    "wof:placetype":"locality"
},
  "geometry": {"coordinates":[9.19,56.44485],"type":"Point"}
}