{
  "type": "Feature",
  "properties": {
    "gn:admin1_code":"19.0",
    "gn:admin2_code":"813.0",
    "gn:asciiname":"Vrangbaek",
    "gn:country_code":"DK",
    "gn:dem":20,
    "gn:feature_class":"P",
    "gn:feature_code":"PPL",
    "gn:name":"Vrangb\u00e6k",
    "gn:population":0,
    "gn:timezone":"Europe/Copenhagen",
    "iso:country":"DK",
    "name:und_x_variant":[
        "Viangb\u00e6k",
        "Vrangb\u00e6k"
    ],
    "wof:name":"Vrangbaek",
    "wof:placetype":"locality"
},
  "geometry": {"coordinates":[10.47463,57.40075],"type":"Point"}
}