{
  "type": "Feature",
  "properties": {
    "gn:admin1_code":"20.0",
    "gn:admin2_code":"376.0",
    "gn:asciiname":"Vestermark",
    "gn:country_code":"DK",
    "gn:dem":1,
    "gn:feature_class":"P",
    "gn:feature_code":"PPL",
    "gn:name":"Vestermark",
    "gn:population":0,
    "gn:timezone":"Europe/Copenhagen",
    "iso:country":"DK",
    "wof:name":"Vestermark",
    "wof:placetype":"locality"
},
  "geometry": {"coordinates":[11.6489,54.89856999999999],"type":"Point"}
}