{
  "type": "Feature",
  "properties": {
    "gn:admin1_code":"18.0",
    "gn:admin2_code":"791.0",
    "gn:asciiname":"Velds",
    "gn:country_code":"DK",
    "gn:dem":56,
    "gn:feature_class":"P",
    "gn:feature_code":"PPL",
    "gn:name":"Velds",
    "gn:population":0,
    "gn:timezone":"Europe/Copenhagen",
    "iso:country":"DK",
    "name:und_x_variant":[
        "V\u00e6lds",
        "Velds"
    ],
    "wof:name":"Velds",
    "wof:placetype":"locality"
},
  "geometry": {"coordinates":[9.61564,56.47382],"type":"Point"}
}