{
  "type": "Feature",
  "properties": {
    "gn:admin1_code":"18.0",
    "gn:admin2_code":"791.0",
    "gn:asciiname":"Sovso",
    "gn:country_code":"DK",
    "gn:dem":43,
    "gn:feature_class":"P",
    "gn:feature_code":"PPLL",
    "gn:name":"S\u00f8vs\u00f8",
    "gn:population":0,
    "gn:timezone":"Europe/Copenhagen",
    "iso:country":"DK",
    "name:und_x_variant":[
        "Sovs\u00f6 Gaarde",
        "S\u00f8vs\u00f8"
    ],
    "wof:name":"Sovso",
    "wof:placetype":"locality"
},
  "geometry": {"coordinates":[9.18069,56.41901],"type":"Point"}
}