{
  "type": "Feature",
  "properties": {
    "gn:admin1_code":"18.0",
    "gn:admin2_code":"707.0",
    "gn:asciiname":"Lille Sjorup",
    "gn:country_code":"DK",
    "gn:dem":20,
    "gn:feature_class":"P",
    "gn:feature_code":"PPL",
    "gn:name":"Lille Sj\u00f8rup",
    "gn:population":0,
    "gn:timezone":"Europe/Copenhagen",
    "iso:country":"DK",
    "wof:name":"Lille Sjorup",
    "wof:placetype":"locality"
},
  "geometry": {"coordinates":[10.31172,56.52943000000001],"type":"Point"}
}