{
  "type": "Feature",
  "properties": {
    "gn:admin1_code":"17.0",
    "gn:admin2_code":"270.0",
    "gn:asciiname":"Hojelt",
    "gn:country_code":"DK",
    "gn:dem":25,
    "gn:feature_class":"P",
    "gn:feature_code":"PPL",
    "gn:name":"H\u00f8jelt",
    "gn:population":0,
    "gn:timezone":"Europe/Copenhagen",
    "iso:country":"DK",
    "wof:name":"Hojelt",
    "wof:placetype":"locality"
},
  "geometry": {"coordinates":[12.22936,56.08463],"type":"Point"}
}