{
  "type": "Feature",
  "properties": {
    "gn:admin1_code":"20.0",
    "gn:admin2_code":"330.0",
    "gn:asciiname":"Halseby",
    "gn:country_code":"DK",
    "gn:dem":6,
    "gn:feature_class":"P",
    "gn:feature_code":"PPL",
    "gn:name":"Halseby",
    "gn:population":0,
    "gn:timezone":"Europe/Copenhagen",
    "iso:country":"DK",
    "wof:name":"Halseby",
    "wof:placetype":"locality"
},
  "geometry": {"coordinates":[11.19386,55.35729],"type":"Point"}
}