{
  "type": "Feature",
  "properties": {
    "gn:admin1_code":"20.0",
    "gn:admin2_code":"259.0",
    "gn:asciiname":"Kanderod",
    "gn:country_code":"DK",
    "gn:dem":20,
    "gn:feature_class":"P",
    "gn:feature_code":"PPL",
    "gn:name":"Kander\u00f8d",
    "gn:population":0,
    "gn:timezone":"Europe/Copenhagen",
    "iso:country":"DK",
    "wof:name":"Kanderod",
    "wof:placetype":"locality"
},
  "geometry": {"coordinates":[12.11439,55.37563000000001],"type":"Point"}
}