{
  "type": "Feature",
  "properties": {
    "gn:admin1_code":"21.0",
    "gn:admin2_code":"630.0",
    "gn:asciiname":"Gadbjerg",
    "gn:country_code":"DK",
    "gn:dem":82,
    "gn:feature_class":"P",
    "gn:feature_code":"PPL",
    "gn:name":"Gadbjerg",
    "gn:population":0,
    "gn:timezone":"Europe/Copenhagen",
    "iso:country":"DK",
    "name:und_x_variant":[
        "Gadbj\u00e6rg",
        "Gadbjerg"
    ],
    "wof:name":"Gadbjerg",
    "wof:placetype":"locality"
},
  "geometry": {"coordinates":[9.32484,55.77152],"type":"Point"}
}