{
  "type": "Feature",
  "properties": {
    "gn:admin1_code":"21.0",
    "gn:admin2_code":"479.0",
    "gn:asciiname":"Hundstrup",
    "gn:country_code":"DK",
    "gn:dem":34,
    "gn:feature_class":"P",
    "gn:feature_code":"PPL",
    "gn:name":"Hundstrup",
    "gn:population":0,
    "gn:timezone":"Europe/Copenhagen",
    "iso:country":"DK",
    "name:und_x_variant":[
        "Hunstrup",
        "Hundstrup"
    ],
    "wof:name":"Hundstrup",
    "wof:placetype":"locality"
},
  "geometry": {"coordinates":[10.43093,55.10036],"type":"Point"}
}