{
  "type": "Feature",
  "properties": {
    "gn:admin1_code":"21.0",
    "gn:admin2_code":"420.0",
    "gn:asciiname":"Lundsbjerg",
    "gn:country_code":"DK",
    "gn:dem":59,
    "gn:feature_class":"P",
    "gn:feature_code":"PPL",
    "gn:name":"Lundsbjerg",
    "gn:population":0,
    "gn:timezone":"Europe/Copenhagen",
    "iso:country":"DK",
    "name:und_x_variant":[
        "Lundsbj\u00e6rg",
        "Lundsbjerg"
    ],
    "wof:name":"Lundsbjerg",
    "wof:placetype":"locality"
},
  "geometry": {"coordinates":[10.07812,55.26371999999999],"type":"Point"}
}