{
  "type": "Feature",
  "properties": {
    "gn:admin1_code":"19.0",
    "gn:admin2_code":"787.0",
    "gn:asciiname":"Hojstrup",
    "gn:country_code":"DK",
    "gn:dem":22,
    "gn:feature_class":"P",
    "gn:feature_code":"PPL",
    "gn:name":"H\u00f8jstrup",
    "gn:population":0,
    "gn:timezone":"Europe/Copenhagen",
    "iso:country":"DK",
    "wof:name":"Hojstrup",
    "wof:placetype":"locality"
},
  "geometry": {"coordinates":[9.01763,57.05548],"type":"Point"}
}