{
  "type": "Feature",
  "properties": {
    "gn:admin1_code":"18.0",
    "gn:admin2_code":"779.0",
    "gn:asciiname":"Bilstrup",
    "gn:country_code":"DK",
    "gn:dem":12,
    "gn:feature_class":"P",
    "gn:feature_code":"PPL",
    "gn:name":"Bilstrup",
    "gn:population":0,
    "gn:timezone":"Europe/Copenhagen",
    "iso:country":"DK",
    "wof:name":"Bilstrup",
    "wof:placetype":"locality"
},
  "geometry": {"coordinates":[9.012,56.54455],"type":"Point"}
}