{
  "type": "Feature",
  "properties": {
    "gn:admin1_code":"18.0",
    "gn:admin2_code":"707.0",
    "gn:asciiname":"Orbaek",
    "gn:country_code":"DK",
    "gn:dem":15,
    "gn:feature_class":"P",
    "gn:feature_code":"PPL",
    "gn:name":"\u00d8rb\u00e6k",
    "gn:population":0,
    "gn:timezone":"Europe/Copenhagen",
    "iso:country":"DK",
    "wof:name":"Orbaek",
    "wof:placetype":"locality"
},
  "geometry": {"coordinates":[10.69473,56.42794],"type":"Point"}
}