{
  "type": "Feature",
  "properties": {
    "iso:country":"DK",
    "qs_pg:aaroncc":"DK",
    "qs_pg:name":"Krakken",
    "qs_pg:name_adm0":"Danmark",
    "qs_pg:name_adm1":"Hovedstaden",
    "qs_pg:photos":283,
    "qs_pg:photos_1k":57,
    "qs_pg:photos_9k":1,
    "qs_pg:photos_9r":4,
    "qs_pg:photos_all":283,
    "qs_pg:photos_sr":5,
    "qs_pg:pop_sr":0,
    "qs_pg:qs_pg_placetype":"locality",
    "qs_pg:qs_pg_placetype_gp":"Town",
    "qs_pg:woe_adm0":23424796,
    "woe:adm0_id":23424796,
    "woe:name_adm0":"Danmark",
    "woe:name_adm1":"Hovedstaden",
    "woe:placetype":"Town",
    "wof:name":"Krakken",
    "wof:placetype":"locality"
},
  "geometry": {"coordinates":[14.755668,55.271667],"type":"Point"}
}