{
  "type": "Feature",
  "properties": {
    "gn:admin1_code":"19.0",
    "gn:admin2_code":"773.0",
    "gn:asciiname":"Centrum",
    "gn:country_code":"DK",
    "gn:dem":26,
    "gn:feature_class":"P",
    "gn:feature_code":"PPL",
    "gn:name":"Centrum",
    "gn:population":0,
    "gn:timezone":"Europe/Copenhagen",
    "iso:country":"DK",
    "name:ces_x_preferred":[
        "Centrum"
    ],
    "name:dan_x_preferred":[
        "Centrum"
    ],
    "name:deu_x_preferred":[
        "Centrum"
    ],
    "name:epo_x_preferred":[
        "Centrum"
    ],
    "name:hun_x_preferred":[
        "Centrum"
    ],
    "name:ita_x_preferred":[
        "Centrum"
    ],
    "name:lat_x_preferred":[
        "Centrum"
    ],
    "name:nld_x_preferred":[
        "Centrum"
    ],
    "name:pol_x_preferred":[
        "Centrum"
    ],
    "name:slk_x_preferred":[
        "Centrum"
    ],
    "name:spa_x_preferred":[
        "Centrum"
    ],
    "name:swe_x_preferred":[
        "Centrum"
    ],
    "wof:name":"Centrum",
    "wof:placetype":"locality"
},
  "geometry": {"coordinates":[8.75398,56.73907],"type":"Point"}
}