{
  "type": "Feature",
  "properties": {
    "gn:gn_country":"DK",
    "iso:country":"DK",
    "qs_pg:aaroncc":"DK",
    "qs_pg:gn_country":"DK",
    "qs_pg:name":"N\u00f8rre St\u00e6nge",
    "qs_pg:name_adm0":"Danmark",
    "qs_pg:name_adm1":"Sj\u00e6lland",
    "qs_pg:photos":57,
    "qs_pg:photos_1k":12,
    "qs_pg:photos_9k":1,
    "qs_pg:photos_9r":2,
    "qs_pg:photos_all":57,
    "qs_pg:photos_sr":2,
    "qs_pg:pop_sr":0,
    "qs_pg:qs_pg_placetype":"locality",
    "qs_pg:qs_pg_placetype_gp":"Town",
    "qs_pg:woe_adm0":23424796,
    "woe:adm0_id":23424796,
    "woe:name_adm0":"Danmark",
    "woe:name_adm1":"Sj\u00e6lland",
    "woe:placetype":"Town",
    "wof:name":"N\u00f8rre St\u00e6nge",
    "wof:placetype":"locality"
},
  "geometry": {"coordinates":[11.795047,55.788217],"type":"Point"}
}