{
  "type": "Feature",
  "properties": {
    "gn:admin1_code":"17.0",
    "gn:admin2_code":"250.0",
    "gn:asciiname":"Bonderup",
    "gn:country_code":"DK",
    "gn:dem":33,
    "gn:feature_class":"P",
    "gn:feature_code":"PPL",
    "gn:name":"Bonderup",
    "gn:population":0,
    "gn:timezone":"Europe/Copenhagen",
    "iso:country":"DK",
    "name:dan_x_preferred":[
        "Bonderup"
    ],
    "wof:name":"Bonderup",
    "wof:placetype":"locality"
},
  "geometry": {"coordinates":[11.96338,55.76671999999999],"type":"Point"}
}