{
  "type": "Feature",
  "properties": {
    "gn:admin1_code":"19.0",
    "gn:admin2_code":"840.0",
    "gn:asciiname":"Durup",
    "gn:country_code":"DK",
    "gn:dem":41,
    "gn:feature_class":"P",
    "gn:feature_code":"PPL",
    "gn:name":"Durup",
    "gn:population":0,
    "gn:timezone":"Europe/Copenhagen",
    "iso:country":"DK",
    "wof:name":"Durup",
    "wof:placetype":"locality"
},
  "geometry": {"coordinates":[9.61995,56.71731],"type":"Point"}
}