{
  "type": "Feature",
  "properties": {
    "gn:country":"DK",
    "gn:fcode":"PPL",
    "gn:population":0,
    "iso:country":"DK",
    "name:dan_x_preferred":[
        "Fjels\u00f8"
    ],
    "name:deu_x_preferred":[
        "Fjels\u00f8"
    ],
    "name:eng_x_preferred":[
        "Fjels\u00f8"
    ],
    "name:nld_x_preferred":[
        "Fjels\u00f8"
    ],
    "name:pol_x_preferred":[
        "Fjels\u00f8"
    ],
    "qs_pg:aaroncc":"DK",
    "qs_pg:gn_country":"DK",
    "qs_pg:gn_fcode":"PPL",
    "qs_pg:gn_pop":0,
    "qs_pg:name":"Fjels\u00f8",
    "qs_pg:name_adm0":"Danmark",
    "qs_pg:name_adm1":"Nordjylland",
    "qs_pg:photos_9r":0,
    "qs_pg:photos_sr":0,
    "qs_pg:pop_sr":0,
    "qs_pg:qs_pg_placetype":"locality",
    "qs_pg:qs_pg_placetype_gp":"Town",
    "qs_pg:woe_adm0":23424796,
    "woe:adm0_id":23424796,
    "woe:name_adm0":"Danmark",
    "woe:name_adm1":"Nordjylland",
    "woe:placetype":"Town",
    "wof:name":"Fjels\u00f8",
    "wof:placetype":"locality"
},
  "geometry": {"coordinates":[9.43378,56.66508],"type":"Point"}
}