{
  "type": "Feature",
  "properties": {
    "gn:admin1_code":"21.0",
    "gn:admin2_code":"480.0",
    "gn:asciiname":"Agernaes",
    "gn:country_code":"DK",
    "gn:dem":5,
    "gn:feature_class":"P",
    "gn:feature_code":"PPL",
    "gn:name":"Agern\u00e6s",
    "gn:population":0,
    "gn:timezone":"Europe/Copenhagen",
    "iso:country":"DK",
    "name:und_x_variant":[
        "Avern\u00e6s",
        "Agern\u00e6s"
    ],
    "wof:name":"Agernaes",
    "wof:placetype":"locality"
},
  "geometry": {"coordinates":[10.34032,55.59025],"type":"Point"}
}