{
  "type": "Feature",
  "properties": {
    "gn:admin1_code":"18.0",
    "gn:admin2_code":"791.0",
    "gn:asciiname":"Sjorup",
    "gn:country_code":"DK",
    "gn:dem":49,
    "gn:feature_class":"P",
    "gn:feature_code":"PPL",
    "gn:name":"Sj\u00f8rup",
    "gn:population":0,
    "gn:timezone":"Europe/Copenhagen",
    "iso:country":"DK",
    "wof:name":"Sjorup",
    "wof:placetype":"locality"
},
  "geometry": {"coordinates":[9.08291,56.42706],"type":"Point"}
}