{
  "type": "Feature",
  "properties": {
    "gn:admin1_code":"20.0",
    "gn:admin2_code":"259.0",
    "gn:asciiname":"Sollerup",
    "gn:country_code":"DK",
    "gn:dem":23,
    "gn:feature_class":"P",
    "gn:feature_code":"PPL",
    "gn:name":"S\u00f8llerup",
    "gn:population":0,
    "gn:timezone":"Europe/Copenhagen",
    "iso:country":"DK",
    "name:ceb_x_preferred":[
        "Sollerup"
    ],
    "name:dan_x_preferred":[
        "Sollerup"
    ],
    "name:deu_x_preferred":[
        "Sollerup"
    ],
    "name:epo_x_preferred":[
        "Sollerup"
    ],
    "name:eus_x_preferred":[
        "Sollerup"
    ],
    "name:fas_x_preferred":[
        "\u0633\u0648\u0644\u0631\u0648\u067e"
    ],
    "name:fra_x_preferred":[
        "Sollerup"
    ],
    "name:hun_x_preferred":[
        "Sollerup"
    ],
    "name:ita_x_preferred":[
        "Sollerup"
    ],
    "name:mkd_x_preferred":[
        "\u0417\u043e\u043b\u0435\u0440\u0443\u043f"
    ],
    "name:msa_x_preferred":[
        "Sollerup"
    ],
    "name:nld_x_preferred":[
        "Sollerup"
    ],
    "name:pol_x_preferred":[
        "Sollerup"
    ],
    "name:por_x_preferred":[
        "Sollerup"
    ],
    "name:ron_x_preferred":[
        "Sollerup"
    ],
    "name:rus_x_preferred":[
        "\u0417\u043e\u043b\u043b\u0435\u0440\u0443\u043f"
    ],
    "name:sco_x_preferred":[
        "Sollerup"
    ],
    "name:spa_x_preferred":[
        "Sollerup"
    ],
    "name:srp_x_preferred":[
        "\u0417\u043e\u043b\u0435\u0440\u0443\u043f"
    ],
    "name:tur_x_preferred":[
        "Sollerup"
    ],
    "name:ukr_x_preferred":[
        "\u0417\u043e\u043b\u043b\u0435\u0440\u0443\u043f"
    ],
    "name:uzb_x_preferred":[
        "Sollerup"
    ],
    "name:vie_x_preferred":[
        "Sollerup"
    ],
    "name:vol_x_preferred":[
        "Sollerup"
    ],
    "name:war_x_preferred":[
        "Sollerup"
    ],
    "name:zho_x_preferred":[
        "\u7d22\u83b1\u9c81\u666e"
    ],
    "wof:name":"Sollerup",
    "wof:placetype":"locality"
},
  "geometry": {"coordinates":[12.11029,55.41239],"type":"Point"}
}