{
  "type": "Feature",
  "properties": {
    "gn:admin1_code":"20.0",
    "gn:admin2_code":"259.0",
    "gn:asciiname":"Sollerup",
    "gn:country_code":"DK",
    "gn:dem":23,
    "gn:feature_class":"P",
    "gn:feature_code":"PPL",
    "gn:name":"S\u00f8llerup",
    "gn:population":0,
    "gn:timezone":"Europe/Copenhagen",
    "iso:country":"DK",
    "wof:name":"Sollerup",
    "wof:placetype":"locality"
},
  "geometry": {"coordinates":[12.11029,55.41239],"type":"Point"}
}