{
  "type": "Feature",
  "properties": {
    "gn:admin1_code":"18.0",
    "gn:admin2_code":"657.0",
    "gn:asciiname":"Ostermark",
    "gn:country_code":"DK",
    "gn:dem":51,
    "gn:feature_class":"P",
    "gn:feature_code":"PPL",
    "gn:name":"\u00d8stermark",
    "gn:population":0,
    "gn:timezone":"Europe/Copenhagen",
    "iso:country":"DK",
    "wof:name":"Ostermark",
    "wof:placetype":"locality"
},
  "geometry": {"coordinates":[9.0844,56.19853000000001],"type":"Point"}
}