{
  "type": "Feature",
  "properties": {
    "gn:admin1_code":"20.0",
    "gn:admin2_code":"350.0",
    "gn:asciiname":"Ny Tolstrup",
    "gn:country_code":"DK",
    "gn:dem":70,
    "gn:feature_class":"P",
    "gn:feature_code":"PPL",
    "gn:name":"Ny Tolstrup",
    "gn:population":0,
    "gn:timezone":"Europe/Copenhagen",
    "iso:country":"DK",
    "wof:name":"Ny Tolstrup",
    "wof:placetype":"locality"
},
  "geometry": {"coordinates":[11.91421,55.55278000000001],"type":"Point"}
}