{
  "type": "Feature",
  "properties": {
    "gn:admin1_code":"21.0",
    "gn:admin2_code":"540.0",
    "gn:asciiname":"Sarup",
    "gn:country_code":"DK",
    "gn:dem":32,
    "gn:feature_class":"P",
    "gn:feature_code":"PPL",
    "gn:name":"Sarup",
    "gn:population":0,
    "gn:timezone":"Europe/Copenhagen",
    "iso:country":"DK",
    "wof:name":"Sarup",
    "wof:placetype":"locality"
},
  "geometry": {"coordinates":[10.0332,54.91038],"type":"Point"}
}