{
  "type": "Feature",
  "properties": {
    "gn:admin1_code":"21.0",
    "gn:admin2_code":"630.0",
    "gn:asciiname":"Godding Huse",
    "gn:country_code":"DK",
    "gn:dem":89,
    "gn:feature_class":"P",
    "gn:feature_code":"PPLL",
    "gn:name":"G\u00f8dding Huse",
    "gn:population":0,
    "gn:timezone":"Europe/Copenhagen",
    "iso:country":"DK",
    "name:und_x_variant":[
        "Gj\u00f6ding Huse",
        "G\u00f6ding Huse",
        "G\u00f8dding Huse"
    ],
    "wof:name":"Godding Huse",
    "wof:placetype":"locality"
},
  "geometry": {"coordinates":[9.24372,55.71327],"type":"Point"}
}