{
  "type": "Feature",
  "properties": {
    "gn:admin1_code":"21.0",
    "gn:admin2_code":"450.0",
    "gn:asciiname":"Kastel",
    "gn:country_code":"DK",
    "gn:dem":54,
    "gn:feature_class":"P",
    "gn:feature_code":"PPL",
    "gn:name":"Kastel",
    "gn:population":0,
    "gn:timezone":"Europe/Copenhagen",
    "iso:country":"DK",
    "name:ceb_x_preferred":[
        "Kastel"
    ],
    "name:deu_x_preferred":[
        "Kastel"
    ],
    "name:fra_x_preferred":[
        "Kastel"
    ],
    "name:pol_x_preferred":[
        "Kastel"
    ],
    "name:rus_x_preferred":[
        "\u041a\u0430\u0441\u0442\u0435\u043b\u044c"
    ],
    "name:slk_x_preferred":[
        "Kastel"
    ],
    "name:swe_x_preferred":[
        "Kastel"
    ],
    "name:ukr_x_preferred":[
        "\u041a\u0430\u0441\u0442\u0435\u043b\u044c"
    ],
    "wof:name":"Kastel",
    "wof:placetype":"locality"
},
  "geometry": {"coordinates":[10.6447,55.27368000000001],"type":"Point"}
}