{
  "type": "Feature",
  "properties": {
    "gn:admin1_code":"21.0",
    "gn:admin2_code":"580.0",
    "gn:asciiname":"Bodum",
    "gn:country_code":"DK",
    "gn:dem":47,
    "gn:feature_class":"P",
    "gn:feature_code":"PPL",
    "gn:name":"Bodum",
    "gn:population":0,
    "gn:timezone":"Europe/Copenhagen",
    "iso:country":"DK",
    "name:dan_x_preferred":[
        "Bodum"
    ],
    "name:deu_x_preferred":[
        "Bodum"
    ],
    "name:fin_x_preferred":[
        "Bodum"
    ],
    "name:fra_x_preferred":[
        "Bodum"
    ],
    "name:ita_x_preferred":[
        "Bodum"
    ],
    "name:nld_x_preferred":[
        "Bodum"
    ],
    "name:rus_x_preferred":[
        "Bodum"
    ],
    "name:spa_x_preferred":[
        "Bodum"
    ],
    "wof:name":"Bodum",
    "wof:placetype":"locality"
},
  "geometry": {"coordinates":[9.42271,55.08421],"type":"Point"}
}