{
  "type": "Feature",
  "properties": {
    "gn:country":"DK",
    "gn:fcode":"PPL",
    "gn:population":0,
    "iso:country":"DK",
    "name:dan_x_preferred":[
        "L\u00f8vel"
    ],
    "name:deu_x_preferred":[
        "L\u00f8vel"
    ],
    "name:eng_x_preferred":[
        "L\u00f8vel"
    ],
    "name:fao_x_preferred":[
        "L\u00f8vel"
    ],
    "name:fra_x_preferred":[
        "L\u00f8vel"
    ],
    "name:isl_x_preferred":[
        "L\u00f8vel"
    ],
    "name:kal_x_preferred":[
        "L\u00f8vel"
    ],
    "name:nld_x_preferred":[
        "L\u00f8vel"
    ],
    "name:nno_x_preferred":[
        "L\u00f8vel"
    ],
    "name:nob_x_preferred":[
        "L\u00f8vel"
    ],
    "name:swe_x_preferred":[
        "L\u00f8vel"
    ],
    "qs_pg:aaroncc":"DK",
    "qs_pg:gn_country":"DK",
    "qs_pg:gn_fcode":"PPL",
    "qs_pg:gn_pop":0,
    "qs_pg:name":"L\u00f8vel",
    "qs_pg:name_adm0":"Danmark",
    "qs_pg:name_adm1":"Midtjylland",
    "qs_pg:photos":19,
    "qs_pg:photos_1k":4,
    "qs_pg:photos_9k":1,
    "qs_pg:photos_9r":1,
    "qs_pg:photos_all":19,
    "qs_pg:photos_sr":1,
    "qs_pg:pop_sr":0,
    "qs_pg:qs_pg_placetype":"locality",
    "qs_pg:qs_pg_placetype_gp":"Town",
    "qs_pg:woe_adm0":23424796,
    "woe:adm0_id":23424796,
    "woe:name_adm0":"Danmark",
    "woe:name_adm1":"Midtjylland",
    "woe:placetype":"Town",
    "wof:name":"L\u00f8vel",
    "wof:placetype":"locality"
},
  "geometry": {"coordinates":[9.4698,56.53377],"type":"Point"}
}