{
  "type": "Feature",
  "properties": {
    "gn:admin1_code":"18.0",
    "gn:admin2_code":"671.0",
    "gn:asciiname":"Jestrup",
    "gn:country_code":"DK",
    "gn:dem":7,
    "gn:feature_class":"P",
    "gn:feature_code":"PPLL",
    "gn:name":"Jestrup",
    "gn:population":0,
    "gn:timezone":"Europe/Copenhagen",
    "iso:country":"DK",
    "wof:name":"Jestrup",
    "wof:placetype":"locality"
},
  "geometry": {"coordinates":[8.44932,56.65618000000001],"type":"Point"}
}