{
  "type": "Feature",
  "properties": {
    "gn:admin1_code":"18.0",
    "gn:admin2_code":"756.0",
    "gn:asciiname":"Hedegard",
    "gn:country_code":"DK",
    "gn:dem":73,
    "gn:feature_class":"P",
    "gn:feature_code":"PPL",
    "gn:name":"Hedeg\u00e5rd",
    "gn:population":0,
    "gn:timezone":"Europe/Copenhagen",
    "iso:country":"DK",
    "name:und_x_variant":[
        "Hedegaarde",
        "Hedeg\u00e5rde",
        "Hedeg\u00e5rd"
    ],
    "wof:name":"Hedegard",
    "wof:placetype":"locality"
},
  "geometry": {"coordinates":[9.29246,55.95271],"type":"Point"}
}