{
  "type": "Feature",
  "properties": {
    "gn:admin1_code":"18.0",
    "gn:admin2_code":"740.0",
    "gn:asciiname":"Vinding",
    "gn:country_code":"DK",
    "gn:dem":106,
    "gn:feature_class":"P",
    "gn:feature_code":"PPL",
    "gn:name":"Vinding",
    "gn:population":0,
    "gn:timezone":"Europe/Copenhagen",
    "iso:country":"DK",
    "wof:name":"Vinding",
    "wof:placetype":"locality"
},
  "geometry": {"coordinates":[9.56698,56.02285],"type":"Point"}
}