{
  "type": "Feature",
  "properties": {
    "gn:admin1_code":"17.0",
    "gn:admin2_code":"165.0",
    "gn:asciiname":"Risby",
    "gn:country_code":"DK",
    "gn:dem":25,
    "gn:feature_class":"P",
    "gn:feature_code":"PPL",
    "gn:name":"Risby",
    "gn:population":0,
    "gn:timezone":"Europe/Copenhagen",
    "iso:country":"DK",
    "name:dan_x_preferred":[
        "Risby"
    ],
    "name:deu_x_preferred":[
        "Risby"
    ],
    "name:nld_x_preferred":[
        "Risby"
    ],
    "name:pol_x_preferred":[
        "Risby"
    ],
    "name:swe_x_preferred":[
        "Risby"
    ],
    "wof:name":"Risby",
    "wof:placetype":"locality"
},
  "geometry": {"coordinates":[12.32639,55.68896],"type":"Point"}
}