{
  "type": "Feature",
  "properties": {
    "gn:gn_country":"DK",
    "gn:gn_fcode":"PPL",
    "gn:gn_pop":0,
    "iso:country":"DK",
    "name:dan_x_preferred":[
        "\u00d8stermarie"
    ],
    "name:deu_x_preferred":[
        "\u00d8stermarie"
    ],
    "name:eng_x_preferred":[
        "\u00d8stermarie"
    ],
    "name:fra_x_preferred":[
        "\u00d8stermarie"
    ],
    "name:nld_x_preferred":[
        "\u00d8stermarie"
    ],
    "name:swe_x_preferred":[
        "\u00d8stermarie"
    ],
    "name:unk_x_variant":[
        "Godthaab"
    ],
    "qs_pg:aaroncc":"DK",
    "qs_pg:gn_country":"DK",
    "qs_pg:gn_fcode":"PPL",
    "qs_pg:gn_pop":0,
    "qs_pg:name":"\u00d8stermarie",
    "qs_pg:name_adm0":"Danmark",
    "qs_pg:name_adm1":"Hovedstaden",
    "qs_pg:photos":138,
    "qs_pg:photos_1k":28,
    "qs_pg:photos_9k":1,
    "qs_pg:photos_9r":3,
    "qs_pg:photos_all":138,
    "qs_pg:photos_sr":3,
    "qs_pg:pop_sr":0,
    "qs_pg:qs_pg_placetype":"locality",
    "qs_pg:qs_pg_placetype_gp":"Town",
    "qs_pg:woe_adm0":23424796,
    "woe:adm0_id":23424796,
    "woe:name_adm0":"Danmark",
    "woe:name_adm1":"Hovedstaden",
    "woe:placetype":"Town",
    "wof:name":"\u00d8stermarie",
    "wof:placetype":"locality"
},
  "geometry": {"coordinates":[15.01247,55.14067],"type":"Point"}
}