{
  "type": "Feature",
  "properties": {
    "gn:admin1_code":"18.0",
    "gn:admin2_code":"779.0",
    "gn:asciiname":"Engelst",
    "gn:country_code":"DK",
    "gn:dem":8,
    "gn:feature_class":"P",
    "gn:feature_code":"PPLL",
    "gn:name":"Engelst",
    "gn:population":0,
    "gn:timezone":"Europe/Copenhagen",
    "iso:country":"DK",
    "name:und_x_variant":[
        "Engels",
        "Engelst"
    ],
    "wof:name":"Engelst",
    "wof:placetype":"locality"
},
  "geometry": {"coordinates":[9.05496,56.82613000000001],"type":"Point"}
}