{
  "type": "Feature",
  "properties": {
    "gn:admin1_code":"21.0",
    "gn:admin2_code":"580.0",
    "gn:asciiname":"Smedeby",
    "gn:country_code":"DK",
    "gn:dem":33,
    "gn:feature_class":"P",
    "gn:feature_code":"PPL",
    "gn:name":"Smedeby",
    "gn:population":0,
    "gn:timezone":"Europe/Copenhagen",
    "iso:country":"DK",
    "name:und_x_variant":[
        "N\u00f8rre Smedeby",
        "Smedeby"
    ],
    "wof:name":"Smedeby",
    "wof:placetype":"locality"
},
  "geometry": {"coordinates":[9.38251,54.84887],"type":"Point"}
}