{
  "type": "Feature",
  "properties": {
    "gn:admin1_code":"19.0",
    "gn:admin2_code":"840.0",
    "gn:asciiname":"Skindbjerg",
    "gn:country_code":"DK",
    "gn:dem":69,
    "gn:feature_class":"P",
    "gn:feature_code":"PPL",
    "gn:name":"Skindbjerg",
    "gn:population":0,
    "gn:timezone":"Europe/Copenhagen",
    "iso:country":"DK",
    "wof:name":"Skindbjerg",
    "wof:placetype":"locality"
},
  "geometry": {"coordinates":[9.92014,56.88096],"type":"Point"}
}