{
  "type": "Feature",
  "properties": {
    "gn:admin1_code":"20.0",
    "gn:admin2_code":"336.0",
    "gn:asciiname":"Lille Heddinge",
    "gn:country_code":"DK",
    "gn:dem":30,
    "gn:feature_class":"P",
    "gn:feature_code":"PPL",
    "gn:name":"Lille Heddinge",
    "gn:population":0,
    "gn:timezone":"Europe/Copenhagen",
    "iso:country":"DK",
    "name:und_x_variant":[
        "Lille Hedinge",
        "Lille Heddinge"
    ],
    "wof:name":"Lille Heddinge",
    "wof:placetype":"locality"
},
  "geometry": {"coordinates":[12.39207,55.27239],"type":"Point"}
}