{
  "type": "Feature",
  "properties": {
    "gn:admin1_code":"18.0",
    "gn:admin2_code":"760.0",
    "gn:asciiname":"Karsbaek",
    "gn:country_code":"DK",
    "gn:dem":26,
    "gn:feature_class":"P",
    "gn:feature_code":"PPL",
    "gn:name":"Karsb\u00e6k",
    "gn:population":0,
    "gn:timezone":"Europe/Copenhagen",
    "iso:country":"DK",
    "wof:name":"Karsbaek",
    "wof:placetype":"locality"
},
  "geometry": {"coordinates":[8.39697,56.0634],"type":"Point"}
}