{
  "type": "Feature",
  "properties": {
    "gn:admin1_code":"19.0",
    "gn:admin2_code":"851.0",
    "gn:asciiname":"Milbakken",
    "gn:country_code":"DK",
    "gn:dem":5,
    "gn:feature_class":"P",
    "gn:feature_code":"PPL",
    "gn:name":"Milbakken",
    "gn:population":0,
    "gn:timezone":"Europe/Copenhagen",
    "iso:country":"DK",
    "name:und_x_variant":[
        "Milbak",
        "Milbak Huse",
        "Milbakken"
    ],
    "wof:name":"Milbakken",
    "wof:placetype":"locality"
},
  "geometry": {"coordinates":[9.89793,57.18042],"type":"Point"}
}