{
  "type": "Feature",
  "properties": {
    "gn:admin1_code":"21.0",
    "gn:admin2_code":"607.0",
    "gn:asciiname":"Bredstrup",
    "gn:country_code":"DK",
    "gn:dem":25,
    "gn:feature_class":"P",
    "gn:feature_code":"PPL",
    "gn:name":"Bredstrup",
    "gn:population":0,
    "gn:timezone":"Europe/Copenhagen",
    "iso:country":"DK",
    "wof:name":"Bredstrup",
    "wof:placetype":"locality"
},
  "geometry": {"coordinates":[9.66607,55.59109],"type":"Point"}
}