{
  "type": "Feature",
  "properties": {
    "gn:gn_country":"DK",
    "gn:gn_fcode":"PPL",
    "gn:gn_pop":0,
    "iso:country":"DK",
    "name:dan_x_preferred":[
        "Melby"
    ],
    "name:deu_x_preferred":[
        "Melby"
    ],
    "name:eng_x_preferred":[
        "Melby"
    ],
    "name:fao_x_preferred":[
        "Melby"
    ],
    "name:fra_x_preferred":[
        "Melby"
    ],
    "name:isl_x_preferred":[
        "Melby"
    ],
    "name:kal_x_preferred":[
        "Melby"
    ],
    "name:nld_x_preferred":[
        "Melby"
    ],
    "name:nno_x_preferred":[
        "Melby"
    ],
    "name:nob_x_preferred":[
        "Melby"
    ],
    "name:swe_x_preferred":[
        "Melby"
    ],
    "qs_pg:aaroncc":"DK",
    "qs_pg:gn_country":"DK",
    "qs_pg:gn_fcode":"PPL",
    "qs_pg:gn_pop":0,
    "qs_pg:name":"Melby",
    "qs_pg:name_adm0":"Danmark",
    "qs_pg:name_adm1":"Hovedstaden",
    "qs_pg:photos":306,
    "qs_pg:photos_1k":62,
    "qs_pg:photos_9k":1,
    "qs_pg:photos_9r":5,
    "qs_pg:photos_all":306,
    "qs_pg:photos_sr":5,
    "qs_pg:pop_sr":0,
    "qs_pg:qs_pg_placetype":"locality",
    "qs_pg:qs_pg_placetype_gp":"Town",
    "qs_pg:woe_adm0":23424796,
    "woe:adm0_id":23424796,
    "woe:name_adm0":"Danmark",
    "woe:name_adm1":"Hovedstaden",
    "woe:placetype":"Town",
    "wof:name":"Melby",
    "wof:placetype":"locality"
},
  "geometry": {"coordinates":[11.96764,55.99619],"type":"Point"}
}