{
  "type": "Feature",
  "properties": {
    "gn:admin1_code":"18.0",
    "gn:admin2_code":"615.0",
    "gn:asciiname":"Tyrsted",
    "gn:country_code":"DK",
    "gn:dem":57,
    "gn:feature_class":"P",
    "gn:feature_code":"PPL",
    "gn:name":"Tyrsted",
    "gn:population":0,
    "gn:timezone":"Europe/Copenhagen",
    "iso:country":"DK",
    "name:dan_x_preferred":[
        "Tyrsted Sogn"
    ],
    "name:nds_x_preferred":[
        "Tyrsted Sogn"
    ],
    "name:nld_x_preferred":[
        "Tyrsted"
    ],
    "name:und_x_variant":[
        "Tvrsted",
        "Tyrsted"
    ],
    "wof:name":"Tyrsted",
    "wof:placetype":"locality"
},
  "geometry": {"coordinates":[9.86038,55.82844],"type":"Point"}
}