{
  "type": "Feature",
  "properties": {
    "gn:admin1_code":"21.0",
    "gn:admin2_code":"561.0",
    "gn:asciiname":"Grisbaek",
    "gn:country_code":"DK",
    "gn:dem":17,
    "gn:feature_class":"P",
    "gn:feature_code":"PPL",
    "gn:name":"Grisb\u00e6k",
    "gn:population":0,
    "gn:timezone":"Europe/Copenhagen",
    "iso:country":"DK",
    "wof:name":"Grisbaek",
    "wof:placetype":"locality"
},
  "geometry": {"coordinates":[8.75615,55.53928000000001],"type":"Point"}
}