{
  "type": "Feature",
  "properties": {
    "gn:admin1_code":"20.0",
    "gn:admin2_code":"336.0",
    "gn:asciiname":"Himlingoje",
    "gn:country_code":"DK",
    "gn:dem":20,
    "gn:feature_class":"P",
    "gn:feature_code":"PPL",
    "gn:name":"Himling\u00f8je",
    "gn:population":0,
    "gn:timezone":"Europe/Copenhagen",
    "iso:country":"DK",
    "wof:name":"Himlingoje",
    "wof:placetype":"locality"
},
  "geometry": {"coordinates":[12.22199,55.37457],"type":"Point"}
}