{
  "type": "Feature",
  "properties": {
    "gn:admin1_code":"19.0",
    "gn:admin2_code":"787.0",
    "gn:asciiname":"Gudnaes",
    "gn:country_code":"DK",
    "gn:dem":12,
    "gn:feature_class":"P",
    "gn:feature_code":"PPL",
    "gn:name":"Gudn\u00e6s",
    "gn:population":0,
    "gn:timezone":"Europe/Copenhagen",
    "iso:country":"DK",
    "wof:name":"Gudnaes",
    "wof:placetype":"locality"
},
  "geometry": {"coordinates":[8.52665,56.81783000000001],"type":"Point"}
}