{
  "type": "Feature",
  "properties": {
    "gn:admin1_code":"20.0",
    "gn:admin2_code":"390.0",
    "gn:asciiname":"Hjertebjerg",
    "gn:country_code":"DK",
    "gn:dem":28,
    "gn:feature_class":"P",
    "gn:feature_code":"PPL",
    "gn:name":"Hjertebjerg",
    "gn:population":0,
    "gn:timezone":"Europe/Copenhagen",
    "iso:country":"DK",
    "name:und_x_variant":[
        "Hjertebj\u00e6rg",
        "Hjertebjerg"
    ],
    "wof:name":"Hjertebjerg",
    "wof:placetype":"locality"
},
  "geometry": {"coordinates":[12.39165,54.99643],"type":"Point"}
}