{
  "type": "Feature",
  "properties": {
    "gn:admin1_code":"21.0",
    "gn:admin2_code":"510.0",
    "gn:asciiname":"Kolsnap",
    "gn:country_code":"DK",
    "gn:dem":46,
    "gn:feature_class":"P",
    "gn:feature_code":"PPL",
    "gn:name":"Kolsnap",
    "gn:population":0,
    "gn:timezone":"Europe/Copenhagen",
    "iso:country":"DK",
    "wof:name":"Kolsnap",
    "wof:placetype":"locality"
},
  "geometry": {"coordinates":[9.19069,55.25235],"type":"Point"}
}