{
  "type": "Feature",
  "properties": {
    "gn:gn_country":"DK",
    "gn:gn_fcode":"PPL",
    "gn:gn_pop":0,
    "iso:country":"DK",
    "name:afr_x_preferred":[
        "L\u00f8nstrup"
    ],
    "name:dan_x_preferred":[
        "L\u00f8nstrup"
    ],
    "name:deu_x_preferred":[
        "L\u00f8nstrup"
    ],
    "name:eng_x_preferred":[
        "L\u00f8nstrup"
    ],
    "name:nld_x_preferred":[
        "L\u00f8nstrup"
    ],
    "name:pol_x_preferred":[
        "L\u00f8nstrup"
    ],
    "name:swe_x_preferred":[
        "L\u00f8nstrup"
    ],
    "qs_pg:aaroncc":"DK",
    "qs_pg:gn_country":"DK",
    "qs_pg:gn_fcode":"PPL",
    "qs_pg:gn_pop":0,
    "qs_pg:name":"L\u00f8nstrup",
    "qs_pg:name_adm0":"Danmark",
    "qs_pg:name_adm1":"Nordjylland",
    "qs_pg:photos":991,
    "qs_pg:photos_1k":201,
    "qs_pg:photos_9k":4,
    "qs_pg:photos_9r":6,
    "qs_pg:photos_all":991,
    "qs_pg:photos_sr":10,
    "qs_pg:pop_sr":0,
    "qs_pg:qs_pg_placetype":"locality",
    "qs_pg:qs_pg_placetype_gp":"Town",
    "qs_pg:woe_adm0":23424796,
    "woe:adm0_id":23424796,
    "woe:name_adm0":"Danmark",
    "woe:name_adm1":"Nordjylland",
    "woe:placetype":"Town",
    "wof:name":"L\u00f8nstrup",
    "wof:placetype":"locality"
},
  "geometry": {"coordinates":[9.79616,57.46956],"type":"Point"}
}