{
  "type": "Feature",
  "properties": {
    "gn:admin1_code":"17.0",
    "gn:admin2_code":"270.0",
    "gn:asciiname":"Helsinge Tofte",
    "gn:cc2":"DK",
    "gn:country_code":"DK",
    "gn:dem":29,
    "gn:feature_class":"P",
    "gn:feature_code":"PPL",
    "gn:name":"Helsinge Tofte",
    "gn:population":0,
    "gn:timezone":"Europe/Copenhagen",
    "iso:country":"DK",
    "name:und_x_variant":[
        "Tofte",
        "Helsinge Tofte"
    ],
    "wof:name":"Helsinge Tofte",
    "wof:placetype":"locality"
},
  "geometry": {"coordinates":[12.18333,56.01667],"type":"Point"}
}