{
  "type": "Feature",
  "properties": {
    "gn:admin1_code":"19.0",
    "gn:admin2_code":"860.0",
    "gn:asciiname":"Tornby",
    "gn:country_code":"DK",
    "gn:dem":27,
    "gn:feature_class":"P",
    "gn:feature_code":"PPL",
    "gn:name":"Tornby",
    "gn:population":0,
    "gn:timezone":"Europe/Copenhagen",
    "iso:country":"DK",
    "name:und_x_variant":[
        "S\u00f8nder Tornby",
        "Tornby"
    ],
    "wof:name":"Tornby",
    "wof:placetype":"locality"
},
  "geometry": {"coordinates":[9.94956,57.52947],"type":"Point"}
}