{
  "type": "Feature",
  "properties": {
    "gn:admin1_code":"18.0",
    "gn:admin2_code":"756.0",
    "gn:asciiname":"Isenvad",
    "gn:country_code":"DK",
    "gn:dem":68,
    "gn:elevation":"67.0",
    "gn:feature_class":"P",
    "gn:feature_code":"PPL",
    "gn:name":"Isenvad",
    "gn:population":645,
    "gn:timezone":"Europe/Copenhagen",
    "iso:country":"DK",
    "wof:name":"Isenvad",
    "wof:placetype":"locality",
    "wof:population":645
},
  "geometry": {"coordinates":[9.2047,56.09915],"type":"Point"}
}