{
  "type": "Feature",
  "properties": {
    "gn:admin1_code":"20.0",
    "gn:admin2_code":"390.0",
    "gn:asciiname":"Kong",
    "gn:country_code":"DK",
    "gn:dem":3,
    "gn:feature_class":"P",
    "gn:feature_code":"PPL",
    "gn:name":"K\u00f8ng",
    "gn:population":0,
    "gn:timezone":"Europe/Copenhagen",
    "iso:country":"DK",
    "name:und_x_variant":[
        "Kj\u00f6ng",
        "Koeng",
        "K\u00f8ng"
    ],
    "wof:name":"Kong",
    "wof:placetype":"locality"
},
  "geometry": {"coordinates":[11.82747,55.10965],"type":"Point"}
}