{
  "type": "Feature",
  "properties": {
    "gn:admin1_code":"20.0",
    "gn:admin2_code":"390.0",
    "gn:asciiname":"Kong",
    "gn:country_code":"DK",
    "gn:dem":3,
    "gn:feature_class":"P",
    "gn:feature_code":"PPL",
    "gn:name":"K\u00f8ng",
    "gn:population":0,
    "gn:timezone":"Europe/Copenhagen",
    "iso:country":"DK",
    "name:aka_x_preferred":[
        "Kong"
    ],
    "name:ceb_x_preferred":[
        "Kong"
    ],
    "name:dan_x_preferred":[
        "Kong"
    ],
    "name:deu_x_preferred":[
        "Kong"
    ],
    "name:fra_x_preferred":[
        "Kong"
    ],
    "name:ita_x_preferred":[
        "Kong"
    ],
    "name:jpn_x_preferred":[
        "\u30b3\u30f3\u30b0"
    ],
    "name:kor_x_preferred":[
        "\ucf69"
    ],
    "name:nld_x_preferred":[
        "Kong"
    ],
    "name:nor_x_preferred":[
        "Kong"
    ],
    "name:pol_x_preferred":[
        "Kong"
    ],
    "name:por_x_preferred":[
        "Kong"
    ],
    "name:rus_x_preferred":[
        "\u041a\u043e\u043d\u0433"
    ],
    "name:swe_x_preferred":[
        "Kong"
    ],
    "name:und_x_variant":[
        "Kj\u00f6ng",
        "Koeng",
        "K\u00f8ng"
    ],
    "wof:name":"Kong",
    "wof:placetype":"locality"
},
  "geometry": {"coordinates":[11.82747,55.10965],"type":"Point"}
}