{
  "type": "Feature",
  "properties": {
    "gn:admin1_code":"20.0",
    "gn:admin2_code":"376.0",
    "gn:asciiname":"Sonder Kirkeby",
    "gn:country_code":"DK",
    "gn:dem":16,
    "gn:feature_class":"P",
    "gn:feature_code":"PPL",
    "gn:name":"S\u00f8nder Kirkeby",
    "gn:population":0,
    "gn:timezone":"Europe/Copenhagen",
    "iso:country":"DK",
    "wof:name":"Sonder Kirkeby",
    "wof:placetype":"locality"
},
  "geometry": {"coordinates":[11.97692,54.76955],"type":"Point"}
}