{
  "type": "Feature",
  "properties": {
    "gn:admin1_code":"21.0",
    "gn:admin2_code":"607.0",
    "gn:asciiname":"Stovstrup",
    "gn:country_code":"DK",
    "gn:dem":24,
    "gn:feature_class":"P",
    "gn:feature_code":"PPL",
    "gn:name":"Stovstrup",
    "gn:population":0,
    "gn:timezone":"Europe/Copenhagen",
    "iso:country":"DK",
    "wof:name":"Stovstrup",
    "wof:placetype":"locality"
},
  "geometry": {"coordinates":[9.69393,55.56834],"type":"Point"}
}