{
  "type": "Feature",
  "properties": {
    "gn:admin1_code":"18.0",
    "gn:admin2_code":"657.0",
    "gn:asciiname":"Skjellund",
    "gn:country_code":"DK",
    "gn:dem":67,
    "gn:feature_class":"P",
    "gn:feature_code":"PPL",
    "gn:name":"Skjellund",
    "gn:population":0,
    "gn:timezone":"Europe/Copenhagen",
    "iso:country":"DK",
    "wof:name":"Skjellund",
    "wof:placetype":"locality"
},
  "geometry": {"coordinates":[9.0895,56.10919000000001],"type":"Point"}
}