{
  "type": "Feature",
  "properties": {
    "gn:admin1_code":"21.0",
    "gn:admin2_code":"580.0",
    "gn:asciiname":"Felstedskov",
    "gn:country_code":"DK",
    "gn:dem":36,
    "gn:feature_class":"P",
    "gn:feature_code":"PPL",
    "gn:name":"Felstedskov",
    "gn:population":0,
    "gn:timezone":"Europe/Copenhagen",
    "iso:country":"DK",
    "wof:name":"Felstedskov",
    "wof:placetype":"locality"
},
  "geometry": {"coordinates":[9.51921,55.0186],"type":"Point"}
}