{
  "type": "Feature",
  "properties": {
    "gn:admin1_code":"20.0",
    "gn:admin2_code":"390.0",
    "gn:asciiname":"Stubberup",
    "gn:country_code":"DK",
    "gn:dem":34,
    "gn:feature_class":"P",
    "gn:feature_code":"PPL",
    "gn:name":"Stubberup",
    "gn:population":0,
    "gn:timezone":"Europe/Copenhagen",
    "iso:country":"DK",
    "wof:name":"Stubberup",
    "wof:placetype":"locality"
},
  "geometry": {"coordinates":[12.4804,54.99446],"type":"Point"}
}