{
  "type": "Feature",
  "properties": {
    "gn:admin1_code":"21.0",
    "gn:admin2_code":"540.0",
    "gn:asciiname":"Torp",
    "gn:country_code":"DK",
    "gn:dem":19,
    "gn:feature_class":"P",
    "gn:feature_code":"PPL",
    "gn:name":"Torp",
    "gn:population":0,
    "gn:timezone":"Europe/Copenhagen",
    "iso:country":"DK",
    "name:ceb_x_preferred":[
        "Torp"
    ],
    "name:dan_x_preferred":[
        "Torp"
    ],
    "name:deu_x_preferred":[
        "Torp"
    ],
    "name:fra_x_preferred":[
        "Torp"
    ],
    "name:nds_x_preferred":[
        "Torp"
    ],
    "name:nld_x_preferred":[
        "Torp"
    ],
    "name:nor_x_preferred":[
        "Torp"
    ],
    "name:srp_x_preferred":[
        "\u0422\u043e\u0440\u043f"
    ],
    "name:swe_x_preferred":[
        "Torp"
    ],
    "wof:name":"Torp",
    "wof:placetype":"locality"
},
  "geometry": {"coordinates":[9.85,55.03333000000001],"type":"Point"}
}