{
  "type": "Feature",
  "properties": {
    "gn:admin1_code":"21.0",
    "gn:admin2_code":"540.0",
    "gn:asciiname":"Torp",
    "gn:country_code":"DK",
    "gn:dem":19,
    "gn:feature_class":"P",
    "gn:feature_code":"PPL",
    "gn:name":"Torp",
    "gn:population":0,
    "gn:timezone":"Europe/Copenhagen",
    "iso:country":"DK",
    "wof:name":"Torp",
    "wof:placetype":"locality"
},
  "geometry": {"coordinates":[9.85,55.03333000000001],"type":"Point"}
}