{
  "type": "Feature",
  "properties": {
    "gn:admin1_code":"21.0",
    "gn:admin2_code":"607.0",
    "gn:asciiname":"Herslev",
    "gn:country_code":"DK",
    "gn:dem":44,
    "gn:feature_class":"P",
    "gn:feature_code":"PPL",
    "gn:name":"Herslev",
    "gn:population":0,
    "gn:timezone":"Europe/Copenhagen",
    "iso:country":"DK",
    "wof:name":"Herslev",
    "wof:placetype":"locality"
},
  "geometry": {"coordinates":[9.58967,55.58418],"type":"Point"}
}