{
  "type": "Feature",
  "properties": {
    "gn:admin1_code":"21.0",
    "gn:admin2_code":"430.0",
    "gn:asciiname":"Staby",
    "gn:country_code":"DK",
    "gn:dem":30,
    "gn:feature_class":"P",
    "gn:feature_code":"PPL",
    "gn:name":"St\u00e5by",
    "gn:population":0,
    "gn:timezone":"Europe/Copenhagen",
    "iso:country":"DK",
    "name:und_x_variant":[
        "Staaby",
        "St\u00e5by"
    ],
    "wof:name":"Staby",
    "wof:placetype":"locality"
},
  "geometry": {"coordinates":[10.27365,55.2576],"type":"Point"}
}