{
  "type": "Feature",
  "properties": {
    "gn:admin1_code":"20.0",
    "gn:admin2_code":"360.0",
    "gn:asciiname":"Skredtorpe",
    "gn:country_code":"DK",
    "gn:dem":1,
    "gn:feature_class":"P",
    "gn:feature_code":"PPL",
    "gn:name":"Skredtorpe",
    "gn:population":0,
    "gn:timezone":"Europe/Copenhagen",
    "iso:country":"DK",
    "wof:name":"Skredtorpe",
    "wof:placetype":"locality"
},
  "geometry": {"coordinates":[11.15731,54.9051],"type":"Point"}
}