{
  "type": "Feature",
  "properties": {
    "gn:admin1_code":"21.0",
    "gn:admin2_code":"575.0",
    "gn:asciiname":"Mojbol",
    "gn:country_code":"DK",
    "gn:dem":31,
    "gn:feature_class":"P",
    "gn:feature_code":"PPL",
    "gn:name":"Mojb\u00f8l",
    "gn:population":0,
    "gn:timezone":"Europe/Copenhagen",
    "iso:country":"DK",
    "wof:name":"Mojbol",
    "wof:placetype":"locality"
},
  "geometry": {"coordinates":[9.17344,55.30026],"type":"Point"}
}