{
  "type": "Feature",
  "properties": {
    "gn:population":2906,
    "iso:country":"DK",
    "name:ceb_x_preferred":[
        "Liseleje"
    ],
    "name:dan_x_preferred":[
        "Liseleje"
    ],
    "name:deu_x_preferred":[
        "Liseleje"
    ],
    "name:eng_x_preferred":[
        "Liseleje"
    ],
    "name:fin_x_preferred":[
        "Liseleje"
    ],
    "name:nld_x_preferred":[
        "Liseleje"
    ],
    "name:nob_x_preferred":[
        "Liseleje"
    ],
    "name:spa_x_preferred":[
        "Liseleje"
    ],
    "name:swe_x_preferred":[
        "Liseleje"
    ],
    "qs:a0":"Danmark",
    "qs:a1":"*Hovedstaden",
    "qs:a1r":"0",
    "qs:adm0":"Danmark",
    "qs:la_lc":"*",
    "qs:level":"locality",
    "qs:loc":"Liseleje",
    "qs:loc_alt":"Liseleje",
    "qs:pop":0,
    "qs:type":"buffered point",
    "wd:wordcount":422,
    "wof:name":"Liseleje",
    "wof:placetype":"locality",
    "wof:population":2906
},
  "geometry": {"coordinates":[11.95806,56.004503],"type":"Point"}
}