{
  "type": "Feature",
  "properties": {
    "gn:admin1_code":"21.0",
    "gn:admin2_code":"492.0",
    "gn:asciiname":"Tranderup",
    "gn:country_code":"DK",
    "gn:dem":42,
    "gn:feature_class":"P",
    "gn:feature_code":"PPL",
    "gn:name":"Tranderup",
    "gn:population":0,
    "gn:timezone":"Europe/Copenhagen",
    "iso:country":"DK",
    "name:und_x_variant":[
        "Trandrup",
        "Tranderup"
    ],
    "wof:name":"Tranderup",
    "wof:placetype":"locality"
},
  "geometry": {"coordinates":[10.36281,54.86749],"type":"Point"}
}