{
  "type": "Feature",
  "properties": {
    "gn:admin1_code":"20.0",
    "gn:admin2_code":"370.0",
    "gn:asciiname":"Vrangstrup",
    "gn:country_code":"DK",
    "gn:dem":18,
    "gn:feature_class":"P",
    "gn:feature_code":"PPL",
    "gn:name":"Vrangstrup",
    "gn:population":0,
    "gn:timezone":"Europe/Copenhagen",
    "iso:country":"DK",
    "wof:name":"Vrangstrup",
    "wof:placetype":"locality"
},
  "geometry": {"coordinates":[11.72617,55.39972],"type":"Point"}
}