{
  "type": "Feature",
  "properties": {
    "gn:admin1_code":"19.0",
    "gn:admin2_code":"860.0",
    "gn:asciiname":"Sankt Knuds By",
    "gn:country_code":"DK",
    "gn:dem":31,
    "gn:feature_class":"P",
    "gn:feature_code":"PPL",
    "gn:name":"Sankt Knuds By",
    "gn:population":0,
    "gn:timezone":"Europe/Copenhagen",
    "iso:country":"DK",
    "wof:name":"Sankt Knuds By",
    "wof:placetype":"locality"
},
  "geometry": {"coordinates":[9.96386,57.45231],"type":"Point"}
}