{
  "type": "Feature",
  "properties": {
    "gn:admin1_code":"20.0",
    "gn:admin2_code":"390.0",
    "gn:asciiname":"Balle",
    "gn:country_code":"DK",
    "gn:dem":19,
    "gn:feature_class":"P",
    "gn:feature_code":"PPL",
    "gn:name":"Balle",
    "gn:population":0,
    "gn:timezone":"Europe/Copenhagen",
    "iso:country":"DK",
    "name:ceb_x_preferred":[
        "Balle"
    ],
    "name:dan_x_preferred":[
        "Balle"
    ],
    "name:deu_x_preferred":[
        "Balle"
    ],
    "name:fra_x_preferred":[
        "Balle"
    ],
    "name:hye_x_preferred":[
        "\u0532\u0561\u056c"
    ],
    "name:ind_x_preferred":[
        "Balle"
    ],
    "name:nld_x_preferred":[
        "Balle"
    ],
    "name:nrm_x_preferred":[
        "Balle"
    ],
    "name:por_x_preferred":[
        "Balle"
    ],
    "name:swe_x_preferred":[
        "Balle"
    ],
    "name:und_x_variant":[
        "Bahl",
        "B\u00e6l",
        "Balle"
    ],
    "wof:name":"Balle",
    "wof:placetype":"locality"
},
  "geometry": {"coordinates":[12.11192,55.02901],"type":"Point"}
}