{
  "type": "Feature",
  "properties": {
    "gn:admin1_code":"18.0",
    "gn:admin2_code":"791.0",
    "gn:asciiname":"Bruunshab",
    "gn:country_code":"DK",
    "gn:dem":22,
    "gn:feature_class":"P",
    "gn:feature_code":"PPL",
    "gn:name":"Bruunsh\u00e5b",
    "gn:population":0,
    "gn:timezone":"Europe/Copenhagen",
    "iso:country":"DK",
    "name:und_x_variant":[
        "Brunshaab",
        "Bruunshaab",
        "Bruunsh\u00e5b"
    ],
    "wof:name":"Bruunshab",
    "wof:placetype":"locality"
},
  "geometry": {"coordinates":[9.4399,56.42084000000001],"type":"Point"}
}