{
  "type": "Feature",
  "properties": {
    "gn:admin1_code":"20.0",
    "gn:admin2_code":"390.0",
    "gn:asciiname":"Svensmarke",
    "gn:country_code":"DK",
    "gn:dem":11,
    "gn:feature_class":"P",
    "gn:feature_code":"PPL",
    "gn:name":"Svensmarke",
    "gn:population":0,
    "gn:timezone":"Europe/Copenhagen",
    "iso:country":"DK",
    "wof:name":"Svensmarke",
    "wof:placetype":"locality"
},
  "geometry": {"coordinates":[12.30977,54.9766],"type":"Point"}
}