{
  "type": "Feature",
  "properties": {
    "gn:admin1_code":"20.0",
    "gn:admin2_code":"376.0",
    "gn:asciiname":"Kettinge Baekkeskov",
    "gn:country_code":"DK",
    "gn:dem":12,
    "gn:feature_class":"P",
    "gn:feature_code":"PPLL",
    "gn:name":"Kettinge B\u00e6kkeskov",
    "gn:population":0,
    "gn:timezone":"Europe/Copenhagen",
    "iso:country":"DK",
    "wof:name":"Kettinge Baekkeskov",
    "wof:placetype":"locality"
},
  "geometry": {"coordinates":[11.76854,54.68561],"type":"Point"}
}