{
  "type": "Feature",
  "properties": {
    "gn:admin1_code":"20.0",
    "gn:admin2_code":"306.0",
    "gn:asciiname":"Bosserup",
    "gn:country_code":"DK",
    "gn:dem":28,
    "gn:feature_class":"P",
    "gn:feature_code":"PPL",
    "gn:name":"B\u00f8sserup",
    "gn:population":0,
    "gn:timezone":"Europe/Copenhagen",
    "iso:country":"DK",
    "wof:name":"Bosserup",
    "wof:placetype":"locality"
},
  "geometry": {"coordinates":[11.68429,55.8661],"type":"Point"}
}