{
  "type": "Feature",
  "properties": {
    "gn:admin1_code":"20.0",
    "gn:admin2_code":"390.0",
    "gn:asciiname":"Pollerup Kullegard",
    "gn:country_code":"DK",
    "gn:dem":5,
    "gn:feature_class":"P",
    "gn:feature_code":"PPLL",
    "gn:name":"Pollerup Kulleg\u00e5rd",
    "gn:population":0,
    "gn:timezone":"Europe/Copenhagen",
    "iso:country":"DK",
    "name:und_x_variant":[
        "Kullegaard",
        "Pollerup Kullegaard",
        "Pollerup Kulleg\u00e5rd"
    ],
    "wof:name":"Pollerup Kullegard",
    "wof:placetype":"locality"
},
  "geometry": {"coordinates":[12.37476,54.97298000000001],"type":"Point"}
}