{
  "type": "Feature",
  "properties": {
    "gn:admin1_code":"18.0",
    "gn:admin2_code":"751.0",
    "gn:asciiname":"Todbjerg",
    "gn:country_code":"DK",
    "gn:dem":63,
    "gn:feature_class":"P",
    "gn:feature_code":"PPL",
    "gn:name":"Todbjerg",
    "gn:population":0,
    "gn:timezone":"Europe/Copenhagen",
    "iso:country":"DK",
    "name:und_x_variant":[
        "Todbj\u00e6rg",
        "Todbjerg"
    ],
    "wof:name":"Todbjerg",
    "wof:placetype":"locality"
},
  "geometry": {"coordinates":[10.20861,56.26806],"type":"Point"}
}