{
  "type": "Feature",
  "properties": {
    "gn:admin1_code":"18.0",
    "gn:admin2_code":"760.0",
    "gn:asciiname":"Alrum",
    "gn:country_code":"DK",
    "gn:dem":3,
    "gn:feature_class":"P",
    "gn:feature_code":"PPLL",
    "gn:name":"Alrum",
    "gn:population":0,
    "gn:timezone":"Europe/Copenhagen",
    "iso:country":"DK",
    "wof:name":"Alrum",
    "wof:placetype":"locality"
},
  "geometry": {"coordinates":[8.23899,56.17865],"type":"Point"}
}